{
  "source_id": "settour",
  "package_type": "unknown",
  "url": "https://fit.settour.com.tw/product/v2?adtCount=2&chdCount=0&pfpClass=&airlineCode=&directFlightOnly=true&depAirportCode=TPE&arrAirportCode=KIX&depDate=20260224,20260228&regionId=HFP0000900308&roomQty=1&childAge=&displayName=OMO%20Kansai%20Airport%20by%20Hoshino%20Resorts%20%E6%98%9F%E9%87%8E%E9%9B%86%E5%9C%98OMO%E9%97%9C%E8%A5%BF%E6%A9%9F%E5%A0%B4%20(%E6%97%A5%E6%9C%AC%20-%20%E6%B3%89%E4%BD%90%E9%87%8E%E5%B8%82(%E9%97%9C%E8%A5%BF%E7%A9%BA%E6%B8%AF))&hotelCheckInDate=20260224&hotelCheckOutDate=20260228&tripType=RT&eventCode=",
  "scraped_at": "2026-02-09T02:52:45.914830",
  "title": "機加酒自由行搜尋推薦 | 東南旅遊",
  "raw_text": "同業專區\n企業專區\n客製旅遊\n訂單查詢\n票券購物車\n追蹤我們 \n會員福利 \n登入/註冊會員\n跟團遊\n自由行\n遊輪\n機票\n飯店\n票券/體驗\n高鐵假期\n護照簽證\n台中出發\n高雄出發\n台灣桃園機場TPE大阪關西國際機場KIX\n2026/02/24(二)~2026/02/28(六)\n1間客房，2成人\n首頁自由行機加酒自由配大阪市\n海外自由配(台北-大阪市)\n貼心提醒！已為您找到最低價的航班飯店組合，您也可點擊更改來選擇其他組合或重新搜尋。\n 精選好禮 \n\n自由行在路上，溫暖聚在一起 ◍•ᴗ•◍2月出發即贈王品聚日式鍋物 說明\n\n✓海外商品包含中信產險旅平險及不便險(最多5日)🛡️大人保額：200萬/20萬/20萬🛡️小孩保額：0萬/20萬/20萬 說明\n\n 來回機票 去程：2026/02/24(二)   回程：2026/02/28(六)修改航班日期\n去程：2026/02/24 (二)\n泰國獅子航空\n09:00\nTPE\n2h30m\n直\n12:30\nKIX\n經濟艙\n航班資訊▼\n飛行時間合計：2h30m\n2026/02/24\n09:00\n2h30m\n2026/02/24\n12:30\nTPE 台灣桃園機場\n泰國獅子航空 SL396 \n經濟艙 M /\n不含行李\nKIX 大阪關西國際機場\n回程：2026/02/28 (六)\n泰國獅子航空\n13:30\nKIX\n3h10m\n直\n15:40\nTPE\n經濟艙\n航班資訊▼\n行李託運規定\n不含行李\n票價規定\n改票：不可\n退票：不可\n行李與票規詳細資訊\n更改航班\n 飯店 Izumisano 入住：2026/02/24(二)   退房：2026/02/28(六)   (共4晚)修改入住日期\n星野集團 OMO 關西機場\nOMO Kansai Airport by Hoshino Resorts\n 3顆星 Izumisano\n靠近臨空名牌暢貨中心\n只剩此飯店\n基本客房, 1 張加大雙人床, 非吸煙房\n1 張加大雙人床\n顯示詳細資訊\n不可退款 \n免費無線網路\n不含餐食\n更改房型\n訂單金額 幣別：新台幣\n成人x2\n機加酒未稅總價\n$30,481\n機票稅金 \n$8,062\n飯店稅金(含銷售稅) \n$974\n此處稅金計算僅供參考，請依付款時金額為準\n總價$39,517\n3期 0利率 $13,172起\n每人機加酒含稅$19,759\n立即結帳\n會員優惠\n\n限時優惠：說明\n\n刷玉山國旅卡自由配滿額現折1000\n國泰世華-自由配滿額折1000\n滙豐卡海外自由配折5%\n航班資訊\n飯店資訊\n注意事項\n航班資訊\n航班1(去程)所有時間皆為當地時間\n2026/02/24(二)台灣桃園機場TPE大阪關西國際機場KIX\n出發\n09:00\n台灣桃園機場\nTPE\n2h30m\n12:30\n大阪關西國際機場\nKIX\n泰國獅子航空SL396\n經濟艙\n不含行李\n航班2(回程)\n2026/02/28(六)大阪關西國際機場KIX台灣桃園機場TPE\n出發\n13:30\n大阪關西國際機場\nKIX\n3h10m\n15:40\n台灣桃園機場\nTPE\n泰國獅子航空SL397\n經濟艙\n不含行李\n票價規定\n機票效期依所預定日期/ 航班/ 行程搭乘，恕無法變更。\n查看更多\n\n開票後欲更改日期、航班、行程或退票，將依航空公司規定收取罰金與本公司作業服務費。\n\n成人\n改票出發前：不可 /  出發後：不可\n退票 不可\n小孩\n改票出發前：不可 /  出發後：不可\n退票 不可\n行李托運規定\n班機 / 航段每成人每小孩\n航班1台灣桃園機場TPE大阪關西國際機場KIX(SL)\n不含行李\n不含行李\n航班2大阪關西國際機場KIX台灣桃園機場TPE(SL)\n不含行李\n不含行李\n託運行李若以件數計算，則每1件不得超過23公斤；若以重量計算，則不得超過表列之公斤數 (部分航空不適用此條款)。\n託運行李資訊是根據航空公司於訂位系統中的票價規則進行自動分析而取得，不保證其準確性，得依實際開票時之確認為準。\n飯店資訊\n飯店\n \nIzumisano\n入住：2026/02/24(二)\n / \n退房：2026/02/28(六)\n（共4晚）\n收合飯店資訊\n星野集團 OMO 關西機場\n 3顆星 \n位置資訊\n\n星野集團 OMO 關西機場在泉佐野市，機場附近，步行 4 分鐘就能抵達臨空遊樂城 Seacle，7 分鐘則能抵達臨空公園。 此飯店地點良好，從這裡開車約 1 公里 (0.6 英哩) 會到臨空名牌暢貨中心，開車 1.9 公里 (1.2 英哩) 則會到田尻漁港周日早市。\n\n客房設施\n\n700 間精心設有電冰箱以及平面電視的冷氣客房等您入住，享受家一般的溫馨與舒適。房內提供免費無線上網讓您隨時保持連線。浴室設有淋浴/浴缸二合一，並精心提供全浸式浴缸以及免費盥洗用品。貼心提供保險箱 (可容納筆記型電腦)以及書桌，而且每日均有客房清潔服務。\n\n飯店政策\n\n最早入住時間 : 15:00 / 最晚入住時間 : 02:00 / 最晚退房時間 : 11:00 / 最低入住登記年紀 : 18\n\n商務設施\n\n住宿精心提供快速入住登記、快速退房以及24 小時櫃台服務。住宿免費提供飯店至機場的接駁車 (應要求提供)。\n\n餐食資訊\n\n您可以到星野集團 OMO 關西機場的餐廳吃頓好料，也可以到雜貨店/便利商店晃晃。想喝點東西解解渴，您可以到酒吧/酒廊點一杯您喜愛的飲料。每日 06:00 至 10:00 付費供應吃到飽早餐。\n\n最新消息\n\n此住宿將於 2026 年 1 月 18 日至 2026 年 1 月 22 日期間暫時停業 (日期可能有變)。\n\n入住提醒\n\n此住宿恕不在營業時間以外提供入住登記服務。抵達住宿時櫃台會有服務人員接待旅客。住宿提供的資訊可能經由自動翻譯工具翻譯。\n\n注意事項\n東南旅遊自由配注意事項\n取消/變更 作業費用規定\n全台市話直撥02-412-8688\n交觀綜字第2027號 品保0150 代表人：李清松 聯絡人：張景翔\n總公司：台北市中山北路二段60號\n統一編號：79228705 代表號：(02)2567-8111\n東南旅行社股份有限公司版權所有 © 2026 SETtour of R.O.C All Rights Reserved.",
  "extracted": {
    "flight": {
      "outbound": {
        "flight_number": "SL396",
        "airline": "",
        "airline_code": "",
        "departure_airport": "",
        "departure_code": "TPE",
        "departure_time": "09:00",
        "arrival_airport": "",
        "arrival_code": "KIX",
        "arrival_time": "12:30",
        "date": ""
      },
      "return": {
        "flight_number": "SL396",
        "airline": "",
        "airline_code": "",
        "departure_airport": "",
        "departure_code": "TPE",
        "departure_time": "12:30",
        "arrival_airport": "",
        "arrival_code": "KIX",
        "arrival_time": "",
        "date": ""
      }
    },
    "hotel": {
      "name": "",
      "names": [],
      "area": "",
      "star_rating": null,
      "access": [],
      "amenities": [],
      "room_type": "",
      "bed_width_cm": null
    },
    "price": {
      "currency": "TWD"
    },
    "dates": {
      "departure_date": "",
      "return_date": ""
    },
    "inclusions": [],
    "date_pricing": {}
  },
  "extracted_elements": {
    "price_element": [
      "$19,759"
    ],
    "flight_element": [
      "2026/02/24(二)台灣桃園機場TPE大阪關西國際機場KIX",
      "2026/02/28(六)大阪關西國際機場KIX台灣桃園機場TPE"
    ],
    "hotel_element": [
      "星野集團 OMO 關西機場\n 3顆星 \n位置資訊\n\n星野集團 OMO 關西機場在泉佐野市，機場附近，步行 4 分鐘就能抵達臨空遊樂城 Seacle，7 分鐘則能抵達臨空公園。 此飯店地點良好，從這裡開車約 1 公里 (0.6 英哩) 會到臨空名牌暢貨中心，開車 1.9 公里 (1.2 英哩) 則會到田尻漁港周日早市。\n\n客房設施\n\n700 間精心設有電冰箱以及平面電視的冷氣客房等您入住，享受家一般的溫馨與舒適。房內提供免費無線上網讓您隨時保持連線。浴室設有淋浴/浴缸二合一，並精心提供全浸式浴缸以及免費盥洗用品。貼心提供保險箱 (可容納筆記型電腦)以及書桌，而且每日均有客房清潔服務。\n\n飯店政策\n\n最早入住時間 : 15:00 / 最晚入住時間 : 02:00 / 最晚退房時間 : 11:00 / 最低入住登記年紀 : 18\n\n商務設施\n\n住宿精心提供快速入住登記、快速退房以及24 小時櫃台服務。住宿免費提供飯店至機場的接駁車 (應要求提供)。\n\n餐食資訊\n\n您可以到星野集團 OMO 關西機場的餐廳吃頓好料，也可以到雜貨店/便利商店晃晃。想喝點東西解解渴，您可以到酒吧/酒廊點一杯您喜愛的飲料。每日 06:00 至 10:00 付費供應吃到飽早餐。\n\n最新消息\n\n此住宿將於 2026 年 1 月 18 日至 2026 年 1 月 22 日期間暫時停業 (日期可能有變)。\n\n入住提醒\n\n此住宿恕不在營業時間以外提供入住登記服務。抵達住宿時櫃台會有服務人員接待旅客。住宿提供的資訊可能經由自動翻譯工具翻譯。"
    ],
    "price_class": [
      "飛行時間合計：2h30m\n2026/02/24\n09:00\n2h30m\n2026/02/24\n12:30\nTPE 台灣桃園機場\n泰國獅子航空 SL396 \n經濟艙 M /\n不含行李\nKIX 大阪關西國際機場",
      "飛行時間合計：2h30m\n2026/02/24\n09:00\n2h30m\n2026/02/24\n12:30\nTPE 台灣桃園機場\n泰國獅子航空 SL396 \n經濟艙 M /\n不含行李\nKIX 大阪關西國際機場",
      "飛行時間合計：2h30m\n2026/02/24\n09:00\n2h30m\n2026/02/24\n12:30\nTPE 台灣桃園機場\n泰國獅子航空 SL396 \n經濟艙 M /\n不含行李\nKIX 大阪關西國際機場",
      "2h30m",
      "飛行時間合計：3h10m2026/02/2813:303h10m2026/02/2815:40KIX 大阪關西國際機場泰國獅子航空 SL397 經濟艙 K  / 不含行李TPE 台灣桃園機場"
    ],
    "flight_class": [
      "去程：2026/02/24 (二)\n泰國獅子航空\n09:00\nTPE\n2h30m\n直\n12:30\nKIX\n經濟艙\n航班資訊▼\n飛行時間合計：2h30m\n2026/02/24\n09:00\n2h30m\n2026/02/24\n12:30\nTPE 台灣桃園機場\n泰國獅子航空 SL396 \n經濟艙 M /\n不含行李\nKIX 大阪關西國際機場\n回程：2026/02/28 (六)\n泰國獅子航空\n13:30\nKIX\n3h10m\n直\n15:40\nTPE\n經濟艙\n航班資訊▼\n行李託運規定\n不含行李\n票價規定\n改票：不可\n退票：不可\n行李與票規詳細資訊\n更改航班",
      "去程：2026/02/24 (二)",
      "泰國獅子航空",
      "泰國獅子航空"
    ],
    "hotel_class": [
      "星野集團 OMO 關西機場\nOMO Kansai Airport by Hoshino Resorts\n 3顆星 Izumisano\n靠近臨空名牌暢貨中心\n只剩此飯店",
      "星野集團 OMO 關西機場\n 3顆星 \n位置資訊\n\n星野集團 OMO 關西機場在泉佐野市，機場附近，步行 4 分鐘就能抵達臨空遊樂城 Seacle，7 分鐘則能抵達臨空公園。 此飯店地點良好，從這裡開車約 1 公里 (0.6 英哩) 會到臨空名牌暢貨中心，開車 1.9 公里 (1.2 英哩) 則會到田尻漁港周日早市。\n\n客房設施\n\n700 間精心設有電冰箱以及平面電視的冷氣客房等您入住，享受家一般的溫馨與舒適。房內提供免費無線上網讓您隨時保持連線。浴室設有淋浴/浴缸二合一，並精心提供全浸式浴缸以及免費盥洗用品。貼心提供保險箱 (可容納筆記型電腦)以及書桌，而且每日均有客房清潔服務。\n\n飯店政策\n\n最早入住時間 : 15:00 / 最晚入住時間 : 02:00 / 最晚退房時間 : 11:00 / 最低入住登記年紀 : 18\n\n商務設施\n\n住宿精心提供快速入住登記、快速退房以及24 小時櫃台服務。住宿免費提供飯店至機場的接駁車 (應要求提供)。\n\n餐食資訊\n\n您可以到星野集團 OMO 關西機場的餐廳吃頓好料，也可以到雜貨店/便利商店晃晃。想喝點東西解解渴，您可以到酒吧/酒廊點一杯您喜愛的飲料。每日 06:00 至 10:00 付費供應吃到飽早餐。\n\n最新消息\n\n此住宿將於 2026 年 1 月 18 日至 2026 年 1 月 22 日期間暫時停業 (日期可能有變)。\n\n入住提醒\n\n此住宿恕不在營業時間以外提供入住登記服務。抵達住宿時櫃台會有服務人員接待旅客。住宿提供的資訊可能經由自動翻譯工具翻譯。",
      "星野集團 OMO 關西機場\n 3顆星"
    ],
    "content_id": [
      "同業專區\n企業專區\n客製旅遊\n訂單查詢\n票券購物車\n追蹤我們 \n會員福利 \n登入/註冊會員\n跟團遊\n自由行\n遊輪\n機票\n飯店\n票券/體驗\n高鐵假期\n護照簽證\n台中出發\n高雄出發\n台灣桃園機場TPE大阪關西國際機場KIX\n2026/02/24(二)~2026/02/28(六)\n1間客房，2成人\n首頁自由行機加酒自由配大阪市\n海外自由配(台北-大阪市)\n貼心提醒！已為您找到最低價的航班飯店組合，您也可點擊更改來選擇其他組合或重新搜尋。\n 精選好禮 \n\n自由行在路上，溫暖聚在一起 ◍•ᴗ•◍2月出發即贈王品聚日式鍋物 說明\n\n✓海外商品包含中信產險旅平險及不便險(最多5日)🛡️大人保額：200萬/20萬/20萬🛡️小孩保額：0萬/20萬/20萬 說明\n\n 來回機票 去程：2026/02/24(二)   回程：2026/02/28(六)修改航班日期\n去程：2026/02/24 (二)\n泰國獅子航空\n09:00\nTPE\n2h30m\n直\n12:30\nKIX\n經濟艙\n航班資訊▼\n飛行時間合計：2h30m\n2026/02/24\n09:00\n2h30m\n2026/02/24\n12:30\nTPE 台灣桃園機場\n泰國獅子航空 SL396 \n經濟艙 M /\n不含行李\nKIX 大阪關西國際機場\n回程：2026/02/28 (六)\n泰國獅子航空\n13:30\nKIX\n3h10m\n直\n15:40\nTPE\n經濟艙\n航班資訊▼\n行李託運規定\n不含行李\n票價規定\n改票：不可\n退票：不可\n行李與票規詳細資訊\n更改航班\n 飯店 Izumisano 入住：2026/02/24(二)   退房：2026/02/28(六)   (共4晚)修改入住日期\n星野集團 OMO 關西機場\nOMO Kansai Airport by Hoshino Resorts\n 3顆星 Izumisano\n靠近臨空名牌暢貨中心\n只剩此飯店\n基本客房, 1 張加大雙人床, 非吸煙房\n1 張加大雙人床\n顯示詳細資訊\n不可退款 \n免費無線網路\n不含餐食\n更改房型\n訂單金額 幣別：新台幣\n成人x2\n機加酒未稅總價\n$30,481\n機票稅金 \n$8,062\n飯店稅金(含銷售稅) \n$974\n此處稅金計算僅供參考，請依付款時金額為準\n總價$39,517\n3期 0利率 $13,172起\n每人機加酒含稅$19,759\n立即結帳\n會員優惠\n\n限時優惠：說明\n\n刷玉山國旅卡自由配滿額現折1000\n國泰世華-自由配滿額折1000\n滙豐卡海外自由配折5%\n航班資訊\n飯店資訊\n注意事項\n航班資訊\n航班1(去程)所有時間皆為當地時間\n2026/02/24(二)台灣桃園機場TPE大阪關西國際機場KIX\n出發\n09:00\n台灣桃園機場\nTPE\n2h30m\n12:30\n大阪關西國際機場\nKIX\n泰國獅子航空SL396\n經濟艙\n不含行李\n航班2(回程)\n2026/02/28(六)大阪關西國際機場KIX台灣桃園機場TPE\n出發\n13:30\n大阪關西國際機場\nKIX\n3h10m\n15:40\n台灣桃園機場\nTPE\n泰國獅子航空SL397\n經濟艙\n不含行李\n票價規定\n機票效期依所預定日期/ 航班/ 行程搭乘，恕無法變更。\n查看更多\n\n開票後欲更改日期、航班、行程或退票，將依航空公司規定收取罰金與本公司作業服務費。\n\n成人\n改票出發前：不可 /  出發後：不可\n退票 不可\n小孩\n改票出發前：不可 /  出發後：不可\n退票 不可\n行李托運規定\n班機 / 航段每成人每小孩\n航班1台灣桃園機場TPE大阪關西國際機場KIX(SL)\n不含行李\n不含行李\n航班2大阪關西國際機場KIX台灣桃園機場TPE(SL)\n不含行李\n不含行李\n託運行李若以件數計算，則每1件不得超過23公斤；若以重量計算，則不得超過表列之公斤數 (部分航空不適用此條款)。\n託運行李資訊是根據航空公司於訂位系統中的票價規則進行自動分析而取得，不保證其準確性，得依實際開票時之確認為準。\n飯店資訊\n飯店\n \nIzumisano\n入住：2026/02/24(二)\n / \n退房：2026/02/28(六)\n（共4晚）\n收合飯店資訊\n星野集團 OMO 關西機場\n 3顆星 \n位置資訊\n\n星野集團 OMO 關西機場在泉佐野市，機場附近，步行 4 分鐘就能抵達臨空遊樂城 Seacle，7 分鐘則能抵達臨空公園。 此飯店地點良好，從這裡開車約 1 公里 (0.6 英哩) 會到臨空名牌暢貨中心，開車 1.9 公里 (1.2 英哩) 則會到田尻漁港周日早市。\n\n客房設施\n\n700 間精心設有電冰箱以及平面電視的冷氣客房等您入住，享受家一般的溫馨與舒適。房內提供免費無線上網讓您隨時保持連線。浴室設有淋浴/浴缸二合一，並精心提供全浸式浴缸以及免費盥洗用品。貼心提供保險箱 (可容納筆記型電腦)以及書桌，而且每日均有客房清潔服務。\n\n飯店政策\n\n最早入住時間 : 15:00 / 最晚入住時間 : 02:00 / 最晚退房時間 : 11:00 / 最低入住登記年紀 : 18\n\n商務設施\n\n住宿精心提供快速入住登記、快速退房以及24 小時櫃台服務。住宿免費提供飯店至機場的接駁車 (應要求提供)。\n\n餐食資訊\n\n您可以到星野集團 OMO 關西機場的餐廳吃頓好料，也可以到雜貨店/便利商店晃晃。想喝點東西解解渴，您可以到酒吧/酒廊點一杯您喜愛的飲料。每日 06:00 至 10:00 付費供應吃到飽早餐。\n\n最新消息\n\n此住宿將於 2026 年 1 月 18 日至 2026 年 1 月 22 日期間暫時停業 (日期可能有變)。\n\n入住提醒\n\n此住宿恕不在營業時間以外提供入住登記服務。抵達住宿時櫃台會有服務人員接待旅客。住宿提供的資訊可能經由自動翻譯工具翻譯。\n\n注意事項\n東南旅遊自由配注意事項\n取消/變更 作業費用規定\n全台市話直撥02-412-8688\n交觀綜字第2027號 品保0150 代表人：李清松 聯絡人：張景翔\n總公司：台北市中山北路二段60號\n統一編號：79228705 代表號：(02)2567-8111\n東南旅行社股份有限公司版權所有 © 2026 SETtour of R.O.C All Rights Reserved."
    ]
  }
}