{
  "url": "https://www.trip.com/flights/taipei-to-osaka/tickets-tpe-kix?dcity=tpe&acity=kix&ddate=2026-02-24&flighttype=ow&class=y&quantity=2",
  "scraped_at": "2026-02-05T14:28:42.311183",
  "title": "Cheap Flights, Airline Tickets & Plane Tickets | Trip.com",
  "raw_text": "Go to main content\nTheme Detection\nHotels & Homes\nFlights\nTrains\nCar services\nApp\nUSD\nCustomer support\nFind bookings\nSign in / Register\nCheap Flights, Airline Tickets & Plane Tickets | Trip.com\nAllow notifications\nDon't miss out! Be the first to find out the latest travel info.\nAllow\nTaipei\nEdit\n2 adults\nEconomy\nFeb 24, 2026\nSat, Feb 21\nView\nSun, Feb 22\nView\nMon, Feb 23\nView\nTue, Feb 24\nUS$107\nWed, Feb 25\nView\nTue, Feb 17\nView\nWed, Feb 18\nView\nThu, Feb 19\nView\nFri, Feb 20\nView\nSat, Feb 21\nView\nSun, Feb 22\nView\nMon, Feb 23\nView\nTue, Feb 24\nUS$107\nWed, Feb 25\nView\nThu, Feb 26\nView\nFri, Feb 27\nView\nSat, Feb 28\nView\nSun, Mar 1\nView\nMon, Mar 2\nView\nTue, Mar 3\nView\nPrice graph\nRecommended\n Nonstop\n Checked baggage included\n Hide budget airlines\n Student tickets\n Carry-on baggage included\n Hide codeshare flights\nCO2e Lower emission flights\nShow More\nAlliance\nSkyTeam\nUS$262\nOneworld\nUS$264\nStar Alliance\nUS$286\nAirlines\nAll flights with the same airline\nAll airlines\nHK Express (8)\nUS$205\nJapan Airlines (7)\nUS$264\nPeach (4)\nUS$134\nHong Kong Airlines (4)\nUS$255\nCathay Pacific (4)\nUS$319\nShow More\nAlliance\nSkyTeam\nUS$262\nOneworld\nUS$264\nStar Alliance\nUS$286\nTimes\nDeparture time\n00:00–24:00\n00:00\n24:00\nArrival time\n00:00–24:00\n00:00\n24:00\nDuration\nAny\nStopover Duration\n1h–23h\n1h\n23h\nTotal Duration\n2h–29h 30m\n2h\n29h 30m\nStops\n1 stop or fewer\nUS$107\nStopover cities\nAny\nHong Kong\nUS$205\nTokyo\nUS$264\nManila\nUS$220\nBusan\nUS$283\nMacau\nUS$185\nDaegu\nUS$229\nSeoul\nUS$169\nJeju\nUS$210\nAirports\nAny\nDeparture Airport\nTSA\nTaipei Songshan Airport\nUS$264\nTPE\nTaiwan Taoyuan International Airport\nUS$107\nArrival Airport\nKIX\nKansai International Airport\nUS$107\nAircrafts\nAny\nLarge aircraft\nUS$107\nMidsize aircraft\nUS$134\nCabin\nEconomy\nEconomy\nEconomy/premium economy\nPremium economy\nBusiness/first\nBusiness\nFirst class\nRecommended\nUS$107\nNonstop first\nUS$107\nCheapest\nUS$107\nSort by\nCreate price alert\nCheapest\nCarry-on baggage included\n- 16% CO2e\nAirAsia X Berhad\n15:40\nTPE T1\n2h 40m\nNonstop\n19:20\nKIX T1\nUS$107\nTotal US$213\nSelect\nCarry-on baggage included\nThai Vietjet Air\n07:30\nTPE T1\n2h 30m\nNonstop\n11:00\nKIX T1\nUS$139\nTotal US$278\nSelect\nCarry-on baggage included\nPeach\n01:45\nTPE T1\n2h 25m\nNonstop\n05:10\nKIX T2\nUS$153\nTotal US$306\nSelect\nCarry-on baggage included\n- 18% CO2e\nPeach\n18:50\nTPE T1\n2h 25m\nNonstop\n22:15\nKIX T2\nUS$134\nTotal US$267\nSelect\nCarry-on baggage included\n- 18% CO2e\nPeach\n09:40\nTPE T1\n2h 30m\nNonstop\n13:10\nKIX T2\nUS$173\nTotal US$346\nSelect\nIncluded\n- 3% CO2e\nChina Airlines\n14:20\nTPE T2\n2h 30m\nNonstop\n17:50\nKIX T1\nUS$262\nTotal US$524\nSelect\nCarry-on baggage included\nTigerair Taiwan\n14:40\nTPE T1\n2h 15m\nNonstop\n17:55\nKIX T1\nUS$168\nTotal US$336\nSelect\nCarry-on baggage included\nPeach\n13:40\nTPE T1\n2h 25m\nNonstop\n17:05\nKIX T2\nUS$173\nTotal US$346\nSelect\nCarry-on baggage included\nJetstar Japan\n18:10\nTPE T1\n2h 30m\nNonstop\n21:40\nKIX T1\nUS$154\nTotal US$308\nSelect\nCarry-on baggage included\nThai Lion Air\n09:00\nTPE T1\n2h 30m\nNonstop\n12:30\nKIX T1\nUS$180\nTotal US$360\nSelect\nIncluded\n- 7% CO2e\nSTARLUX Airlines\n09:20\nTPE T1\n2h 30m\nNonstop\n12:50\nKIX T1\nUS$317\nTotal US$633\nSelect\nIncluded\n- 21% CO2e\nEVA Air\n06:30\nTPE T2\n2h 25m\nNonstop\n09:55\nKIX T1\nUS$296\nTotal US$592\nSelect\nIncluded\n- 20% CO2e\nEVA Air\n08:20\nTPE T2\n2h 35m\nNonstop\n11:55\nKIX T1\nUS$296\nTotal US$592\nSelect\nIncluded\nChina Airlines\n09:45\nTPE T2\n2h 35m\nNonstop\n13:20\nKIX T1\nUS$307\nTotal US$613\nSelect\nIncluded\n- 18% CO2e\nCathay Pacific\n11:15\nTPE T1\n2h 40m\nNonstop\n14:55\nKIX T1\nUS$319\nTotal US$638\nUS$292\nSelect\nIncluded\nHong Kong Airlines\n21:35\nTPE T2\n8h 40m\n3h in Hong Kong\n07:15\nKIX T1\n +1\nUS$255\nTotal US$510\nSelect\nFlights\n > \nFlights\n > \nTaipei to Flights\nBook flights from Taipei to on Trip.com\n\nFirst class | Business class | Economy class | Nonstop\n\nSearch for cheap flights from Taipei to on Trip.com. Trip.com provides the best real-time Taipei to airfares and flight deals available, featuring advanced flight planning tools like price alerts, deal finder fare calendars, and Taipei Flight + Hotel deals that make a vacation or tour more convenient and affordable.\n\nAward-winning\nSupport in approx. 30s\nRewards for booking\nContact us\nCustomer support\nService guarantee\nMore service info\nAbout\nAbout Trip.com\nNews\nCareers\nTerms & Conditions\nPrivacy Statement\nAccessibility statement\nAbout Trip.com Group\nOther services\nInvestor relations\nTrip.com Rewards\nAffiliate program\nList your property\nAll hotels\nBecome a Supplier\nSecurity\nPayment methods\nOur partners\nContact Center\nof the year 2025\nCopyright © 2025 Trip.com Travel Singapore Pte. Ltd. All rights reserved\nSite Operator: Trip.com Travel Singapore Pte. Ltd.",
  "extracted": {
    "flight": {},
    "hotel": {},
    "price": {},
    "dates": {},
    "inclusions": [],
    "date_pricing": {}
  },
  "extracted_elements": {
    "flight_element": [
      "AirAsia X Berhad\n15:40\nTPE T1\n2h 40m\nNonstop\n19:20\nKIX T1",
      "Thai Vietjet Air\n07:30\nTPE T1\n2h 30m\nNonstop\n11:00\nKIX T1",
      "Peach\n01:45\nTPE T1\n2h 25m\nNonstop\n05:10\nKIX T2",
      "Peach\n18:50\nTPE T1\n2h 25m\nNonstop\n22:15\nKIX T2",
      "Peach\n09:40\nTPE T1\n2h 30m\nNonstop\n13:10\nKIX T2"
    ],
    "price_class": [
      "Sat, Feb 21\nView\nSun, Feb 22\nView\nMon, Feb 23\nView\nTue, Feb 24\nUS$107\nWed, Feb 25\nView",
      "Sat, Feb 21\nView\nSun, Feb 22\nView\nMon, Feb 23\nView\nTue, Feb 24\nUS$107\nWed, Feb 25\nView",
      "Sat, Feb 21\nView\nSun, Feb 22\nView\nMon, Feb 23\nView\nTue, Feb 24\nUS$107\nWed, Feb 25\nView",
      "Sat, Feb 21\nView\nSun, Feb 22\nView\nMon, Feb 23\nView\nTue, Feb 24\nUS$107\nWed, Feb 25\nView",
      "Sat, Feb 21\nView\nSun, Feb 22\nView\nMon, Feb 23\nView\nTue, Feb 24\nUS$107\nWed, Feb 25\nView"
    ],
    "flight_class": [
      "Flights",
      "Taipei\nEdit\n2 adults\nEconomy\nFeb 24, 2026\nSat, Feb 21\nView\nSun, Feb 22\nView\nMon, Feb 23\nView\nTue, Feb 24\nUS$107\nWed, Feb 25\nView\nTue, Feb 17\nView\nWed, Feb 18\nView\nThu, Feb 19\nView\nFri, Feb 20\nView\nSat, Feb 21\nView\nSun, Feb 22\nView\nMon, Feb 23\nView\nTue, Feb 24\nUS$107\nWed, Feb 25\nView\nThu, Feb 26\nView\nFri, Feb 27\nView\nSat, Feb 28\nView\nSun, Mar 1\nView\nMon, Mar 2\nView\nTue, Mar 3\nView\nPrice graph\nRecommended\n Nonstop\n Checked baggage included\n Hide budget airlines\n Student tickets\n Carry-on baggage included\n Hide codeshare flights\nCO2e Lower emission flights\nShow More\nAlliance\nSkyTeam\nUS$262\nOneworld\nUS$264\nStar Alliance\nUS$286\nAirlines\nAll flights with the same airline\nAll airlines\nHK Express (8)\nUS$205\nJapan Airlines (7)\nUS$264\nPeach (4)\nUS$134\nHong Kong Airlines (4)\nUS$255\nCathay Pacific (4)\nUS$319\nShow More\nAlliance\nSkyTeam\nUS$262\nOneworld\nUS$264\nStar Alliance\nUS$286\nTimes\nDeparture time\n00:00–24:00\n00:00\n24:00\nArrival time\n00:00–24:00\n00:00\n24:00\nDuration\nAny\nStopover Duration\n1h–23h\n1h\n23h\nTotal Duration\n2h–29h 30m\n2h\n29h 30m\nStops\n1 stop or fewer\nUS$107\nStopover cities\nAny\nHong Kong\nUS$205\nTokyo\nUS$264\nManila\nUS$220\nBusan\nUS$283\nMacau\nUS$185\nDaegu\nUS$229\nSeoul\nUS$169\nJeju\nUS$210\nAirports\nAny\nDeparture Airport\nTSA\nTaipei Songshan Airport\nUS$264\nTPE\nTaiwan Taoyuan International Airport\nUS$107\nArrival Airport\nKIX\nKansai International Airport\nUS$107\nAircrafts\nAny\nLarge aircraft\nUS$107\nMidsize aircraft\nUS$134\nCabin\nEconomy\nEconomy\nEconomy/premium economy\nPremium economy\nBusiness/first\nBusiness\nFirst class\nRecommended\nUS$107\nNonstop first\nUS$107\nCheapest\nUS$107\nSort by\nCreate price alert\nCheapest\nCarry-on baggage included\n- 16% CO2e\nAirAsia X Berhad\n15:40\nTPE T1\n2h 40m\nNonstop\n19:20\nKIX T1\nUS$107\nTotal US$213\nSelect\nCarry-on baggage included\nThai Vietjet Air\n07:30\nTPE T1\n2h 30m\nNonstop\n11:00\nKIX T1\nUS$139\nTotal US$278\nSelect\nCarry-on baggage included\nPeach\n01:45\nTPE T1\n2h 25m\nNonstop\n05:10\nKIX T2\nUS$153\nTotal US$306\nSelect\nCarry-on baggage included\n- 18% CO2e\nPeach\n18:50\nTPE T1\n2h 25m\nNonstop\n22:15\nKIX T2\nUS$134\nTotal US$267\nSelect\nCarry-on baggage included\n- 18% CO2e\nPeach\n09:40\nTPE T1\n2h 30m\nNonstop\n13:10\nKIX T2\nUS$173\nTotal US$346\nSelect\nIncluded\n- 3% CO2e\nChina Airlines\n14:20\nTPE T2\n2h 30m\nNonstop\n17:50\nKIX T1\nUS$262\nTotal US$524\nSelect\nCarry-on baggage included\nTigerair Taiwan\n14:40\nTPE T1\n2h 15m\nNonstop\n17:55\nKIX T1\nUS$168\nTotal US$336\nSelect\nCarry-on baggage included\nPeach\n13:40\nTPE T1\n2h 25m\nNonstop\n17:05\nKIX T2\nUS$173\nTotal US$346\nSelect\nCarry-on baggage included\nJetstar Japan\n18:10\nTPE T1\n2h 30m\nNonstop\n21:40\nKIX T1\nUS$154\nTotal US$308\nSelect\nCarry-on baggage included\nThai Lion Air\n09:00\nTPE T1\n2h 30m\nNonstop\n12:30\nKIX T1\nUS$180\nTotal US$360\nSelect\nIncluded\n- 7% CO2e\nSTARLUX Airlines\n09:20\nTPE T1\n2h 30m\nNonstop\n12:50\nKIX T1\nUS$317\nTotal US$633\nSelect\nIncluded\n- 21% CO2e\nEVA Air\n06:30\nTPE T2\n2h 25m\nNonstop\n09:55\nKIX T1\nUS$296\nTotal US$592\nSelect\nIncluded\n- 20% CO2e\nEVA Air\n08:20\nTPE T2\n2h 35m\nNonstop\n11:55\nKIX T1\nUS$296\nTotal US$592\nSelect\nIncluded\nChina Airlines\n09:45\nTPE T2\n2h 35m\nNonstop\n13:20\nKIX T1\nUS$307\nTotal US$613\nSelect\nIncluded\n- 18% CO2e\nCathay Pacific\n11:15\nTPE T1\n2h 40m\nNonstop\n14:55\nKIX T1\nUS$319\nTotal US$638\nUS$292\nSelect\nIncluded\nHong Kong Airlines\n21:35\nTPE T2\n8h 40m\n3h in Hong Kong\n07:15\nKIX T1\n +1\nUS$255\nTotal US$510\nSelect\nFlights\n > \nFlights\n > \nTaipei to Flights\nBook flights from Taipei to on Trip.com\n\nFirst class | Business class | Economy class | Nonstop\n\nSearch for cheap flights from Taipei to on Trip.com. Trip.com provides the best real-time Taipei to airfares and flight deals available, featuring advanced flight planning tools like price alerts, deal finder fare calendars, and Taipei Flight + Hotel deals that make a vacation or tour more convenient and affordable.\n\nAward-winning\nSupport in approx. 30s\nRewards for booking",
      "Taipei\nEdit\n2 adults\nEconomy\nFeb 24, 2026\nSat, Feb 21\nView\nSun, Feb 22\nView\nMon, Feb 23\nView\nTue, Feb 24\nUS$107\nWed, Feb 25\nView",
      "DepartTue, Feb 24"
    ],
    "hotel_class": [
      "Hotels & Homes"
    ],
    "main": [
      "Cheap Flights, Airline Tickets & Plane Tickets | Trip.com\nAllow notifications\nDon't miss out! Be the first to find out the latest travel info.\nAllow\nTaipei\nEdit\n2 adults\nEconomy\nFeb 24, 2026\nSat, Feb 21\nView\nSun, Feb 22\nView\nMon, Feb 23\nView\nTue, Feb 24\nUS$107\nWed, Feb 25\nView\nTue, Feb 17\nView\nWed, Feb 18\nView\nThu, Feb 19\nView\nFri, Feb 20\nView\nSat, Feb 21\nView\nSun, Feb 22\nView\nMon, Feb 23\nView\nTue, Feb 24\nUS$107\nWed, Feb 25\nView\nThu, Feb 26\nView\nFri, Feb 27\nView\nSat, Feb 28\nView\nSun, Mar 1\nView\nMon, Mar 2\nView\nTue, Mar 3\nView\nPrice graph\nRecommended\n Nonstop\n Checked baggage included\n Hide budget airlines\n Student tickets\n Carry-on baggage included\n Hide codeshare flights\nCO2e Lower emission flights\nShow More\nAlliance\nSkyTeam\nUS$262\nOneworld\nUS$264\nStar Alliance\nUS$286\nAirlines\nAll flights with the same airline\nAll airlines\nHK Express (8)\nUS$205\nJapan Airlines (7)\nUS$264\nPeach (4)\nUS$134\nHong Kong Airlines (4)\nUS$255\nCathay Pacific (4)\nUS$319\nShow More\nAlliance\nSkyTeam\nUS$262\nOneworld\nUS$264\nStar Alliance\nUS$286\nTimes\nDeparture time\n00:00–24:00\n00:00\n24:00\nArrival time\n00:00–24:00\n00:00\n24:00\nDuration\nAny\nStopover Duration\n1h–23h\n1h\n23h\nTotal Duration\n2h–29h 30m\n2h\n29h 30m\nStops\n1 stop or fewer\nUS$107\nStopover cities\nAny\nHong Kong\nUS$205\nTokyo\nUS$264\nManila\nUS$220\nBusan\nUS$283\nMacau\nUS$185\nDaegu\nUS$229\nSeoul\nUS$169\nJeju\nUS$210\nAirports\nAny\nDeparture Airport\nTSA\nTaipei Songshan Airport\nUS$264\nTPE\nTaiwan Taoyuan International Airport\nUS$107\nArrival Airport\nKIX\nKansai International Airport\nUS$107\nAircrafts\nAny\nLarge aircraft\nUS$107\nMidsize aircraft\nUS$134\nCabin\nEconomy\nEconomy\nEconomy/premium economy\nPremium economy\nBusiness/first\nBusiness\nFirst class\nRecommended\nUS$107\nNonstop first\nUS$107\nCheapest\nUS$107\nSort by\nCreate price alert\nCheapest\nCarry-on baggage included\n- 16% CO2e\nAirAsia X Berhad\n15:40\nTPE T1\n2h 40m\nNonstop\n19:20\nKIX T1\nUS$107\nTotal US$213\nSelect\nCarry-on baggage included\nThai Vietjet Air\n07:30\nTPE T1\n2h 30m\nNonstop\n11:00\nKIX T1\nUS$139\nTotal US$278\nSelect\nCarry-on baggage included\nPeach\n01:45\nTPE T1\n2h 25m\nNonstop\n05:10\nKIX T2\nUS$153\nTotal US$306\nSelect\nCarry-on baggage included\n- 18% CO2e\nPeach\n18:50\nTPE T1\n2h 25m\nNonstop\n22:15\nKIX T2\nUS$134\nTotal US$267\nSelect\nCarry-on baggage included\n- 18% CO2e\nPeach\n09:40\nTPE T1\n2h 30m\nNonstop\n13:10\nKIX T2\nUS$173\nTotal US$346\nSelect\nIncluded\n- 3% CO2e\nChina Airlines\n14:20\nTPE T2\n2h 30m\nNonstop\n17:50\nKIX T1\nUS$262\nTotal US$524\nSelect\nCarry-on baggage included\nTigerair Taiwan\n14:40\nTPE T1\n2h 15m\nNonstop\n17:55\nKIX T1\nUS$168\nTotal US$336\nSelect\nCarry-on baggage included\nPeach\n13:40\nTPE T1\n2h 25m\nNonstop\n17:05\nKIX T2\nUS$173\nTotal US$346\nSelect\nCarry-on baggage included\nJetstar Japan\n18:10\nTPE T1\n2h 30m\nNonstop\n21:40\nKIX T1\nUS$154\nTotal US$308\nSelect\nCarry-on baggage included\nThai Lion Air\n09:00\nTPE T1\n2h 30m\nNonstop\n12:30\nKIX T1\nUS$180\nTotal US$360\nSelect\nIncluded\n- 7% CO2e\nSTARLUX Airlines\n09:20\nTPE T1\n2h 30m\nNonstop\n12:50\nKIX T1\nUS$317\nTotal US$633\nSelect\nIncluded\n- 21% CO2e\nEVA Air\n06:30\nTPE T2\n2h 25m\nNonstop\n09:55\nKIX T1\nUS$296\nTotal US$592\nSelect\nIncluded\n- 20% CO2e\nEVA Air\n08:20\nTPE T2\n2h 35m\nNonstop\n11:55\nKIX T1\nUS$296\nTotal US$592\nSelect\nIncluded\nChina Airlines\n09:45\nTPE T2\n2h 35m\nNonstop\n13:20\nKIX T1\nUS$307\nTotal US$613\nSelect\nIncluded\n- 18% CO2e\nCathay Pacific\n11:15\nTPE T1\n2h 40m\nNonstop\n14:55\nKIX T1\nUS$319\nTotal US$638\nUS$292\nSelect\nIncluded\nHong Kong Airlines\n21:35\nTPE T2\n8h 40m\n3h in Hong Kong\n07:15\nKIX T1\n +1\nUS$255\nTotal US$510\nSelect\nFlights\n > \nFlights\n > \nTaipei to Flights\nBook flights from Taipei to on Trip.com\n\nFirst class | Business class | Economy class | Nonstop\n\nSearch for cheap flights from Taipei to on Trip.com. Trip.com provides the best real-time Taipei to airfares and flight deals available, featuring advanced flight planning tools like price alerts, deal finder fare calendars, and Taipei Flight + Hotel deals that make a vacation or tour more convenient and affordable.\n\nAward-winning\nSupport in approx. 30s\nRewards for booking"
    ]
  }
}