{
  "url": "https://www.trip.com/flights/osaka-to-taipei/tickets-kix-tpe?dcity=kix&acity=tpe&ddate=2026-03-01&flighttype=ow&class=y&quantity=2",
  "scraped_at": "2026-02-05T14:28:24.170646",
  "title": "Cheap Flights, Airline Tickets & Plane Tickets | Trip.com",
  "raw_text": "Go to main content\nTheme Detection\nHotels & Homes\nFlights\nTrains\nCar services\nApp\nUSD\nCustomer support\nFind bookings\nSign in / Register\nCheap Flights, Airline Tickets & Plane Tickets | Trip.com\nAllow notifications\nDon't miss out! Be the first to find out the latest travel info.\nAllow\nTaipei\nEdit\n2 adults\nEconomy\nMar 1, 2026\nThu, Feb 26\nView\nFri, Feb 27\nView\nSat, Feb 28\nView\nSun, Mar 1\nUS$261\nMon, Mar 2\nView\nSun, Feb 22\nView\nMon, Feb 23\nView\nTue, Feb 24\nView\nWed, Feb 25\nView\nThu, Feb 26\nView\nFri, Feb 27\nView\nSat, Feb 28\nView\nSun, Mar 1\nUS$261\nMon, Mar 2\nView\nTue, Mar 3\nView\nWed, Mar 4\nView\nThu, Mar 5\nView\nFri, Mar 6\nView\nSat, Mar 7\nView\nSun, Mar 8\nView\nPrice graph\nRecommended\n Nonstop\n Checked baggage included\n Hide budget airlines\n Student tickets\n Carry-on baggage included\n Hide codeshare flights\nCO2e Lower emission flights\nShow More\nAlliance\nSkyTeam\nUS$269\nStar Alliance\nUS$371\nOneworld\nUS$1,537\nAirlines\nAll flights with the same airline\nAll airlines\nHK Express (18)\nUS$286\nHong Kong Airlines (13)\nUS$267\nPeach (4)\nUS$261\nChina Airlines (3)\nUS$417\nSpring Airlines (3)\nUS$273\nShow More\nAlliance\nSkyTeam\nUS$269\nStar Alliance\nUS$371\nOneworld\nUS$1,537\nTimes\nDeparture time\n00:00–24:00\n00:00\n24:00\nArrival time\n00:00–24:00\n00:00\n24:00\nDuration\nAny\nStopover Duration\n3h–24h\n3h\n24h\nTotal Duration\n3h–30h 30m\n3h\n30h 30m\nStops\n1 stop or fewer\nUS$261\nStopover cities\nAny\nHong Kong\nUS$267\nShanghai\nUS$273\nManila\nUS$380\nHanoi\nUS$408\nXiamen\nUS$269\nJeju\nUS$343\nHangzhou\nUS$371\nBusan\nUS$390\nSeoul\nUS$416\nShenzhen\nUS$447\nGuangzhou\nUS$474\nAirports\nAny\nDeparture Airport\nKIX\nKansai International Airport\nUS$261\nArrival Airport\nTPE\nTaiwan Taoyuan International Airport\nUS$261\nAircrafts\nAny\nLarge aircraft\nUS$342\nMidsize aircraft\nUS$261\nCabin\nEconomy\nEconomy\nEconomy/premium economy\nPremium economy\nBusiness/first\nBusiness\nFirst class\nDeparting for Taipei\nRecommended\nUS$261\nNonstop first\nUS$261\nCheapest\nUS$261\nSort by\nCreate price alert\nCheapest\nIncluded\n- 20% CO2e\nPeach\n07:15\nKIX T2\n3h 30m\nNonstop\n09:45\nTPE T1\nUS$261\nTotal US$522\nSelect\nCarry-on baggage included\n- 2% CO2e\nThai Vietjet Air\n12:00\nKIX T1\n3h 15m\nNonstop\n14:15\nTPE T1\nUS$320\nTotal US$639\nSelect\nIncluded\nPeach\n10:10\nKIX T2\n3h 35m\nNonstop\n12:45\nTPE T1\nUS$325\nTotal US$649\nSelect\nIncluded\n- 3% CO2e\nPeach\n22:00\nKIX T2\n3h 30m\nNonstop\n00:30\nTPE T1\n +1\nUS$325\nTotal US$649\nSelect\nCarry-on baggage included\nTigerair Taiwan\n11:30\nKIX T1\n3h 20m\nNonstop\n13:50\nTPE T1\nUS$335\nTotal US$670\nSelect\nCarry-on baggage included\n- 4% CO2e\nThai Lion Air\n13:30\nKIX T1\n3h 10m\nNonstop\n15:40\nTPE T1\nUS$347\nTotal US$693\nSelect\nIncluded\n- 20% CO2e\nPeach\n15:25\nKIX T2\n3h 30m\nNonstop\n17:55\nTPE T1\nUS$379\nTotal US$758\nSelect\nCarry-on baggage included\n- 18% CO2e\nAirAsia X Berhad\n20:45\nKIX T1\n3h 20m\nNonstop\n23:05\nTPE T1\nUS$395\nTotal US$790\nSelect\nIncluded\n- 10% CO2e\nSTARLUX Airlines\n14:00\nKIX T1\n3h 15m\nNonstop\n16:15\nTPE T1\nUS$601\nTotal US$1,202\nSelect\nCarry-on baggage included\n- 2% CO2e\nJetstar Japan\n14:50\nKIX T1\n3h 20m\nNonstop\n17:10\nTPE T1\nUS$627\nTotal US$1,254\nSelect\nIncluded\nJapan Airlines\noperated by China Airlines\n14:30\nKIX T1\n3h 15m\nNonstop\n16:45\nTPE T2\nUS$1,537\nTotal US$3,074\nSelect\nIncluded\nJapan Airlines\noperated by China Airlines\n19:00\nKIX T1\n3h 15m\nNonstop\n21:15\nTPE T2\nUS$1,537\nTotal US$3,074\nSelect\nIncluded\nHong Kong: Free Layover Tour\nHong Kong Airlines\n09:35\nKIX T1\n26h 15m\n19h 50m in Hong Kong\n10:50\nTPE T2\n +1\nUS$267\nTotal US$534\nSelect\nIncluded\nXiamen Airlines\n18:55\nKIX T1\n16h 5m\n10h 15m in Xiamen\n10:00\nTPE T2\n +1\nUS$269\nTotal US$538\nSelect\nCarry-on baggage included\nSpring Airlines\n15:00\nKIX T2\n20h 30m\n15h 25m in Shanghai\n10:30\nTPE T1\n +1\nUS$273\nTotal US$545\nSelect\nHong Kong: Free Layover Tour\nHK Express\n21:05\nKIX T1\n17h 5m\n10h 30m in Hong Kong\n13:10\nTPE T1\n +1\nUS$286\nTotal US$572\nSelect\nHong Kong: Free Layover Tour\nHK Express\n21:05\nKIX T1\n17h 50m\n11h 20m in Hong Kong\n13:55\nTPE T1\n +1\nUS$286\nTotal US$572\nSelect\nHK Express\n15:15\nKIX T1\n23h 40m\n17h 15m in Hong Kong\n13:55\nTPE T1\n +1\nUS$286\nTotal US$572\nSelect\nShow more results\nFlights\n > \nTaipei Flights\n > \nto Taipei Flights\nBook flights from to Taipei on Trip.com\n\nFirst class | Business class | Economy class | Nonstop\n\nSearch for cheap flights from to Taipei on Trip.com. Trip.com provides the best real-time to Taipei airfares and flight deals available, featuring advanced flight planning tools like price alerts, deal finder fare calendars, and Flight + Hotel deals that make a Taipei vacation or Taipei tour more convenient and affordable.\n\nAward-winning\nSupport in approx. 30s\nRewards for booking\nContact us\nCustomer support\nService guarantee\nMore service info\nAbout\nAbout Trip.com\nNews\nCareers\nTerms & Conditions\nPrivacy Statement\nAccessibility statement\nAbout Trip.com Group\nOther services\nInvestor relations\nTrip.com Rewards\nAffiliate program\nList your property\nAll hotels\nBecome a Supplier\nSecurity\nPayment methods\nOur partners\nContact Center\nof the year 2025\nCopyright © 2025 Trip.com Travel Singapore Pte. Ltd. All rights reserved\nSite Operator: Trip.com Travel Singapore Pte. Ltd.",
  "extracted": {
    "flight": {},
    "hotel": {},
    "price": {},
    "dates": {},
    "inclusions": [],
    "date_pricing": {}
  },
  "extracted_elements": {
    "flight_element": [
      "Peach\n07:15\nKIX T2\n3h 30m\nNonstop\n09:45\nTPE T1",
      "Thai Vietjet Air\n12:00\nKIX T1\n3h 15m\nNonstop\n14:15\nTPE T1",
      "Peach\n10:10\nKIX T2\n3h 35m\nNonstop\n12:45\nTPE T1",
      "Peach\n22:00\nKIX T2\n3h 30m\nNonstop\n00:30\nTPE T1\n +1",
      "Tigerair Taiwan\n11:30\nKIX T1\n3h 20m\nNonstop\n13:50\nTPE T1"
    ],
    "price_class": [
      "Thu, Feb 26\nView\nFri, Feb 27\nView\nSat, Feb 28\nView\nSun, Mar 1\nUS$261\nMon, Mar 2\nView",
      "Thu, Feb 26\nView\nFri, Feb 27\nView\nSat, Feb 28\nView\nSun, Mar 1\nUS$261\nMon, Mar 2\nView",
      "Thu, Feb 26\nView\nFri, Feb 27\nView\nSat, Feb 28\nView\nSun, Mar 1\nUS$261\nMon, Mar 2\nView",
      "Thu, Feb 26\nView\nFri, Feb 27\nView\nSat, Feb 28\nView\nSun, Mar 1\nUS$261\nMon, Mar 2\nView",
      "Thu, Feb 26\nView\nFri, Feb 27\nView\nSat, Feb 28\nView\nSun, Mar 1\nUS$261\nMon, Mar 2\nView"
    ],
    "flight_class": [
      "Flights",
      "Taipei\nEdit\n2 adults\nEconomy\nMar 1, 2026\nThu, Feb 26\nView\nFri, Feb 27\nView\nSat, Feb 28\nView\nSun, Mar 1\nUS$261\nMon, Mar 2\nView\nSun, Feb 22\nView\nMon, Feb 23\nView\nTue, Feb 24\nView\nWed, Feb 25\nView\nThu, Feb 26\nView\nFri, Feb 27\nView\nSat, Feb 28\nView\nSun, Mar 1\nUS$261\nMon, Mar 2\nView\nTue, Mar 3\nView\nWed, Mar 4\nView\nThu, Mar 5\nView\nFri, Mar 6\nView\nSat, Mar 7\nView\nSun, Mar 8\nView\nPrice graph\nRecommended\n Nonstop\n Checked baggage included\n Hide budget airlines\n Student tickets\n Carry-on baggage included\n Hide codeshare flights\nCO2e Lower emission flights\nShow More\nAlliance\nSkyTeam\nUS$269\nStar Alliance\nUS$371\nOneworld\nUS$1,537\nAirlines\nAll flights with the same airline\nAll airlines\nHK Express (18)\nUS$286\nHong Kong Airlines (13)\nUS$267\nPeach (4)\nUS$261\nChina Airlines (3)\nUS$417\nSpring Airlines (3)\nUS$273\nShow More\nAlliance\nSkyTeam\nUS$269\nStar Alliance\nUS$371\nOneworld\nUS$1,537\nTimes\nDeparture time\n00:00–24:00\n00:00\n24:00\nArrival time\n00:00–24:00\n00:00\n24:00\nDuration\nAny\nStopover Duration\n3h–24h\n3h\n24h\nTotal Duration\n3h–30h 30m\n3h\n30h 30m\nStops\n1 stop or fewer\nUS$261\nStopover cities\nAny\nHong Kong\nUS$267\nShanghai\nUS$273\nManila\nUS$380\nHanoi\nUS$408\nXiamen\nUS$269\nJeju\nUS$343\nHangzhou\nUS$371\nBusan\nUS$390\nSeoul\nUS$416\nShenzhen\nUS$447\nGuangzhou\nUS$474\nAirports\nAny\nDeparture Airport\nKIX\nKansai International Airport\nUS$261\nArrival Airport\nTPE\nTaiwan Taoyuan International Airport\nUS$261\nAircrafts\nAny\nLarge aircraft\nUS$342\nMidsize aircraft\nUS$261\nCabin\nEconomy\nEconomy\nEconomy/premium economy\nPremium economy\nBusiness/first\nBusiness\nFirst class\nDeparting for Taipei\nRecommended\nUS$261\nNonstop first\nUS$261\nCheapest\nUS$261\nSort by\nCreate price alert\nCheapest\nIncluded\n- 20% CO2e\nPeach\n07:15\nKIX T2\n3h 30m\nNonstop\n09:45\nTPE T1\nUS$261\nTotal US$522\nSelect\nCarry-on baggage included\n- 2% CO2e\nThai Vietjet Air\n12:00\nKIX T1\n3h 15m\nNonstop\n14:15\nTPE T1\nUS$320\nTotal US$639\nSelect\nIncluded\nPeach\n10:10\nKIX T2\n3h 35m\nNonstop\n12:45\nTPE T1\nUS$325\nTotal US$649\nSelect\nIncluded\n- 3% CO2e\nPeach\n22:00\nKIX T2\n3h 30m\nNonstop\n00:30\nTPE T1\n +1\nUS$325\nTotal US$649\nSelect\nCarry-on baggage included\nTigerair Taiwan\n11:30\nKIX T1\n3h 20m\nNonstop\n13:50\nTPE T1\nUS$335\nTotal US$670\nSelect\nCarry-on baggage included\n- 4% CO2e\nThai Lion Air\n13:30\nKIX T1\n3h 10m\nNonstop\n15:40\nTPE T1\nUS$347\nTotal US$693\nSelect\nIncluded\n- 20% CO2e\nPeach\n15:25\nKIX T2\n3h 30m\nNonstop\n17:55\nTPE T1\nUS$379\nTotal US$758\nSelect\nCarry-on baggage included\n- 18% CO2e\nAirAsia X Berhad\n20:45\nKIX T1\n3h 20m\nNonstop\n23:05\nTPE T1\nUS$395\nTotal US$790\nSelect\nIncluded\n- 10% CO2e\nSTARLUX Airlines\n14:00\nKIX T1\n3h 15m\nNonstop\n16:15\nTPE T1\nUS$601\nTotal US$1,202\nSelect\nCarry-on baggage included\n- 2% CO2e\nJetstar Japan\n14:50\nKIX T1\n3h 20m\nNonstop\n17:10\nTPE T1\nUS$627\nTotal US$1,254\nSelect\nIncluded\nJapan Airlines\noperated by China Airlines\n14:30\nKIX T1\n3h 15m\nNonstop\n16:45\nTPE T2\nUS$1,537\nTotal US$3,074\nSelect\nIncluded\nJapan Airlines\noperated by China Airlines\n19:00\nKIX T1\n3h 15m\nNonstop\n21:15\nTPE T2\nUS$1,537\nTotal US$3,074\nSelect\nIncluded\nHong Kong: Free Layover Tour\nHong Kong Airlines\n09:35\nKIX T1\n26h 15m\n19h 50m in Hong Kong\n10:50\nTPE T2\n +1\nUS$267\nTotal US$534\nSelect\nIncluded\nXiamen Airlines\n18:55\nKIX T1\n16h 5m\n10h 15m in Xiamen\n10:00\nTPE T2\n +1\nUS$269\nTotal US$538\nSelect\nCarry-on baggage included\nSpring Airlines\n15:00\nKIX T2\n20h 30m\n15h 25m in Shanghai\n10:30\nTPE T1\n +1\nUS$273\nTotal US$545\nSelect\nHong Kong: Free Layover Tour\nHK Express\n21:05\nKIX T1\n17h 5m\n10h 30m in Hong Kong\n13:10\nTPE T1\n +1\nUS$286\nTotal US$572\nSelect\nHong Kong: Free Layover Tour\nHK Express\n21:05\nKIX T1\n17h 50m\n11h 20m in Hong Kong\n13:55\nTPE T1\n +1\nUS$286\nTotal US$572\nSelect\nHK Express\n15:15\nKIX T1\n23h 40m\n17h 15m in Hong Kong\n13:55\nTPE T1\n +1\nUS$286\nTotal US$572\nSelect\nShow more results\nFlights\n > \nTaipei Flights\n > \nto Taipei Flights\nBook flights from to Taipei on Trip.com\n\nFirst class | Business class | Economy class | Nonstop\n\nSearch for cheap flights from to Taipei on Trip.com. Trip.com provides the best real-time to Taipei airfares and flight deals available, featuring advanced flight planning tools like price alerts, deal finder fare calendars, and Flight + Hotel deals that make a Taipei vacation or Taipei tour more convenient and affordable.\n\nAward-winning\nSupport in approx. 30s\nRewards for booking",
      "Taipei\nEdit\n2 adults\nEconomy\nMar 1, 2026\nThu, Feb 26\nView\nFri, Feb 27\nView\nSat, Feb 28\nView\nSun, Mar 1\nUS$261\nMon, Mar 2\nView",
      "DepartSun, Mar 1"
    ],
    "hotel_class": [
      "Hotels & Homes"
    ],
    "main": [
      "Cheap Flights, Airline Tickets & Plane Tickets | Trip.com\nAllow notifications\nDon't miss out! Be the first to find out the latest travel info.\nAllow\nTaipei\nEdit\n2 adults\nEconomy\nMar 1, 2026\nThu, Feb 26\nView\nFri, Feb 27\nView\nSat, Feb 28\nView\nSun, Mar 1\nUS$261\nMon, Mar 2\nView\nSun, Feb 22\nView\nMon, Feb 23\nView\nTue, Feb 24\nView\nWed, Feb 25\nView\nThu, Feb 26\nView\nFri, Feb 27\nView\nSat, Feb 28\nView\nSun, Mar 1\nUS$261\nMon, Mar 2\nView\nTue, Mar 3\nView\nWed, Mar 4\nView\nThu, Mar 5\nView\nFri, Mar 6\nView\nSat, Mar 7\nView\nSun, Mar 8\nView\nPrice graph\nRecommended\n Nonstop\n Checked baggage included\n Hide budget airlines\n Student tickets\n Carry-on baggage included\n Hide codeshare flights\nCO2e Lower emission flights\nShow More\nAlliance\nSkyTeam\nUS$269\nStar Alliance\nUS$371\nOneworld\nUS$1,537\nAirlines\nAll flights with the same airline\nAll airlines\nHK Express (18)\nUS$286\nHong Kong Airlines (13)\nUS$267\nPeach (4)\nUS$261\nChina Airlines (3)\nUS$417\nSpring Airlines (3)\nUS$273\nShow More\nAlliance\nSkyTeam\nUS$269\nStar Alliance\nUS$371\nOneworld\nUS$1,537\nTimes\nDeparture time\n00:00–24:00\n00:00\n24:00\nArrival time\n00:00–24:00\n00:00\n24:00\nDuration\nAny\nStopover Duration\n3h–24h\n3h\n24h\nTotal Duration\n3h–30h 30m\n3h\n30h 30m\nStops\n1 stop or fewer\nUS$261\nStopover cities\nAny\nHong Kong\nUS$267\nShanghai\nUS$273\nManila\nUS$380\nHanoi\nUS$408\nXiamen\nUS$269\nJeju\nUS$343\nHangzhou\nUS$371\nBusan\nUS$390\nSeoul\nUS$416\nShenzhen\nUS$447\nGuangzhou\nUS$474\nAirports\nAny\nDeparture Airport\nKIX\nKansai International Airport\nUS$261\nArrival Airport\nTPE\nTaiwan Taoyuan International Airport\nUS$261\nAircrafts\nAny\nLarge aircraft\nUS$342\nMidsize aircraft\nUS$261\nCabin\nEconomy\nEconomy\nEconomy/premium economy\nPremium economy\nBusiness/first\nBusiness\nFirst class\nDeparting for Taipei\nRecommended\nUS$261\nNonstop first\nUS$261\nCheapest\nUS$261\nSort by\nCreate price alert\nCheapest\nIncluded\n- 20% CO2e\nPeach\n07:15\nKIX T2\n3h 30m\nNonstop\n09:45\nTPE T1\nUS$261\nTotal US$522\nSelect\nCarry-on baggage included\n- 2% CO2e\nThai Vietjet Air\n12:00\nKIX T1\n3h 15m\nNonstop\n14:15\nTPE T1\nUS$320\nTotal US$639\nSelect\nIncluded\nPeach\n10:10\nKIX T2\n3h 35m\nNonstop\n12:45\nTPE T1\nUS$325\nTotal US$649\nSelect\nIncluded\n- 3% CO2e\nPeach\n22:00\nKIX T2\n3h 30m\nNonstop\n00:30\nTPE T1\n +1\nUS$325\nTotal US$649\nSelect\nCarry-on baggage included\nTigerair Taiwan\n11:30\nKIX T1\n3h 20m\nNonstop\n13:50\nTPE T1\nUS$335\nTotal US$670\nSelect\nCarry-on baggage included\n- 4% CO2e\nThai Lion Air\n13:30\nKIX T1\n3h 10m\nNonstop\n15:40\nTPE T1\nUS$347\nTotal US$693\nSelect\nIncluded\n- 20% CO2e\nPeach\n15:25\nKIX T2\n3h 30m\nNonstop\n17:55\nTPE T1\nUS$379\nTotal US$758\nSelect\nCarry-on baggage included\n- 18% CO2e\nAirAsia X Berhad\n20:45\nKIX T1\n3h 20m\nNonstop\n23:05\nTPE T1\nUS$395\nTotal US$790\nSelect\nIncluded\n- 10% CO2e\nSTARLUX Airlines\n14:00\nKIX T1\n3h 15m\nNonstop\n16:15\nTPE T1\nUS$601\nTotal US$1,202\nSelect\nCarry-on baggage included\n- 2% CO2e\nJetstar Japan\n14:50\nKIX T1\n3h 20m\nNonstop\n17:10\nTPE T1\nUS$627\nTotal US$1,254\nSelect\nIncluded\nJapan Airlines\noperated by China Airlines\n14:30\nKIX T1\n3h 15m\nNonstop\n16:45\nTPE T2\nUS$1,537\nTotal US$3,074\nSelect\nIncluded\nJapan Airlines\noperated by China Airlines\n19:00\nKIX T1\n3h 15m\nNonstop\n21:15\nTPE T2\nUS$1,537\nTotal US$3,074\nSelect\nIncluded\nHong Kong: Free Layover Tour\nHong Kong Airlines\n09:35\nKIX T1\n26h 15m\n19h 50m in Hong Kong\n10:50\nTPE T2\n +1\nUS$267\nTotal US$534\nSelect\nIncluded\nXiamen Airlines\n18:55\nKIX T1\n16h 5m\n10h 15m in Xiamen\n10:00\nTPE T2\n +1\nUS$269\nTotal US$538\nSelect\nCarry-on baggage included\nSpring Airlines\n15:00\nKIX T2\n20h 30m\n15h 25m in Shanghai\n10:30\nTPE T1\n +1\nUS$273\nTotal US$545\nSelect\nHong Kong: Free Layover Tour\nHK Express\n21:05\nKIX T1\n17h 5m\n10h 30m in Hong Kong\n13:10\nTPE T1\n +1\nUS$286\nTotal US$572\nSelect\nHong Kong: Free Layover Tour\nHK Express\n21:05\nKIX T1\n17h 50m\n11h 20m in Hong Kong\n13:55\nTPE T1\n +1\nUS$286\nTotal US$572\nSelect\nHK Express\n15:15\nKIX T1\n23h 40m\n17h 15m in Hong Kong\n13:55\nTPE T1\n +1\nUS$286\nTotal US$572\nSelect\nShow more results\nFlights\n > \nTaipei Flights\n > \nto Taipei Flights\nBook flights from to Taipei on Trip.com\n\nFirst class | Business class | Economy class | Nonstop\n\nSearch for cheap flights from to Taipei on Trip.com. Trip.com provides the best real-time to Taipei airfares and flight deals available, featuring advanced flight planning tools like price alerts, deal finder fare calendars, and Flight + Hotel deals that make a Taipei vacation or Taipei tour more convenient and affordable.\n\nAward-winning\nSupport in approx. 30s\nRewards for booking"
    ]
  }
}