{
  "url": "https://www.trip.com/flights/taipei-to-osaka/tickets-tpe-kix?dcity=tpe&acity=kix&ddate=2026-02-24&rdate=2026-02-28&flighttype=rt&class=y&lowprice=&quantity=2&searchboxarg=t",
  "scraped_at": "2026-02-05T10:10:55.006885",
  "title": "Cheap Flights, Airline Tickets & Plane Tickets | Trip.com",
  "raw_text": "Go to main content\nTheme Detection\nHotels & Homes\nFlights\nTrains\nCar services\nApp\nUSD\nCustomer support\nFind bookings\nSign in / Register\nCheap Flights, Airline Tickets & Plane Tickets | Trip.com\nAllow notifications\nDon't miss out! Be the first to find out the latest travel info.\nAllow\nTaipei\nEdit\n2 adults\nEconomy\nFeb 24, 2026 – Feb 28, 2026\nFeb 21–Feb 25\nView\nFeb 22–Feb 26\nView\nFeb 23–Feb 27\nView\nFeb 24–Feb 28\nUS$323\nFeb 25–Mar 1\nView\nFeb 17–Feb 21\nView\nFeb 18–Feb 22\nView\nFeb 19–Feb 23\nView\nFeb 20–Feb 24\nView\nFeb 21–Feb 25\nView\nFeb 22–Feb 26\nView\nFeb 23–Feb 27\nView\nFeb 24–Feb 28\nUS$323\nFeb 25–Mar 1\nView\nFeb 26–Mar 2\nView\nFeb 27–Mar 3\nView\nFeb 28–Mar 4\nView\nMar 1–Mar 5\nView\nMar 2–Mar 6\nView\nMar 3–Mar 7\nView\nPrice graph\nRecommended\n Nonstop\n Checked baggage included\n Hide budget airlines\n Student tickets\n Carry-on baggage included\n Hide codeshare flights\nCO2e Lower emission flights\nShow More\nAlliance\nSkyTeam\nUS$452\nStar Alliance\nUS$475\nOneworld\nUS$509\nAirlines\nAll flights with the same airline\nAll airlines\nCathay Pacific (17)\nUS$509\nHong Kong Airlines (14)\nUS$444\nAsiana Airlines (7)\nUS$525\nAll Nippon Airways (7)\nUS$903\nKorean Air (6)\nUS$525\nShow More\nAlliance\nSkyTeam\nUS$452\nStar Alliance\nUS$475\nOneworld\nUS$509\nTimes\nDeparture time\n00:00–24:00\n00:00\n24:00\nArrival time\n00:00–24:00\n00:00\n24:00\nDuration\nAny\nStopover Duration\n1h–23h\n1h\n23h\nTotal Duration\n2h–27h 30m\n2h\n27h 30m\nStops\n1 stop or fewer\nUS$323\nStopover cities\nAny\nHong Kong\nUS$442\nSeoul\nUS$404\nTokyo\nUS$623\nBusan\nUS$645\nHo Chi Minh City\nUS$659\nMacau\nUS$458\nDaegu\nUS$679\nManila\nUS$725\nShanghai\nUS$742\nJeju\nUS$663\nAirports\nAny\nDeparture Airport\nTSA\nTaipei Songshan Airport\nUS$903\nTPE\nTaiwan Taoyuan International Airport\nUS$323\nArrival Airport\nKIX\nKansai International Airport\nUS$323\nAircrafts\nAny\nLarge aircraft\nUS$404\nMidsize aircraft\nUS$323\nCabin\nEconomy\nEconomy\nEconomy/premium economy\nPremium economy\nBusiness/first\nBusiness\nFirst class\n1.\nNonstop first\nUS$323\nRecommended\nUS$323\nCheapest\nUS$323\nSort by\nCreate price alert\nCheapest\nCarry-on baggage included\n- 18% CO2e\nPeach\n18:50\nTPE T1\n2h 25m\nNonstop\n22:15\nKIX T2\nUS$323\nRound-trip\nSelect\nCarry-on baggage included\nThai Vietjet Air\n07:30\nTPE T1\n2h 30m\nNonstop\n11:00\nKIX T1\nUS$329\nRound-trip\nSelect\nCarry-on baggage included\nPeach\n01:45\nTPE T1\n2h 25m\nNonstop\n05:10\nKIX T2\nUS$343\nRound-trip\nSelect\nCarry-on baggage included\nJetstar Japan\n18:10\nTPE T1\n2h 30m\nNonstop\n21:40\nKIX T1\nUS$343\nRound-trip\nSelect\nCarry-on baggage included\nTigerair Taiwan\n14:40\nTPE T1\n2h 15m\nNonstop\n17:55\nKIX T1\nUS$358\nRound-trip\nSelect\nCarry-on baggage included\n- 18% CO2e\nPeach\n09:40\nTPE T1\n2h 30m\nNonstop\n13:10\nKIX T2\nUS$362\nRound-trip\nSelect\nCarry-on baggage included\nPeach\n13:40\nTPE T1\n2h 25m\nNonstop\n17:05\nKIX T2\nUS$362\nRound-trip\nSelect\nCarry-on baggage included\nThai Lion Air\n09:00\nTPE T1\n2h 30m\nNonstop\n12:30\nKIX T1\nUS$369\nRound-trip\nSelect\nIncluded\n- 21% CO2e\nEVA Air\n06:30\nTPE T2\n2h 25m\nNonstop\n09:55\nKIX T1\nUS$485\nRound-trip\nSelect\nIncluded\n- 20% CO2e\nEVA Air\n08:20\nTPE T2\n2h 35m\nNonstop\n11:55\nKIX T1\nUS$485\nRound-trip\nSelect\nIncluded\nChina Airlines\n09:45\nTPE T2\n2h 35m\nNonstop\n13:20\nKIX T1\nUS$498\nRound-trip\nSelect\nIncluded\n- 7% CO2e\nSTARLUX Airlines\n09:20\nTPE T1\n2h 30m\nNonstop\n12:50\nKIX T1\nUS$505\nRound-trip\nSelect\nIncluded\n- 11% CO2e\nCathay Pacific\n11:15\nTPE T1\n2h 40m\nNonstop\n14:55\nKIX T1\nUS$509\nRound-trip\nSelect\nIncluded\nSTARLUX Airlines\n07:40\nTPE T1\n2h 30m\nNonstop\n11:10\nKIX T1\nUS$528\nRound-trip\nSelect\nIncluded\nAll Nippon Airways\noperated by EVA Air\n06:30\nTPE T2\n2h 25m\nNonstop\n09:55\nKIX T1\nUS$1,084\nRound-trip\nSelect\nIncluded\nAll Nippon Airways\noperated by EVA Air\n08:20\nTPE T2\n2h 35m\nNonstop\n11:55\nKIX T1\nUS$1,084\nRound-trip\nSelect\nIncluded\nAll Nippon Airways\noperated by EVA Air\n13:30\nTPE T2\n2h 25m\nNonstop\n16:55\nKIX T1\nUS$1,084\nRound-trip\nSelect\nIncluded\nJapan Airlines\noperated by China Airlines\n08:05\nTPE T2\n2h 30m\nNonstop\n11:35\nKIX T1\nUS$1,148\nRound-trip\nSelect\nIncluded\nJapan Airlines\noperated by China Airlines\n09:45\nTPE T2\n2h 35m\nNonstop\n13:20\nKIX T1\nUS$1,148\nRound-trip\nSelect\nIncluded\nJapan Airlines\noperated by China Airlines\n14:20\nTPE T2\n2h 30m\nNonstop\n17:50\nKIX T1\nUS$1,148\nRound-trip\nSelect\nFlights with transfers\nIncluded\nJin Air\n12:40\nTPE T1\n27h 10m\n22h 55m in Seoul\n16:50\nKIX T1\n +1\nUS$404\nRound-trip\nSelect\nHK Express\n21:15\nTPE T1\n16h 5m\n10h 30m in Hong Kong\n14:20\nKIX T1\n +1\nUS$442\nRound-trip\nSelect\nHK Express\n21:15\nTPE T1\n18h\n12h 25m in Hong Kong\n16:15\nKIX T1\n +1\nUS$442\nRound-trip\nSelect\nHK Express\n21:15\nTPE T1\n21h 55m\n16h 20m in Hong Kong\n20:10\nKIX T1\n +1\nUS$442\nRound-trip\nSelect\nIncluded\nHong Kong Airlines\n21:35\nTPE T2\n8h 40m\n3h in Hong Kong\n07:15\nKIX T1\n +1\nUS$444\nRound-trip\nSelect\nIncluded\nAir Macau\n22:20\nTPE T1\n13h 25m\n7h 55m in Macau\n12:45\nKIX T1\n +1\nUS$458\nRound-trip\nSelect\n<9 left\nIncluded\nHong Kong Airlines\n21:35\nTPE T2\n15h 30m\n9h 50m in Hong Kong\n14:05\nKIX T1\n +1\nUS$460\nRound-trip\nSelect\n<9 left\nIncluded\nHong Kong Airlines\n21:35\nTPE T2\n17h 30m\n11h 40m in Hong Kong\n16:05\nKIX T1\n +1\nUS$460\nRound-trip\nSelect\n<9 left\nIncluded\nHong Kong Airlines\n21:35\nTPE T2\n20h 30m\n14h 50m in Hong Kong\n19:05\nKIX T1\n +1\nUS$460\nRound-trip\nSelect\n<9 left\nIncluded\nHong Kong Airlines\n19:20\nTPE T2\n10h 55m\n5h 20m in Hong Kong\n07:15\nKIX T1\n +1\nUS$499\nRound-trip\nSelect\n<9 left\nIncluded\nHong Kong Airlines\n16:30\nTPE T2\n13h 45m\n8h in Hong Kong\n07:15\nKIX T1\n +1\nUS$499\nRound-trip\nSelect\n<9 left\nIncluded\nHong Kong Airlines\n19:20\nTPE T2\n17h 45m\n12h 10m in Hong Kong\n14:05\nKIX T1\n +1\nUS$499\nRound-trip\nSelect\nIncluded\nHong Kong: Free Layover Tour\nHong Kong Airlines\n11:50\nTPE T2\n18h 25m\n12h 45m in Hong Kong\n07:15\nKIX T1\n +1\nUS$499\nRound-trip\nSelect\nIncluded\nHong Kong Airlines\n19:20\nTPE T2\n19h 45m\n14h in Hong Kong\n16:05\nKIX T1\n +1\nUS$499\nRound-trip\nSelect\nIncluded\nHong Kong Airlines\n16:30\nTPE T2\n20h 35m\n14h 50m in Hong Kong\n14:05\nKIX T1\n +1\nUS$504\nRound-trip\nSelect\nIncluded\nHong Kong Airlines\n19:20\nTPE T2\n22h 45m\n17h 10m in Hong Kong\n19:05\nKIX T1\n +1\nUS$504\nRound-trip\nSelect\nIncluded\nKorean Air, Asiana Airlines\n19:25\nTPE T1\n24h 30m\n20h 10m in Seoul\n20:55\nKIX T1\n +1\nUS$640\nRound-trip\nSelect\nIncluded\nJin Air\n02:40\nTPE T1\n11h 40m\n8h in Busan\n15:20\nKIX T1\nUS$645\nRound-trip\nSelect\nChecked baggage included\nVietJet Air\n19:00\nTPE T1\n12h 30m\n3h 55m in Ho Chi Minh City\n08:30\nKIX T1\n +1\nUS$659\nRound-trip\nSelect\nChecked baggage included\nVietJet Air\n06:25\nTPE T1\n25h 5m\n16h 30m in Ho Chi Minh City\n08:30\nKIX T1\n +1\nUS$659\nRound-trip\nSelect\nIncluded\nT'Way Air\n14:25\nTPE T1\n26h 15m\n22h 35m in Jeju\n17:40\nKIX T1\n +1\nUS$663\nRound-trip\nSelect\nIncluded\nJin Air\n02:40\nTPE T1\n6h 20m\n2h 40m in Busan\n10:00\nKIX T1\nUS$672\nRound-trip\nSelect\nIncluded\nT'Way Air\n01:55\nTPE T1\n13h\n9h 5m in Daegu\n15:55\nKIX T1\nUS$679\nRound-trip\nSelect\nFlights\n > \nFlights\n > \nTaipei to Flights\nBook flights from Taipei to on Trip.com\n\nFirst class | Business class | Economy class | Nonstop\n\nSearch for cheap flights from Taipei to on Trip.com. Trip.com provides the best real-time Taipei to airfares and flight deals available, featuring advanced flight planning tools like price alerts, deal finder fare calendars, and Taipei Flight + Hotel deals that make a vacation or tour more convenient and affordable.\n\nAward-winning\nSupport in approx. 30s\nRewards for booking\nContact us\nCustomer support\nService guarantee\nMore service info\nAbout\nAbout Trip.com\nNews\nCareers\nTerms & Conditions\nPrivacy Statement\nAccessibility statement\nAbout Trip.com Group\nOther services\nInvestor relations\nTrip.com Rewards\nAffiliate program\nList your property\nAll hotels\nBecome a Supplier\nSecurity\nPayment methods\nOur partners\nContact Center\nof the year 2025\nCopyright © 2025 Trip.com Travel Singapore Pte. Ltd. All rights reserved\nSite Operator: Trip.com Travel Singapore Pte. Ltd.",
  "extracted": {
    "flight": {},
    "hotel": {},
    "price": {},
    "dates": {},
    "inclusions": [],
    "date_pricing": {}
  },
  "extracted_elements": {
    "flight_element": [
      "Peach\n18:50\nTPE T1\n2h 25m\nNonstop\n22:15\nKIX T2",
      "Thai Vietjet Air\n07:30\nTPE T1\n2h 30m\nNonstop\n11:00\nKIX T1",
      "Peach\n01:45\nTPE T1\n2h 25m\nNonstop\n05:10\nKIX T2",
      "Jetstar Japan\n18:10\nTPE T1\n2h 30m\nNonstop\n21:40\nKIX T1",
      "Tigerair Taiwan\n14:40\nTPE T1\n2h 15m\nNonstop\n17:55\nKIX T1"
    ],
    "price_class": [
      "Feb 21–Feb 25\nView\nFeb 22–Feb 26\nView\nFeb 23–Feb 27\nView\nFeb 24–Feb 28\nUS$323\nFeb 25–Mar 1\nView",
      "Feb 21–Feb 25\nView\nFeb 22–Feb 26\nView\nFeb 23–Feb 27\nView\nFeb 24–Feb 28\nUS$323\nFeb 25–Mar 1\nView",
      "Feb 21–Feb 25\nView\nFeb 22–Feb 26\nView\nFeb 23–Feb 27\nView\nFeb 24–Feb 28\nUS$323\nFeb 25–Mar 1\nView",
      "Feb 21–Feb 25\nView\nFeb 22–Feb 26\nView\nFeb 23–Feb 27\nView\nFeb 24–Feb 28\nUS$323\nFeb 25–Mar 1\nView",
      "Feb 21–Feb 25\nView\nFeb 22–Feb 26\nView\nFeb 23–Feb 27\nView\nFeb 24–Feb 28\nUS$323\nFeb 25–Mar 1\nView"
    ],
    "flight_class": [
      "Flights",
      "Taipei\nEdit\n2 adults\nEconomy\nFeb 24, 2026 – Feb 28, 2026\nFeb 21–Feb 25\nView\nFeb 22–Feb 26\nView\nFeb 23–Feb 27\nView\nFeb 24–Feb 28\nUS$323\nFeb 25–Mar 1\nView\nFeb 17–Feb 21\nView\nFeb 18–Feb 22\nView\nFeb 19–Feb 23\nView\nFeb 20–Feb 24\nView\nFeb 21–Feb 25\nView\nFeb 22–Feb 26\nView\nFeb 23–Feb 27\nView\nFeb 24–Feb 28\nUS$323\nFeb 25–Mar 1\nView\nFeb 26–Mar 2\nView\nFeb 27–Mar 3\nView\nFeb 28–Mar 4\nView\nMar 1–Mar 5\nView\nMar 2–Mar 6\nView\nMar 3–Mar 7\nView\nPrice graph\nRecommended\n Nonstop\n Checked baggage included\n Hide budget airlines\n Student tickets\n Carry-on baggage included\n Hide codeshare flights\nCO2e Lower emission flights\nShow More\nAlliance\nSkyTeam\nUS$452\nStar Alliance\nUS$475\nOneworld\nUS$509\nAirlines\nAll flights with the same airline\nAll airlines\nCathay Pacific (17)\nUS$509\nHong Kong Airlines (14)\nUS$444\nAsiana Airlines (7)\nUS$525\nAll Nippon Airways (7)\nUS$903\nKorean Air (6)\nUS$525\nShow More\nAlliance\nSkyTeam\nUS$452\nStar Alliance\nUS$475\nOneworld\nUS$509\nTimes\nDeparture time\n00:00–24:00\n00:00\n24:00\nArrival time\n00:00–24:00\n00:00\n24:00\nDuration\nAny\nStopover Duration\n1h–23h\n1h\n23h\nTotal Duration\n2h–27h 30m\n2h\n27h 30m\nStops\n1 stop or fewer\nUS$323\nStopover cities\nAny\nHong Kong\nUS$442\nSeoul\nUS$404\nTokyo\nUS$623\nBusan\nUS$645\nHo Chi Minh City\nUS$659\nMacau\nUS$458\nDaegu\nUS$679\nManila\nUS$725\nShanghai\nUS$742\nJeju\nUS$663\nAirports\nAny\nDeparture Airport\nTSA\nTaipei Songshan Airport\nUS$903\nTPE\nTaiwan Taoyuan International Airport\nUS$323\nArrival Airport\nKIX\nKansai International Airport\nUS$323\nAircrafts\nAny\nLarge aircraft\nUS$404\nMidsize aircraft\nUS$323\nCabin\nEconomy\nEconomy\nEconomy/premium economy\nPremium economy\nBusiness/first\nBusiness\nFirst class\n1.\nNonstop first\nUS$323\nRecommended\nUS$323\nCheapest\nUS$323\nSort by\nCreate price alert\nCheapest\nCarry-on baggage included\n- 18% CO2e\nPeach\n18:50\nTPE T1\n2h 25m\nNonstop\n22:15\nKIX T2\nUS$323\nRound-trip\nSelect\nCarry-on baggage included\nThai Vietjet Air\n07:30\nTPE T1\n2h 30m\nNonstop\n11:00\nKIX T1\nUS$329\nRound-trip\nSelect\nCarry-on baggage included\nPeach\n01:45\nTPE T1\n2h 25m\nNonstop\n05:10\nKIX T2\nUS$343\nRound-trip\nSelect\nCarry-on baggage included\nJetstar Japan\n18:10\nTPE T1\n2h 30m\nNonstop\n21:40\nKIX T1\nUS$343\nRound-trip\nSelect\nCarry-on baggage included\nTigerair Taiwan\n14:40\nTPE T1\n2h 15m\nNonstop\n17:55\nKIX T1\nUS$358\nRound-trip\nSelect\nCarry-on baggage included\n- 18% CO2e\nPeach\n09:40\nTPE T1\n2h 30m\nNonstop\n13:10\nKIX T2\nUS$362\nRound-trip\nSelect\nCarry-on baggage included\nPeach\n13:40\nTPE T1\n2h 25m\nNonstop\n17:05\nKIX T2\nUS$362\nRound-trip\nSelect\nCarry-on baggage included\nThai Lion Air\n09:00\nTPE T1\n2h 30m\nNonstop\n12:30\nKIX T1\nUS$369\nRound-trip\nSelect\nIncluded\n- 21% CO2e\nEVA Air\n06:30\nTPE T2\n2h 25m\nNonstop\n09:55\nKIX T1\nUS$485\nRound-trip\nSelect\nIncluded\n- 20% CO2e\nEVA Air\n08:20\nTPE T2\n2h 35m\nNonstop\n11:55\nKIX T1\nUS$485\nRound-trip\nSelect\nIncluded\nChina Airlines\n09:45\nTPE T2\n2h 35m\nNonstop\n13:20\nKIX T1\nUS$498\nRound-trip\nSelect\nIncluded\n- 7% CO2e\nSTARLUX Airlines\n09:20\nTPE T1\n2h 30m\nNonstop\n12:50\nKIX T1\nUS$505\nRound-trip\nSelect\nIncluded\n- 11% CO2e\nCathay Pacific\n11:15\nTPE T1\n2h 40m\nNonstop\n14:55\nKIX T1\nUS$509\nRound-trip\nSelect\nIncluded\nSTARLUX Airlines\n07:40\nTPE T1\n2h 30m\nNonstop\n11:10\nKIX T1\nUS$528\nRound-trip\nSelect\nIncluded\nAll Nippon Airways\noperated by EVA Air\n06:30\nTPE T2\n2h 25m\nNonstop\n09:55\nKIX T1\nUS$1,084\nRound-trip\nSelect\nIncluded\nAll Nippon Airways\noperated by EVA Air\n08:20\nTPE T2\n2h 35m\nNonstop\n11:55\nKIX T1\nUS$1,084\nRound-trip\nSelect\nIncluded\nAll Nippon Airways\noperated by EVA Air\n13:30\nTPE T2\n2h 25m\nNonstop\n16:55\nKIX T1\nUS$1,084\nRound-trip\nSelect\nIncluded\nJapan Airlines\noperated by China Airlines\n08:05\nTPE T2\n2h 30m\nNonstop\n11:35\nKIX T1\nUS$1,148\nRound-trip\nSelect\nIncluded\nJapan Airlines\noperated by China Airlines\n09:45\nTPE T2\n2h 35m\nNonstop\n13:20\nKIX T1\nUS$1,148\nRound-trip\nSelect\nIncluded\nJapan Airlines\noperated by China Airlines\n14:20\nTPE T2\n2h 30m\nNonstop\n17:50\nKIX T1\nUS$1,148\nRound-trip\nSelect\nFlights with transfers\nIncluded\nJin Air\n12:40\nTPE T1\n27h 10m\n22h 55m in Seoul\n16:50\nKIX T1\n +1\nUS$404\nRound-trip\nSelect\nHK Express\n21:15\nTPE T1\n16h 5m\n10h 30m in Hong Kong\n14:20\nKIX T1\n +1\nUS$442\nRound-trip\nSelect\nHK Express\n21:15\nTPE T1\n18h\n12h 25m in Hong Kong\n16:15\nKIX T1\n +1\nUS$442\nRound-trip\nSelect\nHK Express\n21:15\nTPE T1\n21h 55m\n16h 20m in Hong Kong\n20:10\nKIX T1\n +1\nUS$442\nRound-trip\nSelect\nIncluded\nHong Kong Airlines\n21:35\nTPE T2\n8h 40m\n3h in Hong Kong\n07:15\nKIX T1\n +1\nUS$444\nRound-trip\nSelect\nIncluded\nAir Macau\n22:20\nTPE T1\n13h 25m\n7h 55m in Macau\n12:45\nKIX T1\n +1\nUS$458\nRound-trip\nSelect\n<9 left\nIncluded\nHong Kong Airlines\n21:35\nTPE T2\n15h 30m\n9h 50m in Hong Kong\n14:05\nKIX T1\n +1\nUS$460\nRound-trip\nSelect\n<9 left\nIncluded\nHong Kong Airlines\n21:35\nTPE T2\n17h 30m\n11h 40m in Hong Kong\n16:05\nKIX T1\n +1\nUS$460\nRound-trip\nSelect\n<9 left\nIncluded\nHong Kong Airlines\n21:35\nTPE T2\n20h 30m\n14h 50m in Hong Kong\n19:05\nKIX T1\n +1\nUS$460\nRound-trip\nSelect\n<9 left\nIncluded\nHong Kong Airlines\n19:20\nTPE T2\n10h 55m\n5h 20m in Hong Kong\n07:15\nKIX T1\n +1\nUS$499\nRound-trip\nSelect\n<9 left\nIncluded\nHong Kong Airlines\n16:30\nTPE T2\n13h 45m\n8h in Hong Kong\n07:15\nKIX T1\n +1\nUS$499\nRound-trip\nSelect\n<9 left\nIncluded\nHong Kong Airlines\n19:20\nTPE T2\n17h 45m\n12h 10m in Hong Kong\n14:05\nKIX T1\n +1\nUS$499\nRound-trip\nSelect\nIncluded\nHong Kong: Free Layover Tour\nHong Kong Airlines\n11:50\nTPE T2\n18h 25m\n12h 45m in Hong Kong\n07:15\nKIX T1\n +1\nUS$499\nRound-trip\nSelect\nIncluded\nHong Kong Airlines\n19:20\nTPE T2\n19h 45m\n14h in Hong Kong\n16:05\nKIX T1\n +1\nUS$499\nRound-trip\nSelect\nIncluded\nHong Kong Airlines\n16:30\nTPE T2\n20h 35m\n14h 50m in Hong Kong\n14:05\nKIX T1\n +1\nUS$504\nRound-trip\nSelect\nIncluded\nHong Kong Airlines\n19:20\nTPE T2\n22h 45m\n17h 10m in Hong Kong\n19:05\nKIX T1\n +1\nUS$504\nRound-trip\nSelect\nIncluded\nKorean Air, Asiana Airlines\n19:25\nTPE T1\n24h 30m\n20h 10m in Seoul\n20:55\nKIX T1\n +1\nUS$640\nRound-trip\nSelect\nIncluded\nJin Air\n02:40\nTPE T1\n11h 40m\n8h in Busan\n15:20\nKIX T1\nUS$645\nRound-trip\nSelect\nChecked baggage included\nVietJet Air\n19:00\nTPE T1\n12h 30m\n3h 55m in Ho Chi Minh City\n08:30\nKIX T1\n +1\nUS$659\nRound-trip\nSelect\nChecked baggage included\nVietJet Air\n06:25\nTPE T1\n25h 5m\n16h 30m in Ho Chi Minh City\n08:30\nKIX T1\n +1\nUS$659\nRound-trip\nSelect\nIncluded\nT'Way Air\n14:25\nTPE T1\n26h 15m\n22h 35m in Jeju\n17:40\nKIX T1\n +1\nUS$663\nRound-trip\nSelect\nIncluded\nJin Air\n02:40\nTPE T1\n6h 20m\n2h 40m in Busan\n10:00\nKIX T1\nUS$672\nRound-trip\nSelect\nIncluded\nT'Way Air\n01:55\nTPE T1\n13h\n9h 5m in Daegu\n15:55\nKIX T1\nUS$679\nRound-trip\nSelect\nFlights\n > \nFlights\n > \nTaipei to Flights\nBook flights from Taipei to on Trip.com\n\nFirst class | Business class | Economy class | Nonstop\n\nSearch for cheap flights from Taipei to on Trip.com. Trip.com provides the best real-time Taipei to airfares and flight deals available, featuring advanced flight planning tools like price alerts, deal finder fare calendars, and Taipei Flight + Hotel deals that make a vacation or tour more convenient and affordable.\n\nAward-winning\nSupport in approx. 30s\nRewards for booking",
      "Taipei\nEdit\n2 adults\nEconomy\nFeb 24, 2026 – Feb 28, 2026\nFeb 21–Feb 25\nView\nFeb 22–Feb 26\nView\nFeb 23–Feb 27\nView\nFeb 24–Feb 28\nUS$323\nFeb 25–Mar 1\nView",
      "DepartTue, Feb 24ReturnSat, Feb 28"
    ],
    "hotel_class": [
      "Hotels & Homes"
    ],
    "main": [
      "Cheap Flights, Airline Tickets & Plane Tickets | Trip.com\nAllow notifications\nDon't miss out! Be the first to find out the latest travel info.\nAllow\nTaipei\nEdit\n2 adults\nEconomy\nFeb 24, 2026 – Feb 28, 2026\nFeb 21–Feb 25\nView\nFeb 22–Feb 26\nView\nFeb 23–Feb 27\nView\nFeb 24–Feb 28\nUS$323\nFeb 25–Mar 1\nView\nFeb 17–Feb 21\nView\nFeb 18–Feb 22\nView\nFeb 19–Feb 23\nView\nFeb 20–Feb 24\nView\nFeb 21–Feb 25\nView\nFeb 22–Feb 26\nView\nFeb 23–Feb 27\nView\nFeb 24–Feb 28\nUS$323\nFeb 25–Mar 1\nView\nFeb 26–Mar 2\nView\nFeb 27–Mar 3\nView\nFeb 28–Mar 4\nView\nMar 1–Mar 5\nView\nMar 2–Mar 6\nView\nMar 3–Mar 7\nView\nPrice graph\nRecommended\n Nonstop\n Checked baggage included\n Hide budget airlines\n Student tickets\n Carry-on baggage included\n Hide codeshare flights\nCO2e Lower emission flights\nShow More\nAlliance\nSkyTeam\nUS$452\nStar Alliance\nUS$475\nOneworld\nUS$509\nAirlines\nAll flights with the same airline\nAll airlines\nCathay Pacific (17)\nUS$509\nHong Kong Airlines (14)\nUS$444\nAsiana Airlines (7)\nUS$525\nAll Nippon Airways (7)\nUS$903\nKorean Air (6)\nUS$525\nShow More\nAlliance\nSkyTeam\nUS$452\nStar Alliance\nUS$475\nOneworld\nUS$509\nTimes\nDeparture time\n00:00–24:00\n00:00\n24:00\nArrival time\n00:00–24:00\n00:00\n24:00\nDuration\nAny\nStopover Duration\n1h–23h\n1h\n23h\nTotal Duration\n2h–27h 30m\n2h\n27h 30m\nStops\n1 stop or fewer\nUS$323\nStopover cities\nAny\nHong Kong\nUS$442\nSeoul\nUS$404\nTokyo\nUS$623\nBusan\nUS$645\nHo Chi Minh City\nUS$659\nMacau\nUS$458\nDaegu\nUS$679\nManila\nUS$725\nShanghai\nUS$742\nJeju\nUS$663\nAirports\nAny\nDeparture Airport\nTSA\nTaipei Songshan Airport\nUS$903\nTPE\nTaiwan Taoyuan International Airport\nUS$323\nArrival Airport\nKIX\nKansai International Airport\nUS$323\nAircrafts\nAny\nLarge aircraft\nUS$404\nMidsize aircraft\nUS$323\nCabin\nEconomy\nEconomy\nEconomy/premium economy\nPremium economy\nBusiness/first\nBusiness\nFirst class\n1.\nNonstop first\nUS$323\nRecommended\nUS$323\nCheapest\nUS$323\nSort by\nCreate price alert\nCheapest\nCarry-on baggage included\n- 18% CO2e\nPeach\n18:50\nTPE T1\n2h 25m\nNonstop\n22:15\nKIX T2\nUS$323\nRound-trip\nSelect\nCarry-on baggage included\nThai Vietjet Air\n07:30\nTPE T1\n2h 30m\nNonstop\n11:00\nKIX T1\nUS$329\nRound-trip\nSelect\nCarry-on baggage included\nPeach\n01:45\nTPE T1\n2h 25m\nNonstop\n05:10\nKIX T2\nUS$343\nRound-trip\nSelect\nCarry-on baggage included\nJetstar Japan\n18:10\nTPE T1\n2h 30m\nNonstop\n21:40\nKIX T1\nUS$343\nRound-trip\nSelect\nCarry-on baggage included\nTigerair Taiwan\n14:40\nTPE T1\n2h 15m\nNonstop\n17:55\nKIX T1\nUS$358\nRound-trip\nSelect\nCarry-on baggage included\n- 18% CO2e\nPeach\n09:40\nTPE T1\n2h 30m\nNonstop\n13:10\nKIX T2\nUS$362\nRound-trip\nSelect\nCarry-on baggage included\nPeach\n13:40\nTPE T1\n2h 25m\nNonstop\n17:05\nKIX T2\nUS$362\nRound-trip\nSelect\nCarry-on baggage included\nThai Lion Air\n09:00\nTPE T1\n2h 30m\nNonstop\n12:30\nKIX T1\nUS$369\nRound-trip\nSelect\nIncluded\n- 21% CO2e\nEVA Air\n06:30\nTPE T2\n2h 25m\nNonstop\n09:55\nKIX T1\nUS$485\nRound-trip\nSelect\nIncluded\n- 20% CO2e\nEVA Air\n08:20\nTPE T2\n2h 35m\nNonstop\n11:55\nKIX T1\nUS$485\nRound-trip\nSelect\nIncluded\nChina Airlines\n09:45\nTPE T2\n2h 35m\nNonstop\n13:20\nKIX T1\nUS$498\nRound-trip\nSelect\nIncluded\n- 7% CO2e\nSTARLUX Airlines\n09:20\nTPE T1\n2h 30m\nNonstop\n12:50\nKIX T1\nUS$505\nRound-trip\nSelect\nIncluded\n- 11% CO2e\nCathay Pacific\n11:15\nTPE T1\n2h 40m\nNonstop\n14:55\nKIX T1\nUS$509\nRound-trip\nSelect\nIncluded\nSTARLUX Airlines\n07:40\nTPE T1\n2h 30m\nNonstop\n11:10\nKIX T1\nUS$528\nRound-trip\nSelect\nIncluded\nAll Nippon Airways\noperated by EVA Air\n06:30\nTPE T2\n2h 25m\nNonstop\n09:55\nKIX T1\nUS$1,084\nRound-trip\nSelect\nIncluded\nAll Nippon Airways\noperated by EVA Air\n08:20\nTPE T2\n2h 35m\nNonstop\n11:55\nKIX T1\nUS$1,084\nRound-trip\nSelect\nIncluded\nAll Nippon Airways\noperated by EVA Air\n13:30\nTPE T2\n2h 25m\nNonstop\n16:55\nKIX T1\nUS$1,084\nRound-trip\nSelect\nIncluded\nJapan Airlines\noperated by China Airlines\n08:05\nTPE T2\n2h 30m\nNonstop\n11:35\nKIX T1\nUS$1,148\nRound-trip\nSelect\nIncluded\nJapan Airlines\noperated by China Airlines\n09:45\nTPE T2\n2h 35m\nNonstop\n13:20\nKIX T1\nUS$1,148\nRound-trip\nSelect\nIncluded\nJapan Airlines\noperated by China Airlines\n14:20\nTPE T2\n2h 30m\nNonstop\n17:50\nKIX T1\nUS$1,148\nRound-trip\nSelect\nFlights with transfers\nIncluded\nJin Air\n12:40\nTPE T1\n27h 10m\n22h 55m in Seoul\n16:50\nKIX T1\n +1\nUS$404\nRound-trip\nSelect\nHK Express\n21:15\nTPE T1\n16h 5m\n10h 30m in Hong Kong\n14:20\nKIX T1\n +1\nUS$442\nRound-trip\nSelect\nHK Express\n21:15\nTPE T1\n18h\n12h 25m in Hong Kong\n16:15\nKIX T1\n +1\nUS$442\nRound-trip\nSelect\nHK Express\n21:15\nTPE T1\n21h 55m\n16h 20m in Hong Kong\n20:10\nKIX T1\n +1\nUS$442\nRound-trip\nSelect\nIncluded\nHong Kong Airlines\n21:35\nTPE T2\n8h 40m\n3h in Hong Kong\n07:15\nKIX T1\n +1\nUS$444\nRound-trip\nSelect\nIncluded\nAir Macau\n22:20\nTPE T1\n13h 25m\n7h 55m in Macau\n12:45\nKIX T1\n +1\nUS$458\nRound-trip\nSelect\n<9 left\nIncluded\nHong Kong Airlines\n21:35\nTPE T2\n15h 30m\n9h 50m in Hong Kong\n14:05\nKIX T1\n +1\nUS$460\nRound-trip\nSelect\n<9 left\nIncluded\nHong Kong Airlines\n21:35\nTPE T2\n17h 30m\n11h 40m in Hong Kong\n16:05\nKIX T1\n +1\nUS$460\nRound-trip\nSelect\n<9 left\nIncluded\nHong Kong Airlines\n21:35\nTPE T2\n20h 30m\n14h 50m in Hong Kong\n19:05\nKIX T1\n +1\nUS$460\nRound-trip\nSelect\n<9 left\nIncluded\nHong Kong Airlines\n19:20\nTPE T2\n10h 55m\n5h 20m in Hong Kong\n07:15\nKIX T1\n +1\nUS$499\nRound-trip\nSelect\n<9 left\nIncluded\nHong Kong Airlines\n16:30\nTPE T2\n13h 45m\n8h in Hong Kong\n07:15\nKIX T1\n +1\nUS$499\nRound-trip\nSelect\n<9 left\nIncluded\nHong Kong Airlines\n19:20\nTPE T2\n17h 45m\n12h 10m in Hong Kong\n14:05\nKIX T1\n +1\nUS$499\nRound-trip\nSelect\nIncluded\nHong Kong: Free Layover Tour\nHong Kong Airlines\n11:50\nTPE T2\n18h 25m\n12h 45m in Hong Kong\n07:15\nKIX T1\n +1\nUS$499\nRound-trip\nSelect\nIncluded\nHong Kong Airlines\n19:20\nTPE T2\n19h 45m\n14h in Hong Kong\n16:05\nKIX T1\n +1\nUS$499\nRound-trip\nSelect\nIncluded\nHong Kong Airlines\n16:30\nTPE T2\n20h 35m\n14h 50m in Hong Kong\n14:05\nKIX T1\n +1\nUS$504\nRound-trip\nSelect\nIncluded\nHong Kong Airlines\n19:20\nTPE T2\n22h 45m\n17h 10m in Hong Kong\n19:05\nKIX T1\n +1\nUS$504\nRound-trip\nSelect\nIncluded\nKorean Air, Asiana Airlines\n19:25\nTPE T1\n24h 30m\n20h 10m in Seoul\n20:55\nKIX T1\n +1\nUS$640\nRound-trip\nSelect\nIncluded\nJin Air\n02:40\nTPE T1\n11h 40m\n8h in Busan\n15:20\nKIX T1\nUS$645\nRound-trip\nSelect\nChecked baggage included\nVietJet Air\n19:00\nTPE T1\n12h 30m\n3h 55m in Ho Chi Minh City\n08:30\nKIX T1\n +1\nUS$659\nRound-trip\nSelect\nChecked baggage included\nVietJet Air\n06:25\nTPE T1\n25h 5m\n16h 30m in Ho Chi Minh City\n08:30\nKIX T1\n +1\nUS$659\nRound-trip\nSelect\nIncluded\nT'Way Air\n14:25\nTPE T1\n26h 15m\n22h 35m in Jeju\n17:40\nKIX T1\n +1\nUS$663\nRound-trip\nSelect\nIncluded\nJin Air\n02:40\nTPE T1\n6h 20m\n2h 40m in Busan\n10:00\nKIX T1\nUS$672\nRound-trip\nSelect\nIncluded\nT'Way Air\n01:55\nTPE T1\n13h\n9h 5m in Daegu\n15:55\nKIX T1\nUS$679\nRound-trip\nSelect\nFlights\n > \nFlights\n > \nTaipei to Flights\nBook flights from Taipei to on Trip.com\n\nFirst class | Business class | Economy class | Nonstop\n\nSearch for cheap flights from Taipei to on Trip.com. Trip.com provides the best real-time Taipei to airfares and flight deals available, featuring advanced flight planning tools like price alerts, deal finder fare calendars, and Taipei Flight + Hotel deals that make a vacation or tour more convenient and affordable.\n\nAward-winning\nSupport in approx. 30s\nRewards for booking"
    ]
  }
}