{
  "url": "https://www.trip.com/flights/osaka-to-taipei/tickets-kix-tpe?dcity=kix&acity=tpe&ddate=2026-03-02&flighttype=ow&class=y&quantity=2",
  "scraped_at": "2026-02-05T13:01:38.948328",
  "title": "Cheap Flights, Airline Tickets & Plane Tickets | Trip.com",
  "raw_text": "Go to main content\nTheme Detection\nHotels & Homes\nFlights\nTrains\nCar services\nApp\nUSD\nCustomer support\nFind bookings\nSign in / Register\nCheap Flights, Airline Tickets & Plane Tickets | Trip.com\nAllow notifications\nDon't miss out! Be the first to find out the latest travel info.\nAllow\nTaipei\nEdit\n2 adults\nEconomy\nMar 2, 2026\nFri, Feb 27\nView\nSat, Feb 28\nView\nSun, Mar 1\nView\nMon, Mar 2\nUS$134\nTue, Mar 3\nView\nMon, Feb 23\nView\nTue, Feb 24\nView\nWed, Feb 25\nView\nThu, Feb 26\nView\nFri, Feb 27\nView\nSat, Feb 28\nView\nSun, Mar 1\nView\nMon, Mar 2\nUS$134\nTue, Mar 3\nView\nWed, Mar 4\nView\nThu, Mar 5\nView\nFri, Mar 6\nView\nSat, Mar 7\nView\nSun, Mar 8\nView\nMon, Mar 9\nView\nPrice graph\nRecommended\n Nonstop\n Checked baggage included\n Hide budget airlines\n Student tickets\n Carry-on baggage included\n Hide codeshare flights\nCO2e Lower emission flights\nShow More\nAlliance\nStar Alliance\nUS$332\nSkyTeam\nUS$470\nOneworld\nUS$507\nAirlines\nAll flights with the same airline\nAll airlines\nHK Express (19)\nUS$298\nHong Kong Airlines (14)\nUS$235\nEVA Air (6)\nUS$353\nAir Macau (5)\nUS$134\nPeach (3)\nUS$328\nShow More\nAlliance\nStar Alliance\nUS$332\nSkyTeam\nUS$470\nOneworld\nUS$507\nTimes\nDeparture time\n00:00–24:00\n00:00\n24:00\nArrival time\n00:00–24:00\n00:00\n24:00\nDuration\nAny\nStopover Duration\n2h 30m–24h\n2h 30m\n24h\nTotal Duration\n3h–30h 30m\n3h\n30h 30m\nStops\n1 stop or fewer\nUS$134\nStopover cities\nAny\nHong Kong\nUS$235\nMacau\nUS$134\nShanghai\nUS$273\nOkinawa\nUS$213\nHanoi\nUS$412\nTokyo\nUS$507\nHangzhou\nUS$332\nSeoul\nUS$397\nShenzhen\nUS$435\nGuangzhou\nUS$461\nAirports\nAny\nDeparture Airport\nKIX\nKansai International Airport\nUS$134\nArrival Airport\nTSA\nTaipei Songshan Airport\nUS$551\nTPE\nTaiwan Taoyuan International Airport\nUS$134\nAircrafts\nAny\nLarge aircraft\nUS$134\nMidsize aircraft\nUS$134\nCabin\nEconomy\nEconomy\nEconomy/premium economy\nPremium economy\nBusiness/first\nBusiness\nFirst class\nDeparting for Taipei\n71 flights found\nRecommended\nUS$279\nNonstop first\nUS$279\nCheapest\nUS$134\nSort by\nCreate price alert\n\nPrices are low and likely to increase—book now!\n\nCurrent lowest price: US$134.00\nLow price\n2 weeks ago\nToday\nDeparture\nUS$72.39\nAvg. US$335.03\nUS$597.67\nAdd a price alert\nCheapest nonstop\nCarry-on baggage included\nThai Vietjet Air\n12:00\nKIX T1\n3h 15m\nNonstop\n14:15\nTPE T1\nUS$279\nTotal US$557\nSelect\nCarry-on baggage included\nJetstar Japan\n14:50\nKIX T1\n3h 20m\nNonstop\n17:10\nTPE T1\nUS$288\nTotal US$575\nSelect\nCarry-on baggage included\nTigerair Taiwan\n11:30\nKIX T1\n3h 20m\nNonstop\n13:50\nTPE T1\nUS$303\nTotal US$606\nSelect\nIncluded\nPeach\n10:10\nKIX T2\n3h 35m\nNonstop\n12:45\nTPE T1\nUS$328\nTotal US$656\nSelect\nIncluded\n- 23% CO2e\nEVA Air\n10:55\nKIX T1\n3h 15m\nNonstop\n13:10\nTPE T2\nUS$353\nTotal US$705\nSelect\nIncluded\n- 20% CO2e\nPeach\n07:15\nKIX T2\n3h 30m\nNonstop\n09:45\nTPE T1\nUS$379\nTotal US$758\nSelect\nCarry-on baggage included\n- 18% CO2e\nAirAsia X Berhad\n20:45\nKIX T1\n3h 20m\nNonstop\n23:05\nTPE T1\nUS$378\nTotal US$756\nSelect\nCarry-on baggage included\n- 2% CO2e\nTigerair Taiwan\n18:55\nKIX T1\n3h 20m\nNonstop\n21:15\nTPE T1\nUS$401\nTotal US$802\nSelect\nIncluded\n- 20% CO2e\nPeach\n15:25\nKIX T2\n3h 30m\nNonstop\n17:55\nTPE T1\nUS$420\nTotal US$839\nSelect\nIncluded\n- 10% CO2e\nSTARLUX Airlines\n12:20\nKIX T1\n3h 15m\nNonstop\n14:35\nTPE T1\nUS$423\nTotal US$846\nSelect\nIncluded\nEVA Air\n12:55\nKIX T1\n3h 10m\nNonstop\n15:05\nTPE T2\nUS$428\nTotal US$856\nSelect\nIncluded\n- 6% CO2e\nChina Airlines\n19:00\nKIX T1\n3h 15m\nNonstop\n21:15\nTPE T2\nUS$470\nTotal US$940\nSelect\nIncluded\n- 23% CO2e\nEVA Air\n18:10\nKIX T1\n3h 15m\nNonstop\n20:25\nTPE T2\nUS$488\nTotal US$975\nSelect\nCarry-on baggage included\n- 2% CO2e\nJetstar Japan\n23:10\nKIX T1\n3h 20m\nNonstop\n01:30\nTPE T1\n +1\nUS$543\nTotal US$1,085\nSelect\nIncluded\nJapan Airlines\noperated by China Airlines\n19:00\nKIX T1\n3h 15m\nNonstop\n21:15\nTPE T2\nUS$1,537\nTotal US$3,074\nSelect\nCheapest\nIncluded\nAir Macau\noperated by EVA Air\n13:45\nKIX T1\n26h 10m\n20h 5m in Macau\n14:55\nTPE T2\n +1\nUS$134\nTotal US$268\nSelect\n<9 left\nIncluded\nAir Macau\n13:45\nKIX T1\n8h 45m\n2h 40m in Macau\n21:30\nTPE T1\nUS$176\nTotal US$352\nSelect\n<9 left\nIncluded\nHong Kong Airlines\n09:45\nKIX T1\n11h 50m\n5h 30m in Hong Kong\n20:35\nTPE T2\nUS$235\nTotal US$470\nSelect\nIncluded\nHong Kong: Free Layover Tour\nHong Kong Airlines\n09:45\nKIX T1\n26h 5m\n19h 45m in Hong Kong\n10:50\nTPE T2\n +1\nUS$236\nTotal US$472\nSelect\n<9 left\nIncluded\nHong Kong Airlines\n09:45\nKIX T1\n9h 35m\n3h 15m in Hong Kong\n18:20\nTPE T2\nUS$259\nTotal US$518\nSelect\n<9 left\nIncluded\nAir Macau\n13:45\nKIX T1\n19h 35m\n13h 35m in Macau\n08:20\nTPE T1\n +1\nUS$260\nTotal US$520\nSelect\nIncluded\nHong Kong Airlines\n20:05\nKIX T1\n15h 45m\n9h 25m in Hong Kong\n10:50\nTPE T2\n +1\nUS$268\nTotal US$536\nSelect\nShow more results\n*Last updated: 13:01:31\nFlights\n > \nTaipei Flights\n > \nto Taipei Flights\nBook flights from to Taipei on Trip.com\n\nFirst class | Business class | Economy class | Nonstop\n\nSearch for cheap flights from to Taipei on Trip.com. Trip.com provides the best real-time to Taipei airfares and flight deals available, featuring advanced flight planning tools like price alerts, deal finder fare calendars, and Flight + Hotel deals that make a Taipei vacation or Taipei tour more convenient and affordable.\n\nAward-winning\nSupport in approx. 30s\nRewards for booking\nContact us\nCustomer support\nService guarantee\nMore service info\nAbout\nAbout Trip.com\nNews\nCareers\nTerms & Conditions\nPrivacy Statement\nAccessibility statement\nAbout Trip.com Group\nOther services\nInvestor relations\nTrip.com Rewards\nAffiliate program\nList your property\nAll hotels\nBecome a Supplier\nSecurity\nPayment methods\nOur partners\nContact Center\nof the year 2025\nCopyright © 2025 Trip.com Travel Singapore Pte. Ltd. All rights reserved\nSite Operator: Trip.com Travel Singapore Pte. Ltd.",
  "extracted": {
    "flight": {},
    "hotel": {},
    "price": {},
    "dates": {},
    "inclusions": [],
    "date_pricing": {}
  },
  "extracted_elements": {
    "flight_element": [
      "Thai Vietjet Air\n12:00\nKIX T1\n3h 15m\nNonstop\n14:15\nTPE T1",
      "Jetstar Japan\n14:50\nKIX T1\n3h 20m\nNonstop\n17:10\nTPE T1",
      "Tigerair Taiwan\n11:30\nKIX T1\n3h 20m\nNonstop\n13:50\nTPE T1",
      "Peach\n10:10\nKIX T2\n3h 35m\nNonstop\n12:45\nTPE T1",
      "EVA Air\n10:55\nKIX T1\n3h 15m\nNonstop\n13:10\nTPE T2"
    ],
    "price_class": [
      "Fri, Feb 27\nView\nSat, Feb 28\nView\nSun, Mar 1\nView\nMon, Mar 2\nUS$134\nTue, Mar 3\nView",
      "Fri, Feb 27\nView\nSat, Feb 28\nView\nSun, Mar 1\nView\nMon, Mar 2\nUS$134\nTue, Mar 3\nView",
      "Fri, Feb 27\nView\nSat, Feb 28\nView\nSun, Mar 1\nView\nMon, Mar 2\nUS$134\nTue, Mar 3\nView",
      "Fri, Feb 27\nView\nSat, Feb 28\nView\nSun, Mar 1\nView\nMon, Mar 2\nUS$134\nTue, Mar 3\nView",
      "Fri, Feb 27\nView\nSat, Feb 28\nView\nSun, Mar 1\nView\nMon, Mar 2\nUS$134\nTue, Mar 3\nView"
    ],
    "flight_class": [
      "Flights",
      "Taipei\nEdit\n2 adults\nEconomy\nMar 2, 2026\nFri, Feb 27\nView\nSat, Feb 28\nView\nSun, Mar 1\nView\nMon, Mar 2\nUS$134\nTue, Mar 3\nView\nMon, Feb 23\nView\nTue, Feb 24\nView\nWed, Feb 25\nView\nThu, Feb 26\nView\nFri, Feb 27\nView\nSat, Feb 28\nView\nSun, Mar 1\nView\nMon, Mar 2\nUS$134\nTue, Mar 3\nView\nWed, Mar 4\nView\nThu, Mar 5\nView\nFri, Mar 6\nView\nSat, Mar 7\nView\nSun, Mar 8\nView\nMon, Mar 9\nView\nPrice graph\nRecommended\n Nonstop\n Checked baggage included\n Hide budget airlines\n Student tickets\n Carry-on baggage included\n Hide codeshare flights\nCO2e Lower emission flights\nShow More\nAlliance\nStar Alliance\nUS$332\nSkyTeam\nUS$470\nOneworld\nUS$507\nAirlines\nAll flights with the same airline\nAll airlines\nHK Express (19)\nUS$298\nHong Kong Airlines (14)\nUS$235\nEVA Air (6)\nUS$353\nAir Macau (5)\nUS$134\nPeach (3)\nUS$328\nShow More\nAlliance\nStar Alliance\nUS$332\nSkyTeam\nUS$470\nOneworld\nUS$507\nTimes\nDeparture time\n00:00–24:00\n00:00\n24:00\nArrival time\n00:00–24:00\n00:00\n24:00\nDuration\nAny\nStopover Duration\n2h 30m–24h\n2h 30m\n24h\nTotal Duration\n3h–30h 30m\n3h\n30h 30m\nStops\n1 stop or fewer\nUS$134\nStopover cities\nAny\nHong Kong\nUS$235\nMacau\nUS$134\nShanghai\nUS$273\nOkinawa\nUS$213\nHanoi\nUS$412\nTokyo\nUS$507\nHangzhou\nUS$332\nSeoul\nUS$397\nShenzhen\nUS$435\nGuangzhou\nUS$461\nAirports\nAny\nDeparture Airport\nKIX\nKansai International Airport\nUS$134\nArrival Airport\nTSA\nTaipei Songshan Airport\nUS$551\nTPE\nTaiwan Taoyuan International Airport\nUS$134\nAircrafts\nAny\nLarge aircraft\nUS$134\nMidsize aircraft\nUS$134\nCabin\nEconomy\nEconomy\nEconomy/premium economy\nPremium economy\nBusiness/first\nBusiness\nFirst class\nDeparting for Taipei\n71 flights found\nRecommended\nUS$279\nNonstop first\nUS$279\nCheapest\nUS$134\nSort by\nCreate price alert\n\nPrices are low and likely to increase—book now!\n\nCurrent lowest price: US$134.00\nLow price\n2 weeks ago\nToday\nDeparture\nUS$72.39\nAvg. US$335.03\nUS$597.67\nAdd a price alert\nCheapest nonstop\nCarry-on baggage included\nThai Vietjet Air\n12:00\nKIX T1\n3h 15m\nNonstop\n14:15\nTPE T1\nUS$279\nTotal US$557\nSelect\nCarry-on baggage included\nJetstar Japan\n14:50\nKIX T1\n3h 20m\nNonstop\n17:10\nTPE T1\nUS$288\nTotal US$575\nSelect\nCarry-on baggage included\nTigerair Taiwan\n11:30\nKIX T1\n3h 20m\nNonstop\n13:50\nTPE T1\nUS$303\nTotal US$606\nSelect\nIncluded\nPeach\n10:10\nKIX T2\n3h 35m\nNonstop\n12:45\nTPE T1\nUS$328\nTotal US$656\nSelect\nIncluded\n- 23% CO2e\nEVA Air\n10:55\nKIX T1\n3h 15m\nNonstop\n13:10\nTPE T2\nUS$353\nTotal US$705\nSelect\nIncluded\n- 20% CO2e\nPeach\n07:15\nKIX T2\n3h 30m\nNonstop\n09:45\nTPE T1\nUS$379\nTotal US$758\nSelect\nCarry-on baggage included\n- 18% CO2e\nAirAsia X Berhad\n20:45\nKIX T1\n3h 20m\nNonstop\n23:05\nTPE T1\nUS$378\nTotal US$756\nSelect\nCarry-on baggage included\n- 2% CO2e\nTigerair Taiwan\n18:55\nKIX T1\n3h 20m\nNonstop\n21:15\nTPE T1\nUS$401\nTotal US$802\nSelect\nIncluded\n- 20% CO2e\nPeach\n15:25\nKIX T2\n3h 30m\nNonstop\n17:55\nTPE T1\nUS$420\nTotal US$839\nSelect\nIncluded\n- 10% CO2e\nSTARLUX Airlines\n12:20\nKIX T1\n3h 15m\nNonstop\n14:35\nTPE T1\nUS$423\nTotal US$846\nSelect\nIncluded\nEVA Air\n12:55\nKIX T1\n3h 10m\nNonstop\n15:05\nTPE T2\nUS$428\nTotal US$856\nSelect\nIncluded\n- 6% CO2e\nChina Airlines\n19:00\nKIX T1\n3h 15m\nNonstop\n21:15\nTPE T2\nUS$470\nTotal US$940\nSelect\nIncluded\n- 23% CO2e\nEVA Air\n18:10\nKIX T1\n3h 15m\nNonstop\n20:25\nTPE T2\nUS$488\nTotal US$975\nSelect\nCarry-on baggage included\n- 2% CO2e\nJetstar Japan\n23:10\nKIX T1\n3h 20m\nNonstop\n01:30\nTPE T1\n +1\nUS$543\nTotal US$1,085\nSelect\nIncluded\nJapan Airlines\noperated by China Airlines\n19:00\nKIX T1\n3h 15m\nNonstop\n21:15\nTPE T2\nUS$1,537\nTotal US$3,074\nSelect\nCheapest\nIncluded\nAir Macau\noperated by EVA Air\n13:45\nKIX T1\n26h 10m\n20h 5m in Macau\n14:55\nTPE T2\n +1\nUS$134\nTotal US$268\nSelect\n<9 left\nIncluded\nAir Macau\n13:45\nKIX T1\n8h 45m\n2h 40m in Macau\n21:30\nTPE T1\nUS$176\nTotal US$352\nSelect\n<9 left\nIncluded\nHong Kong Airlines\n09:45\nKIX T1\n11h 50m\n5h 30m in Hong Kong\n20:35\nTPE T2\nUS$235\nTotal US$470\nSelect\nIncluded\nHong Kong: Free Layover Tour\nHong Kong Airlines\n09:45\nKIX T1\n26h 5m\n19h 45m in Hong Kong\n10:50\nTPE T2\n +1\nUS$236\nTotal US$472\nSelect\n<9 left\nIncluded\nHong Kong Airlines\n09:45\nKIX T1\n9h 35m\n3h 15m in Hong Kong\n18:20\nTPE T2\nUS$259\nTotal US$518\nSelect\n<9 left\nIncluded\nAir Macau\n13:45\nKIX T1\n19h 35m\n13h 35m in Macau\n08:20\nTPE T1\n +1\nUS$260\nTotal US$520\nSelect\nIncluded\nHong Kong Airlines\n20:05\nKIX T1\n15h 45m\n9h 25m in Hong Kong\n10:50\nTPE T2\n +1\nUS$268\nTotal US$536\nSelect\nShow more results\n*Last updated: 13:01:31\nFlights\n > \nTaipei Flights\n > \nto Taipei Flights\nBook flights from to Taipei on Trip.com\n\nFirst class | Business class | Economy class | Nonstop\n\nSearch for cheap flights from to Taipei on Trip.com. Trip.com provides the best real-time to Taipei airfares and flight deals available, featuring advanced flight planning tools like price alerts, deal finder fare calendars, and Flight + Hotel deals that make a Taipei vacation or Taipei tour more convenient and affordable.\n\nAward-winning\nSupport in approx. 30s\nRewards for booking",
      "Taipei\nEdit\n2 adults\nEconomy\nMar 2, 2026\nFri, Feb 27\nView\nSat, Feb 28\nView\nSun, Mar 1\nView\nMon, Mar 2\nUS$134\nTue, Mar 3\nView",
      "DepartMon, Mar 2"
    ],
    "hotel_class": [
      "Hotels & Homes"
    ],
    "main": [
      "Cheap Flights, Airline Tickets & Plane Tickets | Trip.com\nAllow notifications\nDon't miss out! Be the first to find out the latest travel info.\nAllow\nTaipei\nEdit\n2 adults\nEconomy\nMar 2, 2026\nFri, Feb 27\nView\nSat, Feb 28\nView\nSun, Mar 1\nView\nMon, Mar 2\nUS$134\nTue, Mar 3\nView\nMon, Feb 23\nView\nTue, Feb 24\nView\nWed, Feb 25\nView\nThu, Feb 26\nView\nFri, Feb 27\nView\nSat, Feb 28\nView\nSun, Mar 1\nView\nMon, Mar 2\nUS$134\nTue, Mar 3\nView\nWed, Mar 4\nView\nThu, Mar 5\nView\nFri, Mar 6\nView\nSat, Mar 7\nView\nSun, Mar 8\nView\nMon, Mar 9\nView\nPrice graph\nRecommended\n Nonstop\n Checked baggage included\n Hide budget airlines\n Student tickets\n Carry-on baggage included\n Hide codeshare flights\nCO2e Lower emission flights\nShow More\nAlliance\nStar Alliance\nUS$332\nSkyTeam\nUS$470\nOneworld\nUS$507\nAirlines\nAll flights with the same airline\nAll airlines\nHK Express (19)\nUS$298\nHong Kong Airlines (14)\nUS$235\nEVA Air (6)\nUS$353\nAir Macau (5)\nUS$134\nPeach (3)\nUS$328\nShow More\nAlliance\nStar Alliance\nUS$332\nSkyTeam\nUS$470\nOneworld\nUS$507\nTimes\nDeparture time\n00:00–24:00\n00:00\n24:00\nArrival time\n00:00–24:00\n00:00\n24:00\nDuration\nAny\nStopover Duration\n2h 30m–24h\n2h 30m\n24h\nTotal Duration\n3h–30h 30m\n3h\n30h 30m\nStops\n1 stop or fewer\nUS$134\nStopover cities\nAny\nHong Kong\nUS$235\nMacau\nUS$134\nShanghai\nUS$273\nOkinawa\nUS$213\nHanoi\nUS$412\nTokyo\nUS$507\nHangzhou\nUS$332\nSeoul\nUS$397\nShenzhen\nUS$435\nGuangzhou\nUS$461\nAirports\nAny\nDeparture Airport\nKIX\nKansai International Airport\nUS$134\nArrival Airport\nTSA\nTaipei Songshan Airport\nUS$551\nTPE\nTaiwan Taoyuan International Airport\nUS$134\nAircrafts\nAny\nLarge aircraft\nUS$134\nMidsize aircraft\nUS$134\nCabin\nEconomy\nEconomy\nEconomy/premium economy\nPremium economy\nBusiness/first\nBusiness\nFirst class\nDeparting for Taipei\n71 flights found\nRecommended\nUS$279\nNonstop first\nUS$279\nCheapest\nUS$134\nSort by\nCreate price alert\n\nPrices are low and likely to increase—book now!\n\nCurrent lowest price: US$134.00\nLow price\n2 weeks ago\nToday\nDeparture\nUS$72.39\nAvg. US$335.03\nUS$597.67\nAdd a price alert\nCheapest nonstop\nCarry-on baggage included\nThai Vietjet Air\n12:00\nKIX T1\n3h 15m\nNonstop\n14:15\nTPE T1\nUS$279\nTotal US$557\nSelect\nCarry-on baggage included\nJetstar Japan\n14:50\nKIX T1\n3h 20m\nNonstop\n17:10\nTPE T1\nUS$288\nTotal US$575\nSelect\nCarry-on baggage included\nTigerair Taiwan\n11:30\nKIX T1\n3h 20m\nNonstop\n13:50\nTPE T1\nUS$303\nTotal US$606\nSelect\nIncluded\nPeach\n10:10\nKIX T2\n3h 35m\nNonstop\n12:45\nTPE T1\nUS$328\nTotal US$656\nSelect\nIncluded\n- 23% CO2e\nEVA Air\n10:55\nKIX T1\n3h 15m\nNonstop\n13:10\nTPE T2\nUS$353\nTotal US$705\nSelect\nIncluded\n- 20% CO2e\nPeach\n07:15\nKIX T2\n3h 30m\nNonstop\n09:45\nTPE T1\nUS$379\nTotal US$758\nSelect\nCarry-on baggage included\n- 18% CO2e\nAirAsia X Berhad\n20:45\nKIX T1\n3h 20m\nNonstop\n23:05\nTPE T1\nUS$378\nTotal US$756\nSelect\nCarry-on baggage included\n- 2% CO2e\nTigerair Taiwan\n18:55\nKIX T1\n3h 20m\nNonstop\n21:15\nTPE T1\nUS$401\nTotal US$802\nSelect\nIncluded\n- 20% CO2e\nPeach\n15:25\nKIX T2\n3h 30m\nNonstop\n17:55\nTPE T1\nUS$420\nTotal US$839\nSelect\nIncluded\n- 10% CO2e\nSTARLUX Airlines\n12:20\nKIX T1\n3h 15m\nNonstop\n14:35\nTPE T1\nUS$423\nTotal US$846\nSelect\nIncluded\nEVA Air\n12:55\nKIX T1\n3h 10m\nNonstop\n15:05\nTPE T2\nUS$428\nTotal US$856\nSelect\nIncluded\n- 6% CO2e\nChina Airlines\n19:00\nKIX T1\n3h 15m\nNonstop\n21:15\nTPE T2\nUS$470\nTotal US$940\nSelect\nIncluded\n- 23% CO2e\nEVA Air\n18:10\nKIX T1\n3h 15m\nNonstop\n20:25\nTPE T2\nUS$488\nTotal US$975\nSelect\nCarry-on baggage included\n- 2% CO2e\nJetstar Japan\n23:10\nKIX T1\n3h 20m\nNonstop\n01:30\nTPE T1\n +1\nUS$543\nTotal US$1,085\nSelect\nIncluded\nJapan Airlines\noperated by China Airlines\n19:00\nKIX T1\n3h 15m\nNonstop\n21:15\nTPE T2\nUS$1,537\nTotal US$3,074\nSelect\nCheapest\nIncluded\nAir Macau\noperated by EVA Air\n13:45\nKIX T1\n26h 10m\n20h 5m in Macau\n14:55\nTPE T2\n +1\nUS$134\nTotal US$268\nSelect\n<9 left\nIncluded\nAir Macau\n13:45\nKIX T1\n8h 45m\n2h 40m in Macau\n21:30\nTPE T1\nUS$176\nTotal US$352\nSelect\n<9 left\nIncluded\nHong Kong Airlines\n09:45\nKIX T1\n11h 50m\n5h 30m in Hong Kong\n20:35\nTPE T2\nUS$235\nTotal US$470\nSelect\nIncluded\nHong Kong: Free Layover Tour\nHong Kong Airlines\n09:45\nKIX T1\n26h 5m\n19h 45m in Hong Kong\n10:50\nTPE T2\n +1\nUS$236\nTotal US$472\nSelect\n<9 left\nIncluded\nHong Kong Airlines\n09:45\nKIX T1\n9h 35m\n3h 15m in Hong Kong\n18:20\nTPE T2\nUS$259\nTotal US$518\nSelect\n<9 left\nIncluded\nAir Macau\n13:45\nKIX T1\n19h 35m\n13h 35m in Macau\n08:20\nTPE T1\n +1\nUS$260\nTotal US$520\nSelect\nIncluded\nHong Kong Airlines\n20:05\nKIX T1\n15h 45m\n9h 25m in Hong Kong\n10:50\nTPE T2\n +1\nUS$268\nTotal US$536\nSelect\nShow more results\n*Last updated: 13:01:31\nFlights\n > \nTaipei Flights\n > \nto Taipei Flights\nBook flights from to Taipei on Trip.com\n\nFirst class | Business class | Economy class | Nonstop\n\nSearch for cheap flights from to Taipei on Trip.com. Trip.com provides the best real-time to Taipei airfares and flight deals available, featuring advanced flight planning tools like price alerts, deal finder fare calendars, and Flight + Hotel deals that make a Taipei vacation or Taipei tour more convenient and affordable.\n\nAward-winning\nSupport in approx. 30s\nRewards for booking"
    ]
  }
}