{
  "url": "https://www.trip.com/flights/taipei-to-osaka/tickets-tpe-kix?dcity=tpe&acity=kix&ddate=2026-02-27&flighttype=ow&class=y&quantity=2",
  "scraped_at": "2026-02-05T10:35:19.267059",
  "title": "Cheap Flights, Airline Tickets & Plane Tickets | Trip.com",
  "raw_text": "Go to main content\nTheme Detection\nHotels & Homes\nFlights\nTrains\nCar services\nApp\nUSD\nCustomer support\nFind bookings\nSign in / Register\nCheap Flights, Airline Tickets & Plane Tickets | Trip.com\nAllow notifications\nDon't miss out! Be the first to find out the latest travel info.\nAllow\nTaipei\nEdit\n2 adults\nEconomy\nFeb 27, 2026\nTue, Feb 24\nView\nWed, Feb 25\nView\nThu, Feb 26\nView\nFri, Feb 27\nUS$138\nSat, Feb 28\nView\nFri, Feb 20\nView\nSat, Feb 21\nView\nSun, Feb 22\nView\nMon, Feb 23\nView\nTue, Feb 24\nView\nWed, Feb 25\nView\nThu, Feb 26\nView\nFri, Feb 27\nUS$138\nSat, Feb 28\nView\nSun, Mar 1\nView\nMon, Mar 2\nView\nTue, Mar 3\nView\nWed, Mar 4\nView\nThu, Mar 5\nView\nFri, Mar 6\nView\nPrice graph\nRecommended\n Nonstop\n Checked baggage included\n Hide budget airlines\n Student tickets\n Carry-on baggage included\n Hide codeshare flights\nCO2e Lower emission flights\nShow More\nAlliance\nSkyTeam\nUS$300\nStar Alliance\nUS$337\nOneworld\nUS$420\nAirlines\nAll flights with the same airline\nAll airlines\nHong Kong Airlines (8)\nUS$138\nHK Express (8)\nUS$213\nCathay Pacific (6)\nUS$420\nPeach (4)\nUS$272\nPhilippine Airlines (3)\nUS$272\nShow More\nAlliance\nSkyTeam\nUS$300\nStar Alliance\nUS$337\nOneworld\nUS$420\nTimes\nDeparture time\n00:00–24:00\n00:00\n24:00\nArrival time\n00:00–24:00\n00:00\n24:00\nDuration\nAny\nStopover Duration\n1h–16h 30m\n1h\n16h 30m\nTotal Duration\n2h–22h\n2h\n22h\nStops\n1 stop or fewer\nUS$138\nStopover cities\nAny\nHong Kong\nUS$138\nManila\nUS$272\nMacau\nUS$270\nDaegu\nUS$314\nAirports\nAny\nDeparture Airport\nTPE\nTaiwan Taoyuan International Airport\nUS$138\nArrival Airport\nKIX\nKansai International Airport\nUS$138\nAircrafts\nAny\nLarge aircraft\nUS$138\nMidsize aircraft\nUS$138\nCabin\nEconomy\nEconomy\nEconomy/premium economy\nPremium economy\nBusiness/first\nBusiness\nFirst class\nRecommended\nUS$183\nNonstop first\nUS$298\nCheapest\nUS$138\nSort by\nCreate price alert\nCheapest nonstop\nCarry-on baggage included\n- 16% CO2e\nAirAsia X Berhad\n15:40\nTPE T1\n2h 40m\nNonstop\n19:20\nKIX T1\nUS$183\nTotal US$365\nSelect\nCarry-on baggage included\nThai Vietjet Air\n07:30\nTPE T1\n2h 30m\nNonstop\n11:00\nKIX T1\nUS$195\nTotal US$390\nSelect\nCarry-on baggage included\nJetstar Japan\n18:10\nTPE T1\n2h 30m\nNonstop\n21:40\nKIX T1\nUS$222\nTotal US$443\nSelect\nCarry-on baggage included\nTigerair Taiwan\n14:40\nTPE T1\n2h 15m\nNonstop\n17:55\nKIX T1\nUS$257\nTotal US$513\nSelect\nPrice alerts\nWant a better deal? We'll notify you when the price drops below US$133.\nRecommended: US$133\nHigh chances of success\nOK\nIncluded\n- 18% CO2e\nPeach\n18:50\nTPE T1\n2h 25m\nNonstop\n22:15\nKIX T2\nUS$272\nTotal US$544\nSelect\nIncluded\n- 1% CO2e\nPeach\n01:45\nTPE T1\n2h 25m\nNonstop\n05:10\nKIX T2\nUS$298\nTotal US$596\nSelect\nIncluded\n- 3% CO2e\nChina Airlines\n14:20\nTPE T2\n2h 30m\nNonstop\n17:50\nKIX T1\nUS$300\nTotal US$600\nSelect\n<9 left\nCarry-on baggage included\nTigerair Taiwan\n07:00\nTPE T1\n2h 25m\nNonstop\n10:25\nKIX T1\nUS$322\nTotal US$644\nSelect\nIncluded\nPeach\n13:40\nTPE T1\n2h 25m\nNonstop\n17:05\nKIX T2\nUS$328\nTotal US$656\nSelect\nIncluded\n- 21% CO2e\nEVA Air\n06:30\nTPE T2\n2h 25m\nNonstop\n09:55\nKIX T1\nUS$337\nTotal US$673\nSelect\n<9 left\nIncluded\nChina Airlines\n09:45\nTPE T2\n2h 35m\nNonstop\n13:20\nKIX T1\nUS$398\nTotal US$796\nSelect\nIncluded\n- 18% CO2e\nPeach\n09:40\nTPE T1\n2h 30m\nNonstop\n13:10\nKIX T2\nUS$410\nTotal US$820\nSelect\nCarry-on baggage included\nJetstar Japan\n02:30\nTPE T1\n2h 30m\nNonstop\n06:00\nKIX T1\nUS$422\nTotal US$843\nSelect\nIncluded\n- 20% CO2e\nEVA Air\n08:20\nTPE T2\n2h 35m\nNonstop\n11:55\nKIX T1\nUS$428\nTotal US$856\nSelect\nIncluded\n- 21% CO2e\nEVA Air\n13:30\nTPE T2\n2h 25m\nNonstop\n16:55\nKIX T1\nUS$428\nTotal US$856\nSelect\nIncluded\n- 2% CO2e\nSTARLUX Airlines\n07:40\nTPE T1\n2h 30m\nNonstop\n11:10\nKIX T1\nUS$515\nTotal US$1,029\nSelect\nIncluded\nJapan Airlines\noperated by China Airlines\n08:05\nTPE T2\n2h 30m\nNonstop\n11:35\nKIX T1\nUS$959\nTotal US$1,917\nSelect\nCheapest\nIncluded\nHong Kong Airlines\n21:40\nTPE T2\n17h 25m\n11h 40m in Hong Kong\n16:05\nKIX T1\n +1\nUS$138\nTotal US$275\nSelect\nCheapest\nIncluded\nHong Kong Airlines\n21:40\nTPE T2\n20h 25m\n14h 50m in Hong Kong\n19:05\nKIX T1\n +1\nUS$138\nTotal US$275\nSelect\nCarry-on baggage included\nGreater Bay Airlines\n21:45\nTPE T1\n14h 10m\n8h 40m in Hong Kong\n12:55\nKIX T1\n +1\nUS$184\nTotal US$367\nSelect\nHK Express\n21:15\nTPE T1\n21h 5m\n15h 30m in Hong Kong\n19:20\nKIX T1\n +1\nUS$213\nTotal US$426\nSelect\nShow more results\nFlights\n > \nFlights\n > \nTaipei to Flights\nBook flights from Taipei to on Trip.com\n\nFirst class | Business class | Economy class | Nonstop\n\nSearch for cheap flights from Taipei to on Trip.com. Trip.com provides the best real-time Taipei to airfares and flight deals available, featuring advanced flight planning tools like price alerts, deal finder fare calendars, and Taipei Flight + Hotel deals that make a vacation or tour more convenient and affordable.\n\nAward-winning\nSupport in approx. 30s\nRewards for booking\nContact us\nCustomer support\nService guarantee\nMore service info\nAbout\nAbout Trip.com\nNews\nCareers\nTerms & Conditions\nPrivacy Statement\nAccessibility statement\nAbout Trip.com Group\nOther services\nInvestor relations\nTrip.com Rewards\nAffiliate program\nList your property\nAll hotels\nBecome a Supplier\nSecurity\nPayment methods\nOur partners\nContact Center\nof the year 2025\nCopyright © 2025 Trip.com Travel Singapore Pte. Ltd. All rights reserved\nSite Operator: Trip.com Travel Singapore Pte. Ltd.",
  "extracted": {
    "flight": {},
    "hotel": {},
    "price": {},
    "dates": {},
    "inclusions": [],
    "date_pricing": {}
  },
  "extracted_elements": {
    "flight_element": [
      "AirAsia X Berhad\n15:40\nTPE T1\n2h 40m\nNonstop\n19:20\nKIX T1",
      "Thai Vietjet Air\n07:30\nTPE T1\n2h 30m\nNonstop\n11:00\nKIX T1",
      "Jetstar Japan\n18:10\nTPE T1\n2h 30m\nNonstop\n21:40\nKIX T1",
      "Tigerair Taiwan\n14:40\nTPE T1\n2h 15m\nNonstop\n17:55\nKIX T1",
      "Peach\n18:50\nTPE T1\n2h 25m\nNonstop\n22:15\nKIX T2"
    ],
    "price_class": [
      "Tue, Feb 24\nView\nWed, Feb 25\nView\nThu, Feb 26\nView\nFri, Feb 27\nUS$138\nSat, Feb 28\nView",
      "Tue, Feb 24\nView\nWed, Feb 25\nView\nThu, Feb 26\nView\nFri, Feb 27\nUS$138\nSat, Feb 28\nView",
      "Tue, Feb 24\nView\nWed, Feb 25\nView\nThu, Feb 26\nView\nFri, Feb 27\nUS$138\nSat, Feb 28\nView",
      "Tue, Feb 24\nView\nWed, Feb 25\nView\nThu, Feb 26\nView\nFri, Feb 27\nUS$138\nSat, Feb 28\nView",
      "Tue, Feb 24\nView\nWed, Feb 25\nView\nThu, Feb 26\nView\nFri, Feb 27\nUS$138\nSat, Feb 28\nView"
    ],
    "flight_class": [
      "Flights",
      "Taipei\nEdit\n2 adults\nEconomy\nFeb 27, 2026\nTue, Feb 24\nView\nWed, Feb 25\nView\nThu, Feb 26\nView\nFri, Feb 27\nUS$138\nSat, Feb 28\nView\nFri, Feb 20\nView\nSat, Feb 21\nView\nSun, Feb 22\nView\nMon, Feb 23\nView\nTue, Feb 24\nView\nWed, Feb 25\nView\nThu, Feb 26\nView\nFri, Feb 27\nUS$138\nSat, Feb 28\nView\nSun, Mar 1\nView\nMon, Mar 2\nView\nTue, Mar 3\nView\nWed, Mar 4\nView\nThu, Mar 5\nView\nFri, Mar 6\nView\nPrice graph\nRecommended\n Nonstop\n Checked baggage included\n Hide budget airlines\n Student tickets\n Carry-on baggage included\n Hide codeshare flights\nCO2e Lower emission flights\nShow More\nAlliance\nSkyTeam\nUS$300\nStar Alliance\nUS$337\nOneworld\nUS$420\nAirlines\nAll flights with the same airline\nAll airlines\nHong Kong Airlines (8)\nUS$138\nHK Express (8)\nUS$213\nCathay Pacific (6)\nUS$420\nPeach (4)\nUS$272\nPhilippine Airlines (3)\nUS$272\nShow More\nAlliance\nSkyTeam\nUS$300\nStar Alliance\nUS$337\nOneworld\nUS$420\nTimes\nDeparture time\n00:00–24:00\n00:00\n24:00\nArrival time\n00:00–24:00\n00:00\n24:00\nDuration\nAny\nStopover Duration\n1h–16h 30m\n1h\n16h 30m\nTotal Duration\n2h–22h\n2h\n22h\nStops\n1 stop or fewer\nUS$138\nStopover cities\nAny\nHong Kong\nUS$138\nManila\nUS$272\nMacau\nUS$270\nDaegu\nUS$314\nAirports\nAny\nDeparture Airport\nTPE\nTaiwan Taoyuan International Airport\nUS$138\nArrival Airport\nKIX\nKansai International Airport\nUS$138\nAircrafts\nAny\nLarge aircraft\nUS$138\nMidsize aircraft\nUS$138\nCabin\nEconomy\nEconomy\nEconomy/premium economy\nPremium economy\nBusiness/first\nBusiness\nFirst class\nRecommended\nUS$183\nNonstop first\nUS$298\nCheapest\nUS$138\nSort by\nCreate price alert\nCheapest nonstop\nCarry-on baggage included\n- 16% CO2e\nAirAsia X Berhad\n15:40\nTPE T1\n2h 40m\nNonstop\n19:20\nKIX T1\nUS$183\nTotal US$365\nSelect\nCarry-on baggage included\nThai Vietjet Air\n07:30\nTPE T1\n2h 30m\nNonstop\n11:00\nKIX T1\nUS$195\nTotal US$390\nSelect\nCarry-on baggage included\nJetstar Japan\n18:10\nTPE T1\n2h 30m\nNonstop\n21:40\nKIX T1\nUS$222\nTotal US$443\nSelect\nCarry-on baggage included\nTigerair Taiwan\n14:40\nTPE T1\n2h 15m\nNonstop\n17:55\nKIX T1\nUS$257\nTotal US$513\nSelect\nPrice alerts\nWant a better deal? We'll notify you when the price drops below US$133.\nRecommended: US$133\nHigh chances of success\nOK\nIncluded\n- 18% CO2e\nPeach\n18:50\nTPE T1\n2h 25m\nNonstop\n22:15\nKIX T2\nUS$272\nTotal US$544\nSelect\nIncluded\n- 1% CO2e\nPeach\n01:45\nTPE T1\n2h 25m\nNonstop\n05:10\nKIX T2\nUS$298\nTotal US$596\nSelect\nIncluded\n- 3% CO2e\nChina Airlines\n14:20\nTPE T2\n2h 30m\nNonstop\n17:50\nKIX T1\nUS$300\nTotal US$600\nSelect\n<9 left\nCarry-on baggage included\nTigerair Taiwan\n07:00\nTPE T1\n2h 25m\nNonstop\n10:25\nKIX T1\nUS$322\nTotal US$644\nSelect\nIncluded\nPeach\n13:40\nTPE T1\n2h 25m\nNonstop\n17:05\nKIX T2\nUS$328\nTotal US$656\nSelect\nIncluded\n- 21% CO2e\nEVA Air\n06:30\nTPE T2\n2h 25m\nNonstop\n09:55\nKIX T1\nUS$337\nTotal US$673\nSelect\n<9 left\nIncluded\nChina Airlines\n09:45\nTPE T2\n2h 35m\nNonstop\n13:20\nKIX T1\nUS$398\nTotal US$796\nSelect\nIncluded\n- 18% CO2e\nPeach\n09:40\nTPE T1\n2h 30m\nNonstop\n13:10\nKIX T2\nUS$410\nTotal US$820\nSelect\nCarry-on baggage included\nJetstar Japan\n02:30\nTPE T1\n2h 30m\nNonstop\n06:00\nKIX T1\nUS$422\nTotal US$843\nSelect\nIncluded\n- 20% CO2e\nEVA Air\n08:20\nTPE T2\n2h 35m\nNonstop\n11:55\nKIX T1\nUS$428\nTotal US$856\nSelect\nIncluded\n- 21% CO2e\nEVA Air\n13:30\nTPE T2\n2h 25m\nNonstop\n16:55\nKIX T1\nUS$428\nTotal US$856\nSelect\nIncluded\n- 2% CO2e\nSTARLUX Airlines\n07:40\nTPE T1\n2h 30m\nNonstop\n11:10\nKIX T1\nUS$515\nTotal US$1,029\nSelect\nIncluded\nJapan Airlines\noperated by China Airlines\n08:05\nTPE T2\n2h 30m\nNonstop\n11:35\nKIX T1\nUS$959\nTotal US$1,917\nSelect\nCheapest\nIncluded\nHong Kong Airlines\n21:40\nTPE T2\n17h 25m\n11h 40m in Hong Kong\n16:05\nKIX T1\n +1\nUS$138\nTotal US$275\nSelect\nCheapest\nIncluded\nHong Kong Airlines\n21:40\nTPE T2\n20h 25m\n14h 50m in Hong Kong\n19:05\nKIX T1\n +1\nUS$138\nTotal US$275\nSelect\nCarry-on baggage included\nGreater Bay Airlines\n21:45\nTPE T1\n14h 10m\n8h 40m in Hong Kong\n12:55\nKIX T1\n +1\nUS$184\nTotal US$367\nSelect\nHK Express\n21:15\nTPE T1\n21h 5m\n15h 30m in Hong Kong\n19:20\nKIX T1\n +1\nUS$213\nTotal US$426\nSelect\nShow more results\nFlights\n > \nFlights\n > \nTaipei to Flights\nBook flights from Taipei to on Trip.com\n\nFirst class | Business class | Economy class | Nonstop\n\nSearch for cheap flights from Taipei to on Trip.com. Trip.com provides the best real-time Taipei to airfares and flight deals available, featuring advanced flight planning tools like price alerts, deal finder fare calendars, and Taipei Flight + Hotel deals that make a vacation or tour more convenient and affordable.\n\nAward-winning\nSupport in approx. 30s\nRewards for booking",
      "Taipei\nEdit\n2 adults\nEconomy\nFeb 27, 2026\nTue, Feb 24\nView\nWed, Feb 25\nView\nThu, Feb 26\nView\nFri, Feb 27\nUS$138\nSat, Feb 28\nView",
      "DepartFri, Feb 27"
    ],
    "hotel_class": [
      "Hotels & Homes"
    ],
    "main": [
      "Cheap Flights, Airline Tickets & Plane Tickets | Trip.com\nAllow notifications\nDon't miss out! Be the first to find out the latest travel info.\nAllow\nTaipei\nEdit\n2 adults\nEconomy\nFeb 27, 2026\nTue, Feb 24\nView\nWed, Feb 25\nView\nThu, Feb 26\nView\nFri, Feb 27\nUS$138\nSat, Feb 28\nView\nFri, Feb 20\nView\nSat, Feb 21\nView\nSun, Feb 22\nView\nMon, Feb 23\nView\nTue, Feb 24\nView\nWed, Feb 25\nView\nThu, Feb 26\nView\nFri, Feb 27\nUS$138\nSat, Feb 28\nView\nSun, Mar 1\nView\nMon, Mar 2\nView\nTue, Mar 3\nView\nWed, Mar 4\nView\nThu, Mar 5\nView\nFri, Mar 6\nView\nPrice graph\nRecommended\n Nonstop\n Checked baggage included\n Hide budget airlines\n Student tickets\n Carry-on baggage included\n Hide codeshare flights\nCO2e Lower emission flights\nShow More\nAlliance\nSkyTeam\nUS$300\nStar Alliance\nUS$337\nOneworld\nUS$420\nAirlines\nAll flights with the same airline\nAll airlines\nHong Kong Airlines (8)\nUS$138\nHK Express (8)\nUS$213\nCathay Pacific (6)\nUS$420\nPeach (4)\nUS$272\nPhilippine Airlines (3)\nUS$272\nShow More\nAlliance\nSkyTeam\nUS$300\nStar Alliance\nUS$337\nOneworld\nUS$420\nTimes\nDeparture time\n00:00–24:00\n00:00\n24:00\nArrival time\n00:00–24:00\n00:00\n24:00\nDuration\nAny\nStopover Duration\n1h–16h 30m\n1h\n16h 30m\nTotal Duration\n2h–22h\n2h\n22h\nStops\n1 stop or fewer\nUS$138\nStopover cities\nAny\nHong Kong\nUS$138\nManila\nUS$272\nMacau\nUS$270\nDaegu\nUS$314\nAirports\nAny\nDeparture Airport\nTPE\nTaiwan Taoyuan International Airport\nUS$138\nArrival Airport\nKIX\nKansai International Airport\nUS$138\nAircrafts\nAny\nLarge aircraft\nUS$138\nMidsize aircraft\nUS$138\nCabin\nEconomy\nEconomy\nEconomy/premium economy\nPremium economy\nBusiness/first\nBusiness\nFirst class\nRecommended\nUS$183\nNonstop first\nUS$298\nCheapest\nUS$138\nSort by\nCreate price alert\nCheapest nonstop\nCarry-on baggage included\n- 16% CO2e\nAirAsia X Berhad\n15:40\nTPE T1\n2h 40m\nNonstop\n19:20\nKIX T1\nUS$183\nTotal US$365\nSelect\nCarry-on baggage included\nThai Vietjet Air\n07:30\nTPE T1\n2h 30m\nNonstop\n11:00\nKIX T1\nUS$195\nTotal US$390\nSelect\nCarry-on baggage included\nJetstar Japan\n18:10\nTPE T1\n2h 30m\nNonstop\n21:40\nKIX T1\nUS$222\nTotal US$443\nSelect\nCarry-on baggage included\nTigerair Taiwan\n14:40\nTPE T1\n2h 15m\nNonstop\n17:55\nKIX T1\nUS$257\nTotal US$513\nSelect\nPrice alerts\nWant a better deal? We'll notify you when the price drops below US$133.\nRecommended: US$133\nHigh chances of success\nOK\nIncluded\n- 18% CO2e\nPeach\n18:50\nTPE T1\n2h 25m\nNonstop\n22:15\nKIX T2\nUS$272\nTotal US$544\nSelect\nIncluded\n- 1% CO2e\nPeach\n01:45\nTPE T1\n2h 25m\nNonstop\n05:10\nKIX T2\nUS$298\nTotal US$596\nSelect\nIncluded\n- 3% CO2e\nChina Airlines\n14:20\nTPE T2\n2h 30m\nNonstop\n17:50\nKIX T1\nUS$300\nTotal US$600\nSelect\n<9 left\nCarry-on baggage included\nTigerair Taiwan\n07:00\nTPE T1\n2h 25m\nNonstop\n10:25\nKIX T1\nUS$322\nTotal US$644\nSelect\nIncluded\nPeach\n13:40\nTPE T1\n2h 25m\nNonstop\n17:05\nKIX T2\nUS$328\nTotal US$656\nSelect\nIncluded\n- 21% CO2e\nEVA Air\n06:30\nTPE T2\n2h 25m\nNonstop\n09:55\nKIX T1\nUS$337\nTotal US$673\nSelect\n<9 left\nIncluded\nChina Airlines\n09:45\nTPE T2\n2h 35m\nNonstop\n13:20\nKIX T1\nUS$398\nTotal US$796\nSelect\nIncluded\n- 18% CO2e\nPeach\n09:40\nTPE T1\n2h 30m\nNonstop\n13:10\nKIX T2\nUS$410\nTotal US$820\nSelect\nCarry-on baggage included\nJetstar Japan\n02:30\nTPE T1\n2h 30m\nNonstop\n06:00\nKIX T1\nUS$422\nTotal US$843\nSelect\nIncluded\n- 20% CO2e\nEVA Air\n08:20\nTPE T2\n2h 35m\nNonstop\n11:55\nKIX T1\nUS$428\nTotal US$856\nSelect\nIncluded\n- 21% CO2e\nEVA Air\n13:30\nTPE T2\n2h 25m\nNonstop\n16:55\nKIX T1\nUS$428\nTotal US$856\nSelect\nIncluded\n- 2% CO2e\nSTARLUX Airlines\n07:40\nTPE T1\n2h 30m\nNonstop\n11:10\nKIX T1\nUS$515\nTotal US$1,029\nSelect\nIncluded\nJapan Airlines\noperated by China Airlines\n08:05\nTPE T2\n2h 30m\nNonstop\n11:35\nKIX T1\nUS$959\nTotal US$1,917\nSelect\nCheapest\nIncluded\nHong Kong Airlines\n21:40\nTPE T2\n17h 25m\n11h 40m in Hong Kong\n16:05\nKIX T1\n +1\nUS$138\nTotal US$275\nSelect\nCheapest\nIncluded\nHong Kong Airlines\n21:40\nTPE T2\n20h 25m\n14h 50m in Hong Kong\n19:05\nKIX T1\n +1\nUS$138\nTotal US$275\nSelect\nCarry-on baggage included\nGreater Bay Airlines\n21:45\nTPE T1\n14h 10m\n8h 40m in Hong Kong\n12:55\nKIX T1\n +1\nUS$184\nTotal US$367\nSelect\nHK Express\n21:15\nTPE T1\n21h 5m\n15h 30m in Hong Kong\n19:20\nKIX T1\n +1\nUS$213\nTotal US$426\nSelect\nShow more results\nFlights\n > \nFlights\n > \nTaipei to Flights\nBook flights from Taipei to on Trip.com\n\nFirst class | Business class | Economy class | Nonstop\n\nSearch for cheap flights from Taipei to on Trip.com. Trip.com provides the best real-time Taipei to airfares and flight deals available, featuring advanced flight planning tools like price alerts, deal finder fare calendars, and Taipei Flight + Hotel deals that make a vacation or tour more convenient and affordable.\n\nAward-winning\nSupport in approx. 30s\nRewards for booking"
    ]
  }
}