{
  "url": "https://www.trip.com/flights/osaka-to-taipei/tickets-kix-tpe?dcity=kix&acity=tpe&ddate=2026-02-28&flighttype=ow&class=y&lowprice=&quantity=2&searchboxarg=t",
  "scraped_at": "2026-02-05T10:19:15.956828",
  "title": "Cheap Flights, Airline Tickets & Plane Tickets | Trip.com",
  "raw_text": "Go to main content\nTheme Detection\nHotels & Homes\nFlights\nTrains\nCar services\nApp\nUSD\nCustomer support\nFind bookings\nSign in / Register\nCheap Flights, Airline Tickets & Plane Tickets | Trip.com\nAllow notifications\nDon't miss out! Be the first to find out the latest travel info.\nAllow\nTaipei\nEdit\n2 adults\nEconomy\nFeb 28, 2026\nWed, Feb 25\nView\nThu, Feb 26\nView\nFri, Feb 27\nView\nSat, Feb 28\nUS$189\nSun, Mar 1\nView\nSat, Feb 21\nView\nSun, Feb 22\nView\nMon, Feb 23\nView\nTue, Feb 24\nView\nWed, Feb 25\nView\nThu, Feb 26\nView\nFri, Feb 27\nView\nSat, Feb 28\nUS$189\nSun, Mar 1\nView\nMon, Mar 2\nView\nTue, Mar 3\nView\nWed, Mar 4\nView\nThu, Mar 5\nView\nFri, Mar 6\nView\nSat, Mar 7\nView\nPrice graph\nRecommended\n Nonstop\n Checked baggage included\n Hide budget airlines\n Carry-on baggage included\n Hide codeshare flights\nCO2e Lower emission flights\nShow More\nAlliance\nStar Alliance\nUS$353\nSkyTeam\nUS$488\nOneworld\nUS$2,135\nAirlines\nAll flights with the same airline\nAll airlines\nHong Kong Airlines (10)\nUS$269\nHK Express (7)\nUS$351\nPeach (4)\nUS$259\nChina Airlines (3)\nUS$488\nSpring Airlines (3)\nUS$273\nShow More\nAlliance\nStar Alliance\nUS$353\nSkyTeam\nUS$488\nOneworld\nUS$2,135\nTimes\nDeparture time\n00:00–24:00\n00:00\n24:00\nArrival time\n00:00–24:00\n00:00\n24:00\nDuration\nAny\nStopover Duration\n1h 30m–20h\n1h 30m\n20h\nTotal Duration\n3h–26h 30m\n3h\n26h 30m\nStops\n1 stop or fewer\nUS$189\nStopover cities\nAny\nHong Kong\nUS$269\nShanghai\nUS$273\nMacau\nUS$271\nShenzhen\nUS$448\nAirports\nAny\nDeparture Airport\nKIX\nKansai International Airport\nUS$189\nArrival Airport\nTPE\nTaiwan Taoyuan International Airport\nUS$189\nAircrafts\nAny\nLarge aircraft\nUS$324\nMidsize aircraft\nUS$189\nCabin\nEconomy\nEconomy\nEconomy/premium economy\nPremium economy\nBusiness/first\nBusiness\nFirst class\nDeparting for Taipei\n48 flights found\nRecommended\nUS$189\nNonstop first\nUS$259\nCheapest\nUS$189\nSort by\nCreate price alert\n\nPrices are low and likely to increase—book now!\n\nCurrent lowest price: US$189.00\nLow price\n2 weeks ago\nToday\nDeparture\nUS$109.79\nAvg. US$318.70\nUS$527.60\nAdd a price alert\nCheapest\nCarry-on baggage included\nThai Vietjet Air\n12:00\nKIX T1\n3h 15m\nNonstop\n14:15\nTPE T1\nUS$189\nTotal US$378\nSelect\nCarry-on baggage included\n- 4% CO2e\nThai Lion Air\n13:30\nKIX T1\n3h 10m\nNonstop\n15:40\nTPE T1\nUS$207\nTotal US$413\nSelect\nCarry-on baggage included\nTigerair Taiwan\n11:30\nKIX T1\n3h 20m\nNonstop\n13:50\nTPE T1\nUS$231\nTotal US$462\nSelect\nIncluded\n- 20% CO2e\nPeach\n07:15\nKIX T2\n3h 30m\nNonstop\n09:45\nTPE T1\nUS$259\nTotal US$518\nSelect\nIncluded\nPeach\n10:10\nKIX T2\n3h 35m\nNonstop\n12:45\nTPE T1\nUS$302\nTotal US$603\nSelect\nIncluded\n- 20% CO2e\nPeach\n15:25\nKIX T2\n3h 30m\nNonstop\n17:55\nTPE T1\nUS$302\nTotal US$603\nSelect\nIncluded\n- 3% CO2e\nPeach\n22:00\nKIX T2\n3h 30m\nNonstop\n00:30\nTPE T1\n +1\nUS$302\nTotal US$603\nSelect\nCarry-on baggage included\nTigerair Taiwan\n19:55\nKIX T1\n3h 35m\nNonstop\n22:30\nTPE T1\nUS$303\nTotal US$605\nSelect\nCarry-on baggage included\nJetstar Japan\n23:10\nKIX T1\n3h 20m\nNonstop\n01:30\nTPE T1\n +1\nUS$322\nTotal US$643\nSelect\nCarry-on baggage included\n- 18% CO2e\nAirAsia X Berhad\n20:45\nKIX T1\n3h 20m\nNonstop\n23:05\nTPE T1\nUS$324\nTotal US$648\nSelect\nCarry-on baggage included\nJetstar Japan\n14:50\nKIX T1\n3h 20m\nNonstop\n17:10\nTPE T1\nUS$388\nTotal US$776\nSelect\nIncluded\n- 10% CO2e\nSTARLUX Airlines\n14:00\nKIX T1\n3h 15m\nNonstop\n16:15\nTPE T1\nUS$470\nTotal US$940\nSelect\nIncluded\n- 10% CO2e\nSTARLUX Airlines\n12:20\nKIX T1\n3h 15m\nNonstop\n14:35\nTPE T1\nUS$476\nTotal US$952\nSelect\nIncluded\n- 23% CO2e\nEVA Air\n18:10\nKIX T1\n3h 15m\nNonstop\n20:25\nTPE T2\nUS$488\nTotal US$976\nSelect\nIncluded\nHong Kong Airlines\n09:35\nKIX T1\n9h 45m\n3h 20m in Hong Kong\n18:20\nTPE T2\nUS$269\nTotal US$537\nSelect\nIncluded\nHong Kong Airlines\n09:35\nKIX T1\n12h\n5h 35m in Hong Kong\n20:35\nTPE T2\nUS$269\nTotal US$537\nSelect\nIncluded\nAir Macau\n13:45\nKIX T1\n8h\n1h 55m in Macau\n20:45\nTPE T1\nUS$271\nTotal US$541\nSelect\n<9 left\nCarry-on baggage included\nSpring Airlines\n15:00\nKIX T2\n20h 30m\n15h 25m in Shanghai\n10:30\nTPE T1\n +1\nUS$273\nTotal US$545\nSelect\nCarry-on baggage included\nSpring Airlines\n13:45\nKIX T2\n21h 45m\n16h 50m in Shanghai\n10:30\nTPE T1\n +1\nUS$273\nTotal US$545\nSelect\nIncluded\nHong Kong: Free Layover Tour\nHong Kong Airlines\n09:35\nKIX T1\n26h 15m\n19h 50m in Hong Kong\n10:50\nTPE T2\n +1\nUS$278\nTotal US$556\nSelect\nIncluded\nHong Kong Airlines\n20:05\nKIX T1\n15h 45m\n9h 25m in Hong Kong\n10:50\nTPE T2\n +1\nUS$299\nTotal US$598\nSelect\nIncluded\nHong Kong Airlines\n15:05\nKIX T1\n20h 45m\n14h 25m in Hong Kong\n10:50\nTPE T2\n +1\nUS$301\nTotal US$601\nSelect\nShow more results\n*Last updated: 10:19:07\nFlights\n > \nTaipei Flights\n > \nto Taipei Flights\nBook flights from to Taipei on Trip.com\n\nFirst class | Business class | Economy class | Nonstop\n\nSearch for cheap flights from to Taipei on Trip.com. Trip.com provides the best real-time to Taipei airfares and flight deals available, featuring advanced flight planning tools like price alerts, deal finder fare calendars, and Flight + Hotel deals that make a Taipei vacation or Taipei tour more convenient and affordable.\n\nAward-winning\nSupport in approx. 30s\nRewards for booking\nContact us\nCustomer support\nService guarantee\nMore service info\nAbout\nAbout Trip.com\nNews\nCareers\nTerms & Conditions\nPrivacy Statement\nAccessibility statement\nAbout Trip.com Group\nOther services\nInvestor relations\nTrip.com Rewards\nAffiliate program\nList your property\nAll hotels\nBecome a Supplier\nSecurity\nPayment methods\nOur partners\nContact Center\nof the year 2025\nCopyright © 2025 Trip.com Travel Singapore Pte. Ltd. All rights reserved\nSite Operator: Trip.com Travel Singapore Pte. Ltd.",
  "extracted": {
    "flight": {},
    "hotel": {},
    "price": {},
    "dates": {},
    "inclusions": [],
    "date_pricing": {}
  },
  "extracted_elements": {
    "flight_element": [
      "Thai Vietjet Air\n12:00\nKIX T1\n3h 15m\nNonstop\n14:15\nTPE T1",
      "Thai Lion Air\n13:30\nKIX T1\n3h 10m\nNonstop\n15:40\nTPE T1",
      "Tigerair Taiwan\n11:30\nKIX T1\n3h 20m\nNonstop\n13:50\nTPE T1",
      "Peach\n07:15\nKIX T2\n3h 30m\nNonstop\n09:45\nTPE T1",
      "Peach\n10:10\nKIX T2\n3h 35m\nNonstop\n12:45\nTPE T1"
    ],
    "price_class": [
      "Wed, Feb 25\nView\nThu, Feb 26\nView\nFri, Feb 27\nView\nSat, Feb 28\nUS$189\nSun, Mar 1\nView",
      "Wed, Feb 25\nView\nThu, Feb 26\nView\nFri, Feb 27\nView\nSat, Feb 28\nUS$189\nSun, Mar 1\nView",
      "Wed, Feb 25\nView\nThu, Feb 26\nView\nFri, Feb 27\nView\nSat, Feb 28\nUS$189\nSun, Mar 1\nView",
      "Wed, Feb 25\nView\nThu, Feb 26\nView\nFri, Feb 27\nView\nSat, Feb 28\nUS$189\nSun, Mar 1\nView",
      "Wed, Feb 25\nView\nThu, Feb 26\nView\nFri, Feb 27\nView\nSat, Feb 28\nUS$189\nSun, Mar 1\nView"
    ],
    "flight_class": [
      "Flights",
      "Taipei\nEdit\n2 adults\nEconomy\nFeb 28, 2026\nWed, Feb 25\nView\nThu, Feb 26\nView\nFri, Feb 27\nView\nSat, Feb 28\nUS$189\nSun, Mar 1\nView\nSat, Feb 21\nView\nSun, Feb 22\nView\nMon, Feb 23\nView\nTue, Feb 24\nView\nWed, Feb 25\nView\nThu, Feb 26\nView\nFri, Feb 27\nView\nSat, Feb 28\nUS$189\nSun, Mar 1\nView\nMon, Mar 2\nView\nTue, Mar 3\nView\nWed, Mar 4\nView\nThu, Mar 5\nView\nFri, Mar 6\nView\nSat, Mar 7\nView\nPrice graph\nRecommended\n Nonstop\n Checked baggage included\n Hide budget airlines\n Carry-on baggage included\n Hide codeshare flights\nCO2e Lower emission flights\nShow More\nAlliance\nStar Alliance\nUS$353\nSkyTeam\nUS$488\nOneworld\nUS$2,135\nAirlines\nAll flights with the same airline\nAll airlines\nHong Kong Airlines (10)\nUS$269\nHK Express (7)\nUS$351\nPeach (4)\nUS$259\nChina Airlines (3)\nUS$488\nSpring Airlines (3)\nUS$273\nShow More\nAlliance\nStar Alliance\nUS$353\nSkyTeam\nUS$488\nOneworld\nUS$2,135\nTimes\nDeparture time\n00:00–24:00\n00:00\n24:00\nArrival time\n00:00–24:00\n00:00\n24:00\nDuration\nAny\nStopover Duration\n1h 30m–20h\n1h 30m\n20h\nTotal Duration\n3h–26h 30m\n3h\n26h 30m\nStops\n1 stop or fewer\nUS$189\nStopover cities\nAny\nHong Kong\nUS$269\nShanghai\nUS$273\nMacau\nUS$271\nShenzhen\nUS$448\nAirports\nAny\nDeparture Airport\nKIX\nKansai International Airport\nUS$189\nArrival Airport\nTPE\nTaiwan Taoyuan International Airport\nUS$189\nAircrafts\nAny\nLarge aircraft\nUS$324\nMidsize aircraft\nUS$189\nCabin\nEconomy\nEconomy\nEconomy/premium economy\nPremium economy\nBusiness/first\nBusiness\nFirst class\nDeparting for Taipei\n48 flights found\nRecommended\nUS$189\nNonstop first\nUS$259\nCheapest\nUS$189\nSort by\nCreate price alert\n\nPrices are low and likely to increase—book now!\n\nCurrent lowest price: US$189.00\nLow price\n2 weeks ago\nToday\nDeparture\nUS$109.79\nAvg. US$318.70\nUS$527.60\nAdd a price alert\nCheapest\nCarry-on baggage included\nThai Vietjet Air\n12:00\nKIX T1\n3h 15m\nNonstop\n14:15\nTPE T1\nUS$189\nTotal US$378\nSelect\nCarry-on baggage included\n- 4% CO2e\nThai Lion Air\n13:30\nKIX T1\n3h 10m\nNonstop\n15:40\nTPE T1\nUS$207\nTotal US$413\nSelect\nCarry-on baggage included\nTigerair Taiwan\n11:30\nKIX T1\n3h 20m\nNonstop\n13:50\nTPE T1\nUS$231\nTotal US$462\nSelect\nIncluded\n- 20% CO2e\nPeach\n07:15\nKIX T2\n3h 30m\nNonstop\n09:45\nTPE T1\nUS$259\nTotal US$518\nSelect\nIncluded\nPeach\n10:10\nKIX T2\n3h 35m\nNonstop\n12:45\nTPE T1\nUS$302\nTotal US$603\nSelect\nIncluded\n- 20% CO2e\nPeach\n15:25\nKIX T2\n3h 30m\nNonstop\n17:55\nTPE T1\nUS$302\nTotal US$603\nSelect\nIncluded\n- 3% CO2e\nPeach\n22:00\nKIX T2\n3h 30m\nNonstop\n00:30\nTPE T1\n +1\nUS$302\nTotal US$603\nSelect\nCarry-on baggage included\nTigerair Taiwan\n19:55\nKIX T1\n3h 35m\nNonstop\n22:30\nTPE T1\nUS$303\nTotal US$605\nSelect\nCarry-on baggage included\nJetstar Japan\n23:10\nKIX T1\n3h 20m\nNonstop\n01:30\nTPE T1\n +1\nUS$322\nTotal US$643\nSelect\nCarry-on baggage included\n- 18% CO2e\nAirAsia X Berhad\n20:45\nKIX T1\n3h 20m\nNonstop\n23:05\nTPE T1\nUS$324\nTotal US$648\nSelect\nCarry-on baggage included\nJetstar Japan\n14:50\nKIX T1\n3h 20m\nNonstop\n17:10\nTPE T1\nUS$388\nTotal US$776\nSelect\nIncluded\n- 10% CO2e\nSTARLUX Airlines\n14:00\nKIX T1\n3h 15m\nNonstop\n16:15\nTPE T1\nUS$470\nTotal US$940\nSelect\nIncluded\n- 10% CO2e\nSTARLUX Airlines\n12:20\nKIX T1\n3h 15m\nNonstop\n14:35\nTPE T1\nUS$476\nTotal US$952\nSelect\nIncluded\n- 23% CO2e\nEVA Air\n18:10\nKIX T1\n3h 15m\nNonstop\n20:25\nTPE T2\nUS$488\nTotal US$976\nSelect\nIncluded\nHong Kong Airlines\n09:35\nKIX T1\n9h 45m\n3h 20m in Hong Kong\n18:20\nTPE T2\nUS$269\nTotal US$537\nSelect\nIncluded\nHong Kong Airlines\n09:35\nKIX T1\n12h\n5h 35m in Hong Kong\n20:35\nTPE T2\nUS$269\nTotal US$537\nSelect\nIncluded\nAir Macau\n13:45\nKIX T1\n8h\n1h 55m in Macau\n20:45\nTPE T1\nUS$271\nTotal US$541\nSelect\n<9 left\nCarry-on baggage included\nSpring Airlines\n15:00\nKIX T2\n20h 30m\n15h 25m in Shanghai\n10:30\nTPE T1\n +1\nUS$273\nTotal US$545\nSelect\nCarry-on baggage included\nSpring Airlines\n13:45\nKIX T2\n21h 45m\n16h 50m in Shanghai\n10:30\nTPE T1\n +1\nUS$273\nTotal US$545\nSelect\nIncluded\nHong Kong: Free Layover Tour\nHong Kong Airlines\n09:35\nKIX T1\n26h 15m\n19h 50m in Hong Kong\n10:50\nTPE T2\n +1\nUS$278\nTotal US$556\nSelect\nIncluded\nHong Kong Airlines\n20:05\nKIX T1\n15h 45m\n9h 25m in Hong Kong\n10:50\nTPE T2\n +1\nUS$299\nTotal US$598\nSelect\nIncluded\nHong Kong Airlines\n15:05\nKIX T1\n20h 45m\n14h 25m in Hong Kong\n10:50\nTPE T2\n +1\nUS$301\nTotal US$601\nSelect\nShow more results\n*Last updated: 10:19:07\nFlights\n > \nTaipei Flights\n > \nto Taipei Flights\nBook flights from to Taipei on Trip.com\n\nFirst class | Business class | Economy class | Nonstop\n\nSearch for cheap flights from to Taipei on Trip.com. Trip.com provides the best real-time to Taipei airfares and flight deals available, featuring advanced flight planning tools like price alerts, deal finder fare calendars, and Flight + Hotel deals that make a Taipei vacation or Taipei tour more convenient and affordable.\n\nAward-winning\nSupport in approx. 30s\nRewards for booking",
      "Taipei\nEdit\n2 adults\nEconomy\nFeb 28, 2026\nWed, Feb 25\nView\nThu, Feb 26\nView\nFri, Feb 27\nView\nSat, Feb 28\nUS$189\nSun, Mar 1\nView",
      "DepartSat, Feb 28"
    ],
    "hotel_class": [
      "Hotels & Homes"
    ],
    "main": [
      "Cheap Flights, Airline Tickets & Plane Tickets | Trip.com\nAllow notifications\nDon't miss out! Be the first to find out the latest travel info.\nAllow\nTaipei\nEdit\n2 adults\nEconomy\nFeb 28, 2026\nWed, Feb 25\nView\nThu, Feb 26\nView\nFri, Feb 27\nView\nSat, Feb 28\nUS$189\nSun, Mar 1\nView\nSat, Feb 21\nView\nSun, Feb 22\nView\nMon, Feb 23\nView\nTue, Feb 24\nView\nWed, Feb 25\nView\nThu, Feb 26\nView\nFri, Feb 27\nView\nSat, Feb 28\nUS$189\nSun, Mar 1\nView\nMon, Mar 2\nView\nTue, Mar 3\nView\nWed, Mar 4\nView\nThu, Mar 5\nView\nFri, Mar 6\nView\nSat, Mar 7\nView\nPrice graph\nRecommended\n Nonstop\n Checked baggage included\n Hide budget airlines\n Carry-on baggage included\n Hide codeshare flights\nCO2e Lower emission flights\nShow More\nAlliance\nStar Alliance\nUS$353\nSkyTeam\nUS$488\nOneworld\nUS$2,135\nAirlines\nAll flights with the same airline\nAll airlines\nHong Kong Airlines (10)\nUS$269\nHK Express (7)\nUS$351\nPeach (4)\nUS$259\nChina Airlines (3)\nUS$488\nSpring Airlines (3)\nUS$273\nShow More\nAlliance\nStar Alliance\nUS$353\nSkyTeam\nUS$488\nOneworld\nUS$2,135\nTimes\nDeparture time\n00:00–24:00\n00:00\n24:00\nArrival time\n00:00–24:00\n00:00\n24:00\nDuration\nAny\nStopover Duration\n1h 30m–20h\n1h 30m\n20h\nTotal Duration\n3h–26h 30m\n3h\n26h 30m\nStops\n1 stop or fewer\nUS$189\nStopover cities\nAny\nHong Kong\nUS$269\nShanghai\nUS$273\nMacau\nUS$271\nShenzhen\nUS$448\nAirports\nAny\nDeparture Airport\nKIX\nKansai International Airport\nUS$189\nArrival Airport\nTPE\nTaiwan Taoyuan International Airport\nUS$189\nAircrafts\nAny\nLarge aircraft\nUS$324\nMidsize aircraft\nUS$189\nCabin\nEconomy\nEconomy\nEconomy/premium economy\nPremium economy\nBusiness/first\nBusiness\nFirst class\nDeparting for Taipei\n48 flights found\nRecommended\nUS$189\nNonstop first\nUS$259\nCheapest\nUS$189\nSort by\nCreate price alert\n\nPrices are low and likely to increase—book now!\n\nCurrent lowest price: US$189.00\nLow price\n2 weeks ago\nToday\nDeparture\nUS$109.79\nAvg. US$318.70\nUS$527.60\nAdd a price alert\nCheapest\nCarry-on baggage included\nThai Vietjet Air\n12:00\nKIX T1\n3h 15m\nNonstop\n14:15\nTPE T1\nUS$189\nTotal US$378\nSelect\nCarry-on baggage included\n- 4% CO2e\nThai Lion Air\n13:30\nKIX T1\n3h 10m\nNonstop\n15:40\nTPE T1\nUS$207\nTotal US$413\nSelect\nCarry-on baggage included\nTigerair Taiwan\n11:30\nKIX T1\n3h 20m\nNonstop\n13:50\nTPE T1\nUS$231\nTotal US$462\nSelect\nIncluded\n- 20% CO2e\nPeach\n07:15\nKIX T2\n3h 30m\nNonstop\n09:45\nTPE T1\nUS$259\nTotal US$518\nSelect\nIncluded\nPeach\n10:10\nKIX T2\n3h 35m\nNonstop\n12:45\nTPE T1\nUS$302\nTotal US$603\nSelect\nIncluded\n- 20% CO2e\nPeach\n15:25\nKIX T2\n3h 30m\nNonstop\n17:55\nTPE T1\nUS$302\nTotal US$603\nSelect\nIncluded\n- 3% CO2e\nPeach\n22:00\nKIX T2\n3h 30m\nNonstop\n00:30\nTPE T1\n +1\nUS$302\nTotal US$603\nSelect\nCarry-on baggage included\nTigerair Taiwan\n19:55\nKIX T1\n3h 35m\nNonstop\n22:30\nTPE T1\nUS$303\nTotal US$605\nSelect\nCarry-on baggage included\nJetstar Japan\n23:10\nKIX T1\n3h 20m\nNonstop\n01:30\nTPE T1\n +1\nUS$322\nTotal US$643\nSelect\nCarry-on baggage included\n- 18% CO2e\nAirAsia X Berhad\n20:45\nKIX T1\n3h 20m\nNonstop\n23:05\nTPE T1\nUS$324\nTotal US$648\nSelect\nCarry-on baggage included\nJetstar Japan\n14:50\nKIX T1\n3h 20m\nNonstop\n17:10\nTPE T1\nUS$388\nTotal US$776\nSelect\nIncluded\n- 10% CO2e\nSTARLUX Airlines\n14:00\nKIX T1\n3h 15m\nNonstop\n16:15\nTPE T1\nUS$470\nTotal US$940\nSelect\nIncluded\n- 10% CO2e\nSTARLUX Airlines\n12:20\nKIX T1\n3h 15m\nNonstop\n14:35\nTPE T1\nUS$476\nTotal US$952\nSelect\nIncluded\n- 23% CO2e\nEVA Air\n18:10\nKIX T1\n3h 15m\nNonstop\n20:25\nTPE T2\nUS$488\nTotal US$976\nSelect\nIncluded\nHong Kong Airlines\n09:35\nKIX T1\n9h 45m\n3h 20m in Hong Kong\n18:20\nTPE T2\nUS$269\nTotal US$537\nSelect\nIncluded\nHong Kong Airlines\n09:35\nKIX T1\n12h\n5h 35m in Hong Kong\n20:35\nTPE T2\nUS$269\nTotal US$537\nSelect\nIncluded\nAir Macau\n13:45\nKIX T1\n8h\n1h 55m in Macau\n20:45\nTPE T1\nUS$271\nTotal US$541\nSelect\n<9 left\nCarry-on baggage included\nSpring Airlines\n15:00\nKIX T2\n20h 30m\n15h 25m in Shanghai\n10:30\nTPE T1\n +1\nUS$273\nTotal US$545\nSelect\nCarry-on baggage included\nSpring Airlines\n13:45\nKIX T2\n21h 45m\n16h 50m in Shanghai\n10:30\nTPE T1\n +1\nUS$273\nTotal US$545\nSelect\nIncluded\nHong Kong: Free Layover Tour\nHong Kong Airlines\n09:35\nKIX T1\n26h 15m\n19h 50m in Hong Kong\n10:50\nTPE T2\n +1\nUS$278\nTotal US$556\nSelect\nIncluded\nHong Kong Airlines\n20:05\nKIX T1\n15h 45m\n9h 25m in Hong Kong\n10:50\nTPE T2\n +1\nUS$299\nTotal US$598\nSelect\nIncluded\nHong Kong Airlines\n15:05\nKIX T1\n20h 45m\n14h 25m in Hong Kong\n10:50\nTPE T2\n +1\nUS$301\nTotal US$601\nSelect\nShow more results\n*Last updated: 10:19:07\nFlights\n > \nTaipei Flights\n > \nto Taipei Flights\nBook flights from to Taipei on Trip.com\n\nFirst class | Business class | Economy class | Nonstop\n\nSearch for cheap flights from to Taipei on Trip.com. Trip.com provides the best real-time to Taipei airfares and flight deals available, featuring advanced flight planning tools like price alerts, deal finder fare calendars, and Flight + Hotel deals that make a Taipei vacation or Taipei tour more convenient and affordable.\n\nAward-winning\nSupport in approx. 30s\nRewards for booking"
    ]
  }
}