{
  "url": "https://www.trip.com/flights/taipei-to-osaka/tickets-tpe-kix?dcity=tpe&acity=kix&ddate=2026-02-25&flighttype=ow&class=y&quantity=2",
  "scraped_at": "2026-02-05T14:27:53.321364",
  "title": "Cheap Flights, Airline Tickets & Plane Tickets | Trip.com",
  "raw_text": "Go to main content\nTheme Detection\nHotels & Homes\nFlights\nTrains\nCar services\nApp\nUSD\nCustomer support\nFind bookings\nSign in / Register\nCheap Flights, Airline Tickets & Plane Tickets | Trip.com\nAllow notifications\nDon't miss out! Be the first to find out the latest travel info.\nAllow\nTaipei\nEdit\n2 adults\nEconomy\nFeb 25, 2026\nSun, Feb 22\nView\nMon, Feb 23\nView\nTue, Feb 24\nView\nWed, Feb 25\nUS$145\nThu, Feb 26\nView\nWed, Feb 18\nView\nThu, Feb 19\nView\nFri, Feb 20\nView\nSat, Feb 21\nView\nSun, Feb 22\nView\nMon, Feb 23\nView\nTue, Feb 24\nView\nWed, Feb 25\nUS$145\nThu, Feb 26\nView\nFri, Feb 27\nView\nSat, Feb 28\nView\nSun, Mar 1\nView\nMon, Mar 2\nView\nTue, Mar 3\nView\nWed, Mar 4\nView\nPrice graph\nRecommended\n Nonstop\n Checked baggage included\n Hide budget airlines\n Student tickets\n Carry-on baggage included\n Hide codeshare flights\nCO2e Lower emission flights\nShow More\nAlliance\nSkyTeam\nUS$262\nStar Alliance\nUS$278\nOneworld\nUS$319\nAirlines\nAll flights with the same airline\nAll airlines\nCathay Pacific (14)\nUS$319\nHong Kong Airlines (12)\nUS$191\nHK Express (11)\nUS$193\nJapan Airlines (6)\nUS$329\nPeach (4)\nUS$193\nShow More\nAlliance\nSkyTeam\nUS$262\nStar Alliance\nUS$278\nOneworld\nUS$319\nTimes\nDeparture time\n00:00–24:00\n00:00\n24:00\nArrival time\n00:00–24:00\n00:00\n24:00\nDuration\nAny\nStopover Duration\n1h–24h\n1h\n24h\nTotal Duration\n2h–29h 30m\n2h\n29h 30m\nStops\n1 stop or fewer\nUS$145\nStopover cities\nAny\nHong Kong\nUS$191\nMacau\nUS$270\nManila\nUS$265\nTokyo\nUS$329\nJeju\nUS$210\nDaegu\nUS$275\nSeoul\nUS$278\nHo Chi Minh City\nUS$310\nBusan\nUS$338\nAirports\nAny\nDeparture Airport\nTSA\nTaipei Songshan Airport\nUS$386\nTPE\nTaiwan Taoyuan International Airport\nUS$145\nArrival Airport\nKIX\nKansai International Airport\nUS$145\nAircrafts\nAny\nLarge aircraft\nUS$145\nMidsize aircraft\nUS$154\nCabin\nEconomy\nEconomy\nEconomy/premium economy\nPremium economy\nBusiness/first\nBusiness\nFirst class\n78 flights found\nRecommended\nUS$145\nNonstop first\nUS$145\nCheapest\nUS$145\nSort by\nCreate price alert\nCheapest\nCarry-on baggage included\n- 16% CO2e\nAirAsia X Berhad\n15:40\nTPE T1\n2h 40m\nNonstop\n19:20\nKIX T1\nUS$145\nTotal US$289\nSelect\nCarry-on baggage included\nThai Vietjet Air\n07:30\nTPE T1\n2h 30m\nNonstop\n11:00\nKIX T1\nUS$154\nTotal US$307\nSelect\nCarry-on baggage included\n- 1% CO2e\nPeach\n01:45\nTPE T1\n2h 25m\nNonstop\n05:10\nKIX T2\nUS$193\nTotal US$385\nSelect\nCarry-on baggage included\n- 18% CO2e\nPeach\n18:50\nTPE T1\n2h 25m\nNonstop\n22:15\nKIX T2\nUS$198\nTotal US$395\nSelect\nSign in & save for future trips\nEarn at least 29 Trip Coins worth US$0.29 for this booking, which you can use to save on future trips!\nSign in/register\nCarry-on baggage included\nPeach\n13:40\nTPE T1\n2h 25m\nNonstop\n17:05\nKIX T2\nUS$213\nTotal US$425\nSelect\nCarry-on baggage included\n- 18% CO2e\nPeach\n09:40\nTPE T1\n2h 30m\nNonstop\n13:10\nKIX T2\nUS$218\nTotal US$435\nSelect\nCarry-on baggage included\nTigerair Taiwan\n14:40\nTPE T1\n2h 15m\nNonstop\n17:55\nKIX T1\nUS$218\nTotal US$435\nSelect\nCarry-on baggage included\nTigerair Taiwan\n07:00\nTPE T1\n2h 25m\nNonstop\n10:25\nKIX T1\nUS$256\nTotal US$512\nSelect\nIncluded\n- 3% CO2e\nChina Airlines\n14:20\nTPE T2\n2h 30m\nNonstop\n17:50\nKIX T1\nUS$262\nTotal US$524\nSelect\nIncluded\nChina Airlines\n09:45\nTPE T2\n2h 35m\nNonstop\n13:20\nKIX T1\nUS$271\nTotal US$542\nSelect\nCarry-on baggage included\nJetstar Japan\n02:30\nTPE T1\n2h 30m\nNonstop\n06:00\nKIX T1\nUS$273\nTotal US$546\nSelect\nIncluded\n- 21% CO2e\nEVA Air\n06:30\nTPE T2\n2h 25m\nNonstop\n09:55\nKIX T1\nUS$314\nTotal US$628\nSelect\nIncluded\n- 18% CO2e\nCathay Pacific\n11:15\nTPE T1\n2h 40m\nNonstop\n14:55\nKIX T1\nUS$319\nTotal US$638\nUS$292\nSelect\nIncluded\n- 20% CO2e\nEVA Air\n08:20\nTPE T2\n2h 35m\nNonstop\n11:55\nKIX T1\nUS$337\nTotal US$673\nSelect\nIncluded\n- 2% CO2e\nSTARLUX Airlines\n07:40\nTPE T1\n2h 30m\nNonstop\n11:10\nKIX T1\nUS$339\nTotal US$677\nSelect\nIncluded\n- 7% CO2e\nSTARLUX Airlines\n09:20\nTPE T1\n2h 30m\nNonstop\n12:50\nKIX T1\nUS$340\nTotal US$679\nSelect\nIncluded\nChina Airlines\n08:05\nTPE T2\n2h 30m\nNonstop\n11:35\nKIX T1\nUS$397\nTotal US$794\nSelect\nIncluded\nJapan Airlines\noperated by China Airlines\n08:05\nTPE T2\n2h 30m\nNonstop\n11:35\nKIX T1\nUS$959\nTotal US$1,917\nSelect\nIncluded\nJapan Airlines\noperated by China Airlines\n14:20\nTPE T2\n2h 30m\nNonstop\n17:50\nKIX T1\nUS$959\nTotal US$1,917\nSelect\nIncluded\nAll Nippon Airways\noperated by EVA Air\n06:30\nTPE T2\n2h 25m\nNonstop\n09:55\nKIX T1\nUS$964\nTotal US$1,928\nSelect\nIncluded\nAll Nippon Airways\noperated by EVA Air\n08:20\nTPE T2\n2h 35m\nNonstop\n11:55\nKIX T1\nUS$964\nTotal US$1,928\nSelect\nIncluded\nAll Nippon Airways\noperated by EVA Air\n13:30\nTPE T2\n2h 25m\nNonstop\n16:55\nKIX T1\nUS$964\nTotal US$1,928\nSelect\nIncluded\nHong Kong Airlines\n21:40\nTPE T2\n8h 35m\n3h in Hong Kong\n07:15\nKIX T1\n +1\nUS$191\nTotal US$382\nSelect\nIncluded\nHong Kong Airlines\n21:40\nTPE T2\n15h 25m\n9h 50m in Hong Kong\n14:05\nKIX T1\n +1\nUS$191\nTotal US$382\nSelect\nIncluded\nHong Kong Airlines\n21:40\nTPE T2\n17h 25m\n11h 40m in Hong Kong\n16:05\nKIX T1\n +1\nUS$191\nTotal US$382\nSelect\nIncluded\nHong Kong Airlines\n21:40\nTPE T2\n20h 25m\n14h 50m in Hong Kong\n19:05\nKIX T1\n +1\nUS$191\nTotal US$382\nSelect\nHK Express\n21:15\nTPE T1\n18h\n12h 25m in Hong Kong\n16:15\nKIX T1\n +1\nUS$193\nTotal US$386\nSelect\nHK Express\n21:15\nTPE T1\n21h 5m\n15h 30m in Hong Kong\n19:20\nKIX T1\n +1\nUS$193\nTotal US$386\nSelect\nHK Express\n21:15\nTPE T1\n21h 55m\n16h 20m in Hong Kong\n20:10\nKIX T1\n +1\nUS$193\nTotal US$386\nSelect\nIncluded\nT'Way Air\n14:25\nTPE T1\n26h 15m\n22h 35m in Jeju\n17:40\nKIX T1\n +1\nUS$210\nTotal US$420\nSelect\nHK Express\n17:40\nTPE T1\n21h 35m\n16h 10m in Hong Kong\n16:15\nKIX T1\n +1\nUS$216\nTotal US$431\nSelect\nHong Kong: Free Layover Tour\nHK Express\n13:55\nTPE T1\n25h 20m\n19h 50m in Hong Kong\n16:15\nKIX T1\n +1\nUS$232\nTotal US$464\nSelect\nHK Express\n17:40\nTPE T1\n25h 30m\n20h 5m in Hong Kong\n20:10\nKIX T1\n +1\nUS$232\nTotal US$464\nSelect\nIncluded\nVietJet Air\n19:00\nTPE T1\n12h 30m\n3h 55m in Ho Chi Minh City\n08:30\nKIX T1\n +1\nUS$310\nTotal US$620\nSelect\nIncluded\nPhilippine Airlines\n21:35\nTPE T1\n15h 30m\n9h 5m in Manila\n14:05\nKIX T1\n +1\nUS$310\nTotal US$620\nSelect\nIncluded\nJapan Airlines\noperated by Jetstar Japan\n13:25\nTPE T2\n18h 20m\n13h 30m in Tokyo\n08:45\nKIX T1\n +1\nUS$329\nTotal US$657\nSelect\nIncluded\nJapan Airlines\noperated by Jetstar Japan\n13:25\nTPE T2\n19h 45m\n14h 55m in Tokyo\n10:10\nKIX T1\n +1\nUS$330\nTotal US$659\nSelect\nIncluded\nJin Air\n02:40\nTPE T1\n6h 20m\n2h 40m in Busan\n10:00\nKIX T1\nUS$338\nTotal US$676\nSelect\nIncluded\nJapan Airlines\n15:35\nTSA T1\n15h 50m\n11h 35m in Tokyo\n08:25\nKIX T1\n +1\nUS$386\nTotal US$772\nSelect\nIncluded\nCathay Pacific\n22:20\nTPE T1\n7h\n1h 20m in Hong Kong\n06:20\nKIX T1\n +1\nUS$418\nTotal US$835\nUS$384\nSelect\n*Last updated: 14:27:45\nFlights\n > \nFlights\n > \nTaipei to Flights\nBook flights from Taipei to on Trip.com\n\nFirst class | Business class | Economy class | Nonstop\n\nSearch for cheap flights from Taipei to on Trip.com. Trip.com provides the best real-time Taipei to airfares and flight deals available, featuring advanced flight planning tools like price alerts, deal finder fare calendars, and Taipei Flight + Hotel deals that make a vacation or tour more convenient and affordable.\n\nAward-winning\nSupport in approx. 30s\nRewards for booking\nContact us\nCustomer support\nService guarantee\nMore service info\nAbout\nAbout Trip.com\nNews\nCareers\nTerms & Conditions\nPrivacy Statement\nAccessibility statement\nAbout Trip.com Group\nOther services\nInvestor relations\nTrip.com Rewards\nAffiliate program\nList your property\nAll hotels\nBecome a Supplier\nSecurity\nPayment methods\nOur partners\nContact Center\nof the year 2025\nCopyright © 2025 Trip.com Travel Singapore Pte. Ltd. All rights reserved\nSite Operator: Trip.com Travel Singapore Pte. Ltd.",
  "extracted": {
    "flight": {},
    "hotel": {},
    "price": {},
    "dates": {},
    "inclusions": [],
    "date_pricing": {}
  },
  "extracted_elements": {
    "flight_element": [
      "AirAsia X Berhad\n15:40\nTPE T1\n2h 40m\nNonstop\n19:20\nKIX T1",
      "Thai Vietjet Air\n07:30\nTPE T1\n2h 30m\nNonstop\n11:00\nKIX T1",
      "Peach\n01:45\nTPE T1\n2h 25m\nNonstop\n05:10\nKIX T2",
      "Peach\n18:50\nTPE T1\n2h 25m\nNonstop\n22:15\nKIX T2",
      "Peach\n13:40\nTPE T1\n2h 25m\nNonstop\n17:05\nKIX T2"
    ],
    "price_class": [
      "Sun, Feb 22\nView\nMon, Feb 23\nView\nTue, Feb 24\nView\nWed, Feb 25\nUS$145\nThu, Feb 26\nView",
      "Sun, Feb 22\nView\nMon, Feb 23\nView\nTue, Feb 24\nView\nWed, Feb 25\nUS$145\nThu, Feb 26\nView",
      "Sun, Feb 22\nView\nMon, Feb 23\nView\nTue, Feb 24\nView\nWed, Feb 25\nUS$145\nThu, Feb 26\nView",
      "Sun, Feb 22\nView\nMon, Feb 23\nView\nTue, Feb 24\nView\nWed, Feb 25\nUS$145\nThu, Feb 26\nView",
      "Sun, Feb 22\nView\nMon, Feb 23\nView\nTue, Feb 24\nView\nWed, Feb 25\nUS$145\nThu, Feb 26\nView"
    ],
    "flight_class": [
      "Flights",
      "Taipei\nEdit\n2 adults\nEconomy\nFeb 25, 2026\nSun, Feb 22\nView\nMon, Feb 23\nView\nTue, Feb 24\nView\nWed, Feb 25\nUS$145\nThu, Feb 26\nView\nWed, Feb 18\nView\nThu, Feb 19\nView\nFri, Feb 20\nView\nSat, Feb 21\nView\nSun, Feb 22\nView\nMon, Feb 23\nView\nTue, Feb 24\nView\nWed, Feb 25\nUS$145\nThu, Feb 26\nView\nFri, Feb 27\nView\nSat, Feb 28\nView\nSun, Mar 1\nView\nMon, Mar 2\nView\nTue, Mar 3\nView\nWed, Mar 4\nView\nPrice graph\nRecommended\n Nonstop\n Checked baggage included\n Hide budget airlines\n Student tickets\n Carry-on baggage included\n Hide codeshare flights\nCO2e Lower emission flights\nShow More\nAlliance\nSkyTeam\nUS$262\nStar Alliance\nUS$278\nOneworld\nUS$319\nAirlines\nAll flights with the same airline\nAll airlines\nCathay Pacific (14)\nUS$319\nHong Kong Airlines (12)\nUS$191\nHK Express (11)\nUS$193\nJapan Airlines (6)\nUS$329\nPeach (4)\nUS$193\nShow More\nAlliance\nSkyTeam\nUS$262\nStar Alliance\nUS$278\nOneworld\nUS$319\nTimes\nDeparture time\n00:00–24:00\n00:00\n24:00\nArrival time\n00:00–24:00\n00:00\n24:00\nDuration\nAny\nStopover Duration\n1h–24h\n1h\n24h\nTotal Duration\n2h–29h 30m\n2h\n29h 30m\nStops\n1 stop or fewer\nUS$145\nStopover cities\nAny\nHong Kong\nUS$191\nMacau\nUS$270\nManila\nUS$265\nTokyo\nUS$329\nJeju\nUS$210\nDaegu\nUS$275\nSeoul\nUS$278\nHo Chi Minh City\nUS$310\nBusan\nUS$338\nAirports\nAny\nDeparture Airport\nTSA\nTaipei Songshan Airport\nUS$386\nTPE\nTaiwan Taoyuan International Airport\nUS$145\nArrival Airport\nKIX\nKansai International Airport\nUS$145\nAircrafts\nAny\nLarge aircraft\nUS$145\nMidsize aircraft\nUS$154\nCabin\nEconomy\nEconomy\nEconomy/premium economy\nPremium economy\nBusiness/first\nBusiness\nFirst class\n78 flights found\nRecommended\nUS$145\nNonstop first\nUS$145\nCheapest\nUS$145\nSort by\nCreate price alert\nCheapest\nCarry-on baggage included\n- 16% CO2e\nAirAsia X Berhad\n15:40\nTPE T1\n2h 40m\nNonstop\n19:20\nKIX T1\nUS$145\nTotal US$289\nSelect\nCarry-on baggage included\nThai Vietjet Air\n07:30\nTPE T1\n2h 30m\nNonstop\n11:00\nKIX T1\nUS$154\nTotal US$307\nSelect\nCarry-on baggage included\n- 1% CO2e\nPeach\n01:45\nTPE T1\n2h 25m\nNonstop\n05:10\nKIX T2\nUS$193\nTotal US$385\nSelect\nCarry-on baggage included\n- 18% CO2e\nPeach\n18:50\nTPE T1\n2h 25m\nNonstop\n22:15\nKIX T2\nUS$198\nTotal US$395\nSelect\nSign in & save for future trips\nEarn at least 29 Trip Coins worth US$0.29 for this booking, which you can use to save on future trips!\nSign in/register\nCarry-on baggage included\nPeach\n13:40\nTPE T1\n2h 25m\nNonstop\n17:05\nKIX T2\nUS$213\nTotal US$425\nSelect\nCarry-on baggage included\n- 18% CO2e\nPeach\n09:40\nTPE T1\n2h 30m\nNonstop\n13:10\nKIX T2\nUS$218\nTotal US$435\nSelect\nCarry-on baggage included\nTigerair Taiwan\n14:40\nTPE T1\n2h 15m\nNonstop\n17:55\nKIX T1\nUS$218\nTotal US$435\nSelect\nCarry-on baggage included\nTigerair Taiwan\n07:00\nTPE T1\n2h 25m\nNonstop\n10:25\nKIX T1\nUS$256\nTotal US$512\nSelect\nIncluded\n- 3% CO2e\nChina Airlines\n14:20\nTPE T2\n2h 30m\nNonstop\n17:50\nKIX T1\nUS$262\nTotal US$524\nSelect\nIncluded\nChina Airlines\n09:45\nTPE T2\n2h 35m\nNonstop\n13:20\nKIX T1\nUS$271\nTotal US$542\nSelect\nCarry-on baggage included\nJetstar Japan\n02:30\nTPE T1\n2h 30m\nNonstop\n06:00\nKIX T1\nUS$273\nTotal US$546\nSelect\nIncluded\n- 21% CO2e\nEVA Air\n06:30\nTPE T2\n2h 25m\nNonstop\n09:55\nKIX T1\nUS$314\nTotal US$628\nSelect\nIncluded\n- 18% CO2e\nCathay Pacific\n11:15\nTPE T1\n2h 40m\nNonstop\n14:55\nKIX T1\nUS$319\nTotal US$638\nUS$292\nSelect\nIncluded\n- 20% CO2e\nEVA Air\n08:20\nTPE T2\n2h 35m\nNonstop\n11:55\nKIX T1\nUS$337\nTotal US$673\nSelect\nIncluded\n- 2% CO2e\nSTARLUX Airlines\n07:40\nTPE T1\n2h 30m\nNonstop\n11:10\nKIX T1\nUS$339\nTotal US$677\nSelect\nIncluded\n- 7% CO2e\nSTARLUX Airlines\n09:20\nTPE T1\n2h 30m\nNonstop\n12:50\nKIX T1\nUS$340\nTotal US$679\nSelect\nIncluded\nChina Airlines\n08:05\nTPE T2\n2h 30m\nNonstop\n11:35\nKIX T1\nUS$397\nTotal US$794\nSelect\nIncluded\nJapan Airlines\noperated by China Airlines\n08:05\nTPE T2\n2h 30m\nNonstop\n11:35\nKIX T1\nUS$959\nTotal US$1,917\nSelect\nIncluded\nJapan Airlines\noperated by China Airlines\n14:20\nTPE T2\n2h 30m\nNonstop\n17:50\nKIX T1\nUS$959\nTotal US$1,917\nSelect\nIncluded\nAll Nippon Airways\noperated by EVA Air\n06:30\nTPE T2\n2h 25m\nNonstop\n09:55\nKIX T1\nUS$964\nTotal US$1,928\nSelect\nIncluded\nAll Nippon Airways\noperated by EVA Air\n08:20\nTPE T2\n2h 35m\nNonstop\n11:55\nKIX T1\nUS$964\nTotal US$1,928\nSelect\nIncluded\nAll Nippon Airways\noperated by EVA Air\n13:30\nTPE T2\n2h 25m\nNonstop\n16:55\nKIX T1\nUS$964\nTotal US$1,928\nSelect\nIncluded\nHong Kong Airlines\n21:40\nTPE T2\n8h 35m\n3h in Hong Kong\n07:15\nKIX T1\n +1\nUS$191\nTotal US$382\nSelect\nIncluded\nHong Kong Airlines\n21:40\nTPE T2\n15h 25m\n9h 50m in Hong Kong\n14:05\nKIX T1\n +1\nUS$191\nTotal US$382\nSelect\nIncluded\nHong Kong Airlines\n21:40\nTPE T2\n17h 25m\n11h 40m in Hong Kong\n16:05\nKIX T1\n +1\nUS$191\nTotal US$382\nSelect\nIncluded\nHong Kong Airlines\n21:40\nTPE T2\n20h 25m\n14h 50m in Hong Kong\n19:05\nKIX T1\n +1\nUS$191\nTotal US$382\nSelect\nHK Express\n21:15\nTPE T1\n18h\n12h 25m in Hong Kong\n16:15\nKIX T1\n +1\nUS$193\nTotal US$386\nSelect\nHK Express\n21:15\nTPE T1\n21h 5m\n15h 30m in Hong Kong\n19:20\nKIX T1\n +1\nUS$193\nTotal US$386\nSelect\nHK Express\n21:15\nTPE T1\n21h 55m\n16h 20m in Hong Kong\n20:10\nKIX T1\n +1\nUS$193\nTotal US$386\nSelect\nIncluded\nT'Way Air\n14:25\nTPE T1\n26h 15m\n22h 35m in Jeju\n17:40\nKIX T1\n +1\nUS$210\nTotal US$420\nSelect\nHK Express\n17:40\nTPE T1\n21h 35m\n16h 10m in Hong Kong\n16:15\nKIX T1\n +1\nUS$216\nTotal US$431\nSelect\nHong Kong: Free Layover Tour\nHK Express\n13:55\nTPE T1\n25h 20m\n19h 50m in Hong Kong\n16:15\nKIX T1\n +1\nUS$232\nTotal US$464\nSelect\nHK Express\n17:40\nTPE T1\n25h 30m\n20h 5m in Hong Kong\n20:10\nKIX T1\n +1\nUS$232\nTotal US$464\nSelect\nIncluded\nVietJet Air\n19:00\nTPE T1\n12h 30m\n3h 55m in Ho Chi Minh City\n08:30\nKIX T1\n +1\nUS$310\nTotal US$620\nSelect\nIncluded\nPhilippine Airlines\n21:35\nTPE T1\n15h 30m\n9h 5m in Manila\n14:05\nKIX T1\n +1\nUS$310\nTotal US$620\nSelect\nIncluded\nJapan Airlines\noperated by Jetstar Japan\n13:25\nTPE T2\n18h 20m\n13h 30m in Tokyo\n08:45\nKIX T1\n +1\nUS$329\nTotal US$657\nSelect\nIncluded\nJapan Airlines\noperated by Jetstar Japan\n13:25\nTPE T2\n19h 45m\n14h 55m in Tokyo\n10:10\nKIX T1\n +1\nUS$330\nTotal US$659\nSelect\nIncluded\nJin Air\n02:40\nTPE T1\n6h 20m\n2h 40m in Busan\n10:00\nKIX T1\nUS$338\nTotal US$676\nSelect\nIncluded\nJapan Airlines\n15:35\nTSA T1\n15h 50m\n11h 35m in Tokyo\n08:25\nKIX T1\n +1\nUS$386\nTotal US$772\nSelect\nIncluded\nCathay Pacific\n22:20\nTPE T1\n7h\n1h 20m in Hong Kong\n06:20\nKIX T1\n +1\nUS$418\nTotal US$835\nUS$384\nSelect\n*Last updated: 14:27:45\nFlights\n > \nFlights\n > \nTaipei to Flights\nBook flights from Taipei to on Trip.com\n\nFirst class | Business class | Economy class | Nonstop\n\nSearch for cheap flights from Taipei to on Trip.com. Trip.com provides the best real-time Taipei to airfares and flight deals available, featuring advanced flight planning tools like price alerts, deal finder fare calendars, and Taipei Flight + Hotel deals that make a vacation or tour more convenient and affordable.\n\nAward-winning\nSupport in approx. 30s\nRewards for booking",
      "Taipei\nEdit\n2 adults\nEconomy\nFeb 25, 2026\nSun, Feb 22\nView\nMon, Feb 23\nView\nTue, Feb 24\nView\nWed, Feb 25\nUS$145\nThu, Feb 26\nView",
      "DepartWed, Feb 25"
    ],
    "hotel_class": [
      "Hotels & Homes"
    ],
    "main": [
      "Cheap Flights, Airline Tickets & Plane Tickets | Trip.com\nAllow notifications\nDon't miss out! Be the first to find out the latest travel info.\nAllow\nTaipei\nEdit\n2 adults\nEconomy\nFeb 25, 2026\nSun, Feb 22\nView\nMon, Feb 23\nView\nTue, Feb 24\nView\nWed, Feb 25\nUS$145\nThu, Feb 26\nView\nWed, Feb 18\nView\nThu, Feb 19\nView\nFri, Feb 20\nView\nSat, Feb 21\nView\nSun, Feb 22\nView\nMon, Feb 23\nView\nTue, Feb 24\nView\nWed, Feb 25\nUS$145\nThu, Feb 26\nView\nFri, Feb 27\nView\nSat, Feb 28\nView\nSun, Mar 1\nView\nMon, Mar 2\nView\nTue, Mar 3\nView\nWed, Mar 4\nView\nPrice graph\nRecommended\n Nonstop\n Checked baggage included\n Hide budget airlines\n Student tickets\n Carry-on baggage included\n Hide codeshare flights\nCO2e Lower emission flights\nShow More\nAlliance\nSkyTeam\nUS$262\nStar Alliance\nUS$278\nOneworld\nUS$319\nAirlines\nAll flights with the same airline\nAll airlines\nCathay Pacific (14)\nUS$319\nHong Kong Airlines (12)\nUS$191\nHK Express (11)\nUS$193\nJapan Airlines (6)\nUS$329\nPeach (4)\nUS$193\nShow More\nAlliance\nSkyTeam\nUS$262\nStar Alliance\nUS$278\nOneworld\nUS$319\nTimes\nDeparture time\n00:00–24:00\n00:00\n24:00\nArrival time\n00:00–24:00\n00:00\n24:00\nDuration\nAny\nStopover Duration\n1h–24h\n1h\n24h\nTotal Duration\n2h–29h 30m\n2h\n29h 30m\nStops\n1 stop or fewer\nUS$145\nStopover cities\nAny\nHong Kong\nUS$191\nMacau\nUS$270\nManila\nUS$265\nTokyo\nUS$329\nJeju\nUS$210\nDaegu\nUS$275\nSeoul\nUS$278\nHo Chi Minh City\nUS$310\nBusan\nUS$338\nAirports\nAny\nDeparture Airport\nTSA\nTaipei Songshan Airport\nUS$386\nTPE\nTaiwan Taoyuan International Airport\nUS$145\nArrival Airport\nKIX\nKansai International Airport\nUS$145\nAircrafts\nAny\nLarge aircraft\nUS$145\nMidsize aircraft\nUS$154\nCabin\nEconomy\nEconomy\nEconomy/premium economy\nPremium economy\nBusiness/first\nBusiness\nFirst class\n78 flights found\nRecommended\nUS$145\nNonstop first\nUS$145\nCheapest\nUS$145\nSort by\nCreate price alert\nCheapest\nCarry-on baggage included\n- 16% CO2e\nAirAsia X Berhad\n15:40\nTPE T1\n2h 40m\nNonstop\n19:20\nKIX T1\nUS$145\nTotal US$289\nSelect\nCarry-on baggage included\nThai Vietjet Air\n07:30\nTPE T1\n2h 30m\nNonstop\n11:00\nKIX T1\nUS$154\nTotal US$307\nSelect\nCarry-on baggage included\n- 1% CO2e\nPeach\n01:45\nTPE T1\n2h 25m\nNonstop\n05:10\nKIX T2\nUS$193\nTotal US$385\nSelect\nCarry-on baggage included\n- 18% CO2e\nPeach\n18:50\nTPE T1\n2h 25m\nNonstop\n22:15\nKIX T2\nUS$198\nTotal US$395\nSelect\nSign in & save for future trips\nEarn at least 29 Trip Coins worth US$0.29 for this booking, which you can use to save on future trips!\nSign in/register\nCarry-on baggage included\nPeach\n13:40\nTPE T1\n2h 25m\nNonstop\n17:05\nKIX T2\nUS$213\nTotal US$425\nSelect\nCarry-on baggage included\n- 18% CO2e\nPeach\n09:40\nTPE T1\n2h 30m\nNonstop\n13:10\nKIX T2\nUS$218\nTotal US$435\nSelect\nCarry-on baggage included\nTigerair Taiwan\n14:40\nTPE T1\n2h 15m\nNonstop\n17:55\nKIX T1\nUS$218\nTotal US$435\nSelect\nCarry-on baggage included\nTigerair Taiwan\n07:00\nTPE T1\n2h 25m\nNonstop\n10:25\nKIX T1\nUS$256\nTotal US$512\nSelect\nIncluded\n- 3% CO2e\nChina Airlines\n14:20\nTPE T2\n2h 30m\nNonstop\n17:50\nKIX T1\nUS$262\nTotal US$524\nSelect\nIncluded\nChina Airlines\n09:45\nTPE T2\n2h 35m\nNonstop\n13:20\nKIX T1\nUS$271\nTotal US$542\nSelect\nCarry-on baggage included\nJetstar Japan\n02:30\nTPE T1\n2h 30m\nNonstop\n06:00\nKIX T1\nUS$273\nTotal US$546\nSelect\nIncluded\n- 21% CO2e\nEVA Air\n06:30\nTPE T2\n2h 25m\nNonstop\n09:55\nKIX T1\nUS$314\nTotal US$628\nSelect\nIncluded\n- 18% CO2e\nCathay Pacific\n11:15\nTPE T1\n2h 40m\nNonstop\n14:55\nKIX T1\nUS$319\nTotal US$638\nUS$292\nSelect\nIncluded\n- 20% CO2e\nEVA Air\n08:20\nTPE T2\n2h 35m\nNonstop\n11:55\nKIX T1\nUS$337\nTotal US$673\nSelect\nIncluded\n- 2% CO2e\nSTARLUX Airlines\n07:40\nTPE T1\n2h 30m\nNonstop\n11:10\nKIX T1\nUS$339\nTotal US$677\nSelect\nIncluded\n- 7% CO2e\nSTARLUX Airlines\n09:20\nTPE T1\n2h 30m\nNonstop\n12:50\nKIX T1\nUS$340\nTotal US$679\nSelect\nIncluded\nChina Airlines\n08:05\nTPE T2\n2h 30m\nNonstop\n11:35\nKIX T1\nUS$397\nTotal US$794\nSelect\nIncluded\nJapan Airlines\noperated by China Airlines\n08:05\nTPE T2\n2h 30m\nNonstop\n11:35\nKIX T1\nUS$959\nTotal US$1,917\nSelect\nIncluded\nJapan Airlines\noperated by China Airlines\n14:20\nTPE T2\n2h 30m\nNonstop\n17:50\nKIX T1\nUS$959\nTotal US$1,917\nSelect\nIncluded\nAll Nippon Airways\noperated by EVA Air\n06:30\nTPE T2\n2h 25m\nNonstop\n09:55\nKIX T1\nUS$964\nTotal US$1,928\nSelect\nIncluded\nAll Nippon Airways\noperated by EVA Air\n08:20\nTPE T2\n2h 35m\nNonstop\n11:55\nKIX T1\nUS$964\nTotal US$1,928\nSelect\nIncluded\nAll Nippon Airways\noperated by EVA Air\n13:30\nTPE T2\n2h 25m\nNonstop\n16:55\nKIX T1\nUS$964\nTotal US$1,928\nSelect\nIncluded\nHong Kong Airlines\n21:40\nTPE T2\n8h 35m\n3h in Hong Kong\n07:15\nKIX T1\n +1\nUS$191\nTotal US$382\nSelect\nIncluded\nHong Kong Airlines\n21:40\nTPE T2\n15h 25m\n9h 50m in Hong Kong\n14:05\nKIX T1\n +1\nUS$191\nTotal US$382\nSelect\nIncluded\nHong Kong Airlines\n21:40\nTPE T2\n17h 25m\n11h 40m in Hong Kong\n16:05\nKIX T1\n +1\nUS$191\nTotal US$382\nSelect\nIncluded\nHong Kong Airlines\n21:40\nTPE T2\n20h 25m\n14h 50m in Hong Kong\n19:05\nKIX T1\n +1\nUS$191\nTotal US$382\nSelect\nHK Express\n21:15\nTPE T1\n18h\n12h 25m in Hong Kong\n16:15\nKIX T1\n +1\nUS$193\nTotal US$386\nSelect\nHK Express\n21:15\nTPE T1\n21h 5m\n15h 30m in Hong Kong\n19:20\nKIX T1\n +1\nUS$193\nTotal US$386\nSelect\nHK Express\n21:15\nTPE T1\n21h 55m\n16h 20m in Hong Kong\n20:10\nKIX T1\n +1\nUS$193\nTotal US$386\nSelect\nIncluded\nT'Way Air\n14:25\nTPE T1\n26h 15m\n22h 35m in Jeju\n17:40\nKIX T1\n +1\nUS$210\nTotal US$420\nSelect\nHK Express\n17:40\nTPE T1\n21h 35m\n16h 10m in Hong Kong\n16:15\nKIX T1\n +1\nUS$216\nTotal US$431\nSelect\nHong Kong: Free Layover Tour\nHK Express\n13:55\nTPE T1\n25h 20m\n19h 50m in Hong Kong\n16:15\nKIX T1\n +1\nUS$232\nTotal US$464\nSelect\nHK Express\n17:40\nTPE T1\n25h 30m\n20h 5m in Hong Kong\n20:10\nKIX T1\n +1\nUS$232\nTotal US$464\nSelect\nIncluded\nVietJet Air\n19:00\nTPE T1\n12h 30m\n3h 55m in Ho Chi Minh City\n08:30\nKIX T1\n +1\nUS$310\nTotal US$620\nSelect\nIncluded\nPhilippine Airlines\n21:35\nTPE T1\n15h 30m\n9h 5m in Manila\n14:05\nKIX T1\n +1\nUS$310\nTotal US$620\nSelect\nIncluded\nJapan Airlines\noperated by Jetstar Japan\n13:25\nTPE T2\n18h 20m\n13h 30m in Tokyo\n08:45\nKIX T1\n +1\nUS$329\nTotal US$657\nSelect\nIncluded\nJapan Airlines\noperated by Jetstar Japan\n13:25\nTPE T2\n19h 45m\n14h 55m in Tokyo\n10:10\nKIX T1\n +1\nUS$330\nTotal US$659\nSelect\nIncluded\nJin Air\n02:40\nTPE T1\n6h 20m\n2h 40m in Busan\n10:00\nKIX T1\nUS$338\nTotal US$676\nSelect\nIncluded\nJapan Airlines\n15:35\nTSA T1\n15h 50m\n11h 35m in Tokyo\n08:25\nKIX T1\n +1\nUS$386\nTotal US$772\nSelect\nIncluded\nCathay Pacific\n22:20\nTPE T1\n7h\n1h 20m in Hong Kong\n06:20\nKIX T1\n +1\nUS$418\nTotal US$835\nUS$384\nSelect\n*Last updated: 14:27:45\nFlights\n > \nFlights\n > \nTaipei to Flights\nBook flights from Taipei to on Trip.com\n\nFirst class | Business class | Economy class | Nonstop\n\nSearch for cheap flights from Taipei to on Trip.com. Trip.com provides the best real-time Taipei to airfares and flight deals available, featuring advanced flight planning tools like price alerts, deal finder fare calendars, and Taipei Flight + Hotel deals that make a vacation or tour more convenient and affordable.\n\nAward-winning\nSupport in approx. 30s\nRewards for booking"
    ]
  }
}