{
  "url": "https://www.trip.com/flights/taipei-to-osaka/tickets-tpe-kix?dcity=tpe&acity=kix&ddate=2026-02-26&flighttype=ow&class=y&quantity=2",
  "scraped_at": "2026-02-05T13:01:35.996092",
  "title": "Cheap Flights, Airline Tickets & Plane Tickets | Trip.com",
  "raw_text": "Go to main content\nTheme Detection\nHotels & Homes\nFlights\nTrains\nCar services\nApp\nUSD\nCustomer support\nFind bookings\nSign in / Register\nCheap Flights, Airline Tickets & Plane Tickets | Trip.com\nAllow notifications\nDon't miss out! Be the first to find out the latest travel info.\nAllow\nTaipei\nEdit\n2 adults\nEconomy\nFeb 26, 2026\nMon, Feb 23\nView\nTue, Feb 24\nView\nWed, Feb 25\nView\nThu, Feb 26\nUS$175\nFri, Feb 27\nView\nThu, Feb 19\nView\nFri, Feb 20\nView\nSat, Feb 21\nView\nSun, Feb 22\nView\nMon, Feb 23\nView\nTue, Feb 24\nView\nWed, Feb 25\nView\nThu, Feb 26\nUS$175\nFri, Feb 27\nView\nSat, Feb 28\nView\nSun, Mar 1\nView\nMon, Mar 2\nView\nTue, Mar 3\nView\nWed, Mar 4\nView\nThu, Mar 5\nView\nPrice graph\nRecommended\n Nonstop\n Checked baggage included\n Hide budget airlines\n Student tickets\n Carry-on baggage included\n Hide codeshare flights\nCO2e Lower emission flights\nShow More\nAlliance\nStar Alliance\nUS$314\nOneworld\nUS$332\nSkyTeam\nUS$425\nAirlines\nAll flights with the same airline\nAll airlines\nHK Express (16)\nUS$287\nHong Kong Airlines (13)\nUS$309\nCathay Pacific (9)\nUS$419\nAir Macau (4)\nUS$270\nPeach (3)\nUS$257\nShow More\nAlliance\nStar Alliance\nUS$314\nOneworld\nUS$332\nSkyTeam\nUS$425\nTimes\nDeparture time\n00:00–24:00\n00:00\n24:00\nArrival time\n00:00–24:00\n00:00\n24:00\nDuration\nAny\nStopover Duration\n1h–24h\n1h\n24h\nTotal Duration\n2h–29h 30m\n2h\n29h 30m\nStops\n1 stop or fewer\nUS$175\nStopover cities\nAny\nHong Kong\nUS$287\nMacau\nUS$270\nManila\nUS$272\nDaegu\nUS$275\nKuala Lumpur\nUS$283\nTokyo\nUS$332\nSeoul\nUS$371\nHo Chi Minh City\nUS$374\nAirports\nAny\nDeparture Airport\nTPE\nTaiwan Taoyuan International Airport\nUS$175\nArrival Airport\nKIX\nKansai International Airport\nUS$175\nAircrafts\nAny\nLarge aircraft\nUS$220\nMidsize aircraft\nUS$175\nCabin\nEconomy\nEconomy\nEconomy/premium economy\nPremium economy\nBusiness/first\nBusiness\nFirst class\nRecommended\nUS$175\nNonstop first\nUS$175\nCheapest\nUS$175\nSort by\nCreate price alert\nCheapest\nCarry-on baggage included\nJetstar Japan\n02:30\nTPE T1\n2h 30m\nNonstop\n06:00\nKIX T1\nUS$175\nTotal US$350\nSelect\nCarry-on baggage included\nThai Vietjet Air\n07:30\nTPE T1\n2h 30m\nNonstop\n11:00\nKIX T1\nUS$195\nTotal US$390\nSelect\nCarry-on baggage included\n- 16% CO2e\nAirAsia X Berhad\n15:40\nTPE T1\n2h 40m\nNonstop\n19:20\nKIX T1\nUS$220\nTotal US$440\nSelect\nCarry-on baggage included\nJetstar Japan\n18:10\nTPE T1\n2h 30m\nNonstop\n21:40\nKIX T1\nUS$222\nTotal US$443\nSelect\nSign in & save for future trips\nEarn at least 35 Trip Coins worth US$0.35 for this booking, which you can use to save on future trips!\nSign in/register\nCarry-on baggage included\nTigerair Taiwan\n06:10\nTPE T1\n2h 25m\nNonstop\n09:35\nKIX T1\nUS$234\nTotal US$467\nSelect\nIncluded\n- 1% CO2e\nPeach\n01:45\nTPE T1\n2h 25m\nNonstop\n05:10\nKIX T2\nUS$257\nTotal US$513\nSelect\nCarry-on baggage included\nTigerair Taiwan\n14:40\nTPE T1\n2h 15m\nNonstop\n17:55\nKIX T1\nUS$257\nTotal US$513\nSelect\nIncluded\n- 18% CO2e\nPeach\n09:40\nTPE T1\n2h 30m\nNonstop\n13:10\nKIX T2\nUS$304\nTotal US$607\nSelect\nPrice alerts\nWant a better deal? We'll notify you when the price drops below US$169.\nRecommended: US$169\nHigh chances of success\nOK\nIncluded\nPeach\n13:40\nTPE T1\n2h 25m\nNonstop\n17:05\nKIX T2\nUS$304\nTotal US$607\nSelect\nIncluded\n- 21% CO2e\nEVA Air\n06:30\nTPE T2\n2h 25m\nNonstop\n09:55\nKIX T1\nUS$314\nTotal US$628\nSelect\n<9 left\nCarry-on baggage included\n- 1% CO2e\nThai Lion Air\n09:00\nTPE T1\n2h 30m\nNonstop\n12:30\nKIX T1\nUS$334\nTotal US$668\nSelect\nIncluded\n- 20% CO2e\nEVA Air\n08:20\nTPE T2\n2h 35m\nNonstop\n11:55\nKIX T1\nUS$337\nTotal US$673\nSelect\nIncluded\n- 21% CO2e\nEVA Air\n13:30\nTPE T2\n2h 25m\nNonstop\n16:55\nKIX T1\nUS$339\nTotal US$678\nSelect\nIncluded\n- 2% CO2e\nSTARLUX Airlines\n07:40\nTPE T1\n2h 30m\nNonstop\n11:10\nKIX T1\nUS$401\nTotal US$801\nSelect\nIncluded\nChina Airlines\n08:05\nTPE T2\n2h 30m\nNonstop\n11:35\nKIX T1\nUS$425\nTotal US$849\nSelect\nIncluded\n- 7% CO2e\nSTARLUX Airlines\n09:20\nTPE T1\n2h 30m\nNonstop\n12:50\nKIX T1\nUS$514\nTotal US$1,028\nSelect\nIncluded\nChina Airlines\n14:20\nTPE T2\n2h 30m\nNonstop\n17:50\nKIX T1\nUS$515\nTotal US$1,029\nSelect\nIncluded\nJapan Airlines\noperated by China Airlines\n08:05\nTPE T2\n2h 30m\nNonstop\n11:35\nKIX T1\nUS$959\nTotal US$1,917\nSelect\nIncluded\nAll Nippon Airways\noperated by EVA Air\n08:20\nTPE T2\n2h 35m\nNonstop\n11:55\nKIX T1\nUS$965\nTotal US$1,929\nSelect\nIncluded\nAll Nippon Airways\noperated by EVA Air\n13:30\nTPE T2\n2h 25m\nNonstop\n16:55\nKIX T1\nUS$965\nTotal US$1,929\nSelect\nIncluded\nAir Macau\n22:20\nTPE T1\n13h 25m\n7h 55m in Macau\n12:45\nKIX T1\n +1\nUS$270\nTotal US$540\nSelect\nIncluded\nAir Macau\n20:10\nTPE T1\n15h 35m\n10h 15m in Macau\n12:45\nKIX T1\n +1\nUS$270\nTotal US$540\nSelect\nIncluded\nAir Macau\n14:40\nTPE T1\n21h 5m\n15h 45m in Macau\n12:45\nKIX T1\n +1\nUS$270\nTotal US$540\nSelect\nShow more results\nFlights\n > \nFlights\n > \nTaipei to Flights\nBook flights from Taipei to on Trip.com\n\nFirst class | Business class | Economy class | Nonstop\n\nSearch for cheap flights from Taipei to on Trip.com. Trip.com provides the best real-time Taipei to airfares and flight deals available, featuring advanced flight planning tools like price alerts, deal finder fare calendars, and Taipei Flight + Hotel deals that make a vacation or tour more convenient and affordable.\n\nAward-winning\nSupport in approx. 30s\nRewards for booking\nContact us\nCustomer support\nService guarantee\nMore service info\nAbout\nAbout Trip.com\nNews\nCareers\nTerms & Conditions\nPrivacy Statement\nAccessibility statement\nAbout Trip.com Group\nOther services\nInvestor relations\nTrip.com Rewards\nAffiliate program\nList your property\nAll hotels\nBecome a Supplier\nSecurity\nPayment methods\nOur partners\nContact Center\nof the year 2025\nCopyright © 2025 Trip.com Travel Singapore Pte. Ltd. All rights reserved\nSite Operator: Trip.com Travel Singapore Pte. Ltd.",
  "extracted": {
    "flight": {},
    "hotel": {},
    "price": {},
    "dates": {},
    "inclusions": [],
    "date_pricing": {}
  },
  "extracted_elements": {
    "flight_element": [
      "Jetstar Japan\n02:30\nTPE T1\n2h 30m\nNonstop\n06:00\nKIX T1",
      "Thai Vietjet Air\n07:30\nTPE T1\n2h 30m\nNonstop\n11:00\nKIX T1",
      "AirAsia X Berhad\n15:40\nTPE T1\n2h 40m\nNonstop\n19:20\nKIX T1",
      "Jetstar Japan\n18:10\nTPE T1\n2h 30m\nNonstop\n21:40\nKIX T1",
      "Tigerair Taiwan\n06:10\nTPE T1\n2h 25m\nNonstop\n09:35\nKIX T1"
    ],
    "price_class": [
      "Mon, Feb 23\nView\nTue, Feb 24\nView\nWed, Feb 25\nView\nThu, Feb 26\nUS$175\nFri, Feb 27\nView",
      "Mon, Feb 23\nView\nTue, Feb 24\nView\nWed, Feb 25\nView\nThu, Feb 26\nUS$175\nFri, Feb 27\nView",
      "Mon, Feb 23\nView\nTue, Feb 24\nView\nWed, Feb 25\nView\nThu, Feb 26\nUS$175\nFri, Feb 27\nView",
      "Mon, Feb 23\nView\nTue, Feb 24\nView\nWed, Feb 25\nView\nThu, Feb 26\nUS$175\nFri, Feb 27\nView",
      "Mon, Feb 23\nView\nTue, Feb 24\nView\nWed, Feb 25\nView\nThu, Feb 26\nUS$175\nFri, Feb 27\nView"
    ],
    "flight_class": [
      "Flights",
      "Taipei\nEdit\n2 adults\nEconomy\nFeb 26, 2026\nMon, Feb 23\nView\nTue, Feb 24\nView\nWed, Feb 25\nView\nThu, Feb 26\nUS$175\nFri, Feb 27\nView\nThu, Feb 19\nView\nFri, Feb 20\nView\nSat, Feb 21\nView\nSun, Feb 22\nView\nMon, Feb 23\nView\nTue, Feb 24\nView\nWed, Feb 25\nView\nThu, Feb 26\nUS$175\nFri, Feb 27\nView\nSat, Feb 28\nView\nSun, Mar 1\nView\nMon, Mar 2\nView\nTue, Mar 3\nView\nWed, Mar 4\nView\nThu, Mar 5\nView\nPrice graph\nRecommended\n Nonstop\n Checked baggage included\n Hide budget airlines\n Student tickets\n Carry-on baggage included\n Hide codeshare flights\nCO2e Lower emission flights\nShow More\nAlliance\nStar Alliance\nUS$314\nOneworld\nUS$332\nSkyTeam\nUS$425\nAirlines\nAll flights with the same airline\nAll airlines\nHK Express (16)\nUS$287\nHong Kong Airlines (13)\nUS$309\nCathay Pacific (9)\nUS$419\nAir Macau (4)\nUS$270\nPeach (3)\nUS$257\nShow More\nAlliance\nStar Alliance\nUS$314\nOneworld\nUS$332\nSkyTeam\nUS$425\nTimes\nDeparture time\n00:00–24:00\n00:00\n24:00\nArrival time\n00:00–24:00\n00:00\n24:00\nDuration\nAny\nStopover Duration\n1h–24h\n1h\n24h\nTotal Duration\n2h–29h 30m\n2h\n29h 30m\nStops\n1 stop or fewer\nUS$175\nStopover cities\nAny\nHong Kong\nUS$287\nMacau\nUS$270\nManila\nUS$272\nDaegu\nUS$275\nKuala Lumpur\nUS$283\nTokyo\nUS$332\nSeoul\nUS$371\nHo Chi Minh City\nUS$374\nAirports\nAny\nDeparture Airport\nTPE\nTaiwan Taoyuan International Airport\nUS$175\nArrival Airport\nKIX\nKansai International Airport\nUS$175\nAircrafts\nAny\nLarge aircraft\nUS$220\nMidsize aircraft\nUS$175\nCabin\nEconomy\nEconomy\nEconomy/premium economy\nPremium economy\nBusiness/first\nBusiness\nFirst class\nRecommended\nUS$175\nNonstop first\nUS$175\nCheapest\nUS$175\nSort by\nCreate price alert\nCheapest\nCarry-on baggage included\nJetstar Japan\n02:30\nTPE T1\n2h 30m\nNonstop\n06:00\nKIX T1\nUS$175\nTotal US$350\nSelect\nCarry-on baggage included\nThai Vietjet Air\n07:30\nTPE T1\n2h 30m\nNonstop\n11:00\nKIX T1\nUS$195\nTotal US$390\nSelect\nCarry-on baggage included\n- 16% CO2e\nAirAsia X Berhad\n15:40\nTPE T1\n2h 40m\nNonstop\n19:20\nKIX T1\nUS$220\nTotal US$440\nSelect\nCarry-on baggage included\nJetstar Japan\n18:10\nTPE T1\n2h 30m\nNonstop\n21:40\nKIX T1\nUS$222\nTotal US$443\nSelect\nSign in & save for future trips\nEarn at least 35 Trip Coins worth US$0.35 for this booking, which you can use to save on future trips!\nSign in/register\nCarry-on baggage included\nTigerair Taiwan\n06:10\nTPE T1\n2h 25m\nNonstop\n09:35\nKIX T1\nUS$234\nTotal US$467\nSelect\nIncluded\n- 1% CO2e\nPeach\n01:45\nTPE T1\n2h 25m\nNonstop\n05:10\nKIX T2\nUS$257\nTotal US$513\nSelect\nCarry-on baggage included\nTigerair Taiwan\n14:40\nTPE T1\n2h 15m\nNonstop\n17:55\nKIX T1\nUS$257\nTotal US$513\nSelect\nIncluded\n- 18% CO2e\nPeach\n09:40\nTPE T1\n2h 30m\nNonstop\n13:10\nKIX T2\nUS$304\nTotal US$607\nSelect\nPrice alerts\nWant a better deal? We'll notify you when the price drops below US$169.\nRecommended: US$169\nHigh chances of success\nOK\nIncluded\nPeach\n13:40\nTPE T1\n2h 25m\nNonstop\n17:05\nKIX T2\nUS$304\nTotal US$607\nSelect\nIncluded\n- 21% CO2e\nEVA Air\n06:30\nTPE T2\n2h 25m\nNonstop\n09:55\nKIX T1\nUS$314\nTotal US$628\nSelect\n<9 left\nCarry-on baggage included\n- 1% CO2e\nThai Lion Air\n09:00\nTPE T1\n2h 30m\nNonstop\n12:30\nKIX T1\nUS$334\nTotal US$668\nSelect\nIncluded\n- 20% CO2e\nEVA Air\n08:20\nTPE T2\n2h 35m\nNonstop\n11:55\nKIX T1\nUS$337\nTotal US$673\nSelect\nIncluded\n- 21% CO2e\nEVA Air\n13:30\nTPE T2\n2h 25m\nNonstop\n16:55\nKIX T1\nUS$339\nTotal US$678\nSelect\nIncluded\n- 2% CO2e\nSTARLUX Airlines\n07:40\nTPE T1\n2h 30m\nNonstop\n11:10\nKIX T1\nUS$401\nTotal US$801\nSelect\nIncluded\nChina Airlines\n08:05\nTPE T2\n2h 30m\nNonstop\n11:35\nKIX T1\nUS$425\nTotal US$849\nSelect\nIncluded\n- 7% CO2e\nSTARLUX Airlines\n09:20\nTPE T1\n2h 30m\nNonstop\n12:50\nKIX T1\nUS$514\nTotal US$1,028\nSelect\nIncluded\nChina Airlines\n14:20\nTPE T2\n2h 30m\nNonstop\n17:50\nKIX T1\nUS$515\nTotal US$1,029\nSelect\nIncluded\nJapan Airlines\noperated by China Airlines\n08:05\nTPE T2\n2h 30m\nNonstop\n11:35\nKIX T1\nUS$959\nTotal US$1,917\nSelect\nIncluded\nAll Nippon Airways\noperated by EVA Air\n08:20\nTPE T2\n2h 35m\nNonstop\n11:55\nKIX T1\nUS$965\nTotal US$1,929\nSelect\nIncluded\nAll Nippon Airways\noperated by EVA Air\n13:30\nTPE T2\n2h 25m\nNonstop\n16:55\nKIX T1\nUS$965\nTotal US$1,929\nSelect\nIncluded\nAir Macau\n22:20\nTPE T1\n13h 25m\n7h 55m in Macau\n12:45\nKIX T1\n +1\nUS$270\nTotal US$540\nSelect\nIncluded\nAir Macau\n20:10\nTPE T1\n15h 35m\n10h 15m in Macau\n12:45\nKIX T1\n +1\nUS$270\nTotal US$540\nSelect\nIncluded\nAir Macau\n14:40\nTPE T1\n21h 5m\n15h 45m in Macau\n12:45\nKIX T1\n +1\nUS$270\nTotal US$540\nSelect\nShow more results\nFlights\n > \nFlights\n > \nTaipei to Flights\nBook flights from Taipei to on Trip.com\n\nFirst class | Business class | Economy class | Nonstop\n\nSearch for cheap flights from Taipei to on Trip.com. Trip.com provides the best real-time Taipei to airfares and flight deals available, featuring advanced flight planning tools like price alerts, deal finder fare calendars, and Taipei Flight + Hotel deals that make a vacation or tour more convenient and affordable.\n\nAward-winning\nSupport in approx. 30s\nRewards for booking",
      "Taipei\nEdit\n2 adults\nEconomy\nFeb 26, 2026\nMon, Feb 23\nView\nTue, Feb 24\nView\nWed, Feb 25\nView\nThu, Feb 26\nUS$175\nFri, Feb 27\nView",
      "DepartThu, Feb 26"
    ],
    "hotel_class": [
      "Hotels & Homes"
    ],
    "main": [
      "Cheap Flights, Airline Tickets & Plane Tickets | Trip.com\nAllow notifications\nDon't miss out! Be the first to find out the latest travel info.\nAllow\nTaipei\nEdit\n2 adults\nEconomy\nFeb 26, 2026\nMon, Feb 23\nView\nTue, Feb 24\nView\nWed, Feb 25\nView\nThu, Feb 26\nUS$175\nFri, Feb 27\nView\nThu, Feb 19\nView\nFri, Feb 20\nView\nSat, Feb 21\nView\nSun, Feb 22\nView\nMon, Feb 23\nView\nTue, Feb 24\nView\nWed, Feb 25\nView\nThu, Feb 26\nUS$175\nFri, Feb 27\nView\nSat, Feb 28\nView\nSun, Mar 1\nView\nMon, Mar 2\nView\nTue, Mar 3\nView\nWed, Mar 4\nView\nThu, Mar 5\nView\nPrice graph\nRecommended\n Nonstop\n Checked baggage included\n Hide budget airlines\n Student tickets\n Carry-on baggage included\n Hide codeshare flights\nCO2e Lower emission flights\nShow More\nAlliance\nStar Alliance\nUS$314\nOneworld\nUS$332\nSkyTeam\nUS$425\nAirlines\nAll flights with the same airline\nAll airlines\nHK Express (16)\nUS$287\nHong Kong Airlines (13)\nUS$309\nCathay Pacific (9)\nUS$419\nAir Macau (4)\nUS$270\nPeach (3)\nUS$257\nShow More\nAlliance\nStar Alliance\nUS$314\nOneworld\nUS$332\nSkyTeam\nUS$425\nTimes\nDeparture time\n00:00–24:00\n00:00\n24:00\nArrival time\n00:00–24:00\n00:00\n24:00\nDuration\nAny\nStopover Duration\n1h–24h\n1h\n24h\nTotal Duration\n2h–29h 30m\n2h\n29h 30m\nStops\n1 stop or fewer\nUS$175\nStopover cities\nAny\nHong Kong\nUS$287\nMacau\nUS$270\nManila\nUS$272\nDaegu\nUS$275\nKuala Lumpur\nUS$283\nTokyo\nUS$332\nSeoul\nUS$371\nHo Chi Minh City\nUS$374\nAirports\nAny\nDeparture Airport\nTPE\nTaiwan Taoyuan International Airport\nUS$175\nArrival Airport\nKIX\nKansai International Airport\nUS$175\nAircrafts\nAny\nLarge aircraft\nUS$220\nMidsize aircraft\nUS$175\nCabin\nEconomy\nEconomy\nEconomy/premium economy\nPremium economy\nBusiness/first\nBusiness\nFirst class\nRecommended\nUS$175\nNonstop first\nUS$175\nCheapest\nUS$175\nSort by\nCreate price alert\nCheapest\nCarry-on baggage included\nJetstar Japan\n02:30\nTPE T1\n2h 30m\nNonstop\n06:00\nKIX T1\nUS$175\nTotal US$350\nSelect\nCarry-on baggage included\nThai Vietjet Air\n07:30\nTPE T1\n2h 30m\nNonstop\n11:00\nKIX T1\nUS$195\nTotal US$390\nSelect\nCarry-on baggage included\n- 16% CO2e\nAirAsia X Berhad\n15:40\nTPE T1\n2h 40m\nNonstop\n19:20\nKIX T1\nUS$220\nTotal US$440\nSelect\nCarry-on baggage included\nJetstar Japan\n18:10\nTPE T1\n2h 30m\nNonstop\n21:40\nKIX T1\nUS$222\nTotal US$443\nSelect\nSign in & save for future trips\nEarn at least 35 Trip Coins worth US$0.35 for this booking, which you can use to save on future trips!\nSign in/register\nCarry-on baggage included\nTigerair Taiwan\n06:10\nTPE T1\n2h 25m\nNonstop\n09:35\nKIX T1\nUS$234\nTotal US$467\nSelect\nIncluded\n- 1% CO2e\nPeach\n01:45\nTPE T1\n2h 25m\nNonstop\n05:10\nKIX T2\nUS$257\nTotal US$513\nSelect\nCarry-on baggage included\nTigerair Taiwan\n14:40\nTPE T1\n2h 15m\nNonstop\n17:55\nKIX T1\nUS$257\nTotal US$513\nSelect\nIncluded\n- 18% CO2e\nPeach\n09:40\nTPE T1\n2h 30m\nNonstop\n13:10\nKIX T2\nUS$304\nTotal US$607\nSelect\nPrice alerts\nWant a better deal? We'll notify you when the price drops below US$169.\nRecommended: US$169\nHigh chances of success\nOK\nIncluded\nPeach\n13:40\nTPE T1\n2h 25m\nNonstop\n17:05\nKIX T2\nUS$304\nTotal US$607\nSelect\nIncluded\n- 21% CO2e\nEVA Air\n06:30\nTPE T2\n2h 25m\nNonstop\n09:55\nKIX T1\nUS$314\nTotal US$628\nSelect\n<9 left\nCarry-on baggage included\n- 1% CO2e\nThai Lion Air\n09:00\nTPE T1\n2h 30m\nNonstop\n12:30\nKIX T1\nUS$334\nTotal US$668\nSelect\nIncluded\n- 20% CO2e\nEVA Air\n08:20\nTPE T2\n2h 35m\nNonstop\n11:55\nKIX T1\nUS$337\nTotal US$673\nSelect\nIncluded\n- 21% CO2e\nEVA Air\n13:30\nTPE T2\n2h 25m\nNonstop\n16:55\nKIX T1\nUS$339\nTotal US$678\nSelect\nIncluded\n- 2% CO2e\nSTARLUX Airlines\n07:40\nTPE T1\n2h 30m\nNonstop\n11:10\nKIX T1\nUS$401\nTotal US$801\nSelect\nIncluded\nChina Airlines\n08:05\nTPE T2\n2h 30m\nNonstop\n11:35\nKIX T1\nUS$425\nTotal US$849\nSelect\nIncluded\n- 7% CO2e\nSTARLUX Airlines\n09:20\nTPE T1\n2h 30m\nNonstop\n12:50\nKIX T1\nUS$514\nTotal US$1,028\nSelect\nIncluded\nChina Airlines\n14:20\nTPE T2\n2h 30m\nNonstop\n17:50\nKIX T1\nUS$515\nTotal US$1,029\nSelect\nIncluded\nJapan Airlines\noperated by China Airlines\n08:05\nTPE T2\n2h 30m\nNonstop\n11:35\nKIX T1\nUS$959\nTotal US$1,917\nSelect\nIncluded\nAll Nippon Airways\noperated by EVA Air\n08:20\nTPE T2\n2h 35m\nNonstop\n11:55\nKIX T1\nUS$965\nTotal US$1,929\nSelect\nIncluded\nAll Nippon Airways\noperated by EVA Air\n13:30\nTPE T2\n2h 25m\nNonstop\n16:55\nKIX T1\nUS$965\nTotal US$1,929\nSelect\nIncluded\nAir Macau\n22:20\nTPE T1\n13h 25m\n7h 55m in Macau\n12:45\nKIX T1\n +1\nUS$270\nTotal US$540\nSelect\nIncluded\nAir Macau\n20:10\nTPE T1\n15h 35m\n10h 15m in Macau\n12:45\nKIX T1\n +1\nUS$270\nTotal US$540\nSelect\nIncluded\nAir Macau\n14:40\nTPE T1\n21h 5m\n15h 45m in Macau\n12:45\nKIX T1\n +1\nUS$270\nTotal US$540\nSelect\nShow more results\nFlights\n > \nFlights\n > \nTaipei to Flights\nBook flights from Taipei to on Trip.com\n\nFirst class | Business class | Economy class | Nonstop\n\nSearch for cheap flights from Taipei to on Trip.com. Trip.com provides the best real-time Taipei to airfares and flight deals available, featuring advanced flight planning tools like price alerts, deal finder fare calendars, and Taipei Flight + Hotel deals that make a vacation or tour more convenient and affordable.\n\nAward-winning\nSupport in approx. 30s\nRewards for booking"
    ]
  }
}