{
  "url": "https://www.trip.com/flights/taipei-to-osaka/tickets-tpe-kix?dcity=tpe&acity=kix&ddate=2026-02-25&flighttype=ow&class=y&quantity=2",
  "scraped_at": "2026-02-05T10:32:33.118300",
  "title": "Cheap Flights, Airline Tickets & Plane Tickets | Trip.com",
  "raw_text": "Go to main content\nTheme Detection\nHotels & Homes\nFlights\nTrains\nCar services\nApp\nUSD\nCustomer support\nFind bookings\nSign in / Register\nCheap Flights, Airline Tickets & Plane Tickets | Trip.com\nAllow notifications\nDon't miss out! Be the first to find out the latest travel info.\nAllow\nTaipei\nEdit\n2 adults\nEconomy\nFeb 25, 2026\nSun, Feb 22\nView\nMon, Feb 23\nView\nTue, Feb 24\nView\nWed, Feb 25\nUS$140\nThu, Feb 26\nView\nWed, Feb 18\nView\nThu, Feb 19\nView\nFri, Feb 20\nView\nSat, Feb 21\nView\nSun, Feb 22\nView\nMon, Feb 23\nView\nTue, Feb 24\nView\nWed, Feb 25\nUS$140\nThu, Feb 26\nView\nFri, Feb 27\nView\nSat, Feb 28\nView\nSun, Mar 1\nView\nMon, Mar 2\nView\nTue, Mar 3\nView\nWed, Mar 4\nView\nPrice graph\nRecommended\n Nonstop\n Checked baggage included\n Hide budget airlines\n Student tickets\n Carry-on baggage included\n Hide codeshare flights\nCO2e Lower emission flights\nShow More\nAlliance\nSkyTeam\nUS$263\nStar Alliance\nUS$278\nOneworld\nUS$320\nAirlines\nAll flights with the same airline\nAll airlines\nHong Kong Airlines (12)\nUS$191\nHK Express (6)\nUS$205\nJapan Airlines (5)\nUS$329\nCathay Pacific (5)\nUS$320\nPeach (4)\nUS$193\nShow More\nAlliance\nSkyTeam\nUS$263\nStar Alliance\nUS$278\nOneworld\nUS$320\nTimes\nDeparture time\n00:00–24:00\n00:00\n24:00\nArrival time\n00:00–24:00\n00:00\n24:00\nDuration\nAny\nStopover Duration\n1h–23h\n1h\n23h\nTotal Duration\n2h–26h 30m\n2h\n26h 30m\nStops\n1 stop or fewer\nUS$140\nStopover cities\nAny\nHong Kong\nUS$191\nMacau\nUS$270\nManila\nUS$280\nTokyo\nUS$329\nJeju\nUS$210\nDaegu\nUS$275\nSeoul\nUS$278\nHo Chi Minh City\nUS$309\nBusan\nUS$337\nAirports\nAny\nDeparture Airport\nTPE\nTaiwan Taoyuan International Airport\nUS$140\nArrival Airport\nKIX\nKansai International Airport\nUS$140\nAircrafts\nAny\nLarge aircraft\nUS$140\nMidsize aircraft\nUS$154\nCabin\nEconomy\nEconomy\nEconomy/premium economy\nPremium economy\nBusiness/first\nBusiness\nFirst class\nRecommended\nUS$140\nNonstop first\nUS$193\nCheapest\nUS$140\nSort by\nCreate price alert\nCheapest\nCarry-on baggage included\n- 16% CO2e\nAirAsia X Berhad\n15:40\nTPE T1\n2h 40m\nNonstop\n19:20\nKIX T1\nUS$140\nTotal US$279\nSelect\nCarry-on baggage included\nThai Vietjet Air\n07:30\nTPE T1\n2h 30m\nNonstop\n11:00\nKIX T1\nUS$154\nTotal US$307\nSelect\nCarry-on baggage included\nPeach\n01:45\nTPE T1\n2h 25m\nNonstop\n05:10\nKIX T2\nUS$193\nTotal US$386\nSelect\nCarry-on baggage included\n- 18% CO2e\nPeach\n18:50\nTPE T1\n2h 25m\nNonstop\n22:15\nKIX T2\nUS$193\nTotal US$386\nSelect\nSign in & save for future trips\nEarn at least 28 Trip Coins worth US$0.28 for this booking, which you can use to save on future trips!\nSign in/register\nCarry-on baggage included\n- 18% CO2e\nPeach\n09:40\nTPE T1\n2h 30m\nNonstop\n13:10\nKIX T2\nUS$213\nTotal US$425\nSelect\nCarry-on baggage included\nPeach\n13:40\nTPE T1\n2h 25m\nNonstop\n17:05\nKIX T2\nUS$213\nTotal US$425\nSelect\nCarry-on baggage included\nTigerair Taiwan\n14:40\nTPE T1\n2h 15m\nNonstop\n17:55\nKIX T1\nUS$218\nTotal US$435\nSelect\nCarry-on baggage included\nTigerair Taiwan\n07:00\nTPE T1\n2h 25m\nNonstop\n10:25\nKIX T1\nUS$257\nTotal US$513\nSelect\nPrice alerts\nWant a better deal? We'll notify you when the price drops below US$135.\nRecommended: US$135\nHigh chances of success\nOK\nIncluded\n- 3% CO2e\nChina Airlines\n14:20\nTPE T2\n2h 30m\nNonstop\n17:50\nKIX T1\nUS$263\nTotal US$526\nSelect\nIncluded\nChina Airlines\n09:45\nTPE T2\n2h 35m\nNonstop\n13:20\nKIX T1\nUS$271\nTotal US$542\nSelect\n<9 left\nCarry-on baggage included\nJetstar Japan\n18:10\nTPE T1\n2h 30m\nNonstop\n21:40\nKIX T1\nUS$273\nTotal US$546\nSelect\nIncluded\n- 21% CO2e\nEVA Air\n13:30\nTPE T2\n2h 25m\nNonstop\n16:55\nKIX T1\nUS$286\nTotal US$572\nSelect\nIncluded\n- 21% CO2e\nEVA Air\n06:30\nTPE T2\n2h 25m\nNonstop\n09:55\nKIX T1\nUS$314\nTotal US$628\nSelect\nIncluded\n- 11% CO2e\nCathay Pacific\n11:15\nTPE T1\n2h 40m\nNonstop\n14:55\nKIX T1\nUS$320\nTotal US$640\nUS$294\nSelect\nIncluded\n- 20% CO2e\nEVA Air\n08:20\nTPE T2\n2h 35m\nNonstop\n11:55\nKIX T1\nUS$337\nTotal US$673\nSelect\nIncluded\n- 1% CO2e\nSTARLUX Airlines\n07:40\nTPE T1\n2h 30m\nNonstop\n11:10\nKIX T1\nUS$339\nTotal US$677\nSelect\nIncluded\n- 7% CO2e\nSTARLUX Airlines\n09:20\nTPE T1\n2h 30m\nNonstop\n12:50\nKIX T1\nUS$339\nTotal US$677\nSelect\nIncluded\nChina Airlines\n08:05\nTPE T2\n2h 30m\nNonstop\n11:35\nKIX T1\nUS$398\nTotal US$795\nSelect\nIncluded\nJapan Airlines\noperated by China Airlines\n14:20\nTPE T2\n2h 30m\nNonstop\n17:50\nKIX T1\nUS$959\nTotal US$1,917\nSelect\nIncluded\nAll Nippon Airways\noperated by EVA Air\n06:30\nTPE T2\n2h 25m\nNonstop\n09:55\nKIX T1\nUS$965\nTotal US$1,929\nSelect\nIncluded\nAll Nippon Airways\noperated by EVA Air\n08:20\nTPE T2\n2h 35m\nNonstop\n11:55\nKIX T1\nUS$965\nTotal US$1,929\nSelect\nIncluded\nAll Nippon Airways\noperated by EVA Air\n13:30\nTPE T2\n2h 25m\nNonstop\n16:55\nKIX T1\nUS$965\nTotal US$1,929\nSelect\nIncluded\nHong Kong Airlines\n21:40\nTPE T2\n8h 35m\n3h in Hong Kong\n07:15\nKIX T1\n +1\nUS$191\nTotal US$382\nSelect\nShow more results\nFlights\n > \nFlights\n > \nTaipei to Flights\nBook flights from Taipei to on Trip.com\n\nFirst class | Business class | Economy class | Nonstop\n\nSearch for cheap flights from Taipei to on Trip.com. Trip.com provides the best real-time Taipei to airfares and flight deals available, featuring advanced flight planning tools like price alerts, deal finder fare calendars, and Taipei Flight + Hotel deals that make a vacation or tour more convenient and affordable.\n\nAward-winning\nSupport in approx. 30s\nRewards for booking\nContact us\nCustomer support\nService guarantee\nMore service info\nAbout\nAbout Trip.com\nNews\nCareers\nTerms & Conditions\nPrivacy Statement\nAccessibility statement\nAbout Trip.com Group\nOther services\nInvestor relations\nTrip.com Rewards\nAffiliate program\nList your property\nAll hotels\nBecome a Supplier\nSecurity\nPayment methods\nOur partners\nContact Center\nof the year 2025\nCopyright © 2025 Trip.com Travel Singapore Pte. Ltd. All rights reserved\nSite Operator: Trip.com Travel Singapore Pte. Ltd.",
  "extracted": {
    "flight": {},
    "hotel": {},
    "price": {},
    "dates": {},
    "inclusions": [],
    "date_pricing": {}
  },
  "extracted_elements": {
    "flight_element": [
      "AirAsia X Berhad\n15:40\nTPE T1\n2h 40m\nNonstop\n19:20\nKIX T1",
      "Thai Vietjet Air\n07:30\nTPE T1\n2h 30m\nNonstop\n11:00\nKIX T1",
      "Peach\n01:45\nTPE T1\n2h 25m\nNonstop\n05:10\nKIX T2",
      "Peach\n18:50\nTPE T1\n2h 25m\nNonstop\n22:15\nKIX T2",
      "Peach\n09:40\nTPE T1\n2h 30m\nNonstop\n13:10\nKIX T2"
    ],
    "price_class": [
      "Sun, Feb 22\nView\nMon, Feb 23\nView\nTue, Feb 24\nView\nWed, Feb 25\nUS$140\nThu, Feb 26\nView",
      "Sun, Feb 22\nView\nMon, Feb 23\nView\nTue, Feb 24\nView\nWed, Feb 25\nUS$140\nThu, Feb 26\nView",
      "Sun, Feb 22\nView\nMon, Feb 23\nView\nTue, Feb 24\nView\nWed, Feb 25\nUS$140\nThu, Feb 26\nView",
      "Sun, Feb 22\nView\nMon, Feb 23\nView\nTue, Feb 24\nView\nWed, Feb 25\nUS$140\nThu, Feb 26\nView",
      "Sun, Feb 22\nView\nMon, Feb 23\nView\nTue, Feb 24\nView\nWed, Feb 25\nUS$140\nThu, Feb 26\nView"
    ],
    "flight_class": [
      "Flights",
      "Taipei\nEdit\n2 adults\nEconomy\nFeb 25, 2026\nSun, Feb 22\nView\nMon, Feb 23\nView\nTue, Feb 24\nView\nWed, Feb 25\nUS$140\nThu, Feb 26\nView\nWed, Feb 18\nView\nThu, Feb 19\nView\nFri, Feb 20\nView\nSat, Feb 21\nView\nSun, Feb 22\nView\nMon, Feb 23\nView\nTue, Feb 24\nView\nWed, Feb 25\nUS$140\nThu, Feb 26\nView\nFri, Feb 27\nView\nSat, Feb 28\nView\nSun, Mar 1\nView\nMon, Mar 2\nView\nTue, Mar 3\nView\nWed, Mar 4\nView\nPrice graph\nRecommended\n Nonstop\n Checked baggage included\n Hide budget airlines\n Student tickets\n Carry-on baggage included\n Hide codeshare flights\nCO2e Lower emission flights\nShow More\nAlliance\nSkyTeam\nUS$263\nStar Alliance\nUS$278\nOneworld\nUS$320\nAirlines\nAll flights with the same airline\nAll airlines\nHong Kong Airlines (12)\nUS$191\nHK Express (6)\nUS$205\nJapan Airlines (5)\nUS$329\nCathay Pacific (5)\nUS$320\nPeach (4)\nUS$193\nShow More\nAlliance\nSkyTeam\nUS$263\nStar Alliance\nUS$278\nOneworld\nUS$320\nTimes\nDeparture time\n00:00–24:00\n00:00\n24:00\nArrival time\n00:00–24:00\n00:00\n24:00\nDuration\nAny\nStopover Duration\n1h–23h\n1h\n23h\nTotal Duration\n2h–26h 30m\n2h\n26h 30m\nStops\n1 stop or fewer\nUS$140\nStopover cities\nAny\nHong Kong\nUS$191\nMacau\nUS$270\nManila\nUS$280\nTokyo\nUS$329\nJeju\nUS$210\nDaegu\nUS$275\nSeoul\nUS$278\nHo Chi Minh City\nUS$309\nBusan\nUS$337\nAirports\nAny\nDeparture Airport\nTPE\nTaiwan Taoyuan International Airport\nUS$140\nArrival Airport\nKIX\nKansai International Airport\nUS$140\nAircrafts\nAny\nLarge aircraft\nUS$140\nMidsize aircraft\nUS$154\nCabin\nEconomy\nEconomy\nEconomy/premium economy\nPremium economy\nBusiness/first\nBusiness\nFirst class\nRecommended\nUS$140\nNonstop first\nUS$193\nCheapest\nUS$140\nSort by\nCreate price alert\nCheapest\nCarry-on baggage included\n- 16% CO2e\nAirAsia X Berhad\n15:40\nTPE T1\n2h 40m\nNonstop\n19:20\nKIX T1\nUS$140\nTotal US$279\nSelect\nCarry-on baggage included\nThai Vietjet Air\n07:30\nTPE T1\n2h 30m\nNonstop\n11:00\nKIX T1\nUS$154\nTotal US$307\nSelect\nCarry-on baggage included\nPeach\n01:45\nTPE T1\n2h 25m\nNonstop\n05:10\nKIX T2\nUS$193\nTotal US$386\nSelect\nCarry-on baggage included\n- 18% CO2e\nPeach\n18:50\nTPE T1\n2h 25m\nNonstop\n22:15\nKIX T2\nUS$193\nTotal US$386\nSelect\nSign in & save for future trips\nEarn at least 28 Trip Coins worth US$0.28 for this booking, which you can use to save on future trips!\nSign in/register\nCarry-on baggage included\n- 18% CO2e\nPeach\n09:40\nTPE T1\n2h 30m\nNonstop\n13:10\nKIX T2\nUS$213\nTotal US$425\nSelect\nCarry-on baggage included\nPeach\n13:40\nTPE T1\n2h 25m\nNonstop\n17:05\nKIX T2\nUS$213\nTotal US$425\nSelect\nCarry-on baggage included\nTigerair Taiwan\n14:40\nTPE T1\n2h 15m\nNonstop\n17:55\nKIX T1\nUS$218\nTotal US$435\nSelect\nCarry-on baggage included\nTigerair Taiwan\n07:00\nTPE T1\n2h 25m\nNonstop\n10:25\nKIX T1\nUS$257\nTotal US$513\nSelect\nPrice alerts\nWant a better deal? We'll notify you when the price drops below US$135.\nRecommended: US$135\nHigh chances of success\nOK\nIncluded\n- 3% CO2e\nChina Airlines\n14:20\nTPE T2\n2h 30m\nNonstop\n17:50\nKIX T1\nUS$263\nTotal US$526\nSelect\nIncluded\nChina Airlines\n09:45\nTPE T2\n2h 35m\nNonstop\n13:20\nKIX T1\nUS$271\nTotal US$542\nSelect\n<9 left\nCarry-on baggage included\nJetstar Japan\n18:10\nTPE T1\n2h 30m\nNonstop\n21:40\nKIX T1\nUS$273\nTotal US$546\nSelect\nIncluded\n- 21% CO2e\nEVA Air\n13:30\nTPE T2\n2h 25m\nNonstop\n16:55\nKIX T1\nUS$286\nTotal US$572\nSelect\nIncluded\n- 21% CO2e\nEVA Air\n06:30\nTPE T2\n2h 25m\nNonstop\n09:55\nKIX T1\nUS$314\nTotal US$628\nSelect\nIncluded\n- 11% CO2e\nCathay Pacific\n11:15\nTPE T1\n2h 40m\nNonstop\n14:55\nKIX T1\nUS$320\nTotal US$640\nUS$294\nSelect\nIncluded\n- 20% CO2e\nEVA Air\n08:20\nTPE T2\n2h 35m\nNonstop\n11:55\nKIX T1\nUS$337\nTotal US$673\nSelect\nIncluded\n- 1% CO2e\nSTARLUX Airlines\n07:40\nTPE T1\n2h 30m\nNonstop\n11:10\nKIX T1\nUS$339\nTotal US$677\nSelect\nIncluded\n- 7% CO2e\nSTARLUX Airlines\n09:20\nTPE T1\n2h 30m\nNonstop\n12:50\nKIX T1\nUS$339\nTotal US$677\nSelect\nIncluded\nChina Airlines\n08:05\nTPE T2\n2h 30m\nNonstop\n11:35\nKIX T1\nUS$398\nTotal US$795\nSelect\nIncluded\nJapan Airlines\noperated by China Airlines\n14:20\nTPE T2\n2h 30m\nNonstop\n17:50\nKIX T1\nUS$959\nTotal US$1,917\nSelect\nIncluded\nAll Nippon Airways\noperated by EVA Air\n06:30\nTPE T2\n2h 25m\nNonstop\n09:55\nKIX T1\nUS$965\nTotal US$1,929\nSelect\nIncluded\nAll Nippon Airways\noperated by EVA Air\n08:20\nTPE T2\n2h 35m\nNonstop\n11:55\nKIX T1\nUS$965\nTotal US$1,929\nSelect\nIncluded\nAll Nippon Airways\noperated by EVA Air\n13:30\nTPE T2\n2h 25m\nNonstop\n16:55\nKIX T1\nUS$965\nTotal US$1,929\nSelect\nIncluded\nHong Kong Airlines\n21:40\nTPE T2\n8h 35m\n3h in Hong Kong\n07:15\nKIX T1\n +1\nUS$191\nTotal US$382\nSelect\nShow more results\nFlights\n > \nFlights\n > \nTaipei to Flights\nBook flights from Taipei to on Trip.com\n\nFirst class | Business class | Economy class | Nonstop\n\nSearch for cheap flights from Taipei to on Trip.com. Trip.com provides the best real-time Taipei to airfares and flight deals available, featuring advanced flight planning tools like price alerts, deal finder fare calendars, and Taipei Flight + Hotel deals that make a vacation or tour more convenient and affordable.\n\nAward-winning\nSupport in approx. 30s\nRewards for booking",
      "Taipei\nEdit\n2 adults\nEconomy\nFeb 25, 2026\nSun, Feb 22\nView\nMon, Feb 23\nView\nTue, Feb 24\nView\nWed, Feb 25\nUS$140\nThu, Feb 26\nView",
      "DepartWed, Feb 25"
    ],
    "hotel_class": [
      "Hotels & Homes"
    ],
    "main": [
      "Cheap Flights, Airline Tickets & Plane Tickets | Trip.com\nAllow notifications\nDon't miss out! Be the first to find out the latest travel info.\nAllow\nTaipei\nEdit\n2 adults\nEconomy\nFeb 25, 2026\nSun, Feb 22\nView\nMon, Feb 23\nView\nTue, Feb 24\nView\nWed, Feb 25\nUS$140\nThu, Feb 26\nView\nWed, Feb 18\nView\nThu, Feb 19\nView\nFri, Feb 20\nView\nSat, Feb 21\nView\nSun, Feb 22\nView\nMon, Feb 23\nView\nTue, Feb 24\nView\nWed, Feb 25\nUS$140\nThu, Feb 26\nView\nFri, Feb 27\nView\nSat, Feb 28\nView\nSun, Mar 1\nView\nMon, Mar 2\nView\nTue, Mar 3\nView\nWed, Mar 4\nView\nPrice graph\nRecommended\n Nonstop\n Checked baggage included\n Hide budget airlines\n Student tickets\n Carry-on baggage included\n Hide codeshare flights\nCO2e Lower emission flights\nShow More\nAlliance\nSkyTeam\nUS$263\nStar Alliance\nUS$278\nOneworld\nUS$320\nAirlines\nAll flights with the same airline\nAll airlines\nHong Kong Airlines (12)\nUS$191\nHK Express (6)\nUS$205\nJapan Airlines (5)\nUS$329\nCathay Pacific (5)\nUS$320\nPeach (4)\nUS$193\nShow More\nAlliance\nSkyTeam\nUS$263\nStar Alliance\nUS$278\nOneworld\nUS$320\nTimes\nDeparture time\n00:00–24:00\n00:00\n24:00\nArrival time\n00:00–24:00\n00:00\n24:00\nDuration\nAny\nStopover Duration\n1h–23h\n1h\n23h\nTotal Duration\n2h–26h 30m\n2h\n26h 30m\nStops\n1 stop or fewer\nUS$140\nStopover cities\nAny\nHong Kong\nUS$191\nMacau\nUS$270\nManila\nUS$280\nTokyo\nUS$329\nJeju\nUS$210\nDaegu\nUS$275\nSeoul\nUS$278\nHo Chi Minh City\nUS$309\nBusan\nUS$337\nAirports\nAny\nDeparture Airport\nTPE\nTaiwan Taoyuan International Airport\nUS$140\nArrival Airport\nKIX\nKansai International Airport\nUS$140\nAircrafts\nAny\nLarge aircraft\nUS$140\nMidsize aircraft\nUS$154\nCabin\nEconomy\nEconomy\nEconomy/premium economy\nPremium economy\nBusiness/first\nBusiness\nFirst class\nRecommended\nUS$140\nNonstop first\nUS$193\nCheapest\nUS$140\nSort by\nCreate price alert\nCheapest\nCarry-on baggage included\n- 16% CO2e\nAirAsia X Berhad\n15:40\nTPE T1\n2h 40m\nNonstop\n19:20\nKIX T1\nUS$140\nTotal US$279\nSelect\nCarry-on baggage included\nThai Vietjet Air\n07:30\nTPE T1\n2h 30m\nNonstop\n11:00\nKIX T1\nUS$154\nTotal US$307\nSelect\nCarry-on baggage included\nPeach\n01:45\nTPE T1\n2h 25m\nNonstop\n05:10\nKIX T2\nUS$193\nTotal US$386\nSelect\nCarry-on baggage included\n- 18% CO2e\nPeach\n18:50\nTPE T1\n2h 25m\nNonstop\n22:15\nKIX T2\nUS$193\nTotal US$386\nSelect\nSign in & save for future trips\nEarn at least 28 Trip Coins worth US$0.28 for this booking, which you can use to save on future trips!\nSign in/register\nCarry-on baggage included\n- 18% CO2e\nPeach\n09:40\nTPE T1\n2h 30m\nNonstop\n13:10\nKIX T2\nUS$213\nTotal US$425\nSelect\nCarry-on baggage included\nPeach\n13:40\nTPE T1\n2h 25m\nNonstop\n17:05\nKIX T2\nUS$213\nTotal US$425\nSelect\nCarry-on baggage included\nTigerair Taiwan\n14:40\nTPE T1\n2h 15m\nNonstop\n17:55\nKIX T1\nUS$218\nTotal US$435\nSelect\nCarry-on baggage included\nTigerair Taiwan\n07:00\nTPE T1\n2h 25m\nNonstop\n10:25\nKIX T1\nUS$257\nTotal US$513\nSelect\nPrice alerts\nWant a better deal? We'll notify you when the price drops below US$135.\nRecommended: US$135\nHigh chances of success\nOK\nIncluded\n- 3% CO2e\nChina Airlines\n14:20\nTPE T2\n2h 30m\nNonstop\n17:50\nKIX T1\nUS$263\nTotal US$526\nSelect\nIncluded\nChina Airlines\n09:45\nTPE T2\n2h 35m\nNonstop\n13:20\nKIX T1\nUS$271\nTotal US$542\nSelect\n<9 left\nCarry-on baggage included\nJetstar Japan\n18:10\nTPE T1\n2h 30m\nNonstop\n21:40\nKIX T1\nUS$273\nTotal US$546\nSelect\nIncluded\n- 21% CO2e\nEVA Air\n13:30\nTPE T2\n2h 25m\nNonstop\n16:55\nKIX T1\nUS$286\nTotal US$572\nSelect\nIncluded\n- 21% CO2e\nEVA Air\n06:30\nTPE T2\n2h 25m\nNonstop\n09:55\nKIX T1\nUS$314\nTotal US$628\nSelect\nIncluded\n- 11% CO2e\nCathay Pacific\n11:15\nTPE T1\n2h 40m\nNonstop\n14:55\nKIX T1\nUS$320\nTotal US$640\nUS$294\nSelect\nIncluded\n- 20% CO2e\nEVA Air\n08:20\nTPE T2\n2h 35m\nNonstop\n11:55\nKIX T1\nUS$337\nTotal US$673\nSelect\nIncluded\n- 1% CO2e\nSTARLUX Airlines\n07:40\nTPE T1\n2h 30m\nNonstop\n11:10\nKIX T1\nUS$339\nTotal US$677\nSelect\nIncluded\n- 7% CO2e\nSTARLUX Airlines\n09:20\nTPE T1\n2h 30m\nNonstop\n12:50\nKIX T1\nUS$339\nTotal US$677\nSelect\nIncluded\nChina Airlines\n08:05\nTPE T2\n2h 30m\nNonstop\n11:35\nKIX T1\nUS$398\nTotal US$795\nSelect\nIncluded\nJapan Airlines\noperated by China Airlines\n14:20\nTPE T2\n2h 30m\nNonstop\n17:50\nKIX T1\nUS$959\nTotal US$1,917\nSelect\nIncluded\nAll Nippon Airways\noperated by EVA Air\n06:30\nTPE T2\n2h 25m\nNonstop\n09:55\nKIX T1\nUS$965\nTotal US$1,929\nSelect\nIncluded\nAll Nippon Airways\noperated by EVA Air\n08:20\nTPE T2\n2h 35m\nNonstop\n11:55\nKIX T1\nUS$965\nTotal US$1,929\nSelect\nIncluded\nAll Nippon Airways\noperated by EVA Air\n13:30\nTPE T2\n2h 25m\nNonstop\n16:55\nKIX T1\nUS$965\nTotal US$1,929\nSelect\nIncluded\nHong Kong Airlines\n21:40\nTPE T2\n8h 35m\n3h in Hong Kong\n07:15\nKIX T1\n +1\nUS$191\nTotal US$382\nSelect\nShow more results\nFlights\n > \nFlights\n > \nTaipei to Flights\nBook flights from Taipei to on Trip.com\n\nFirst class | Business class | Economy class | Nonstop\n\nSearch for cheap flights from Taipei to on Trip.com. Trip.com provides the best real-time Taipei to airfares and flight deals available, featuring advanced flight planning tools like price alerts, deal finder fare calendars, and Taipei Flight + Hotel deals that make a vacation or tour more convenient and affordable.\n\nAward-winning\nSupport in approx. 30s\nRewards for booking"
    ]
  }
}