{
  "url": "https://www.trip.com/flights/osaka-to-taipei/tickets-kix-tpe?dcity=kix&acity=tpe&ddate=2026-03-03&flighttype=ow&class=y&quantity=2",
  "scraped_at": "2026-02-05T10:39:32.254280",
  "title": "Cheap Flights, Airline Tickets & Plane Tickets | Trip.com",
  "raw_text": "Go to main content\nTheme Detection\nHotels & Homes\nFlights\nTrains\nCar services\nApp\nUSD\nCustomer support\nFind bookings\nSign in / Register\nCheap Flights, Airline Tickets & Plane Tickets | Trip.com\nAllow notifications\nDon't miss out! Be the first to find out the latest travel info.\nAllow\nTaipei\nEdit\n2 adults\nEconomy\nMar 3, 2026\nSat, Feb 28\nView\nSun, Mar 1\nView\nMon, Mar 2\nView\nTue, Mar 3\nUS$176\nWed, Mar 4\nView\nTue, Feb 24\nView\nWed, Feb 25\nView\nThu, Feb 26\nView\nFri, Feb 27\nView\nSat, Feb 28\nView\nSun, Mar 1\nView\nMon, Mar 2\nView\nTue, Mar 3\nUS$176\nWed, Mar 4\nView\nThu, Mar 5\nView\nFri, Mar 6\nView\nSat, Mar 7\nView\nSun, Mar 8\nView\nMon, Mar 9\nView\nTue, Mar 10\nView\nPrice graph\nRecommended\n Nonstop\n Checked baggage included\n Hide budget airlines\n Student tickets\n Carry-on baggage included\n Hide codeshare flights\nCO2e Lower emission flights\nShow More\nAlliance\nStar Alliance\nUS$253\nSkyTeam\nUS$363\nOneworld\nUS$406\nAirlines\nAll flights with the same airline\nAll airlines\nHong Kong Airlines (11)\nUS$198\nHK Express (11)\nUS$177\nJeju Air (10)\nUS$247\nT'Way Air (8)\nUS$203\nEVA Air (7)\nUS$384\nShow More\nAlliance\nStar Alliance\nUS$253\nSkyTeam\nUS$363\nOneworld\nUS$406\nTimes\nDeparture time\n00:00–24:00\n00:00\n24:00\nArrival time\n00:00–24:00\n00:00\n24:00\nDuration\nAny\nStopover Duration\n1h 30m–23h\n1h 30m\n23h\nTotal Duration\n3h–29h\n3h\n29h\nStops\n1 stop or fewer\nUS$176\nStopover cities\nAny\nHong Kong\nUS$177\nBusan\nUS$200\nSeoul\nUS$298\nMacau\nUS$176\nOkinawa\nUS$253\nTokyo\nUS$235\nDaegu\nUS$203\nCheongju\nUS$205\nJeju\nUS$270\nHanoi\nUS$351\nManila\nUS$373\nGuangzhou\nUS$377\nAirports\nAny\nDeparture Airport\nKIX\nKansai International Airport\nUS$176\nArrival Airport\nTSA\nTaipei Songshan Airport\nUS$315\nTPE\nTaiwan Taoyuan International Airport\nUS$176\nAircrafts\nAny\nLarge aircraft\nUS$176\nMidsize aircraft\nUS$176\nCabin\nEconomy\nEconomy\nEconomy/premium economy\nPremium economy\nBusiness/first\nBusiness\nFirst class\nDeparting for Taipei\nRecommended\nUS$226\nNonstop first\nUS$283\nCheapest\nUS$176\nSort by\nCreate price alert\n\nPrices are low and likely to increase—book now!\n\nCurrent lowest price: US$176.00\nLow price\n2 weeks ago\nToday\nDeparture\nUS$72.80\nAvg. US$255.67\nUS$438.53\nAdd a price alert\nCheapest nonstop\nCarry-on baggage included\n- 4% CO2e\nThai Lion Air\n13:30\nKIX T1\n3h 10m\nNonstop\n15:40\nTPE T1\nUS$226\nTotal US$451\nSelect\nCarry-on baggage included\n- 2% CO2e\nThai Vietjet Air\n12:00\nKIX T1\n3h 15m\nNonstop\n14:15\nTPE T1\nUS$241\nTotal US$481\nSelect\nCarry-on baggage included\n- 18% CO2e\nAirAsia X Berhad\n20:45\nKIX T1\n3h 20m\nNonstop\n23:05\nTPE T1\nUS$257\nTotal US$514\nSelect\nIncluded\n- 10% CO2e\nSTARLUX Airlines\n14:00\nKIX T1\n3h 15m\nNonstop\n16:15\nTPE T1\nUS$260\nTotal US$520\nSelect\nCarry-on baggage included\n- 1% CO2e\nTigerair Taiwan\n11:30\nKIX T1\n3h 20m\nNonstop\n13:50\nTPE T1\nUS$268\nTotal US$536\nSelect\nIncluded\n- 20% CO2e\nPeach\n07:15\nKIX T2\n3h 30m\nNonstop\n09:45\nTPE T1\nUS$283\nTotal US$565\nSelect\nIncluded\nPeach\n10:10\nKIX T2\n3h 35m\nNonstop\n12:45\nTPE T1\nUS$283\nTotal US$565\nSelect\nCarry-on baggage included\n- 2% CO2e\nTigerair Taiwan\n18:55\nKIX T1\n3h 20m\nNonstop\n21:15\nTPE T1\nUS$335\nTotal US$669\nSelect\nIncluded\nChina Airlines\n14:30\nKIX T1\n3h 15m\nNonstop\n16:45\nTPE T2\nUS$384\nTotal US$768\nSelect\nCarry-on baggage included\n- 2% CO2e\nJetstar Japan\n14:50\nKIX T1\n3h 20m\nNonstop\n17:10\nTPE T1\nUS$388\nTotal US$776\nSelect\nIncluded\n- 20% CO2e\nPeach\n15:25\nKIX T2\n3h 30m\nNonstop\n17:55\nTPE T1\nUS$415\nTotal US$829\nSelect\nIncluded\n- 23% CO2e\nEVA Air\n10:55\nKIX T1\n3h 15m\nNonstop\n13:10\nTPE T2\nUS$428\nTotal US$856\nSelect\nIncluded\n- 6% CO2e\nChina Airlines\n19:00\nKIX T1\n3h 15m\nNonstop\n21:15\nTPE T2\nUS$469\nTotal US$938\nSelect\nIncluded\n- 10% CO2e\nSTARLUX Airlines\n12:20\nKIX T1\n3h 15m\nNonstop\n14:35\nTPE T1\nUS$488\nTotal US$975\nSelect\nIncluded\nJapan Airlines\noperated by China Airlines\n14:30\nKIX T1\n3h 15m\nNonstop\n16:45\nTPE T2\nUS$1,406\nTotal US$2,811\nSelect\nIncluded\nJapan Airlines\noperated by China Airlines\n19:00\nKIX T1\n3h 15m\nNonstop\n21:15\nTPE T2\nUS$1,406\nTotal US$2,811\nSelect\nCheapest\nIncluded\nAir Macau\n13:45\nKIX T1\n8h 45m\n2h 30m in Macau\n21:30\nTPE T1\nUS$176\nTotal US$352\nSelect\n<9 left\nCheapest\nIncluded\nAir Macau\noperated by EVA Air\n13:45\nKIX T1\n26h 10m\n20h 5m in Macau\n14:55\nTPE T2\n +1\nUS$176\nTotal US$352\nSelect\nHong Kong: Free Layover Tour\nHK Express\n21:05\nKIX T1\n17h 5m\n10h 30m in Hong Kong\n13:10\nTPE T1\n +1\nUS$177\nTotal US$354\nSelect\nHong Kong: Free Layover Tour\nHK Express\n20:15\nKIX T1\n17h 55m\n11h 20m in Hong Kong\n13:10\nTPE T1\n +1\nUS$177\nTotal US$354\nSelect\nHK Express\n15:15\nKIX T1\n22h 55m\n16h 25m in Hong Kong\n13:10\nTPE T1\n +1\nUS$177\nTotal US$354\nSelect\nHong Kong: Free Layover Tour\nHK Express\n21:05\nKIX T1\n17h 50m\n11h 20m in Hong Kong\n13:55\nTPE T1\n +1\nUS$184\nTotal US$368\nSelect\nHong Kong: Free Layover Tour\nHK Express\n20:15\nKIX T1\n18h 40m\n12h 10m in Hong Kong\n13:55\nTPE T1\n +1\nUS$184\nTotal US$368\nSelect\nShow more results\nFlights\n > \nTaipei Flights\n > \nto Taipei Flights\nBook flights from to Taipei on Trip.com\n\nFirst class | Business class | Economy class | Nonstop\n\nSearch for cheap flights from to Taipei on Trip.com. Trip.com provides the best real-time to Taipei airfares and flight deals available, featuring advanced flight planning tools like price alerts, deal finder fare calendars, and Flight + Hotel deals that make a Taipei vacation or Taipei tour more convenient and affordable.\n\nAward-winning\nSupport in approx. 30s\nRewards for booking\nContact us\nCustomer support\nService guarantee\nMore service info\nAbout\nAbout Trip.com\nNews\nCareers\nTerms & Conditions\nPrivacy Statement\nAccessibility statement\nAbout Trip.com Group\nOther services\nInvestor relations\nTrip.com Rewards\nAffiliate program\nList your property\nAll hotels\nBecome a Supplier\nSecurity\nPayment methods\nOur partners\nContact Center\nof the year 2025\nCopyright © 2025 Trip.com Travel Singapore Pte. Ltd. All rights reserved\nSite Operator: Trip.com Travel Singapore Pte. Ltd.",
  "extracted": {
    "flight": {},
    "hotel": {},
    "price": {},
    "dates": {},
    "inclusions": [],
    "date_pricing": {}
  },
  "extracted_elements": {
    "flight_element": [
      "Thai Lion Air\n13:30\nKIX T1\n3h 10m\nNonstop\n15:40\nTPE T1",
      "Thai Vietjet Air\n12:00\nKIX T1\n3h 15m\nNonstop\n14:15\nTPE T1",
      "AirAsia X Berhad\n20:45\nKIX T1\n3h 20m\nNonstop\n23:05\nTPE T1",
      "STARLUX Airlines\n14:00\nKIX T1\n3h 15m\nNonstop\n16:15\nTPE T1",
      "Tigerair Taiwan\n11:30\nKIX T1\n3h 20m\nNonstop\n13:50\nTPE T1"
    ],
    "price_class": [
      "Sat, Feb 28\nView\nSun, Mar 1\nView\nMon, Mar 2\nView\nTue, Mar 3\nUS$176\nWed, Mar 4\nView",
      "Sat, Feb 28\nView\nSun, Mar 1\nView\nMon, Mar 2\nView\nTue, Mar 3\nUS$176\nWed, Mar 4\nView",
      "Sat, Feb 28\nView\nSun, Mar 1\nView\nMon, Mar 2\nView\nTue, Mar 3\nUS$176\nWed, Mar 4\nView",
      "Sat, Feb 28\nView\nSun, Mar 1\nView\nMon, Mar 2\nView\nTue, Mar 3\nUS$176\nWed, Mar 4\nView",
      "Sat, Feb 28\nView\nSun, Mar 1\nView\nMon, Mar 2\nView\nTue, Mar 3\nUS$176\nWed, Mar 4\nView"
    ],
    "flight_class": [
      "Flights",
      "Taipei\nEdit\n2 adults\nEconomy\nMar 3, 2026\nSat, Feb 28\nView\nSun, Mar 1\nView\nMon, Mar 2\nView\nTue, Mar 3\nUS$176\nWed, Mar 4\nView\nTue, Feb 24\nView\nWed, Feb 25\nView\nThu, Feb 26\nView\nFri, Feb 27\nView\nSat, Feb 28\nView\nSun, Mar 1\nView\nMon, Mar 2\nView\nTue, Mar 3\nUS$176\nWed, Mar 4\nView\nThu, Mar 5\nView\nFri, Mar 6\nView\nSat, Mar 7\nView\nSun, Mar 8\nView\nMon, Mar 9\nView\nTue, Mar 10\nView\nPrice graph\nRecommended\n Nonstop\n Checked baggage included\n Hide budget airlines\n Student tickets\n Carry-on baggage included\n Hide codeshare flights\nCO2e Lower emission flights\nShow More\nAlliance\nStar Alliance\nUS$253\nSkyTeam\nUS$363\nOneworld\nUS$406\nAirlines\nAll flights with the same airline\nAll airlines\nHong Kong Airlines (11)\nUS$198\nHK Express (11)\nUS$177\nJeju Air (10)\nUS$247\nT'Way Air (8)\nUS$203\nEVA Air (7)\nUS$384\nShow More\nAlliance\nStar Alliance\nUS$253\nSkyTeam\nUS$363\nOneworld\nUS$406\nTimes\nDeparture time\n00:00–24:00\n00:00\n24:00\nArrival time\n00:00–24:00\n00:00\n24:00\nDuration\nAny\nStopover Duration\n1h 30m–23h\n1h 30m\n23h\nTotal Duration\n3h–29h\n3h\n29h\nStops\n1 stop or fewer\nUS$176\nStopover cities\nAny\nHong Kong\nUS$177\nBusan\nUS$200\nSeoul\nUS$298\nMacau\nUS$176\nOkinawa\nUS$253\nTokyo\nUS$235\nDaegu\nUS$203\nCheongju\nUS$205\nJeju\nUS$270\nHanoi\nUS$351\nManila\nUS$373\nGuangzhou\nUS$377\nAirports\nAny\nDeparture Airport\nKIX\nKansai International Airport\nUS$176\nArrival Airport\nTSA\nTaipei Songshan Airport\nUS$315\nTPE\nTaiwan Taoyuan International Airport\nUS$176\nAircrafts\nAny\nLarge aircraft\nUS$176\nMidsize aircraft\nUS$176\nCabin\nEconomy\nEconomy\nEconomy/premium economy\nPremium economy\nBusiness/first\nBusiness\nFirst class\nDeparting for Taipei\nRecommended\nUS$226\nNonstop first\nUS$283\nCheapest\nUS$176\nSort by\nCreate price alert\n\nPrices are low and likely to increase—book now!\n\nCurrent lowest price: US$176.00\nLow price\n2 weeks ago\nToday\nDeparture\nUS$72.80\nAvg. US$255.67\nUS$438.53\nAdd a price alert\nCheapest nonstop\nCarry-on baggage included\n- 4% CO2e\nThai Lion Air\n13:30\nKIX T1\n3h 10m\nNonstop\n15:40\nTPE T1\nUS$226\nTotal US$451\nSelect\nCarry-on baggage included\n- 2% CO2e\nThai Vietjet Air\n12:00\nKIX T1\n3h 15m\nNonstop\n14:15\nTPE T1\nUS$241\nTotal US$481\nSelect\nCarry-on baggage included\n- 18% CO2e\nAirAsia X Berhad\n20:45\nKIX T1\n3h 20m\nNonstop\n23:05\nTPE T1\nUS$257\nTotal US$514\nSelect\nIncluded\n- 10% CO2e\nSTARLUX Airlines\n14:00\nKIX T1\n3h 15m\nNonstop\n16:15\nTPE T1\nUS$260\nTotal US$520\nSelect\nCarry-on baggage included\n- 1% CO2e\nTigerair Taiwan\n11:30\nKIX T1\n3h 20m\nNonstop\n13:50\nTPE T1\nUS$268\nTotal US$536\nSelect\nIncluded\n- 20% CO2e\nPeach\n07:15\nKIX T2\n3h 30m\nNonstop\n09:45\nTPE T1\nUS$283\nTotal US$565\nSelect\nIncluded\nPeach\n10:10\nKIX T2\n3h 35m\nNonstop\n12:45\nTPE T1\nUS$283\nTotal US$565\nSelect\nCarry-on baggage included\n- 2% CO2e\nTigerair Taiwan\n18:55\nKIX T1\n3h 20m\nNonstop\n21:15\nTPE T1\nUS$335\nTotal US$669\nSelect\nIncluded\nChina Airlines\n14:30\nKIX T1\n3h 15m\nNonstop\n16:45\nTPE T2\nUS$384\nTotal US$768\nSelect\nCarry-on baggage included\n- 2% CO2e\nJetstar Japan\n14:50\nKIX T1\n3h 20m\nNonstop\n17:10\nTPE T1\nUS$388\nTotal US$776\nSelect\nIncluded\n- 20% CO2e\nPeach\n15:25\nKIX T2\n3h 30m\nNonstop\n17:55\nTPE T1\nUS$415\nTotal US$829\nSelect\nIncluded\n- 23% CO2e\nEVA Air\n10:55\nKIX T1\n3h 15m\nNonstop\n13:10\nTPE T2\nUS$428\nTotal US$856\nSelect\nIncluded\n- 6% CO2e\nChina Airlines\n19:00\nKIX T1\n3h 15m\nNonstop\n21:15\nTPE T2\nUS$469\nTotal US$938\nSelect\nIncluded\n- 10% CO2e\nSTARLUX Airlines\n12:20\nKIX T1\n3h 15m\nNonstop\n14:35\nTPE T1\nUS$488\nTotal US$975\nSelect\nIncluded\nJapan Airlines\noperated by China Airlines\n14:30\nKIX T1\n3h 15m\nNonstop\n16:45\nTPE T2\nUS$1,406\nTotal US$2,811\nSelect\nIncluded\nJapan Airlines\noperated by China Airlines\n19:00\nKIX T1\n3h 15m\nNonstop\n21:15\nTPE T2\nUS$1,406\nTotal US$2,811\nSelect\nCheapest\nIncluded\nAir Macau\n13:45\nKIX T1\n8h 45m\n2h 30m in Macau\n21:30\nTPE T1\nUS$176\nTotal US$352\nSelect\n<9 left\nCheapest\nIncluded\nAir Macau\noperated by EVA Air\n13:45\nKIX T1\n26h 10m\n20h 5m in Macau\n14:55\nTPE T2\n +1\nUS$176\nTotal US$352\nSelect\nHong Kong: Free Layover Tour\nHK Express\n21:05\nKIX T1\n17h 5m\n10h 30m in Hong Kong\n13:10\nTPE T1\n +1\nUS$177\nTotal US$354\nSelect\nHong Kong: Free Layover Tour\nHK Express\n20:15\nKIX T1\n17h 55m\n11h 20m in Hong Kong\n13:10\nTPE T1\n +1\nUS$177\nTotal US$354\nSelect\nHK Express\n15:15\nKIX T1\n22h 55m\n16h 25m in Hong Kong\n13:10\nTPE T1\n +1\nUS$177\nTotal US$354\nSelect\nHong Kong: Free Layover Tour\nHK Express\n21:05\nKIX T1\n17h 50m\n11h 20m in Hong Kong\n13:55\nTPE T1\n +1\nUS$184\nTotal US$368\nSelect\nHong Kong: Free Layover Tour\nHK Express\n20:15\nKIX T1\n18h 40m\n12h 10m in Hong Kong\n13:55\nTPE T1\n +1\nUS$184\nTotal US$368\nSelect\nShow more results\nFlights\n > \nTaipei Flights\n > \nto Taipei Flights\nBook flights from to Taipei on Trip.com\n\nFirst class | Business class | Economy class | Nonstop\n\nSearch for cheap flights from to Taipei on Trip.com. Trip.com provides the best real-time to Taipei airfares and flight deals available, featuring advanced flight planning tools like price alerts, deal finder fare calendars, and Flight + Hotel deals that make a Taipei vacation or Taipei tour more convenient and affordable.\n\nAward-winning\nSupport in approx. 30s\nRewards for booking",
      "Taipei\nEdit\n2 adults\nEconomy\nMar 3, 2026\nSat, Feb 28\nView\nSun, Mar 1\nView\nMon, Mar 2\nView\nTue, Mar 3\nUS$176\nWed, Mar 4\nView",
      "DepartTue, Mar 3"
    ],
    "hotel_class": [
      "Hotels & Homes"
    ],
    "main": [
      "Cheap Flights, Airline Tickets & Plane Tickets | Trip.com\nAllow notifications\nDon't miss out! Be the first to find out the latest travel info.\nAllow\nTaipei\nEdit\n2 adults\nEconomy\nMar 3, 2026\nSat, Feb 28\nView\nSun, Mar 1\nView\nMon, Mar 2\nView\nTue, Mar 3\nUS$176\nWed, Mar 4\nView\nTue, Feb 24\nView\nWed, Feb 25\nView\nThu, Feb 26\nView\nFri, Feb 27\nView\nSat, Feb 28\nView\nSun, Mar 1\nView\nMon, Mar 2\nView\nTue, Mar 3\nUS$176\nWed, Mar 4\nView\nThu, Mar 5\nView\nFri, Mar 6\nView\nSat, Mar 7\nView\nSun, Mar 8\nView\nMon, Mar 9\nView\nTue, Mar 10\nView\nPrice graph\nRecommended\n Nonstop\n Checked baggage included\n Hide budget airlines\n Student tickets\n Carry-on baggage included\n Hide codeshare flights\nCO2e Lower emission flights\nShow More\nAlliance\nStar Alliance\nUS$253\nSkyTeam\nUS$363\nOneworld\nUS$406\nAirlines\nAll flights with the same airline\nAll airlines\nHong Kong Airlines (11)\nUS$198\nHK Express (11)\nUS$177\nJeju Air (10)\nUS$247\nT'Way Air (8)\nUS$203\nEVA Air (7)\nUS$384\nShow More\nAlliance\nStar Alliance\nUS$253\nSkyTeam\nUS$363\nOneworld\nUS$406\nTimes\nDeparture time\n00:00–24:00\n00:00\n24:00\nArrival time\n00:00–24:00\n00:00\n24:00\nDuration\nAny\nStopover Duration\n1h 30m–23h\n1h 30m\n23h\nTotal Duration\n3h–29h\n3h\n29h\nStops\n1 stop or fewer\nUS$176\nStopover cities\nAny\nHong Kong\nUS$177\nBusan\nUS$200\nSeoul\nUS$298\nMacau\nUS$176\nOkinawa\nUS$253\nTokyo\nUS$235\nDaegu\nUS$203\nCheongju\nUS$205\nJeju\nUS$270\nHanoi\nUS$351\nManila\nUS$373\nGuangzhou\nUS$377\nAirports\nAny\nDeparture Airport\nKIX\nKansai International Airport\nUS$176\nArrival Airport\nTSA\nTaipei Songshan Airport\nUS$315\nTPE\nTaiwan Taoyuan International Airport\nUS$176\nAircrafts\nAny\nLarge aircraft\nUS$176\nMidsize aircraft\nUS$176\nCabin\nEconomy\nEconomy\nEconomy/premium economy\nPremium economy\nBusiness/first\nBusiness\nFirst class\nDeparting for Taipei\nRecommended\nUS$226\nNonstop first\nUS$283\nCheapest\nUS$176\nSort by\nCreate price alert\n\nPrices are low and likely to increase—book now!\n\nCurrent lowest price: US$176.00\nLow price\n2 weeks ago\nToday\nDeparture\nUS$72.80\nAvg. US$255.67\nUS$438.53\nAdd a price alert\nCheapest nonstop\nCarry-on baggage included\n- 4% CO2e\nThai Lion Air\n13:30\nKIX T1\n3h 10m\nNonstop\n15:40\nTPE T1\nUS$226\nTotal US$451\nSelect\nCarry-on baggage included\n- 2% CO2e\nThai Vietjet Air\n12:00\nKIX T1\n3h 15m\nNonstop\n14:15\nTPE T1\nUS$241\nTotal US$481\nSelect\nCarry-on baggage included\n- 18% CO2e\nAirAsia X Berhad\n20:45\nKIX T1\n3h 20m\nNonstop\n23:05\nTPE T1\nUS$257\nTotal US$514\nSelect\nIncluded\n- 10% CO2e\nSTARLUX Airlines\n14:00\nKIX T1\n3h 15m\nNonstop\n16:15\nTPE T1\nUS$260\nTotal US$520\nSelect\nCarry-on baggage included\n- 1% CO2e\nTigerair Taiwan\n11:30\nKIX T1\n3h 20m\nNonstop\n13:50\nTPE T1\nUS$268\nTotal US$536\nSelect\nIncluded\n- 20% CO2e\nPeach\n07:15\nKIX T2\n3h 30m\nNonstop\n09:45\nTPE T1\nUS$283\nTotal US$565\nSelect\nIncluded\nPeach\n10:10\nKIX T2\n3h 35m\nNonstop\n12:45\nTPE T1\nUS$283\nTotal US$565\nSelect\nCarry-on baggage included\n- 2% CO2e\nTigerair Taiwan\n18:55\nKIX T1\n3h 20m\nNonstop\n21:15\nTPE T1\nUS$335\nTotal US$669\nSelect\nIncluded\nChina Airlines\n14:30\nKIX T1\n3h 15m\nNonstop\n16:45\nTPE T2\nUS$384\nTotal US$768\nSelect\nCarry-on baggage included\n- 2% CO2e\nJetstar Japan\n14:50\nKIX T1\n3h 20m\nNonstop\n17:10\nTPE T1\nUS$388\nTotal US$776\nSelect\nIncluded\n- 20% CO2e\nPeach\n15:25\nKIX T2\n3h 30m\nNonstop\n17:55\nTPE T1\nUS$415\nTotal US$829\nSelect\nIncluded\n- 23% CO2e\nEVA Air\n10:55\nKIX T1\n3h 15m\nNonstop\n13:10\nTPE T2\nUS$428\nTotal US$856\nSelect\nIncluded\n- 6% CO2e\nChina Airlines\n19:00\nKIX T1\n3h 15m\nNonstop\n21:15\nTPE T2\nUS$469\nTotal US$938\nSelect\nIncluded\n- 10% CO2e\nSTARLUX Airlines\n12:20\nKIX T1\n3h 15m\nNonstop\n14:35\nTPE T1\nUS$488\nTotal US$975\nSelect\nIncluded\nJapan Airlines\noperated by China Airlines\n14:30\nKIX T1\n3h 15m\nNonstop\n16:45\nTPE T2\nUS$1,406\nTotal US$2,811\nSelect\nIncluded\nJapan Airlines\noperated by China Airlines\n19:00\nKIX T1\n3h 15m\nNonstop\n21:15\nTPE T2\nUS$1,406\nTotal US$2,811\nSelect\nCheapest\nIncluded\nAir Macau\n13:45\nKIX T1\n8h 45m\n2h 30m in Macau\n21:30\nTPE T1\nUS$176\nTotal US$352\nSelect\n<9 left\nCheapest\nIncluded\nAir Macau\noperated by EVA Air\n13:45\nKIX T1\n26h 10m\n20h 5m in Macau\n14:55\nTPE T2\n +1\nUS$176\nTotal US$352\nSelect\nHong Kong: Free Layover Tour\nHK Express\n21:05\nKIX T1\n17h 5m\n10h 30m in Hong Kong\n13:10\nTPE T1\n +1\nUS$177\nTotal US$354\nSelect\nHong Kong: Free Layover Tour\nHK Express\n20:15\nKIX T1\n17h 55m\n11h 20m in Hong Kong\n13:10\nTPE T1\n +1\nUS$177\nTotal US$354\nSelect\nHK Express\n15:15\nKIX T1\n22h 55m\n16h 25m in Hong Kong\n13:10\nTPE T1\n +1\nUS$177\nTotal US$354\nSelect\nHong Kong: Free Layover Tour\nHK Express\n21:05\nKIX T1\n17h 50m\n11h 20m in Hong Kong\n13:55\nTPE T1\n +1\nUS$184\nTotal US$368\nSelect\nHong Kong: Free Layover Tour\nHK Express\n20:15\nKIX T1\n18h 40m\n12h 10m in Hong Kong\n13:55\nTPE T1\n +1\nUS$184\nTotal US$368\nSelect\nShow more results\nFlights\n > \nTaipei Flights\n > \nto Taipei Flights\nBook flights from to Taipei on Trip.com\n\nFirst class | Business class | Economy class | Nonstop\n\nSearch for cheap flights from to Taipei on Trip.com. Trip.com provides the best real-time to Taipei airfares and flight deals available, featuring advanced flight planning tools like price alerts, deal finder fare calendars, and Flight + Hotel deals that make a Taipei vacation or Taipei tour more convenient and affordable.\n\nAward-winning\nSupport in approx. 30s\nRewards for booking"
    ]
  }
}