{
  "url": "https://www.trip.com/flights/osaka-to-taipei/tickets-kix-tpe?dcity=kix&acity=tpe&ddate=2026-03-03&flighttype=ow&class=y&quantity=2",
  "scraped_at": "2026-02-05T14:28:34.931745",
  "title": "Cheap Flights, Airline Tickets & Plane Tickets | Trip.com",
  "raw_text": "Go to main content\nTheme Detection\nHotels & Homes\nFlights\nTrains\nCar services\nApp\nUSD\nCustomer support\nFind bookings\nSign in / Register\nCheap Flights, Airline Tickets & Plane Tickets | Trip.com\nAllow notifications\nDon't miss out! Be the first to find out the latest travel info.\nAllow\nTaipei\nEdit\n2 adults\nEconomy\nMar 3, 2026\nSat, Feb 28\nView\nSun, Mar 1\nView\nMon, Mar 2\nView\nTue, Mar 3\nUS$176\nWed, Mar 4\nView\nTue, Feb 24\nView\nWed, Feb 25\nView\nThu, Feb 26\nView\nFri, Feb 27\nView\nSat, Feb 28\nView\nSun, Mar 1\nView\nMon, Mar 2\nView\nTue, Mar 3\nUS$176\nWed, Mar 4\nView\nThu, Mar 5\nView\nFri, Mar 6\nView\nSat, Mar 7\nView\nSun, Mar 8\nView\nMon, Mar 9\nView\nTue, Mar 10\nView\nPrice graph\nRecommended\n Nonstop\n Checked baggage included\n Hide budget airlines\n Student tickets\n Carry-on baggage included\n Hide codeshare flights\nCO2e Lower emission flights\nShow More\nAlliance\nStar Alliance\nUS$310\nSkyTeam\nUS$359\nOneworld\nUS$1,406\nAirlines\nAll flights with the same airline\nAll airlines\nHong Kong Airlines (11)\nUS$214\nJeju Air (10)\nUS$246\nHK Express (9)\nUS$185\nT'Way Air (7)\nUS$203\nAir Macau (5)\nUS$176\nShow More\nAlliance\nStar Alliance\nUS$310\nSkyTeam\nUS$359\nOneworld\nUS$1,406\nTimes\nDeparture time\n00:00–24:00\n00:00\n24:00\nArrival time\n00:00–24:00\n00:00\n24:00\nDuration\nAny\nStopover Duration\n1h 30m–23h\n1h 30m\n23h\nTotal Duration\n3h–29h\n3h\n29h\nStops\n1 stop or fewer\nUS$176\nStopover cities\nAny\nHong Kong\nUS$185\nBusan\nUS$204\nSeoul\nUS$293\nMacau\nUS$176\nOkinawa\nUS$359\nDaegu\nUS$203\nManila\nUS$364\nCheongju\nUS$232\nTokyo\nUS$236\nJeju\nUS$269\nHanoi\nUS$342\nGuangzhou\nUS$377\nAirports\nAny\nDeparture Airport\nKIX\nKansai International Airport\nUS$176\nArrival Airport\nTSA\nTaipei Songshan Airport\nUS$293\nTPE\nTaiwan Taoyuan International Airport\nUS$176\nAircrafts\nAny\nLarge aircraft\nUS$176\nMidsize aircraft\nUS$176\nCabin\nEconomy\nEconomy\nEconomy/premium economy\nPremium economy\nBusiness/first\nBusiness\nFirst class\nDeparting for Taipei\n85 flights found\nRecommended\nUS$259\nNonstop first\nUS$226\nCheapest\nUS$176\nSort by\nCreate price alert\nIncluded\n- 10% CO2e\nSTARLUX Airlines\n14:00\nKIX T1\n3h 15m\nNonstop\n16:15\nTPE T1\nUS$259\nTotal US$517\nSelect\nCheapest nonstop\nCarry-on baggage included\n- 4% CO2e\nThai Lion Air\n13:30\nKIX T1\n3h 10m\nNonstop\n15:40\nTPE T1\nUS$226\nTotal US$451\nSelect\nCarry-on baggage included\n- 18% CO2e\nAirAsia X Berhad\n20:45\nKIX T1\n3h 20m\nNonstop\n23:05\nTPE T1\nUS$257\nTotal US$514\nSelect\nIncluded\n- 23% CO2e\nEVA Air\n10:55\nKIX T1\n3h 15m\nNonstop\n13:10\nTPE T2\nUS$327\nTotal US$653\nSelect\nCarry-on baggage included\n- 2% CO2e\nThai Vietjet Air\n12:00\nKIX T1\n3h 15m\nNonstop\n14:15\nTPE T1\nUS$240\nTotal US$480\nSelect\nCheapest\nIncluded\nAir Macau\n13:45\nKIX T1\n8h 45m\n2h 30m in Macau\n21:30\nTPE T1\nUS$176\nTotal US$351\nSelect\n<9 left\nIncluded\nPeach\n10:10\nKIX T2\n3h 35m\nNonstop\n12:45\nTPE T1\nUS$259\nTotal US$518\nSelect\nIncluded\nChina Airlines\n14:30\nKIX T1\n3h 15m\nNonstop\n16:45\nTPE T2\nUS$384\nTotal US$767\nSelect\nIncluded\n- 20% CO2e\nPeach\n15:25\nKIX T2\n3h 30m\nNonstop\n17:55\nTPE T1\nUS$414\nTotal US$828\nSelect\nCarry-on baggage included\n- 2% CO2e\nJetstar Japan\n14:50\nKIX T1\n3h 20m\nNonstop\n17:10\nTPE T1\nUS$388\nTotal US$776\nSelect\nCheapest\nIncluded\nAir Macau\noperated by EVA Air\n13:45\nKIX T1\n26h 10m\n20h 5m in Macau\n14:55\nTPE T2\n +1\nUS$176\nTotal US$351\nSelect\nCarry-on baggage included\n- 2% CO2e\nJetstar Japan\n23:10\nKIX T1\n3h 20m\nNonstop\n01:30\nTPE T1\n +1\nUS$463\nTotal US$925\nSelect\nIncluded\nHong Kong Airlines\n09:45\nKIX T1\n9h 35m\n3h 15m in Hong Kong\n18:20\nTPE T2\nUS$214\nTotal US$427\nSelect\nIncluded\nAir Macau\n13:45\nKIX T1\n24h 55m\n18h 50m in Macau\n13:40\nTPE T1\n +1\nUS$199\nTotal US$398\nSelect\nIncluded\nHong Kong Airlines\n09:45\nKIX T1\n11h 50m\n5h 30m in Hong Kong\n20:35\nTPE T2\nUS$219\nTotal US$438\nSelect\nIncluded\nAll Nippon Airways, China Airlines\n15:30\nKIX T1\n6h 30m\n2h 30m in Okinawa\n21:00\nTPE T2\nUS$359\nTotal US$718\nSelect\nIncluded\nHong Kong Airlines\n17:05\nKIX T1\n28h 35m\n21h 55m in Hong Kong\n20:40\nTPE T2\n +1\nUS$244\nTotal US$488\nSelect\nCarry-on baggage included\nT'Way Air, Tigerair Taiwan\n16:35\nKIX T1\n6h 55m\n2h 40m in Busan\n22:30\nTPE T1\nUS$217\nTotal US$434\nSelect\nShow more results\n*Last updated: 14:28:28\nFlights\n > \nTaipei Flights\n > \nto Taipei Flights\nBook flights from to Taipei on Trip.com\n\nFirst class | Business class | Economy class | Nonstop\n\nSearch for cheap flights from to Taipei on Trip.com. Trip.com provides the best real-time to Taipei airfares and flight deals available, featuring advanced flight planning tools like price alerts, deal finder fare calendars, and Flight + Hotel deals that make a Taipei vacation or Taipei tour more convenient and affordable.\n\nAward-winning\nSupport in approx. 30s\nRewards for booking\nContact us\nCustomer support\nService guarantee\nMore service info\nAbout\nAbout Trip.com\nNews\nCareers\nTerms & Conditions\nPrivacy Statement\nAccessibility statement\nAbout Trip.com Group\nOther services\nInvestor relations\nTrip.com Rewards\nAffiliate program\nList your property\nAll hotels\nBecome a Supplier\nSecurity\nPayment methods\nOur partners\nContact Center\nof the year 2025\nCopyright © 2025 Trip.com Travel Singapore Pte. Ltd. All rights reserved\nSite Operator: Trip.com Travel Singapore Pte. Ltd.",
  "extracted": {
    "flight": {},
    "hotel": {},
    "price": {},
    "dates": {},
    "inclusions": [],
    "date_pricing": {}
  },
  "extracted_elements": {
    "flight_element": [
      "STARLUX Airlines\n14:00\nKIX T1\n3h 15m\nNonstop\n16:15\nTPE T1",
      "Thai Lion Air\n13:30\nKIX T1\n3h 10m\nNonstop\n15:40\nTPE T1",
      "AirAsia X Berhad\n20:45\nKIX T1\n3h 20m\nNonstop\n23:05\nTPE T1",
      "EVA Air\n10:55\nKIX T1\n3h 15m\nNonstop\n13:10\nTPE T2",
      "Thai Vietjet Air\n12:00\nKIX T1\n3h 15m\nNonstop\n14:15\nTPE T1"
    ],
    "price_class": [
      "Sat, Feb 28\nView\nSun, Mar 1\nView\nMon, Mar 2\nView\nTue, Mar 3\nUS$176\nWed, Mar 4\nView",
      "Sat, Feb 28\nView\nSun, Mar 1\nView\nMon, Mar 2\nView\nTue, Mar 3\nUS$176\nWed, Mar 4\nView",
      "Sat, Feb 28\nView\nSun, Mar 1\nView\nMon, Mar 2\nView\nTue, Mar 3\nUS$176\nWed, Mar 4\nView",
      "Sat, Feb 28\nView\nSun, Mar 1\nView\nMon, Mar 2\nView\nTue, Mar 3\nUS$176\nWed, Mar 4\nView",
      "Sat, Feb 28\nView\nSun, Mar 1\nView\nMon, Mar 2\nView\nTue, Mar 3\nUS$176\nWed, Mar 4\nView"
    ],
    "flight_class": [
      "Flights",
      "Taipei\nEdit\n2 adults\nEconomy\nMar 3, 2026\nSat, Feb 28\nView\nSun, Mar 1\nView\nMon, Mar 2\nView\nTue, Mar 3\nUS$176\nWed, Mar 4\nView\nTue, Feb 24\nView\nWed, Feb 25\nView\nThu, Feb 26\nView\nFri, Feb 27\nView\nSat, Feb 28\nView\nSun, Mar 1\nView\nMon, Mar 2\nView\nTue, Mar 3\nUS$176\nWed, Mar 4\nView\nThu, Mar 5\nView\nFri, Mar 6\nView\nSat, Mar 7\nView\nSun, Mar 8\nView\nMon, Mar 9\nView\nTue, Mar 10\nView\nPrice graph\nRecommended\n Nonstop\n Checked baggage included\n Hide budget airlines\n Student tickets\n Carry-on baggage included\n Hide codeshare flights\nCO2e Lower emission flights\nShow More\nAlliance\nStar Alliance\nUS$310\nSkyTeam\nUS$359\nOneworld\nUS$1,406\nAirlines\nAll flights with the same airline\nAll airlines\nHong Kong Airlines (11)\nUS$214\nJeju Air (10)\nUS$246\nHK Express (9)\nUS$185\nT'Way Air (7)\nUS$203\nAir Macau (5)\nUS$176\nShow More\nAlliance\nStar Alliance\nUS$310\nSkyTeam\nUS$359\nOneworld\nUS$1,406\nTimes\nDeparture time\n00:00–24:00\n00:00\n24:00\nArrival time\n00:00–24:00\n00:00\n24:00\nDuration\nAny\nStopover Duration\n1h 30m–23h\n1h 30m\n23h\nTotal Duration\n3h–29h\n3h\n29h\nStops\n1 stop or fewer\nUS$176\nStopover cities\nAny\nHong Kong\nUS$185\nBusan\nUS$204\nSeoul\nUS$293\nMacau\nUS$176\nOkinawa\nUS$359\nDaegu\nUS$203\nManila\nUS$364\nCheongju\nUS$232\nTokyo\nUS$236\nJeju\nUS$269\nHanoi\nUS$342\nGuangzhou\nUS$377\nAirports\nAny\nDeparture Airport\nKIX\nKansai International Airport\nUS$176\nArrival Airport\nTSA\nTaipei Songshan Airport\nUS$293\nTPE\nTaiwan Taoyuan International Airport\nUS$176\nAircrafts\nAny\nLarge aircraft\nUS$176\nMidsize aircraft\nUS$176\nCabin\nEconomy\nEconomy\nEconomy/premium economy\nPremium economy\nBusiness/first\nBusiness\nFirst class\nDeparting for Taipei\n85 flights found\nRecommended\nUS$259\nNonstop first\nUS$226\nCheapest\nUS$176\nSort by\nCreate price alert\nIncluded\n- 10% CO2e\nSTARLUX Airlines\n14:00\nKIX T1\n3h 15m\nNonstop\n16:15\nTPE T1\nUS$259\nTotal US$517\nSelect\nCheapest nonstop\nCarry-on baggage included\n- 4% CO2e\nThai Lion Air\n13:30\nKIX T1\n3h 10m\nNonstop\n15:40\nTPE T1\nUS$226\nTotal US$451\nSelect\nCarry-on baggage included\n- 18% CO2e\nAirAsia X Berhad\n20:45\nKIX T1\n3h 20m\nNonstop\n23:05\nTPE T1\nUS$257\nTotal US$514\nSelect\nIncluded\n- 23% CO2e\nEVA Air\n10:55\nKIX T1\n3h 15m\nNonstop\n13:10\nTPE T2\nUS$327\nTotal US$653\nSelect\nCarry-on baggage included\n- 2% CO2e\nThai Vietjet Air\n12:00\nKIX T1\n3h 15m\nNonstop\n14:15\nTPE T1\nUS$240\nTotal US$480\nSelect\nCheapest\nIncluded\nAir Macau\n13:45\nKIX T1\n8h 45m\n2h 30m in Macau\n21:30\nTPE T1\nUS$176\nTotal US$351\nSelect\n<9 left\nIncluded\nPeach\n10:10\nKIX T2\n3h 35m\nNonstop\n12:45\nTPE T1\nUS$259\nTotal US$518\nSelect\nIncluded\nChina Airlines\n14:30\nKIX T1\n3h 15m\nNonstop\n16:45\nTPE T2\nUS$384\nTotal US$767\nSelect\nIncluded\n- 20% CO2e\nPeach\n15:25\nKIX T2\n3h 30m\nNonstop\n17:55\nTPE T1\nUS$414\nTotal US$828\nSelect\nCarry-on baggage included\n- 2% CO2e\nJetstar Japan\n14:50\nKIX T1\n3h 20m\nNonstop\n17:10\nTPE T1\nUS$388\nTotal US$776\nSelect\nCheapest\nIncluded\nAir Macau\noperated by EVA Air\n13:45\nKIX T1\n26h 10m\n20h 5m in Macau\n14:55\nTPE T2\n +1\nUS$176\nTotal US$351\nSelect\nCarry-on baggage included\n- 2% CO2e\nJetstar Japan\n23:10\nKIX T1\n3h 20m\nNonstop\n01:30\nTPE T1\n +1\nUS$463\nTotal US$925\nSelect\nIncluded\nHong Kong Airlines\n09:45\nKIX T1\n9h 35m\n3h 15m in Hong Kong\n18:20\nTPE T2\nUS$214\nTotal US$427\nSelect\nIncluded\nAir Macau\n13:45\nKIX T1\n24h 55m\n18h 50m in Macau\n13:40\nTPE T1\n +1\nUS$199\nTotal US$398\nSelect\nIncluded\nHong Kong Airlines\n09:45\nKIX T1\n11h 50m\n5h 30m in Hong Kong\n20:35\nTPE T2\nUS$219\nTotal US$438\nSelect\nIncluded\nAll Nippon Airways, China Airlines\n15:30\nKIX T1\n6h 30m\n2h 30m in Okinawa\n21:00\nTPE T2\nUS$359\nTotal US$718\nSelect\nIncluded\nHong Kong Airlines\n17:05\nKIX T1\n28h 35m\n21h 55m in Hong Kong\n20:40\nTPE T2\n +1\nUS$244\nTotal US$488\nSelect\nCarry-on baggage included\nT'Way Air, Tigerair Taiwan\n16:35\nKIX T1\n6h 55m\n2h 40m in Busan\n22:30\nTPE T1\nUS$217\nTotal US$434\nSelect\nShow more results\n*Last updated: 14:28:28\nFlights\n > \nTaipei Flights\n > \nto Taipei Flights\nBook flights from to Taipei on Trip.com\n\nFirst class | Business class | Economy class | Nonstop\n\nSearch for cheap flights from to Taipei on Trip.com. Trip.com provides the best real-time to Taipei airfares and flight deals available, featuring advanced flight planning tools like price alerts, deal finder fare calendars, and Flight + Hotel deals that make a Taipei vacation or Taipei tour more convenient and affordable.\n\nAward-winning\nSupport in approx. 30s\nRewards for booking",
      "Taipei\nEdit\n2 adults\nEconomy\nMar 3, 2026\nSat, Feb 28\nView\nSun, Mar 1\nView\nMon, Mar 2\nView\nTue, Mar 3\nUS$176\nWed, Mar 4\nView",
      "DepartTue, Mar 3"
    ],
    "hotel_class": [
      "Hotels & Homes"
    ],
    "main": [
      "Cheap Flights, Airline Tickets & Plane Tickets | Trip.com\nAllow notifications\nDon't miss out! Be the first to find out the latest travel info.\nAllow\nTaipei\nEdit\n2 adults\nEconomy\nMar 3, 2026\nSat, Feb 28\nView\nSun, Mar 1\nView\nMon, Mar 2\nView\nTue, Mar 3\nUS$176\nWed, Mar 4\nView\nTue, Feb 24\nView\nWed, Feb 25\nView\nThu, Feb 26\nView\nFri, Feb 27\nView\nSat, Feb 28\nView\nSun, Mar 1\nView\nMon, Mar 2\nView\nTue, Mar 3\nUS$176\nWed, Mar 4\nView\nThu, Mar 5\nView\nFri, Mar 6\nView\nSat, Mar 7\nView\nSun, Mar 8\nView\nMon, Mar 9\nView\nTue, Mar 10\nView\nPrice graph\nRecommended\n Nonstop\n Checked baggage included\n Hide budget airlines\n Student tickets\n Carry-on baggage included\n Hide codeshare flights\nCO2e Lower emission flights\nShow More\nAlliance\nStar Alliance\nUS$310\nSkyTeam\nUS$359\nOneworld\nUS$1,406\nAirlines\nAll flights with the same airline\nAll airlines\nHong Kong Airlines (11)\nUS$214\nJeju Air (10)\nUS$246\nHK Express (9)\nUS$185\nT'Way Air (7)\nUS$203\nAir Macau (5)\nUS$176\nShow More\nAlliance\nStar Alliance\nUS$310\nSkyTeam\nUS$359\nOneworld\nUS$1,406\nTimes\nDeparture time\n00:00–24:00\n00:00\n24:00\nArrival time\n00:00–24:00\n00:00\n24:00\nDuration\nAny\nStopover Duration\n1h 30m–23h\n1h 30m\n23h\nTotal Duration\n3h–29h\n3h\n29h\nStops\n1 stop or fewer\nUS$176\nStopover cities\nAny\nHong Kong\nUS$185\nBusan\nUS$204\nSeoul\nUS$293\nMacau\nUS$176\nOkinawa\nUS$359\nDaegu\nUS$203\nManila\nUS$364\nCheongju\nUS$232\nTokyo\nUS$236\nJeju\nUS$269\nHanoi\nUS$342\nGuangzhou\nUS$377\nAirports\nAny\nDeparture Airport\nKIX\nKansai International Airport\nUS$176\nArrival Airport\nTSA\nTaipei Songshan Airport\nUS$293\nTPE\nTaiwan Taoyuan International Airport\nUS$176\nAircrafts\nAny\nLarge aircraft\nUS$176\nMidsize aircraft\nUS$176\nCabin\nEconomy\nEconomy\nEconomy/premium economy\nPremium economy\nBusiness/first\nBusiness\nFirst class\nDeparting for Taipei\n85 flights found\nRecommended\nUS$259\nNonstop first\nUS$226\nCheapest\nUS$176\nSort by\nCreate price alert\nIncluded\n- 10% CO2e\nSTARLUX Airlines\n14:00\nKIX T1\n3h 15m\nNonstop\n16:15\nTPE T1\nUS$259\nTotal US$517\nSelect\nCheapest nonstop\nCarry-on baggage included\n- 4% CO2e\nThai Lion Air\n13:30\nKIX T1\n3h 10m\nNonstop\n15:40\nTPE T1\nUS$226\nTotal US$451\nSelect\nCarry-on baggage included\n- 18% CO2e\nAirAsia X Berhad\n20:45\nKIX T1\n3h 20m\nNonstop\n23:05\nTPE T1\nUS$257\nTotal US$514\nSelect\nIncluded\n- 23% CO2e\nEVA Air\n10:55\nKIX T1\n3h 15m\nNonstop\n13:10\nTPE T2\nUS$327\nTotal US$653\nSelect\nCarry-on baggage included\n- 2% CO2e\nThai Vietjet Air\n12:00\nKIX T1\n3h 15m\nNonstop\n14:15\nTPE T1\nUS$240\nTotal US$480\nSelect\nCheapest\nIncluded\nAir Macau\n13:45\nKIX T1\n8h 45m\n2h 30m in Macau\n21:30\nTPE T1\nUS$176\nTotal US$351\nSelect\n<9 left\nIncluded\nPeach\n10:10\nKIX T2\n3h 35m\nNonstop\n12:45\nTPE T1\nUS$259\nTotal US$518\nSelect\nIncluded\nChina Airlines\n14:30\nKIX T1\n3h 15m\nNonstop\n16:45\nTPE T2\nUS$384\nTotal US$767\nSelect\nIncluded\n- 20% CO2e\nPeach\n15:25\nKIX T2\n3h 30m\nNonstop\n17:55\nTPE T1\nUS$414\nTotal US$828\nSelect\nCarry-on baggage included\n- 2% CO2e\nJetstar Japan\n14:50\nKIX T1\n3h 20m\nNonstop\n17:10\nTPE T1\nUS$388\nTotal US$776\nSelect\nCheapest\nIncluded\nAir Macau\noperated by EVA Air\n13:45\nKIX T1\n26h 10m\n20h 5m in Macau\n14:55\nTPE T2\n +1\nUS$176\nTotal US$351\nSelect\nCarry-on baggage included\n- 2% CO2e\nJetstar Japan\n23:10\nKIX T1\n3h 20m\nNonstop\n01:30\nTPE T1\n +1\nUS$463\nTotal US$925\nSelect\nIncluded\nHong Kong Airlines\n09:45\nKIX T1\n9h 35m\n3h 15m in Hong Kong\n18:20\nTPE T2\nUS$214\nTotal US$427\nSelect\nIncluded\nAir Macau\n13:45\nKIX T1\n24h 55m\n18h 50m in Macau\n13:40\nTPE T1\n +1\nUS$199\nTotal US$398\nSelect\nIncluded\nHong Kong Airlines\n09:45\nKIX T1\n11h 50m\n5h 30m in Hong Kong\n20:35\nTPE T2\nUS$219\nTotal US$438\nSelect\nIncluded\nAll Nippon Airways, China Airlines\n15:30\nKIX T1\n6h 30m\n2h 30m in Okinawa\n21:00\nTPE T2\nUS$359\nTotal US$718\nSelect\nIncluded\nHong Kong Airlines\n17:05\nKIX T1\n28h 35m\n21h 55m in Hong Kong\n20:40\nTPE T2\n +1\nUS$244\nTotal US$488\nSelect\nCarry-on baggage included\nT'Way Air, Tigerair Taiwan\n16:35\nKIX T1\n6h 55m\n2h 40m in Busan\n22:30\nTPE T1\nUS$217\nTotal US$434\nSelect\nShow more results\n*Last updated: 14:28:28\nFlights\n > \nTaipei Flights\n > \nto Taipei Flights\nBook flights from to Taipei on Trip.com\n\nFirst class | Business class | Economy class | Nonstop\n\nSearch for cheap flights from to Taipei on Trip.com. Trip.com provides the best real-time to Taipei airfares and flight deals available, featuring advanced flight planning tools like price alerts, deal finder fare calendars, and Flight + Hotel deals that make a Taipei vacation or Taipei tour more convenient and affordable.\n\nAward-winning\nSupport in approx. 30s\nRewards for booking"
    ]
  }
}