{
  "url": "https://www.trip.com/flights/osaka-to-taipei/tickets-kix-tpe?dcity=kix&acity=tpe&ddate=2026-02-28&flighttype=ow&class=y&quantity=2",
  "scraped_at": "2026-02-05T14:28:11.532099",
  "title": "Cheap Flights, Airline Tickets & Plane Tickets | Trip.com",
  "raw_text": "Go to main content\nTheme Detection\nHotels & Homes\nFlights\nTrains\nCar services\nApp\nUSD\nCustomer support\nFind bookings\nSign in / Register\nCheap Flights, Airline Tickets & Plane Tickets | Trip.com\nAllow notifications\nDon't miss out! Be the first to find out the latest travel info.\nAllow\nTaipei\nEdit\n2 adults\nEconomy\nFeb 28, 2026\nWed, Feb 25\nView\nThu, Feb 26\nView\nFri, Feb 27\nView\nSat, Feb 28\nUS$195\nSun, Mar 1\nView\nSat, Feb 21\nView\nSun, Feb 22\nView\nMon, Feb 23\nView\nTue, Feb 24\nView\nWed, Feb 25\nView\nThu, Feb 26\nView\nFri, Feb 27\nView\nSat, Feb 28\nUS$195\nSun, Mar 1\nView\nMon, Mar 2\nView\nTue, Mar 3\nView\nWed, Mar 4\nView\nThu, Mar 5\nView\nFri, Mar 6\nView\nSat, Mar 7\nView\nPrice graph\nRecommended\n Nonstop\n Checked baggage included\n Hide budget airlines\n Carry-on baggage included\n Hide codeshare flights\nCO2e Lower emission flights\nShow More\nAlliance\nStar Alliance\nUS$302\nSkyTeam\nUS$336\nOneworld\nUS$2,129\nAirlines\nAll flights with the same airline\nAll airlines\nHong Kong Airlines (8)\nUS$267\nPeach (4)\nUS$259\nHK Express (4)\nUS$366\nChina Airlines (3)\nUS$336\nAir Macau (3)\nUS$271\nShow More\nAlliance\nStar Alliance\nUS$302\nSkyTeam\nUS$336\nOneworld\nUS$2,129\nTimes\nDeparture time\n00:00–24:00\n00:00\n24:00\nArrival time\n00:00–24:00\n00:00\n24:00\nDuration\nAny\nStopover Duration\n1h 30m–20h\n1h 30m\n20h\nTotal Duration\n3h–26h 30m\n3h\n26h 30m\nStops\n1 stop or fewer\nUS$195\nStopover cities\nAny\nHong Kong\nUS$267\nShanghai\nUS$273\nMacau\nUS$271\nShenzhen\nUS$447\nAirports\nAny\nDeparture Airport\nKIX\nKansai International Airport\nUS$195\nArrival Airport\nTPE\nTaiwan Taoyuan International Airport\nUS$195\nAircrafts\nAny\nLarge aircraft\nUS$302\nMidsize aircraft\nUS$195\nCabin\nEconomy\nEconomy\nEconomy/premium economy\nPremium economy\nBusiness/first\nBusiness\nFirst class\nDeparting for Taipei\nRecommended\nUS$195\nNonstop first\nUS$195\nCheapest\nUS$195\nSort by\nCreate price alert\nCheapest\nCarry-on baggage included\nThai Vietjet Air\n12:00\nKIX T1\n3h 15m\nNonstop\n14:15\nTPE T1\nUS$195\nTotal US$390\nSelect\nCarry-on baggage included\n- 4% CO2e\nThai Lion Air\n13:30\nKIX T1\n3h 10m\nNonstop\n15:40\nTPE T1\nUS$226\nTotal US$451\nSelect\nCarry-on baggage included\nTigerair Taiwan\n11:30\nKIX T1\n3h 20m\nNonstop\n13:50\nTPE T1\nUS$231\nTotal US$462\nSelect\nIncluded\n- 20% CO2e\nPeach\n07:15\nKIX T2\n3h 30m\nNonstop\n09:45\nTPE T1\nUS$259\nTotal US$518\nSelect\nIncluded\nPeach\n10:10\nKIX T2\n3h 35m\nNonstop\n12:45\nTPE T1\nUS$282\nTotal US$564\nSelect\nIncluded\n- 23% CO2e\nEVA Air\n12:55\nKIX T1\n3h 10m\nNonstop\n15:05\nTPE T2\nUS$302\nTotal US$604\nSelect\n<9 left\nIncluded\nPeach\n22:00\nKIX T2\n3h 30m\nNonstop\n00:30\nTPE T1\n +1\nUS$302\nTotal US$603\nSelect\nCarry-on baggage included\nTigerair Taiwan\n19:55\nKIX T1\n3h 35m\nNonstop\n22:30\nTPE T1\nUS$303\nTotal US$606\nSelect\nCarry-on baggage included\nJetstar Japan\n23:10\nKIX T1\n3h 20m\nNonstop\n01:30\nTPE T1\n +1\nUS$322\nTotal US$643\nSelect\nCarry-on baggage included\n- 18% CO2e\nAirAsia X Berhad\n20:45\nKIX T1\n3h 20m\nNonstop\n23:05\nTPE T1\nUS$324\nTotal US$647\nSelect\nIncluded\n- 20% CO2e\nPeach\n15:25\nKIX T2\n3h 30m\nNonstop\n17:55\nTPE T1\nUS$325\nTotal US$649\nSelect\nIncluded\n- 6% CO2e\nChina Airlines\n19:00\nKIX T1\n3h 15m\nNonstop\n21:15\nTPE T2\nUS$336\nTotal US$671\nSelect\n<9 left\nIncluded\n- 23% CO2e\nEVA Air\n10:55\nKIX T1\n3h 15m\nNonstop\n13:10\nTPE T2\nUS$352\nTotal US$704\nSelect\n<9 left\nIncluded\nChina Airlines\n12:45\nKIX T1\n3h 15m\nNonstop\n15:00\nTPE T2\nUS$384\nTotal US$767\nSelect\nCarry-on baggage included\nJetstar Japan\n14:50\nKIX T1\n3h 20m\nNonstop\n17:10\nTPE T1\nUS$388\nTotal US$776\nSelect\nIncluded\nHong Kong Airlines\n20:05\nKIX T1\n20h 15m\n14h in Hong Kong\n15:20\nTPE T2\n +1\nUS$342\nTotal US$683\nSelect\nIncluded\nAir Macau\n13:45\nKIX T1\n24h 55m\n18h 50m in Macau\n13:40\nTPE T1\n +1\nUS$346\nTotal US$691\nSelect\nIncluded\nHong Kong Airlines\n17:05\nKIX T1\n18h 45m\n12h 10m in Hong Kong\n10:50\nTPE T2\n +1\nUS$355\nTotal US$709\nSelect\nIncluded\nHong Kong Airlines\n20:05\nKIX T1\n25h 30m\n19h 10m in Hong Kong\n20:35\nTPE T2\n +1\nUS$355\nTotal US$709\nSelect\nHong Kong: Free Layover Tour\nHK Express\n20:15\nKIX T1\n17h 55m\n11h 20m in Hong Kong\n13:10\nTPE T1\n +1\nUS$366\nTotal US$731\nSelect\nHong Kong: Free Layover Tour\nHK Express\n21:05\nKIX T1\n17h 5m\n10h 30m in Hong Kong\n13:10\nTPE T1\n +1\nUS$368\nTotal US$735\nSelect\nIncluded\nAir China\n13:30\nKIX T1\n21h 25m\n16h 45m in Shanghai\n09:55\nTPE T2\n +1\nUS$371\nTotal US$742\nSelect\n<9 left\nIncluded\nAir China\n16:30\nKIX T1\n18h 25m\n13h 40m in Shanghai\n09:55\nTPE T2\n +1\nUS$430\nTotal US$859\nSelect\nIncluded\nShenzhen Airlines\n15:05\nKIX T1\n21h 25m\n14h 35m in Shenzhen\n11:30\nTPE T2\n +1\nUS$447\nTotal US$893\nSelect\nNo more results for economy\nOther classes\nBusiness\nIncluded\nChina Airlines\n14:30\nKIX T1\n3h 15m\nNonstop\n16:45\nTPE T2\nUS$488\nTotal US$975\nBusiness\nSelect\nBusiness\nIncluded\nAll Nippon Airways\noperated by EVA Air\n10:55\nKIX T1\n3h 15m\nNonstop\n13:10\nTPE T2\nUS$1,700\nTotal US$3,399\nBusiness\nSelect\nBusiness\nIncluded\nAll Nippon Airways\noperated by EVA Air\n18:10\nKIX T1\n3h 15m\nNonstop\n20:25\nTPE T2\nUS$2,002\nTotal US$4,004\nBusiness\nSelect\nBusiness\nIncluded\nJapan Airlines\noperated by China Airlines\n12:45\nKIX T1\n3h 15m\nNonstop\n15:00\nTPE T2\nUS$2,129\nTotal US$4,258\nBusiness\nSelect\nBusiness\nIncluded\nJapan Airlines\noperated by China Airlines\n14:30\nKIX T1\n3h 15m\nNonstop\n16:45\nTPE T2\nUS$2,129\nTotal US$4,258\nBusiness\nSelect\nFlights\n > \nTaipei Flights\n > \nto Taipei Flights\nBook flights from to Taipei on Trip.com\n\nFirst class | Business class | Economy class | Nonstop\n\nSearch for cheap flights from to Taipei on Trip.com. Trip.com provides the best real-time to Taipei airfares and flight deals available, featuring advanced flight planning tools like price alerts, deal finder fare calendars, and Flight + Hotel deals that make a Taipei vacation or Taipei tour more convenient and affordable.\n\nAward-winning\nSupport in approx. 30s\nRewards for booking\nContact us\nCustomer support\nService guarantee\nMore service info\nAbout\nAbout Trip.com\nNews\nCareers\nTerms & Conditions\nPrivacy Statement\nAccessibility statement\nAbout Trip.com Group\nOther services\nInvestor relations\nTrip.com Rewards\nAffiliate program\nList your property\nAll hotels\nBecome a Supplier\nSecurity\nPayment methods\nOur partners\nContact Center\nof the year 2025\nCopyright © 2025 Trip.com Travel Singapore Pte. Ltd. All rights reserved\nSite Operator: Trip.com Travel Singapore Pte. Ltd.",
  "extracted": {
    "flight": {},
    "hotel": {},
    "price": {},
    "dates": {},
    "inclusions": [],
    "date_pricing": {}
  },
  "extracted_elements": {
    "flight_element": [
      "Thai Vietjet Air\n12:00\nKIX T1\n3h 15m\nNonstop\n14:15\nTPE T1",
      "Thai Lion Air\n13:30\nKIX T1\n3h 10m\nNonstop\n15:40\nTPE T1",
      "Tigerair Taiwan\n11:30\nKIX T1\n3h 20m\nNonstop\n13:50\nTPE T1",
      "Peach\n07:15\nKIX T2\n3h 30m\nNonstop\n09:45\nTPE T1",
      "Peach\n10:10\nKIX T2\n3h 35m\nNonstop\n12:45\nTPE T1"
    ],
    "price_class": [
      "Wed, Feb 25\nView\nThu, Feb 26\nView\nFri, Feb 27\nView\nSat, Feb 28\nUS$195\nSun, Mar 1\nView",
      "Wed, Feb 25\nView\nThu, Feb 26\nView\nFri, Feb 27\nView\nSat, Feb 28\nUS$195\nSun, Mar 1\nView",
      "Wed, Feb 25\nView\nThu, Feb 26\nView\nFri, Feb 27\nView\nSat, Feb 28\nUS$195\nSun, Mar 1\nView",
      "Wed, Feb 25\nView\nThu, Feb 26\nView\nFri, Feb 27\nView\nSat, Feb 28\nUS$195\nSun, Mar 1\nView",
      "Wed, Feb 25\nView\nThu, Feb 26\nView\nFri, Feb 27\nView\nSat, Feb 28\nUS$195\nSun, Mar 1\nView"
    ],
    "flight_class": [
      "Flights",
      "Taipei\nEdit\n2 adults\nEconomy\nFeb 28, 2026\nWed, Feb 25\nView\nThu, Feb 26\nView\nFri, Feb 27\nView\nSat, Feb 28\nUS$195\nSun, Mar 1\nView\nSat, Feb 21\nView\nSun, Feb 22\nView\nMon, Feb 23\nView\nTue, Feb 24\nView\nWed, Feb 25\nView\nThu, Feb 26\nView\nFri, Feb 27\nView\nSat, Feb 28\nUS$195\nSun, Mar 1\nView\nMon, Mar 2\nView\nTue, Mar 3\nView\nWed, Mar 4\nView\nThu, Mar 5\nView\nFri, Mar 6\nView\nSat, Mar 7\nView\nPrice graph\nRecommended\n Nonstop\n Checked baggage included\n Hide budget airlines\n Carry-on baggage included\n Hide codeshare flights\nCO2e Lower emission flights\nShow More\nAlliance\nStar Alliance\nUS$302\nSkyTeam\nUS$336\nOneworld\nUS$2,129\nAirlines\nAll flights with the same airline\nAll airlines\nHong Kong Airlines (8)\nUS$267\nPeach (4)\nUS$259\nHK Express (4)\nUS$366\nChina Airlines (3)\nUS$336\nAir Macau (3)\nUS$271\nShow More\nAlliance\nStar Alliance\nUS$302\nSkyTeam\nUS$336\nOneworld\nUS$2,129\nTimes\nDeparture time\n00:00–24:00\n00:00\n24:00\nArrival time\n00:00–24:00\n00:00\n24:00\nDuration\nAny\nStopover Duration\n1h 30m–20h\n1h 30m\n20h\nTotal Duration\n3h–26h 30m\n3h\n26h 30m\nStops\n1 stop or fewer\nUS$195\nStopover cities\nAny\nHong Kong\nUS$267\nShanghai\nUS$273\nMacau\nUS$271\nShenzhen\nUS$447\nAirports\nAny\nDeparture Airport\nKIX\nKansai International Airport\nUS$195\nArrival Airport\nTPE\nTaiwan Taoyuan International Airport\nUS$195\nAircrafts\nAny\nLarge aircraft\nUS$302\nMidsize aircraft\nUS$195\nCabin\nEconomy\nEconomy\nEconomy/premium economy\nPremium economy\nBusiness/first\nBusiness\nFirst class\nDeparting for Taipei\nRecommended\nUS$195\nNonstop first\nUS$195\nCheapest\nUS$195\nSort by\nCreate price alert\nCheapest\nCarry-on baggage included\nThai Vietjet Air\n12:00\nKIX T1\n3h 15m\nNonstop\n14:15\nTPE T1\nUS$195\nTotal US$390\nSelect\nCarry-on baggage included\n- 4% CO2e\nThai Lion Air\n13:30\nKIX T1\n3h 10m\nNonstop\n15:40\nTPE T1\nUS$226\nTotal US$451\nSelect\nCarry-on baggage included\nTigerair Taiwan\n11:30\nKIX T1\n3h 20m\nNonstop\n13:50\nTPE T1\nUS$231\nTotal US$462\nSelect\nIncluded\n- 20% CO2e\nPeach\n07:15\nKIX T2\n3h 30m\nNonstop\n09:45\nTPE T1\nUS$259\nTotal US$518\nSelect\nIncluded\nPeach\n10:10\nKIX T2\n3h 35m\nNonstop\n12:45\nTPE T1\nUS$282\nTotal US$564\nSelect\nIncluded\n- 23% CO2e\nEVA Air\n12:55\nKIX T1\n3h 10m\nNonstop\n15:05\nTPE T2\nUS$302\nTotal US$604\nSelect\n<9 left\nIncluded\nPeach\n22:00\nKIX T2\n3h 30m\nNonstop\n00:30\nTPE T1\n +1\nUS$302\nTotal US$603\nSelect\nCarry-on baggage included\nTigerair Taiwan\n19:55\nKIX T1\n3h 35m\nNonstop\n22:30\nTPE T1\nUS$303\nTotal US$606\nSelect\nCarry-on baggage included\nJetstar Japan\n23:10\nKIX T1\n3h 20m\nNonstop\n01:30\nTPE T1\n +1\nUS$322\nTotal US$643\nSelect\nCarry-on baggage included\n- 18% CO2e\nAirAsia X Berhad\n20:45\nKIX T1\n3h 20m\nNonstop\n23:05\nTPE T1\nUS$324\nTotal US$647\nSelect\nIncluded\n- 20% CO2e\nPeach\n15:25\nKIX T2\n3h 30m\nNonstop\n17:55\nTPE T1\nUS$325\nTotal US$649\nSelect\nIncluded\n- 6% CO2e\nChina Airlines\n19:00\nKIX T1\n3h 15m\nNonstop\n21:15\nTPE T2\nUS$336\nTotal US$671\nSelect\n<9 left\nIncluded\n- 23% CO2e\nEVA Air\n10:55\nKIX T1\n3h 15m\nNonstop\n13:10\nTPE T2\nUS$352\nTotal US$704\nSelect\n<9 left\nIncluded\nChina Airlines\n12:45\nKIX T1\n3h 15m\nNonstop\n15:00\nTPE T2\nUS$384\nTotal US$767\nSelect\nCarry-on baggage included\nJetstar Japan\n14:50\nKIX T1\n3h 20m\nNonstop\n17:10\nTPE T1\nUS$388\nTotal US$776\nSelect\nIncluded\nHong Kong Airlines\n20:05\nKIX T1\n20h 15m\n14h in Hong Kong\n15:20\nTPE T2\n +1\nUS$342\nTotal US$683\nSelect\nIncluded\nAir Macau\n13:45\nKIX T1\n24h 55m\n18h 50m in Macau\n13:40\nTPE T1\n +1\nUS$346\nTotal US$691\nSelect\nIncluded\nHong Kong Airlines\n17:05\nKIX T1\n18h 45m\n12h 10m in Hong Kong\n10:50\nTPE T2\n +1\nUS$355\nTotal US$709\nSelect\nIncluded\nHong Kong Airlines\n20:05\nKIX T1\n25h 30m\n19h 10m in Hong Kong\n20:35\nTPE T2\n +1\nUS$355\nTotal US$709\nSelect\nHong Kong: Free Layover Tour\nHK Express\n20:15\nKIX T1\n17h 55m\n11h 20m in Hong Kong\n13:10\nTPE T1\n +1\nUS$366\nTotal US$731\nSelect\nHong Kong: Free Layover Tour\nHK Express\n21:05\nKIX T1\n17h 5m\n10h 30m in Hong Kong\n13:10\nTPE T1\n +1\nUS$368\nTotal US$735\nSelect\nIncluded\nAir China\n13:30\nKIX T1\n21h 25m\n16h 45m in Shanghai\n09:55\nTPE T2\n +1\nUS$371\nTotal US$742\nSelect\n<9 left\nIncluded\nAir China\n16:30\nKIX T1\n18h 25m\n13h 40m in Shanghai\n09:55\nTPE T2\n +1\nUS$430\nTotal US$859\nSelect\nIncluded\nShenzhen Airlines\n15:05\nKIX T1\n21h 25m\n14h 35m in Shenzhen\n11:30\nTPE T2\n +1\nUS$447\nTotal US$893\nSelect\nNo more results for economy\nOther classes\nBusiness\nIncluded\nChina Airlines\n14:30\nKIX T1\n3h 15m\nNonstop\n16:45\nTPE T2\nUS$488\nTotal US$975\nBusiness\nSelect\nBusiness\nIncluded\nAll Nippon Airways\noperated by EVA Air\n10:55\nKIX T1\n3h 15m\nNonstop\n13:10\nTPE T2\nUS$1,700\nTotal US$3,399\nBusiness\nSelect\nBusiness\nIncluded\nAll Nippon Airways\noperated by EVA Air\n18:10\nKIX T1\n3h 15m\nNonstop\n20:25\nTPE T2\nUS$2,002\nTotal US$4,004\nBusiness\nSelect\nBusiness\nIncluded\nJapan Airlines\noperated by China Airlines\n12:45\nKIX T1\n3h 15m\nNonstop\n15:00\nTPE T2\nUS$2,129\nTotal US$4,258\nBusiness\nSelect\nBusiness\nIncluded\nJapan Airlines\noperated by China Airlines\n14:30\nKIX T1\n3h 15m\nNonstop\n16:45\nTPE T2\nUS$2,129\nTotal US$4,258\nBusiness\nSelect\nFlights\n > \nTaipei Flights\n > \nto Taipei Flights\nBook flights from to Taipei on Trip.com\n\nFirst class | Business class | Economy class | Nonstop\n\nSearch for cheap flights from to Taipei on Trip.com. Trip.com provides the best real-time to Taipei airfares and flight deals available, featuring advanced flight planning tools like price alerts, deal finder fare calendars, and Flight + Hotel deals that make a Taipei vacation or Taipei tour more convenient and affordable.\n\nAward-winning\nSupport in approx. 30s\nRewards for booking",
      "Taipei\nEdit\n2 adults\nEconomy\nFeb 28, 2026\nWed, Feb 25\nView\nThu, Feb 26\nView\nFri, Feb 27\nView\nSat, Feb 28\nUS$195\nSun, Mar 1\nView",
      "DepartSat, Feb 28"
    ],
    "hotel_class": [
      "Hotels & Homes"
    ],
    "main": [
      "Cheap Flights, Airline Tickets & Plane Tickets | Trip.com\nAllow notifications\nDon't miss out! Be the first to find out the latest travel info.\nAllow\nTaipei\nEdit\n2 adults\nEconomy\nFeb 28, 2026\nWed, Feb 25\nView\nThu, Feb 26\nView\nFri, Feb 27\nView\nSat, Feb 28\nUS$195\nSun, Mar 1\nView\nSat, Feb 21\nView\nSun, Feb 22\nView\nMon, Feb 23\nView\nTue, Feb 24\nView\nWed, Feb 25\nView\nThu, Feb 26\nView\nFri, Feb 27\nView\nSat, Feb 28\nUS$195\nSun, Mar 1\nView\nMon, Mar 2\nView\nTue, Mar 3\nView\nWed, Mar 4\nView\nThu, Mar 5\nView\nFri, Mar 6\nView\nSat, Mar 7\nView\nPrice graph\nRecommended\n Nonstop\n Checked baggage included\n Hide budget airlines\n Carry-on baggage included\n Hide codeshare flights\nCO2e Lower emission flights\nShow More\nAlliance\nStar Alliance\nUS$302\nSkyTeam\nUS$336\nOneworld\nUS$2,129\nAirlines\nAll flights with the same airline\nAll airlines\nHong Kong Airlines (8)\nUS$267\nPeach (4)\nUS$259\nHK Express (4)\nUS$366\nChina Airlines (3)\nUS$336\nAir Macau (3)\nUS$271\nShow More\nAlliance\nStar Alliance\nUS$302\nSkyTeam\nUS$336\nOneworld\nUS$2,129\nTimes\nDeparture time\n00:00–24:00\n00:00\n24:00\nArrival time\n00:00–24:00\n00:00\n24:00\nDuration\nAny\nStopover Duration\n1h 30m–20h\n1h 30m\n20h\nTotal Duration\n3h–26h 30m\n3h\n26h 30m\nStops\n1 stop or fewer\nUS$195\nStopover cities\nAny\nHong Kong\nUS$267\nShanghai\nUS$273\nMacau\nUS$271\nShenzhen\nUS$447\nAirports\nAny\nDeparture Airport\nKIX\nKansai International Airport\nUS$195\nArrival Airport\nTPE\nTaiwan Taoyuan International Airport\nUS$195\nAircrafts\nAny\nLarge aircraft\nUS$302\nMidsize aircraft\nUS$195\nCabin\nEconomy\nEconomy\nEconomy/premium economy\nPremium economy\nBusiness/first\nBusiness\nFirst class\nDeparting for Taipei\nRecommended\nUS$195\nNonstop first\nUS$195\nCheapest\nUS$195\nSort by\nCreate price alert\nCheapest\nCarry-on baggage included\nThai Vietjet Air\n12:00\nKIX T1\n3h 15m\nNonstop\n14:15\nTPE T1\nUS$195\nTotal US$390\nSelect\nCarry-on baggage included\n- 4% CO2e\nThai Lion Air\n13:30\nKIX T1\n3h 10m\nNonstop\n15:40\nTPE T1\nUS$226\nTotal US$451\nSelect\nCarry-on baggage included\nTigerair Taiwan\n11:30\nKIX T1\n3h 20m\nNonstop\n13:50\nTPE T1\nUS$231\nTotal US$462\nSelect\nIncluded\n- 20% CO2e\nPeach\n07:15\nKIX T2\n3h 30m\nNonstop\n09:45\nTPE T1\nUS$259\nTotal US$518\nSelect\nIncluded\nPeach\n10:10\nKIX T2\n3h 35m\nNonstop\n12:45\nTPE T1\nUS$282\nTotal US$564\nSelect\nIncluded\n- 23% CO2e\nEVA Air\n12:55\nKIX T1\n3h 10m\nNonstop\n15:05\nTPE T2\nUS$302\nTotal US$604\nSelect\n<9 left\nIncluded\nPeach\n22:00\nKIX T2\n3h 30m\nNonstop\n00:30\nTPE T1\n +1\nUS$302\nTotal US$603\nSelect\nCarry-on baggage included\nTigerair Taiwan\n19:55\nKIX T1\n3h 35m\nNonstop\n22:30\nTPE T1\nUS$303\nTotal US$606\nSelect\nCarry-on baggage included\nJetstar Japan\n23:10\nKIX T1\n3h 20m\nNonstop\n01:30\nTPE T1\n +1\nUS$322\nTotal US$643\nSelect\nCarry-on baggage included\n- 18% CO2e\nAirAsia X Berhad\n20:45\nKIX T1\n3h 20m\nNonstop\n23:05\nTPE T1\nUS$324\nTotal US$647\nSelect\nIncluded\n- 20% CO2e\nPeach\n15:25\nKIX T2\n3h 30m\nNonstop\n17:55\nTPE T1\nUS$325\nTotal US$649\nSelect\nIncluded\n- 6% CO2e\nChina Airlines\n19:00\nKIX T1\n3h 15m\nNonstop\n21:15\nTPE T2\nUS$336\nTotal US$671\nSelect\n<9 left\nIncluded\n- 23% CO2e\nEVA Air\n10:55\nKIX T1\n3h 15m\nNonstop\n13:10\nTPE T2\nUS$352\nTotal US$704\nSelect\n<9 left\nIncluded\nChina Airlines\n12:45\nKIX T1\n3h 15m\nNonstop\n15:00\nTPE T2\nUS$384\nTotal US$767\nSelect\nCarry-on baggage included\nJetstar Japan\n14:50\nKIX T1\n3h 20m\nNonstop\n17:10\nTPE T1\nUS$388\nTotal US$776\nSelect\nIncluded\nHong Kong Airlines\n20:05\nKIX T1\n20h 15m\n14h in Hong Kong\n15:20\nTPE T2\n +1\nUS$342\nTotal US$683\nSelect\nIncluded\nAir Macau\n13:45\nKIX T1\n24h 55m\n18h 50m in Macau\n13:40\nTPE T1\n +1\nUS$346\nTotal US$691\nSelect\nIncluded\nHong Kong Airlines\n17:05\nKIX T1\n18h 45m\n12h 10m in Hong Kong\n10:50\nTPE T2\n +1\nUS$355\nTotal US$709\nSelect\nIncluded\nHong Kong Airlines\n20:05\nKIX T1\n25h 30m\n19h 10m in Hong Kong\n20:35\nTPE T2\n +1\nUS$355\nTotal US$709\nSelect\nHong Kong: Free Layover Tour\nHK Express\n20:15\nKIX T1\n17h 55m\n11h 20m in Hong Kong\n13:10\nTPE T1\n +1\nUS$366\nTotal US$731\nSelect\nHong Kong: Free Layover Tour\nHK Express\n21:05\nKIX T1\n17h 5m\n10h 30m in Hong Kong\n13:10\nTPE T1\n +1\nUS$368\nTotal US$735\nSelect\nIncluded\nAir China\n13:30\nKIX T1\n21h 25m\n16h 45m in Shanghai\n09:55\nTPE T2\n +1\nUS$371\nTotal US$742\nSelect\n<9 left\nIncluded\nAir China\n16:30\nKIX T1\n18h 25m\n13h 40m in Shanghai\n09:55\nTPE T2\n +1\nUS$430\nTotal US$859\nSelect\nIncluded\nShenzhen Airlines\n15:05\nKIX T1\n21h 25m\n14h 35m in Shenzhen\n11:30\nTPE T2\n +1\nUS$447\nTotal US$893\nSelect\nNo more results for economy\nOther classes\nBusiness\nIncluded\nChina Airlines\n14:30\nKIX T1\n3h 15m\nNonstop\n16:45\nTPE T2\nUS$488\nTotal US$975\nBusiness\nSelect\nBusiness\nIncluded\nAll Nippon Airways\noperated by EVA Air\n10:55\nKIX T1\n3h 15m\nNonstop\n13:10\nTPE T2\nUS$1,700\nTotal US$3,399\nBusiness\nSelect\nBusiness\nIncluded\nAll Nippon Airways\noperated by EVA Air\n18:10\nKIX T1\n3h 15m\nNonstop\n20:25\nTPE T2\nUS$2,002\nTotal US$4,004\nBusiness\nSelect\nBusiness\nIncluded\nJapan Airlines\noperated by China Airlines\n12:45\nKIX T1\n3h 15m\nNonstop\n15:00\nTPE T2\nUS$2,129\nTotal US$4,258\nBusiness\nSelect\nBusiness\nIncluded\nJapan Airlines\noperated by China Airlines\n14:30\nKIX T1\n3h 15m\nNonstop\n16:45\nTPE T2\nUS$2,129\nTotal US$4,258\nBusiness\nSelect\nFlights\n > \nTaipei Flights\n > \nto Taipei Flights\nBook flights from to Taipei on Trip.com\n\nFirst class | Business class | Economy class | Nonstop\n\nSearch for cheap flights from to Taipei on Trip.com. Trip.com provides the best real-time to Taipei airfares and flight deals available, featuring advanced flight planning tools like price alerts, deal finder fare calendars, and Flight + Hotel deals that make a Taipei vacation or Taipei tour more convenient and affordable.\n\nAward-winning\nSupport in approx. 30s\nRewards for booking"
    ]
  }
}