{
  "url": "https://www.trip.com/flights/osaka-to-taipei/tickets-kix-tpe?dcity=kix&acity=tpe&ddate=2026-03-01&flighttype=ow&class=y&quantity=2",
  "scraped_at": "2026-02-05T10:36:51.030985",
  "title": "Cheap Flights, Airline Tickets & Plane Tickets | Trip.com",
  "raw_text": "Go to main content\nTheme Detection\nHotels & Homes\nFlights\nTrains\nCar services\nApp\nUSD\nCustomer support\nFind bookings\nSign in / Register\nCheap Flights, Airline Tickets & Plane Tickets | Trip.com\nAllow notifications\nDon't miss out! Be the first to find out the latest travel info.\nAllow\nTaipei\nEdit\n2 adults\nEconomy\nMar 1, 2026\nThu, Feb 26\nView\nFri, Feb 27\nView\nSat, Feb 28\nView\nSun, Mar 1\nUS$259\nMon, Mar 2\nView\nSun, Feb 22\nView\nMon, Feb 23\nView\nTue, Feb 24\nView\nWed, Feb 25\nView\nThu, Feb 26\nView\nFri, Feb 27\nView\nSat, Feb 28\nView\nSun, Mar 1\nUS$259\nMon, Mar 2\nView\nTue, Mar 3\nView\nWed, Mar 4\nView\nThu, Mar 5\nView\nFri, Mar 6\nView\nSat, Mar 7\nView\nSun, Mar 8\nView\nPrice graph\nRecommended\n Nonstop\n Checked baggage included\n Hide budget airlines\n Student tickets\n Carry-on baggage included\n Hide codeshare flights\nCO2e Lower emission flights\nShow More\nAlliance\nSkyTeam\nUS$270\nStar Alliance\nUS$353\nOneworld\nUS$1,538\nAirlines\nAll flights with the same airline\nAll airlines\nHK Express (18)\nUS$286\nHong Kong Airlines (13)\nUS$278\nPeach (4)\nUS$259\nSpring Airlines (3)\nUS$273\nChina Airlines (2)\nUS$460\nShow More\nAlliance\nSkyTeam\nUS$270\nStar Alliance\nUS$353\nOneworld\nUS$1,538\nTimes\nDeparture time\n00:00–24:00\n00:00\n24:00\nArrival time\n00:00–24:00\n00:00\n24:00\nDuration\nAny\nStopover Duration\n3h–24h\n3h\n24h\nTotal Duration\n3h–30h 30m\n3h\n30h 30m\nStops\n1 stop or fewer\nUS$259\nStopover cities\nAny\nHong Kong\nUS$278\nShanghai\nUS$273\nXiamen\nUS$270\nShenzhen\nUS$353\nHangzhou\nUS$372\nBusan\nUS$418\nManila\nUS$438\nDaegu\nUS$445\nGuangzhou\nUS$474\nAirports\nAny\nDeparture Airport\nKIX\nKansai International Airport\nUS$259\nArrival Airport\nTPE\nTaiwan Taoyuan International Airport\nUS$259\nAircrafts\nAny\nLarge aircraft\nUS$335\nMidsize aircraft\nUS$259\nCabin\nEconomy\nEconomy\nEconomy/premium economy\nPremium economy\nBusiness/first\nBusiness\nFirst class\nDeparting for Taipei\n62 flights found\nRecommended\nUS$259\nNonstop first\nUS$259\nCheapest\nUS$259\nSort by\nCreate price alert\nCheapest\nIncluded\n- 20% CO2e\nPeach\n07:15\nKIX T2\n3h 30m\nNonstop\n09:45\nTPE T1\nUS$259\nTotal US$518\nSelect\nIncluded\n- 20% CO2e\nPeach\n15:25\nKIX T2\n3h 30m\nNonstop\n17:55\nTPE T1\nUS$375\nTotal US$749\nSelect\nIncluded\n- 23% CO2e\nEVA Air\n12:55\nKIX T1\n3h 10m\nNonstop\n15:05\nTPE T2\nUS$428\nTotal US$856\nSelect\nCarry-on baggage included\n- 2% CO2e\nThai Vietjet Air\n12:00\nKIX T1\n3h 15m\nNonstop\n14:15\nTPE T1\nUS$320\nTotal US$640\nSelect\nSign in & save for future trips\nEarn at least 52 Trip Coins worth US$0.52 for this booking, which you can use to save on future trips!\nSign in/register\nIncluded\n- 6% CO2e\nChina Airlines\n19:00\nKIX T1\n3h 15m\nNonstop\n21:15\nTPE T2\nUS$469\nTotal US$938\nSelect\nIncluded\n- 3% CO2e\nPeach\n22:00\nKIX T2\n3h 30m\nNonstop\n00:30\nTPE T1\n +1\nUS$348\nTotal US$696\nSelect\nIncluded\nPeach\n10:10\nKIX T2\n3h 35m\nNonstop\n12:45\nTPE T1\nUS$325\nTotal US$650\nSelect\nIncluded\n- 23% CO2e\nEVA Air\n10:55\nKIX T1\n3h 15m\nNonstop\n13:10\nTPE T2\nUS$428\nTotal US$856\nSelect\nPrice alerts\nWant a better deal? We'll notify you when the price drops below US$250.\nRecommended: US$250\nHigh chances of success\nOK\nCarry-on baggage included\nTigerair Taiwan\n11:30\nKIX T1\n3h 20m\nNonstop\n13:50\nTPE T1\nUS$335\nTotal US$669\nSelect\nIncluded\nChina Airlines\n12:45\nKIX T1\n3h 15m\nNonstop\n15:00\nTPE T2\nUS$460\nTotal US$919\nSelect\nCarry-on baggage included\n- 4% CO2e\nThai Lion Air\n13:30\nKIX T1\n3h 10m\nNonstop\n15:40\nTPE T1\nUS$347\nTotal US$693\nSelect\nCarry-on baggage included\n- 18% CO2e\nAirAsia X Berhad\n20:45\nKIX T1\n3h 20m\nNonstop\n23:05\nTPE T1\nUS$396\nTotal US$792\nSelect\nIncluded\n- 10% CO2e\nSTARLUX Airlines\n14:00\nKIX T1\n3h 15m\nNonstop\n16:15\nTPE T1\nUS$603\nTotal US$1,205\nSelect\nCarry-on baggage included\n- 2% CO2e\nTigerair Taiwan\n18:55\nKIX T1\n3h 20m\nNonstop\n21:15\nTPE T1\nUS$464\nTotal US$927\nSelect\nCarry-on baggage included\n- 2% CO2e\nJetstar Japan\n14:50\nKIX T1\n3h 20m\nNonstop\n17:10\nTPE T1\nUS$627\nTotal US$1,253\nSelect\nIncluded\nJapan Airlines\noperated by China Airlines\n19:00\nKIX T1\n3h 15m\nNonstop\n21:15\nTPE T2\nUS$1,538\nTotal US$3,075\nSelect\nIncluded\nXiamen Airlines\n18:55\nKIX T1\n16h 5m\n10h 15m in Xiamen\n10:00\nTPE T2\n +1\nUS$270\nTotal US$539\nSelect\nIncluded\nHong Kong Airlines\n20:05\nKIX T1\n15h 45m\n9h 25m in Hong Kong\n10:50\nTPE T2\n +1\nUS$298\nTotal US$596\nSelect\nIncluded\nHong Kong Airlines\n15:05\nKIX T1\n28h 15m\n21h 55m in Hong Kong\n18:20\nTPE T2\n +1\nUS$294\nTotal US$588\nSelect\n<9 left\nIncluded\nHong Kong Airlines\n15:05\nKIX T1\n25h 35m\n19h in Hong Kong\n15:40\nTPE T2\n +1\nUS$294\nTotal US$588\nSelect\n<9 left\nIncluded\nJuneyao Airlines\n22:10\nKIX T1\n14h 25m\n9h 50m in Shanghai\n11:35\nTPE T1\n +1\nUS$335\nTotal US$670\nSelect\nIncluded\nHong Kong Airlines\n15:05\nKIX T1\n20h 45m\n14h 25m in Hong Kong\n10:50\nTPE T2\n +1\nUS$294\nTotal US$588\nSelect\n<9 left\nIncluded\nHong Kong Airlines\n09:35\nKIX T1\n12h\n5h 35m in Hong Kong\n20:35\nTPE T2\nUS$343\nTotal US$686\nSelect\nIncluded\nHong Kong Airlines\n20:05\nKIX T1\n20h 35m\n14h in Hong Kong\n15:40\nTPE T2\n +1\nUS$299\nTotal US$598\nSelect\nIncluded\nShenzhen Airlines\n15:05\nKIX T1\n26h 10m\n19h 20m in Shenzhen\n16:15\nTPE T2\n +1\nUS$353\nTotal US$705\nUS$353\nSelect\nCarry-on baggage included\nSpring Airlines\n15:00\nKIX T2\n20h 30m\n15h 25m in Shanghai\n10:30\nTPE T1\n +1\nUS$273\nTotal US$545\nSelect\nIncluded\nAir China\n12:15\nKIX T1\n24h 10m\n19h 25m in Hangzhou\n11:25\nTPE T2\n +1\nUS$372\nTotal US$743\nSelect\nIncluded\nHong Kong Airlines\n20:05\nKIX T1\n25h 30m\n19h 10m in Hong Kong\n20:35\nTPE T2\n +1\nUS$310\nTotal US$620\nSelect\nCarry-on baggage included\nSpring Airlines\n13:45\nKIX T2\n21h 45m\n16h 50m in Shanghai\n10:30\nTPE T1\n +1\nUS$273\nTotal US$545\nSelect\nHong Kong: Free Layover Tour\nHK Express\n21:05\nKIX T1\n17h 5m\n10h 30m in Hong Kong\n13:10\nTPE T1\n +1\nUS$286\nTotal US$572\nSelect\nIncluded\nGreater Bay Airlines\n14:00\nKIX T1\n12h 10m\n5h 10m in Hong Kong\n01:10\nTPE T1\n +1\nUS$401\nTotal US$801\nSelect\nIncluded\nHong Kong Airlines\n17:05\nKIX T1\n28h 30m\n21h 55m in Hong Kong\n20:35\nTPE T2\n +1\nUS$357\nTotal US$713\nSelect\nIncluded\nJuneyao Airlines\n12:15\nKIX T1\n24h 20m\n19h 30m in Shanghai\n11:35\nTPE T1\n +1\nUS$401\nTotal US$802\nSelect\nIncluded\nHong Kong Airlines\n17:05\nKIX T1\n18h 45m\n12h 10m in Hong Kong\n10:50\nTPE T2\n +1\nUS$343\nTotal US$686\nSelect\nHK Express\n15:15\nKIX T1\n30h 10m\n23h 50m in Hong Kong\n20:25\nTPE T1\n +1\nUS$310\nTotal US$620\nSelect\n<9 left\nIncluded\nT'Way Air\n16:55\nKIX T1\n8h 35m\n4h 10m in Daegu\n00:30\nTPE T1\n +1\nUS$445\nTotal US$890\nSelect\nIncluded\nChina Southern Airlines\n16:00\nKIX T1\n23h 15m\n16h 15m in Guangzhou\n14:15\nTPE T2\n +1\nUS$474\nTotal US$947\nUS$473\nSelect\nIncluded\nHong Kong Airlines\n17:05\nKIX T1\n23h 35m\n16h 45m in Hong Kong\n15:40\nTPE T2\n +1\nUS$357\nTotal US$713\nSelect\nHK Express\n15:15\nKIX T1\n23h 40m\n17h 15m in Hong Kong\n13:55\nTPE T1\n +1\nUS$286\nTotal US$572\nSelect\nHK Express\n15:15\nKIX T1\n22h 55m\n16h 25m in Hong Kong\n13:10\nTPE T1\n +1\nUS$286\nTotal US$572\nSelect\nIncluded\nJeju Air\n10:40\nKIX T2\n14h 10m\n9h 50m in Busan\n23:50\nTPE T1\nUS$418\nTotal US$836\nSelect\nHong Kong: Free Layover Tour\nHK Express\n20:15\nKIX T1\n21h 30m\n15h in Hong Kong\n16:45\nTPE T1\n +1\nUS$323\nTotal US$646\nSelect\nHK Express\n17:10\nKIX T1\n21h 45m\n15h 15m in Hong Kong\n13:55\nTPE T1\n +1\nUS$334\nTotal US$668\nSelect\nNo more results for economy\nOther classes\nBusiness\nIncluded\nSTARLUX Airlines\n12:20\nKIX T1\n3h 15m\nNonstop\n14:35\nTPE T1\nUS$542\nTotal US$1,083\nBusiness\nSelect\n*Last updated: 10:36:39\nFlights\n > \nTaipei Flights\n > \nto Taipei Flights\nBook flights from to Taipei on Trip.com\n\nFirst class | Business class | Economy class | Nonstop\n\nSearch for cheap flights from to Taipei on Trip.com. Trip.com provides the best real-time to Taipei airfares and flight deals available, featuring advanced flight planning tools like price alerts, deal finder fare calendars, and Flight + Hotel deals that make a Taipei vacation or Taipei tour more convenient and affordable.\n\nAward-winning\nSupport in approx. 30s\nRewards for booking\nContact us\nCustomer support\nService guarantee\nMore service info\nAbout\nAbout Trip.com\nNews\nCareers\nTerms & Conditions\nPrivacy Statement\nAccessibility statement\nAbout Trip.com Group\nOther services\nInvestor relations\nTrip.com Rewards\nAffiliate program\nList your property\nAll hotels\nBecome a Supplier\nSecurity\nPayment methods\nOur partners\nContact Center\nof the year 2025\nCopyright © 2025 Trip.com Travel Singapore Pte. Ltd. All rights reserved\nSite Operator: Trip.com Travel Singapore Pte. Ltd.",
  "extracted": {
    "flight": {},
    "hotel": {},
    "price": {},
    "dates": {},
    "inclusions": [],
    "date_pricing": {}
  },
  "extracted_elements": {
    "flight_element": [
      "Peach\n07:15\nKIX T2\n3h 30m\nNonstop\n09:45\nTPE T1",
      "Peach\n15:25\nKIX T2\n3h 30m\nNonstop\n17:55\nTPE T1",
      "EVA Air\n12:55\nKIX T1\n3h 10m\nNonstop\n15:05\nTPE T2",
      "Thai Vietjet Air\n12:00\nKIX T1\n3h 15m\nNonstop\n14:15\nTPE T1",
      "China Airlines\n19:00\nKIX T1\n3h 15m\nNonstop\n21:15\nTPE T2"
    ],
    "price_class": [
      "Thu, Feb 26\nView\nFri, Feb 27\nView\nSat, Feb 28\nView\nSun, Mar 1\nUS$259\nMon, Mar 2\nView",
      "Thu, Feb 26\nView\nFri, Feb 27\nView\nSat, Feb 28\nView\nSun, Mar 1\nUS$259\nMon, Mar 2\nView",
      "Thu, Feb 26\nView\nFri, Feb 27\nView\nSat, Feb 28\nView\nSun, Mar 1\nUS$259\nMon, Mar 2\nView",
      "Thu, Feb 26\nView\nFri, Feb 27\nView\nSat, Feb 28\nView\nSun, Mar 1\nUS$259\nMon, Mar 2\nView",
      "Thu, Feb 26\nView\nFri, Feb 27\nView\nSat, Feb 28\nView\nSun, Mar 1\nUS$259\nMon, Mar 2\nView"
    ],
    "flight_class": [
      "Flights",
      "Taipei\nEdit\n2 adults\nEconomy\nMar 1, 2026\nThu, Feb 26\nView\nFri, Feb 27\nView\nSat, Feb 28\nView\nSun, Mar 1\nUS$259\nMon, Mar 2\nView\nSun, Feb 22\nView\nMon, Feb 23\nView\nTue, Feb 24\nView\nWed, Feb 25\nView\nThu, Feb 26\nView\nFri, Feb 27\nView\nSat, Feb 28\nView\nSun, Mar 1\nUS$259\nMon, Mar 2\nView\nTue, Mar 3\nView\nWed, Mar 4\nView\nThu, Mar 5\nView\nFri, Mar 6\nView\nSat, Mar 7\nView\nSun, Mar 8\nView\nPrice graph\nRecommended\n Nonstop\n Checked baggage included\n Hide budget airlines\n Student tickets\n Carry-on baggage included\n Hide codeshare flights\nCO2e Lower emission flights\nShow More\nAlliance\nSkyTeam\nUS$270\nStar Alliance\nUS$353\nOneworld\nUS$1,538\nAirlines\nAll flights with the same airline\nAll airlines\nHK Express (18)\nUS$286\nHong Kong Airlines (13)\nUS$278\nPeach (4)\nUS$259\nSpring Airlines (3)\nUS$273\nChina Airlines (2)\nUS$460\nShow More\nAlliance\nSkyTeam\nUS$270\nStar Alliance\nUS$353\nOneworld\nUS$1,538\nTimes\nDeparture time\n00:00–24:00\n00:00\n24:00\nArrival time\n00:00–24:00\n00:00\n24:00\nDuration\nAny\nStopover Duration\n3h–24h\n3h\n24h\nTotal Duration\n3h–30h 30m\n3h\n30h 30m\nStops\n1 stop or fewer\nUS$259\nStopover cities\nAny\nHong Kong\nUS$278\nShanghai\nUS$273\nXiamen\nUS$270\nShenzhen\nUS$353\nHangzhou\nUS$372\nBusan\nUS$418\nManila\nUS$438\nDaegu\nUS$445\nGuangzhou\nUS$474\nAirports\nAny\nDeparture Airport\nKIX\nKansai International Airport\nUS$259\nArrival Airport\nTPE\nTaiwan Taoyuan International Airport\nUS$259\nAircrafts\nAny\nLarge aircraft\nUS$335\nMidsize aircraft\nUS$259\nCabin\nEconomy\nEconomy\nEconomy/premium economy\nPremium economy\nBusiness/first\nBusiness\nFirst class\nDeparting for Taipei\n62 flights found\nRecommended\nUS$259\nNonstop first\nUS$259\nCheapest\nUS$259\nSort by\nCreate price alert\nCheapest\nIncluded\n- 20% CO2e\nPeach\n07:15\nKIX T2\n3h 30m\nNonstop\n09:45\nTPE T1\nUS$259\nTotal US$518\nSelect\nIncluded\n- 20% CO2e\nPeach\n15:25\nKIX T2\n3h 30m\nNonstop\n17:55\nTPE T1\nUS$375\nTotal US$749\nSelect\nIncluded\n- 23% CO2e\nEVA Air\n12:55\nKIX T1\n3h 10m\nNonstop\n15:05\nTPE T2\nUS$428\nTotal US$856\nSelect\nCarry-on baggage included\n- 2% CO2e\nThai Vietjet Air\n12:00\nKIX T1\n3h 15m\nNonstop\n14:15\nTPE T1\nUS$320\nTotal US$640\nSelect\nSign in & save for future trips\nEarn at least 52 Trip Coins worth US$0.52 for this booking, which you can use to save on future trips!\nSign in/register\nIncluded\n- 6% CO2e\nChina Airlines\n19:00\nKIX T1\n3h 15m\nNonstop\n21:15\nTPE T2\nUS$469\nTotal US$938\nSelect\nIncluded\n- 3% CO2e\nPeach\n22:00\nKIX T2\n3h 30m\nNonstop\n00:30\nTPE T1\n +1\nUS$348\nTotal US$696\nSelect\nIncluded\nPeach\n10:10\nKIX T2\n3h 35m\nNonstop\n12:45\nTPE T1\nUS$325\nTotal US$650\nSelect\nIncluded\n- 23% CO2e\nEVA Air\n10:55\nKIX T1\n3h 15m\nNonstop\n13:10\nTPE T2\nUS$428\nTotal US$856\nSelect\nPrice alerts\nWant a better deal? We'll notify you when the price drops below US$250.\nRecommended: US$250\nHigh chances of success\nOK\nCarry-on baggage included\nTigerair Taiwan\n11:30\nKIX T1\n3h 20m\nNonstop\n13:50\nTPE T1\nUS$335\nTotal US$669\nSelect\nIncluded\nChina Airlines\n12:45\nKIX T1\n3h 15m\nNonstop\n15:00\nTPE T2\nUS$460\nTotal US$919\nSelect\nCarry-on baggage included\n- 4% CO2e\nThai Lion Air\n13:30\nKIX T1\n3h 10m\nNonstop\n15:40\nTPE T1\nUS$347\nTotal US$693\nSelect\nCarry-on baggage included\n- 18% CO2e\nAirAsia X Berhad\n20:45\nKIX T1\n3h 20m\nNonstop\n23:05\nTPE T1\nUS$396\nTotal US$792\nSelect\nIncluded\n- 10% CO2e\nSTARLUX Airlines\n14:00\nKIX T1\n3h 15m\nNonstop\n16:15\nTPE T1\nUS$603\nTotal US$1,205\nSelect\nCarry-on baggage included\n- 2% CO2e\nTigerair Taiwan\n18:55\nKIX T1\n3h 20m\nNonstop\n21:15\nTPE T1\nUS$464\nTotal US$927\nSelect\nCarry-on baggage included\n- 2% CO2e\nJetstar Japan\n14:50\nKIX T1\n3h 20m\nNonstop\n17:10\nTPE T1\nUS$627\nTotal US$1,253\nSelect\nIncluded\nJapan Airlines\noperated by China Airlines\n19:00\nKIX T1\n3h 15m\nNonstop\n21:15\nTPE T2\nUS$1,538\nTotal US$3,075\nSelect\nIncluded\nXiamen Airlines\n18:55\nKIX T1\n16h 5m\n10h 15m in Xiamen\n10:00\nTPE T2\n +1\nUS$270\nTotal US$539\nSelect\nIncluded\nHong Kong Airlines\n20:05\nKIX T1\n15h 45m\n9h 25m in Hong Kong\n10:50\nTPE T2\n +1\nUS$298\nTotal US$596\nSelect\nIncluded\nHong Kong Airlines\n15:05\nKIX T1\n28h 15m\n21h 55m in Hong Kong\n18:20\nTPE T2\n +1\nUS$294\nTotal US$588\nSelect\n<9 left\nIncluded\nHong Kong Airlines\n15:05\nKIX T1\n25h 35m\n19h in Hong Kong\n15:40\nTPE T2\n +1\nUS$294\nTotal US$588\nSelect\n<9 left\nIncluded\nJuneyao Airlines\n22:10\nKIX T1\n14h 25m\n9h 50m in Shanghai\n11:35\nTPE T1\n +1\nUS$335\nTotal US$670\nSelect\nIncluded\nHong Kong Airlines\n15:05\nKIX T1\n20h 45m\n14h 25m in Hong Kong\n10:50\nTPE T2\n +1\nUS$294\nTotal US$588\nSelect\n<9 left\nIncluded\nHong Kong Airlines\n09:35\nKIX T1\n12h\n5h 35m in Hong Kong\n20:35\nTPE T2\nUS$343\nTotal US$686\nSelect\nIncluded\nHong Kong Airlines\n20:05\nKIX T1\n20h 35m\n14h in Hong Kong\n15:40\nTPE T2\n +1\nUS$299\nTotal US$598\nSelect\nIncluded\nShenzhen Airlines\n15:05\nKIX T1\n26h 10m\n19h 20m in Shenzhen\n16:15\nTPE T2\n +1\nUS$353\nTotal US$705\nUS$353\nSelect\nCarry-on baggage included\nSpring Airlines\n15:00\nKIX T2\n20h 30m\n15h 25m in Shanghai\n10:30\nTPE T1\n +1\nUS$273\nTotal US$545\nSelect\nIncluded\nAir China\n12:15\nKIX T1\n24h 10m\n19h 25m in Hangzhou\n11:25\nTPE T2\n +1\nUS$372\nTotal US$743\nSelect\nIncluded\nHong Kong Airlines\n20:05\nKIX T1\n25h 30m\n19h 10m in Hong Kong\n20:35\nTPE T2\n +1\nUS$310\nTotal US$620\nSelect\nCarry-on baggage included\nSpring Airlines\n13:45\nKIX T2\n21h 45m\n16h 50m in Shanghai\n10:30\nTPE T1\n +1\nUS$273\nTotal US$545\nSelect\nHong Kong: Free Layover Tour\nHK Express\n21:05\nKIX T1\n17h 5m\n10h 30m in Hong Kong\n13:10\nTPE T1\n +1\nUS$286\nTotal US$572\nSelect\nIncluded\nGreater Bay Airlines\n14:00\nKIX T1\n12h 10m\n5h 10m in Hong Kong\n01:10\nTPE T1\n +1\nUS$401\nTotal US$801\nSelect\nIncluded\nHong Kong Airlines\n17:05\nKIX T1\n28h 30m\n21h 55m in Hong Kong\n20:35\nTPE T2\n +1\nUS$357\nTotal US$713\nSelect\nIncluded\nJuneyao Airlines\n12:15\nKIX T1\n24h 20m\n19h 30m in Shanghai\n11:35\nTPE T1\n +1\nUS$401\nTotal US$802\nSelect\nIncluded\nHong Kong Airlines\n17:05\nKIX T1\n18h 45m\n12h 10m in Hong Kong\n10:50\nTPE T2\n +1\nUS$343\nTotal US$686\nSelect\nHK Express\n15:15\nKIX T1\n30h 10m\n23h 50m in Hong Kong\n20:25\nTPE T1\n +1\nUS$310\nTotal US$620\nSelect\n<9 left\nIncluded\nT'Way Air\n16:55\nKIX T1\n8h 35m\n4h 10m in Daegu\n00:30\nTPE T1\n +1\nUS$445\nTotal US$890\nSelect\nIncluded\nChina Southern Airlines\n16:00\nKIX T1\n23h 15m\n16h 15m in Guangzhou\n14:15\nTPE T2\n +1\nUS$474\nTotal US$947\nUS$473\nSelect\nIncluded\nHong Kong Airlines\n17:05\nKIX T1\n23h 35m\n16h 45m in Hong Kong\n15:40\nTPE T2\n +1\nUS$357\nTotal US$713\nSelect\nHK Express\n15:15\nKIX T1\n23h 40m\n17h 15m in Hong Kong\n13:55\nTPE T1\n +1\nUS$286\nTotal US$572\nSelect\nHK Express\n15:15\nKIX T1\n22h 55m\n16h 25m in Hong Kong\n13:10\nTPE T1\n +1\nUS$286\nTotal US$572\nSelect\nIncluded\nJeju Air\n10:40\nKIX T2\n14h 10m\n9h 50m in Busan\n23:50\nTPE T1\nUS$418\nTotal US$836\nSelect\nHong Kong: Free Layover Tour\nHK Express\n20:15\nKIX T1\n21h 30m\n15h in Hong Kong\n16:45\nTPE T1\n +1\nUS$323\nTotal US$646\nSelect\nHK Express\n17:10\nKIX T1\n21h 45m\n15h 15m in Hong Kong\n13:55\nTPE T1\n +1\nUS$334\nTotal US$668\nSelect\nNo more results for economy\nOther classes\nBusiness\nIncluded\nSTARLUX Airlines\n12:20\nKIX T1\n3h 15m\nNonstop\n14:35\nTPE T1\nUS$542\nTotal US$1,083\nBusiness\nSelect\n*Last updated: 10:36:39\nFlights\n > \nTaipei Flights\n > \nto Taipei Flights\nBook flights from to Taipei on Trip.com\n\nFirst class | Business class | Economy class | Nonstop\n\nSearch for cheap flights from to Taipei on Trip.com. Trip.com provides the best real-time to Taipei airfares and flight deals available, featuring advanced flight planning tools like price alerts, deal finder fare calendars, and Flight + Hotel deals that make a Taipei vacation or Taipei tour more convenient and affordable.\n\nAward-winning\nSupport in approx. 30s\nRewards for booking",
      "Taipei\nEdit\n2 adults\nEconomy\nMar 1, 2026\nThu, Feb 26\nView\nFri, Feb 27\nView\nSat, Feb 28\nView\nSun, Mar 1\nUS$259\nMon, Mar 2\nView",
      "DepartSun, Mar 1"
    ],
    "hotel_class": [
      "Hotels & Homes"
    ],
    "main": [
      "Cheap Flights, Airline Tickets & Plane Tickets | Trip.com\nAllow notifications\nDon't miss out! Be the first to find out the latest travel info.\nAllow\nTaipei\nEdit\n2 adults\nEconomy\nMar 1, 2026\nThu, Feb 26\nView\nFri, Feb 27\nView\nSat, Feb 28\nView\nSun, Mar 1\nUS$259\nMon, Mar 2\nView\nSun, Feb 22\nView\nMon, Feb 23\nView\nTue, Feb 24\nView\nWed, Feb 25\nView\nThu, Feb 26\nView\nFri, Feb 27\nView\nSat, Feb 28\nView\nSun, Mar 1\nUS$259\nMon, Mar 2\nView\nTue, Mar 3\nView\nWed, Mar 4\nView\nThu, Mar 5\nView\nFri, Mar 6\nView\nSat, Mar 7\nView\nSun, Mar 8\nView\nPrice graph\nRecommended\n Nonstop\n Checked baggage included\n Hide budget airlines\n Student tickets\n Carry-on baggage included\n Hide codeshare flights\nCO2e Lower emission flights\nShow More\nAlliance\nSkyTeam\nUS$270\nStar Alliance\nUS$353\nOneworld\nUS$1,538\nAirlines\nAll flights with the same airline\nAll airlines\nHK Express (18)\nUS$286\nHong Kong Airlines (13)\nUS$278\nPeach (4)\nUS$259\nSpring Airlines (3)\nUS$273\nChina Airlines (2)\nUS$460\nShow More\nAlliance\nSkyTeam\nUS$270\nStar Alliance\nUS$353\nOneworld\nUS$1,538\nTimes\nDeparture time\n00:00–24:00\n00:00\n24:00\nArrival time\n00:00–24:00\n00:00\n24:00\nDuration\nAny\nStopover Duration\n3h–24h\n3h\n24h\nTotal Duration\n3h–30h 30m\n3h\n30h 30m\nStops\n1 stop or fewer\nUS$259\nStopover cities\nAny\nHong Kong\nUS$278\nShanghai\nUS$273\nXiamen\nUS$270\nShenzhen\nUS$353\nHangzhou\nUS$372\nBusan\nUS$418\nManila\nUS$438\nDaegu\nUS$445\nGuangzhou\nUS$474\nAirports\nAny\nDeparture Airport\nKIX\nKansai International Airport\nUS$259\nArrival Airport\nTPE\nTaiwan Taoyuan International Airport\nUS$259\nAircrafts\nAny\nLarge aircraft\nUS$335\nMidsize aircraft\nUS$259\nCabin\nEconomy\nEconomy\nEconomy/premium economy\nPremium economy\nBusiness/first\nBusiness\nFirst class\nDeparting for Taipei\n62 flights found\nRecommended\nUS$259\nNonstop first\nUS$259\nCheapest\nUS$259\nSort by\nCreate price alert\nCheapest\nIncluded\n- 20% CO2e\nPeach\n07:15\nKIX T2\n3h 30m\nNonstop\n09:45\nTPE T1\nUS$259\nTotal US$518\nSelect\nIncluded\n- 20% CO2e\nPeach\n15:25\nKIX T2\n3h 30m\nNonstop\n17:55\nTPE T1\nUS$375\nTotal US$749\nSelect\nIncluded\n- 23% CO2e\nEVA Air\n12:55\nKIX T1\n3h 10m\nNonstop\n15:05\nTPE T2\nUS$428\nTotal US$856\nSelect\nCarry-on baggage included\n- 2% CO2e\nThai Vietjet Air\n12:00\nKIX T1\n3h 15m\nNonstop\n14:15\nTPE T1\nUS$320\nTotal US$640\nSelect\nSign in & save for future trips\nEarn at least 52 Trip Coins worth US$0.52 for this booking, which you can use to save on future trips!\nSign in/register\nIncluded\n- 6% CO2e\nChina Airlines\n19:00\nKIX T1\n3h 15m\nNonstop\n21:15\nTPE T2\nUS$469\nTotal US$938\nSelect\nIncluded\n- 3% CO2e\nPeach\n22:00\nKIX T2\n3h 30m\nNonstop\n00:30\nTPE T1\n +1\nUS$348\nTotal US$696\nSelect\nIncluded\nPeach\n10:10\nKIX T2\n3h 35m\nNonstop\n12:45\nTPE T1\nUS$325\nTotal US$650\nSelect\nIncluded\n- 23% CO2e\nEVA Air\n10:55\nKIX T1\n3h 15m\nNonstop\n13:10\nTPE T2\nUS$428\nTotal US$856\nSelect\nPrice alerts\nWant a better deal? We'll notify you when the price drops below US$250.\nRecommended: US$250\nHigh chances of success\nOK\nCarry-on baggage included\nTigerair Taiwan\n11:30\nKIX T1\n3h 20m\nNonstop\n13:50\nTPE T1\nUS$335\nTotal US$669\nSelect\nIncluded\nChina Airlines\n12:45\nKIX T1\n3h 15m\nNonstop\n15:00\nTPE T2\nUS$460\nTotal US$919\nSelect\nCarry-on baggage included\n- 4% CO2e\nThai Lion Air\n13:30\nKIX T1\n3h 10m\nNonstop\n15:40\nTPE T1\nUS$347\nTotal US$693\nSelect\nCarry-on baggage included\n- 18% CO2e\nAirAsia X Berhad\n20:45\nKIX T1\n3h 20m\nNonstop\n23:05\nTPE T1\nUS$396\nTotal US$792\nSelect\nIncluded\n- 10% CO2e\nSTARLUX Airlines\n14:00\nKIX T1\n3h 15m\nNonstop\n16:15\nTPE T1\nUS$603\nTotal US$1,205\nSelect\nCarry-on baggage included\n- 2% CO2e\nTigerair Taiwan\n18:55\nKIX T1\n3h 20m\nNonstop\n21:15\nTPE T1\nUS$464\nTotal US$927\nSelect\nCarry-on baggage included\n- 2% CO2e\nJetstar Japan\n14:50\nKIX T1\n3h 20m\nNonstop\n17:10\nTPE T1\nUS$627\nTotal US$1,253\nSelect\nIncluded\nJapan Airlines\noperated by China Airlines\n19:00\nKIX T1\n3h 15m\nNonstop\n21:15\nTPE T2\nUS$1,538\nTotal US$3,075\nSelect\nIncluded\nXiamen Airlines\n18:55\nKIX T1\n16h 5m\n10h 15m in Xiamen\n10:00\nTPE T2\n +1\nUS$270\nTotal US$539\nSelect\nIncluded\nHong Kong Airlines\n20:05\nKIX T1\n15h 45m\n9h 25m in Hong Kong\n10:50\nTPE T2\n +1\nUS$298\nTotal US$596\nSelect\nIncluded\nHong Kong Airlines\n15:05\nKIX T1\n28h 15m\n21h 55m in Hong Kong\n18:20\nTPE T2\n +1\nUS$294\nTotal US$588\nSelect\n<9 left\nIncluded\nHong Kong Airlines\n15:05\nKIX T1\n25h 35m\n19h in Hong Kong\n15:40\nTPE T2\n +1\nUS$294\nTotal US$588\nSelect\n<9 left\nIncluded\nJuneyao Airlines\n22:10\nKIX T1\n14h 25m\n9h 50m in Shanghai\n11:35\nTPE T1\n +1\nUS$335\nTotal US$670\nSelect\nIncluded\nHong Kong Airlines\n15:05\nKIX T1\n20h 45m\n14h 25m in Hong Kong\n10:50\nTPE T2\n +1\nUS$294\nTotal US$588\nSelect\n<9 left\nIncluded\nHong Kong Airlines\n09:35\nKIX T1\n12h\n5h 35m in Hong Kong\n20:35\nTPE T2\nUS$343\nTotal US$686\nSelect\nIncluded\nHong Kong Airlines\n20:05\nKIX T1\n20h 35m\n14h in Hong Kong\n15:40\nTPE T2\n +1\nUS$299\nTotal US$598\nSelect\nIncluded\nShenzhen Airlines\n15:05\nKIX T1\n26h 10m\n19h 20m in Shenzhen\n16:15\nTPE T2\n +1\nUS$353\nTotal US$705\nUS$353\nSelect\nCarry-on baggage included\nSpring Airlines\n15:00\nKIX T2\n20h 30m\n15h 25m in Shanghai\n10:30\nTPE T1\n +1\nUS$273\nTotal US$545\nSelect\nIncluded\nAir China\n12:15\nKIX T1\n24h 10m\n19h 25m in Hangzhou\n11:25\nTPE T2\n +1\nUS$372\nTotal US$743\nSelect\nIncluded\nHong Kong Airlines\n20:05\nKIX T1\n25h 30m\n19h 10m in Hong Kong\n20:35\nTPE T2\n +1\nUS$310\nTotal US$620\nSelect\nCarry-on baggage included\nSpring Airlines\n13:45\nKIX T2\n21h 45m\n16h 50m in Shanghai\n10:30\nTPE T1\n +1\nUS$273\nTotal US$545\nSelect\nHong Kong: Free Layover Tour\nHK Express\n21:05\nKIX T1\n17h 5m\n10h 30m in Hong Kong\n13:10\nTPE T1\n +1\nUS$286\nTotal US$572\nSelect\nIncluded\nGreater Bay Airlines\n14:00\nKIX T1\n12h 10m\n5h 10m in Hong Kong\n01:10\nTPE T1\n +1\nUS$401\nTotal US$801\nSelect\nIncluded\nHong Kong Airlines\n17:05\nKIX T1\n28h 30m\n21h 55m in Hong Kong\n20:35\nTPE T2\n +1\nUS$357\nTotal US$713\nSelect\nIncluded\nJuneyao Airlines\n12:15\nKIX T1\n24h 20m\n19h 30m in Shanghai\n11:35\nTPE T1\n +1\nUS$401\nTotal US$802\nSelect\nIncluded\nHong Kong Airlines\n17:05\nKIX T1\n18h 45m\n12h 10m in Hong Kong\n10:50\nTPE T2\n +1\nUS$343\nTotal US$686\nSelect\nHK Express\n15:15\nKIX T1\n30h 10m\n23h 50m in Hong Kong\n20:25\nTPE T1\n +1\nUS$310\nTotal US$620\nSelect\n<9 left\nIncluded\nT'Way Air\n16:55\nKIX T1\n8h 35m\n4h 10m in Daegu\n00:30\nTPE T1\n +1\nUS$445\nTotal US$890\nSelect\nIncluded\nChina Southern Airlines\n16:00\nKIX T1\n23h 15m\n16h 15m in Guangzhou\n14:15\nTPE T2\n +1\nUS$474\nTotal US$947\nUS$473\nSelect\nIncluded\nHong Kong Airlines\n17:05\nKIX T1\n23h 35m\n16h 45m in Hong Kong\n15:40\nTPE T2\n +1\nUS$357\nTotal US$713\nSelect\nHK Express\n15:15\nKIX T1\n23h 40m\n17h 15m in Hong Kong\n13:55\nTPE T1\n +1\nUS$286\nTotal US$572\nSelect\nHK Express\n15:15\nKIX T1\n22h 55m\n16h 25m in Hong Kong\n13:10\nTPE T1\n +1\nUS$286\nTotal US$572\nSelect\nIncluded\nJeju Air\n10:40\nKIX T2\n14h 10m\n9h 50m in Busan\n23:50\nTPE T1\nUS$418\nTotal US$836\nSelect\nHong Kong: Free Layover Tour\nHK Express\n20:15\nKIX T1\n21h 30m\n15h in Hong Kong\n16:45\nTPE T1\n +1\nUS$323\nTotal US$646\nSelect\nHK Express\n17:10\nKIX T1\n21h 45m\n15h 15m in Hong Kong\n13:55\nTPE T1\n +1\nUS$334\nTotal US$668\nSelect\nNo more results for economy\nOther classes\nBusiness\nIncluded\nSTARLUX Airlines\n12:20\nKIX T1\n3h 15m\nNonstop\n14:35\nTPE T1\nUS$542\nTotal US$1,083\nBusiness\nSelect\n*Last updated: 10:36:39\nFlights\n > \nTaipei Flights\n > \nto Taipei Flights\nBook flights from to Taipei on Trip.com\n\nFirst class | Business class | Economy class | Nonstop\n\nSearch for cheap flights from to Taipei on Trip.com. Trip.com provides the best real-time to Taipei airfares and flight deals available, featuring advanced flight planning tools like price alerts, deal finder fare calendars, and Flight + Hotel deals that make a Taipei vacation or Taipei tour more convenient and affordable.\n\nAward-winning\nSupport in approx. 30s\nRewards for booking"
    ]
  }
}