{
  "url": "https://www.trip.com/flights/osaka-to-taipei/tickets-kix-tpe?dcity=kix&acity=tpe&ddate=2026-03-04&flighttype=ow&class=y&quantity=2",
  "scraped_at": "2026-02-05T17:37:58.703224",
  "title": "Cheap Flights, Airline Tickets & Plane Tickets | Trip.com",
  "raw_text": "Go to main content\nTheme Detection\nHotels & Homes\nFlights\nTrains\nCar services\nApp\nUSD\nCustomer support\nFind bookings\nSign in / Register\nCheap Flights, Airline Tickets & Plane Tickets | Trip.com\nAllow notifications\nDon't miss out! Be the first to find out the latest travel info.\nAllow\nTaipei\nEdit\n2 adults\nEconomy\nMar 4, 2026\nSun, Mar 1\nView\nMon, Mar 2\nView\nTue, Mar 3\nView\nWed, Mar 4\nUS$116\nThu, Mar 5\nView\nWed, Feb 25\nView\nThu, Feb 26\nView\nFri, Feb 27\nView\nSat, Feb 28\nView\nSun, Mar 1\nView\nMon, Mar 2\nView\nTue, Mar 3\nView\nWed, Mar 4\nUS$116\nThu, Mar 5\nView\nFri, Mar 6\nView\nSat, Mar 7\nView\nSun, Mar 8\nView\nMon, Mar 9\nView\nTue, Mar 10\nView\nWed, Mar 11\nView\nPrice graph\nRecommended\n Nonstop\n Checked baggage included\n Hide budget airlines\n Student tickets\n Carry-on baggage included\n Hide codeshare flights\nCO2e Lower emission flights\nShow More\nAlliance\nStar Alliance\nUS$218\nOneworld\nUS$324\nSkyTeam\nUS$470\nAirlines\nAll flights with the same airline\nAll airlines\nHong Kong Airlines (14)\nUS$198\nHK Express (8)\nUS$196\nAir Macau (4)\nUS$134\nEVA Air (3)\nUS$218\nPeach (3)\nUS$191\nShow More\nAlliance\nStar Alliance\nUS$218\nOneworld\nUS$324\nSkyTeam\nUS$470\nTimes\nDeparture time\n00:00–24:00\n00:00\n24:00\nArrival time\n00:00–24:00\n00:00\n24:00\nDuration\nAny\nStopover Duration\n1h–22h 30m\n1h\n22h 30m\nTotal Duration\n3h–28h 30m\n3h\n28h 30m\nStops\n1 stop or fewer\nUS$116\nStopover cities\nAny\nHong Kong\nUS$170\nBusan\nUS$197\nMacau\nUS$134\nShanghai\nUS$211\nSeoul\nUS$180\nOkinawa\nUS$195\nJeju\nUS$119\nDaegu\nUS$187\nBeijing\nUS$265\nShenzhen\nUS$337\nManila\nUS$346\nAirports\nAny\nDeparture Airport\nKIX\nKansai International Airport\nUS$116\nArrival Airport\nTPE\nTaiwan Taoyuan International Airport\nUS$116\nAircrafts\nAny\nLarge aircraft\nUS$116\nMidsize aircraft\nUS$119\nCabin\nEconomy\nEconomy\nEconomy/premium economy\nPremium economy\nBusiness/first\nBusiness\nFirst class\nDeparting for Taipei\nRecommended\nUS$116\nNonstop first\nUS$116\nCheapest\nUS$116\nSort by\nCreate price alert\nCheapest\nCarry-on baggage included\n- 18% CO2e\nAirAsia X Berhad\n20:45\nKIX T1\n3h 20m\nNonstop\n23:05\nTPE T1\nUS$116\nTotal US$232\nSelect\nCarry-on baggage included\nThai Vietjet Air\n12:00\nKIX T1\n3h 15m\nNonstop\n14:15\nTPE T1\nUS$156\nTotal US$311\nSelect\nCarry-on baggage included\n- 2% CO2e\nJetstar Japan\n23:10\nKIX T1\n3h 20m\nNonstop\n01:30\nTPE T1\n +1\nUS$157\nTotal US$313\nSelect\nCarry-on baggage included\nTigerair Taiwan\n11:30\nKIX T1\n3h 20m\nNonstop\n13:50\nTPE T1\nUS$179\nTotal US$358\nSelect\nSign in & save for future trips\nEarn at least 24 Trip Coins worth US$0.24 for this booking, which you can use to save on future trips!\nSign in/register\nCarry-on baggage included\nJetstar Japan\n14:50\nKIX T1\n3h 20m\nNonstop\n17:10\nTPE T1\nUS$184\nTotal US$367\nSelect\nCarry-on baggage included\nPeach\n10:10\nKIX T2\n3h 35m\nNonstop\n12:45\nTPE T1\nUS$191\nTotal US$381\nSelect\nCarry-on baggage included\n- 2% CO2e\nTigerair Taiwan\n18:55\nKIX T1\n3h 35m\nNonstop\n21:30\nTPE T1\nUS$212\nTotal US$423\nSelect\nIncluded\n- 23% CO2e\nEVA Air\n12:55\nKIX T1\n3h 10m\nNonstop\n15:05\nTPE T2\nUS$218\nTotal US$435\nSelect\nIncluded\n- 20% CO2e\nPeach\n15:25\nKIX T2\n3h 30m\nNonstop\n17:55\nTPE T1\nUS$219\nTotal US$438\nSelect\nIncluded\n- 20% CO2e\nPeach\n07:15\nKIX T2\n3h 30m\nNonstop\n09:45\nTPE T1\nUS$239\nTotal US$478\nSelect\nIncluded\n- 23% CO2e\nEVA Air\n10:55\nKIX T1\n3h 15m\nNonstop\n13:10\nTPE T2\nUS$302\nTotal US$604\nSelect\nIncluded\n- 23% CO2e\nEVA Air\n18:10\nKIX T1\n3h 15m\nNonstop\n20:25\nTPE T2\nUS$327\nTotal US$654\nSelect\nIncluded\n- 10% CO2e\nSTARLUX Airlines\n14:00\nKIX T1\n3h 15m\nNonstop\n16:15\nTPE T1\nUS$346\nTotal US$691\nSelect\nIncluded\n- 6% CO2e\nChina Airlines\n19:00\nKIX T1\n3h 15m\nNonstop\n21:15\nTPE T2\nUS$470\nTotal US$939\nSelect\nIncluded\nAll Nippon Airways\noperated by EVA Air\n12:55\nKIX T1\n3h 10m\nNonstop\n15:05\nTPE T2\nUS$1,262\nTotal US$2,524\nSelect\nIncluded\nJapan Airlines\noperated by China Airlines\n19:00\nKIX T1\n3h 15m\nNonstop\n21:15\nTPE T2\nUS$1,406\nTotal US$2,812\nSelect\nIncluded\nAll Nippon Airways\noperated by EVA Air\n18:10\nKIX T1\n3h 15m\nNonstop\n20:25\nTPE T2\nUS$1,529\nTotal US$3,057\nSelect\nIncluded\nAll Nippon Airways\noperated by EVA Air\n10:55\nKIX T1\n3h 15m\nNonstop\n13:10\nTPE T2\nUS$1,573\nTotal US$3,146\nSelect\nIncluded\nAir Macau\noperated by EVA Air\n13:45\nKIX T1\n26h 10m\n20h 5m in Macau\n14:55\nTPE T2\n +1\nUS$134\nTotal US$268\nSelect\nIncluded\nAir Macau\n13:45\nKIX T1\n24h 55m\n18h 50m in Macau\n13:40\nTPE T1\n +1\nUS$148\nTotal US$296\nSelect\nCarry-on baggage included\nGreater Bay Airlines\n14:00\nKIX T1\n7h 15m\n1h in Hong Kong\n20:15\nTPE T1\nUS$170\nTotal US$339\nSelect\nCarry-on baggage included\nGreater Bay Airlines\n14:00\nKIX T1\n20h 50m\n14h 35m in Hong Kong\n09:50\nTPE T1\n +1\nUS$170\nTotal US$339\nSelect\nIncluded\nJin Air\n11:05\nKIX T1\n25h 25m\n20h 30m in Seoul\n11:30\nTPE T1\n +1\nUS$180\nTotal US$359\nSelect\nIncluded\nT'Way Air\n16:55\nKIX T1\n8h 35m\n4h 10m in Daegu\n00:30\nTPE T1\n +1\nUS$187\nTotal US$374\nSelect\nIncluded\nAir Macau\noperated by EVA Air\n13:45\nKIX T1\n9h 15m\n3h 5m in Macau\n22:00\nTPE T2\nUS$196\nTotal US$392\nSelect\nIncluded\nJeju Air\n10:40\nKIX T2\n14h 10m\n9h 50m in Busan\n23:50\nTPE T1\nUS$197\nTotal US$393\nSelect\nHong Kong: Free Layover Tour\nHK Express\n21:05\nKIX T1\n17h 50m\n11h 20m in Hong Kong\n13:55\nTPE T1\n +1\nUS$196\nTotal US$392\nSelect\nHong Kong: Free Layover Tour\nHK Express\n20:15\nKIX T1\n18h 40m\n12h 10m in Hong Kong\n13:55\nTPE T1\n +1\nUS$196\nTotal US$392\nSelect\nHong Kong: Free Layover Tour\nHK Express\n21:05\nKIX T1\n20h 40m\n14h 10m in Hong Kong\n16:45\nTPE T1\n +1\nUS$196\nTotal US$392\nSelect\nHong Kong: Free Layover Tour\nHK Express\n20:15\nKIX T1\n21h 30m\n15h in Hong Kong\n16:45\nTPE T1\n +1\nUS$196\nTotal US$392\nSelect\nHK Express\n17:10\nKIX T1\n21h 45m\n15h 15m in Hong Kong\n13:55\nTPE T1\n +1\nUS$196\nTotal US$392\nSelect\nIncluded\nHong Kong Airlines\n09:45\nKIX T1\n9h 35m\n3h 15m in Hong Kong\n18:20\nTPE T2\nUS$198\nTotal US$395\nSelect\nIncluded\nJapan Transocean Air\n14:00\nKIX T1\n19h 45m\n15h 35m in Okinawa\n08:45\nTPE T2\n +1\nUS$199\nTotal US$398\nSelect\nIncluded\nHong Kong Airlines\n09:45\nKIX T1\n11h 55m\n5h 30m in Hong Kong\n20:40\nTPE T2\nUS$200\nTotal US$399\nSelect\nIncluded\nHong Kong Airlines\n15:05\nKIX T1\n25h 25m\n19h in Hong Kong\n15:30\nTPE T2\n +1\nUS$204\nTotal US$407\nSelect\nIncluded\nHong Kong: Free Layover Tour\nHong Kong Airlines\n09:45\nKIX T1\n26h 5m\n19h 45m in Hong Kong\n10:50\nTPE T2\n +1\nUS$205\nTotal US$409\nSelect\nIncluded\nHong Kong Airlines\n15:05\nKIX T1\n28h 15m\n21h 55m in Hong Kong\n18:20\nTPE T2\n +1\nUS$205\nTotal US$409\nSelect\nHong Kong: Free Layover Tour\nHK Express\n21:05\nKIX T1\n17h 5m\n10h 30m in Hong Kong\n13:10\nTPE T1\n +1\nUS$209\nTotal US$417\nSelect\nHong Kong: Free Layover Tour\nHK Express\n20:15\nKIX T1\n17h 55m\n11h 20m in Hong Kong\n13:10\nTPE T1\n +1\nUS$209\nTotal US$417\nSelect\nHK Express\n17:10\nKIX T1\n21h\n14h 25m in Hong Kong\n13:10\nTPE T1\n +1\nUS$209\nTotal US$417\nSelect\nCarry-on baggage included\nSpring Airlines\n17:00\nKIX T2\n18h 30m\n13h 25m in Shanghai\n10:30\nTPE T1\n +1\nUS$211\nTotal US$422\nSelect\nIncluded\nHong Kong Airlines\n17:05\nKIX T1\n26h 15m\n19h 40m in Hong Kong\n18:20\nTPE T2\n +1\nUS$245\nTotal US$489\nSelect\nIncluded\nJuneyao Airlines\n22:10\nKIX T1\n14h 25m\n9h 50m in Shanghai\n11:35\nTPE T1\n +1\nUS$250\nTotal US$500\nSelect\nIncluded\nAir China\n13:50\nKIX T1\n22h 50m\n16h 10m in Beijing\n11:40\nTPE T2\n +1\nUS$265\nTotal US$529\nSelect\nIncluded\nJuneyao Airlines\n12:15\nKIX T1\n24h 20m\n19h 30m in Shanghai\n11:35\nTPE T1\n +1\nUS$311\nTotal US$621\nSelect\nIncluded\nShenzhen Airlines\n15:05\nKIX T1\n26h 10m\n19h 20m in Shenzhen\n16:15\nTPE T2\n +1\nUS$337\nTotal US$674\nUS$337\nSelect\nIncluded\nAsiana Airlines\n09:00\nKIX T1\n7h 45m\n2h 50m in Seoul\n15:45\nTPE T2\nUS$340\nTotal US$679\nSelect\nIncluded\nPhilippine Airlines\n10:15\nKIX T1\n11h 20m\n4h 20m in Manila\n20:35\nTPE T1\nUS$346\nTotal US$691\nSelect\nNo more results for economy\nOther classes\nBusiness\nIncluded\nChina Airlines\n(180°)\n12:45\nKIX T1\n3h 15m\nNonstop\n15:00\nTPE T2\nUS$592\nTotal US$1,183\nBusiness\nSelect\nFlights\n > \nTaipei Flights\n > \nto Taipei Flights\nBook flights from to Taipei on Trip.com\n\nFirst class | Business class | Economy class | Nonstop\n\nSearch for cheap flights from to Taipei on Trip.com. Trip.com provides the best real-time to Taipei airfares and flight deals available, featuring advanced flight planning tools like price alerts, deal finder fare calendars, and Flight + Hotel deals that make a Taipei vacation or Taipei tour more convenient and affordable.\n\nAward-winning\nSupport in approx. 30s\nRewards for booking\nContact us\nCustomer support\nService guarantee\nMore service info\nAbout\nAbout Trip.com\nNews\nCareers\nTerms & Conditions\nPrivacy Statement\nAccessibility statement\nAbout Trip.com Group\nOther services\nInvestor relations\nTrip.com Rewards\nAffiliate program\nList your property\nAll hotels\nBecome a Supplier\nSecurity\nPayment methods\nOur partners\nContact Center\nof the year 2025\nCopyright © 2025 Trip.com Travel Singapore Pte. Ltd. All rights reserved\nSite Operator: Trip.com Travel Singapore Pte. Ltd.",
  "extracted": {
    "flight": {},
    "hotel": {},
    "price": {},
    "dates": {},
    "inclusions": [],
    "date_pricing": {}
  },
  "extracted_elements": {
    "flight_element": [
      "AirAsia X Berhad\n20:45\nKIX T1\n3h 20m\nNonstop\n23:05\nTPE T1",
      "Thai Vietjet Air\n12:00\nKIX T1\n3h 15m\nNonstop\n14:15\nTPE T1",
      "Jetstar Japan\n23:10\nKIX T1\n3h 20m\nNonstop\n01:30\nTPE T1\n +1",
      "Tigerair Taiwan\n11:30\nKIX T1\n3h 20m\nNonstop\n13:50\nTPE T1",
      "Jetstar Japan\n14:50\nKIX T1\n3h 20m\nNonstop\n17:10\nTPE T1"
    ],
    "price_class": [
      "Sun, Mar 1\nView\nMon, Mar 2\nView\nTue, Mar 3\nView\nWed, Mar 4\nUS$116\nThu, Mar 5\nView",
      "Sun, Mar 1\nView\nMon, Mar 2\nView\nTue, Mar 3\nView\nWed, Mar 4\nUS$116\nThu, Mar 5\nView",
      "Sun, Mar 1\nView\nMon, Mar 2\nView\nTue, Mar 3\nView\nWed, Mar 4\nUS$116\nThu, Mar 5\nView",
      "Sun, Mar 1\nView\nMon, Mar 2\nView\nTue, Mar 3\nView\nWed, Mar 4\nUS$116\nThu, Mar 5\nView",
      "Sun, Mar 1\nView\nMon, Mar 2\nView\nTue, Mar 3\nView\nWed, Mar 4\nUS$116\nThu, Mar 5\nView"
    ],
    "flight_class": [
      "Flights",
      "Taipei\nEdit\n2 adults\nEconomy\nMar 4, 2026\nSun, Mar 1\nView\nMon, Mar 2\nView\nTue, Mar 3\nView\nWed, Mar 4\nUS$116\nThu, Mar 5\nView\nWed, Feb 25\nView\nThu, Feb 26\nView\nFri, Feb 27\nView\nSat, Feb 28\nView\nSun, Mar 1\nView\nMon, Mar 2\nView\nTue, Mar 3\nView\nWed, Mar 4\nUS$116\nThu, Mar 5\nView\nFri, Mar 6\nView\nSat, Mar 7\nView\nSun, Mar 8\nView\nMon, Mar 9\nView\nTue, Mar 10\nView\nWed, Mar 11\nView\nPrice graph\nRecommended\n Nonstop\n Checked baggage included\n Hide budget airlines\n Student tickets\n Carry-on baggage included\n Hide codeshare flights\nCO2e Lower emission flights\nShow More\nAlliance\nStar Alliance\nUS$218\nOneworld\nUS$324\nSkyTeam\nUS$470\nAirlines\nAll flights with the same airline\nAll airlines\nHong Kong Airlines (14)\nUS$198\nHK Express (8)\nUS$196\nAir Macau (4)\nUS$134\nEVA Air (3)\nUS$218\nPeach (3)\nUS$191\nShow More\nAlliance\nStar Alliance\nUS$218\nOneworld\nUS$324\nSkyTeam\nUS$470\nTimes\nDeparture time\n00:00–24:00\n00:00\n24:00\nArrival time\n00:00–24:00\n00:00\n24:00\nDuration\nAny\nStopover Duration\n1h–22h 30m\n1h\n22h 30m\nTotal Duration\n3h–28h 30m\n3h\n28h 30m\nStops\n1 stop or fewer\nUS$116\nStopover cities\nAny\nHong Kong\nUS$170\nBusan\nUS$197\nMacau\nUS$134\nShanghai\nUS$211\nSeoul\nUS$180\nOkinawa\nUS$195\nJeju\nUS$119\nDaegu\nUS$187\nBeijing\nUS$265\nShenzhen\nUS$337\nManila\nUS$346\nAirports\nAny\nDeparture Airport\nKIX\nKansai International Airport\nUS$116\nArrival Airport\nTPE\nTaiwan Taoyuan International Airport\nUS$116\nAircrafts\nAny\nLarge aircraft\nUS$116\nMidsize aircraft\nUS$119\nCabin\nEconomy\nEconomy\nEconomy/premium economy\nPremium economy\nBusiness/first\nBusiness\nFirst class\nDeparting for Taipei\nRecommended\nUS$116\nNonstop first\nUS$116\nCheapest\nUS$116\nSort by\nCreate price alert\nCheapest\nCarry-on baggage included\n- 18% CO2e\nAirAsia X Berhad\n20:45\nKIX T1\n3h 20m\nNonstop\n23:05\nTPE T1\nUS$116\nTotal US$232\nSelect\nCarry-on baggage included\nThai Vietjet Air\n12:00\nKIX T1\n3h 15m\nNonstop\n14:15\nTPE T1\nUS$156\nTotal US$311\nSelect\nCarry-on baggage included\n- 2% CO2e\nJetstar Japan\n23:10\nKIX T1\n3h 20m\nNonstop\n01:30\nTPE T1\n +1\nUS$157\nTotal US$313\nSelect\nCarry-on baggage included\nTigerair Taiwan\n11:30\nKIX T1\n3h 20m\nNonstop\n13:50\nTPE T1\nUS$179\nTotal US$358\nSelect\nSign in & save for future trips\nEarn at least 24 Trip Coins worth US$0.24 for this booking, which you can use to save on future trips!\nSign in/register\nCarry-on baggage included\nJetstar Japan\n14:50\nKIX T1\n3h 20m\nNonstop\n17:10\nTPE T1\nUS$184\nTotal US$367\nSelect\nCarry-on baggage included\nPeach\n10:10\nKIX T2\n3h 35m\nNonstop\n12:45\nTPE T1\nUS$191\nTotal US$381\nSelect\nCarry-on baggage included\n- 2% CO2e\nTigerair Taiwan\n18:55\nKIX T1\n3h 35m\nNonstop\n21:30\nTPE T1\nUS$212\nTotal US$423\nSelect\nIncluded\n- 23% CO2e\nEVA Air\n12:55\nKIX T1\n3h 10m\nNonstop\n15:05\nTPE T2\nUS$218\nTotal US$435\nSelect\nIncluded\n- 20% CO2e\nPeach\n15:25\nKIX T2\n3h 30m\nNonstop\n17:55\nTPE T1\nUS$219\nTotal US$438\nSelect\nIncluded\n- 20% CO2e\nPeach\n07:15\nKIX T2\n3h 30m\nNonstop\n09:45\nTPE T1\nUS$239\nTotal US$478\nSelect\nIncluded\n- 23% CO2e\nEVA Air\n10:55\nKIX T1\n3h 15m\nNonstop\n13:10\nTPE T2\nUS$302\nTotal US$604\nSelect\nIncluded\n- 23% CO2e\nEVA Air\n18:10\nKIX T1\n3h 15m\nNonstop\n20:25\nTPE T2\nUS$327\nTotal US$654\nSelect\nIncluded\n- 10% CO2e\nSTARLUX Airlines\n14:00\nKIX T1\n3h 15m\nNonstop\n16:15\nTPE T1\nUS$346\nTotal US$691\nSelect\nIncluded\n- 6% CO2e\nChina Airlines\n19:00\nKIX T1\n3h 15m\nNonstop\n21:15\nTPE T2\nUS$470\nTotal US$939\nSelect\nIncluded\nAll Nippon Airways\noperated by EVA Air\n12:55\nKIX T1\n3h 10m\nNonstop\n15:05\nTPE T2\nUS$1,262\nTotal US$2,524\nSelect\nIncluded\nJapan Airlines\noperated by China Airlines\n19:00\nKIX T1\n3h 15m\nNonstop\n21:15\nTPE T2\nUS$1,406\nTotal US$2,812\nSelect\nIncluded\nAll Nippon Airways\noperated by EVA Air\n18:10\nKIX T1\n3h 15m\nNonstop\n20:25\nTPE T2\nUS$1,529\nTotal US$3,057\nSelect\nIncluded\nAll Nippon Airways\noperated by EVA Air\n10:55\nKIX T1\n3h 15m\nNonstop\n13:10\nTPE T2\nUS$1,573\nTotal US$3,146\nSelect\nIncluded\nAir Macau\noperated by EVA Air\n13:45\nKIX T1\n26h 10m\n20h 5m in Macau\n14:55\nTPE T2\n +1\nUS$134\nTotal US$268\nSelect\nIncluded\nAir Macau\n13:45\nKIX T1\n24h 55m\n18h 50m in Macau\n13:40\nTPE T1\n +1\nUS$148\nTotal US$296\nSelect\nCarry-on baggage included\nGreater Bay Airlines\n14:00\nKIX T1\n7h 15m\n1h in Hong Kong\n20:15\nTPE T1\nUS$170\nTotal US$339\nSelect\nCarry-on baggage included\nGreater Bay Airlines\n14:00\nKIX T1\n20h 50m\n14h 35m in Hong Kong\n09:50\nTPE T1\n +1\nUS$170\nTotal US$339\nSelect\nIncluded\nJin Air\n11:05\nKIX T1\n25h 25m\n20h 30m in Seoul\n11:30\nTPE T1\n +1\nUS$180\nTotal US$359\nSelect\nIncluded\nT'Way Air\n16:55\nKIX T1\n8h 35m\n4h 10m in Daegu\n00:30\nTPE T1\n +1\nUS$187\nTotal US$374\nSelect\nIncluded\nAir Macau\noperated by EVA Air\n13:45\nKIX T1\n9h 15m\n3h 5m in Macau\n22:00\nTPE T2\nUS$196\nTotal US$392\nSelect\nIncluded\nJeju Air\n10:40\nKIX T2\n14h 10m\n9h 50m in Busan\n23:50\nTPE T1\nUS$197\nTotal US$393\nSelect\nHong Kong: Free Layover Tour\nHK Express\n21:05\nKIX T1\n17h 50m\n11h 20m in Hong Kong\n13:55\nTPE T1\n +1\nUS$196\nTotal US$392\nSelect\nHong Kong: Free Layover Tour\nHK Express\n20:15\nKIX T1\n18h 40m\n12h 10m in Hong Kong\n13:55\nTPE T1\n +1\nUS$196\nTotal US$392\nSelect\nHong Kong: Free Layover Tour\nHK Express\n21:05\nKIX T1\n20h 40m\n14h 10m in Hong Kong\n16:45\nTPE T1\n +1\nUS$196\nTotal US$392\nSelect\nHong Kong: Free Layover Tour\nHK Express\n20:15\nKIX T1\n21h 30m\n15h in Hong Kong\n16:45\nTPE T1\n +1\nUS$196\nTotal US$392\nSelect\nHK Express\n17:10\nKIX T1\n21h 45m\n15h 15m in Hong Kong\n13:55\nTPE T1\n +1\nUS$196\nTotal US$392\nSelect\nIncluded\nHong Kong Airlines\n09:45\nKIX T1\n9h 35m\n3h 15m in Hong Kong\n18:20\nTPE T2\nUS$198\nTotal US$395\nSelect\nIncluded\nJapan Transocean Air\n14:00\nKIX T1\n19h 45m\n15h 35m in Okinawa\n08:45\nTPE T2\n +1\nUS$199\nTotal US$398\nSelect\nIncluded\nHong Kong Airlines\n09:45\nKIX T1\n11h 55m\n5h 30m in Hong Kong\n20:40\nTPE T2\nUS$200\nTotal US$399\nSelect\nIncluded\nHong Kong Airlines\n15:05\nKIX T1\n25h 25m\n19h in Hong Kong\n15:30\nTPE T2\n +1\nUS$204\nTotal US$407\nSelect\nIncluded\nHong Kong: Free Layover Tour\nHong Kong Airlines\n09:45\nKIX T1\n26h 5m\n19h 45m in Hong Kong\n10:50\nTPE T2\n +1\nUS$205\nTotal US$409\nSelect\nIncluded\nHong Kong Airlines\n15:05\nKIX T1\n28h 15m\n21h 55m in Hong Kong\n18:20\nTPE T2\n +1\nUS$205\nTotal US$409\nSelect\nHong Kong: Free Layover Tour\nHK Express\n21:05\nKIX T1\n17h 5m\n10h 30m in Hong Kong\n13:10\nTPE T1\n +1\nUS$209\nTotal US$417\nSelect\nHong Kong: Free Layover Tour\nHK Express\n20:15\nKIX T1\n17h 55m\n11h 20m in Hong Kong\n13:10\nTPE T1\n +1\nUS$209\nTotal US$417\nSelect\nHK Express\n17:10\nKIX T1\n21h\n14h 25m in Hong Kong\n13:10\nTPE T1\n +1\nUS$209\nTotal US$417\nSelect\nCarry-on baggage included\nSpring Airlines\n17:00\nKIX T2\n18h 30m\n13h 25m in Shanghai\n10:30\nTPE T1\n +1\nUS$211\nTotal US$422\nSelect\nIncluded\nHong Kong Airlines\n17:05\nKIX T1\n26h 15m\n19h 40m in Hong Kong\n18:20\nTPE T2\n +1\nUS$245\nTotal US$489\nSelect\nIncluded\nJuneyao Airlines\n22:10\nKIX T1\n14h 25m\n9h 50m in Shanghai\n11:35\nTPE T1\n +1\nUS$250\nTotal US$500\nSelect\nIncluded\nAir China\n13:50\nKIX T1\n22h 50m\n16h 10m in Beijing\n11:40\nTPE T2\n +1\nUS$265\nTotal US$529\nSelect\nIncluded\nJuneyao Airlines\n12:15\nKIX T1\n24h 20m\n19h 30m in Shanghai\n11:35\nTPE T1\n +1\nUS$311\nTotal US$621\nSelect\nIncluded\nShenzhen Airlines\n15:05\nKIX T1\n26h 10m\n19h 20m in Shenzhen\n16:15\nTPE T2\n +1\nUS$337\nTotal US$674\nUS$337\nSelect\nIncluded\nAsiana Airlines\n09:00\nKIX T1\n7h 45m\n2h 50m in Seoul\n15:45\nTPE T2\nUS$340\nTotal US$679\nSelect\nIncluded\nPhilippine Airlines\n10:15\nKIX T1\n11h 20m\n4h 20m in Manila\n20:35\nTPE T1\nUS$346\nTotal US$691\nSelect\nNo more results for economy\nOther classes\nBusiness\nIncluded\nChina Airlines\n(180°)\n12:45\nKIX T1\n3h 15m\nNonstop\n15:00\nTPE T2\nUS$592\nTotal US$1,183\nBusiness\nSelect\nFlights\n > \nTaipei Flights\n > \nto Taipei Flights\nBook flights from to Taipei on Trip.com\n\nFirst class | Business class | Economy class | Nonstop\n\nSearch for cheap flights from to Taipei on Trip.com. Trip.com provides the best real-time to Taipei airfares and flight deals available, featuring advanced flight planning tools like price alerts, deal finder fare calendars, and Flight + Hotel deals that make a Taipei vacation or Taipei tour more convenient and affordable.\n\nAward-winning\nSupport in approx. 30s\nRewards for booking",
      "Taipei\nEdit\n2 adults\nEconomy\nMar 4, 2026\nSun, Mar 1\nView\nMon, Mar 2\nView\nTue, Mar 3\nView\nWed, Mar 4\nUS$116\nThu, Mar 5\nView",
      "DepartWed, Mar 4"
    ],
    "hotel_class": [
      "Hotels & Homes"
    ],
    "main": [
      "Cheap Flights, Airline Tickets & Plane Tickets | Trip.com\nAllow notifications\nDon't miss out! Be the first to find out the latest travel info.\nAllow\nTaipei\nEdit\n2 adults\nEconomy\nMar 4, 2026\nSun, Mar 1\nView\nMon, Mar 2\nView\nTue, Mar 3\nView\nWed, Mar 4\nUS$116\nThu, Mar 5\nView\nWed, Feb 25\nView\nThu, Feb 26\nView\nFri, Feb 27\nView\nSat, Feb 28\nView\nSun, Mar 1\nView\nMon, Mar 2\nView\nTue, Mar 3\nView\nWed, Mar 4\nUS$116\nThu, Mar 5\nView\nFri, Mar 6\nView\nSat, Mar 7\nView\nSun, Mar 8\nView\nMon, Mar 9\nView\nTue, Mar 10\nView\nWed, Mar 11\nView\nPrice graph\nRecommended\n Nonstop\n Checked baggage included\n Hide budget airlines\n Student tickets\n Carry-on baggage included\n Hide codeshare flights\nCO2e Lower emission flights\nShow More\nAlliance\nStar Alliance\nUS$218\nOneworld\nUS$324\nSkyTeam\nUS$470\nAirlines\nAll flights with the same airline\nAll airlines\nHong Kong Airlines (14)\nUS$198\nHK Express (8)\nUS$196\nAir Macau (4)\nUS$134\nEVA Air (3)\nUS$218\nPeach (3)\nUS$191\nShow More\nAlliance\nStar Alliance\nUS$218\nOneworld\nUS$324\nSkyTeam\nUS$470\nTimes\nDeparture time\n00:00–24:00\n00:00\n24:00\nArrival time\n00:00–24:00\n00:00\n24:00\nDuration\nAny\nStopover Duration\n1h–22h 30m\n1h\n22h 30m\nTotal Duration\n3h–28h 30m\n3h\n28h 30m\nStops\n1 stop or fewer\nUS$116\nStopover cities\nAny\nHong Kong\nUS$170\nBusan\nUS$197\nMacau\nUS$134\nShanghai\nUS$211\nSeoul\nUS$180\nOkinawa\nUS$195\nJeju\nUS$119\nDaegu\nUS$187\nBeijing\nUS$265\nShenzhen\nUS$337\nManila\nUS$346\nAirports\nAny\nDeparture Airport\nKIX\nKansai International Airport\nUS$116\nArrival Airport\nTPE\nTaiwan Taoyuan International Airport\nUS$116\nAircrafts\nAny\nLarge aircraft\nUS$116\nMidsize aircraft\nUS$119\nCabin\nEconomy\nEconomy\nEconomy/premium economy\nPremium economy\nBusiness/first\nBusiness\nFirst class\nDeparting for Taipei\nRecommended\nUS$116\nNonstop first\nUS$116\nCheapest\nUS$116\nSort by\nCreate price alert\nCheapest\nCarry-on baggage included\n- 18% CO2e\nAirAsia X Berhad\n20:45\nKIX T1\n3h 20m\nNonstop\n23:05\nTPE T1\nUS$116\nTotal US$232\nSelect\nCarry-on baggage included\nThai Vietjet Air\n12:00\nKIX T1\n3h 15m\nNonstop\n14:15\nTPE T1\nUS$156\nTotal US$311\nSelect\nCarry-on baggage included\n- 2% CO2e\nJetstar Japan\n23:10\nKIX T1\n3h 20m\nNonstop\n01:30\nTPE T1\n +1\nUS$157\nTotal US$313\nSelect\nCarry-on baggage included\nTigerair Taiwan\n11:30\nKIX T1\n3h 20m\nNonstop\n13:50\nTPE T1\nUS$179\nTotal US$358\nSelect\nSign in & save for future trips\nEarn at least 24 Trip Coins worth US$0.24 for this booking, which you can use to save on future trips!\nSign in/register\nCarry-on baggage included\nJetstar Japan\n14:50\nKIX T1\n3h 20m\nNonstop\n17:10\nTPE T1\nUS$184\nTotal US$367\nSelect\nCarry-on baggage included\nPeach\n10:10\nKIX T2\n3h 35m\nNonstop\n12:45\nTPE T1\nUS$191\nTotal US$381\nSelect\nCarry-on baggage included\n- 2% CO2e\nTigerair Taiwan\n18:55\nKIX T1\n3h 35m\nNonstop\n21:30\nTPE T1\nUS$212\nTotal US$423\nSelect\nIncluded\n- 23% CO2e\nEVA Air\n12:55\nKIX T1\n3h 10m\nNonstop\n15:05\nTPE T2\nUS$218\nTotal US$435\nSelect\nIncluded\n- 20% CO2e\nPeach\n15:25\nKIX T2\n3h 30m\nNonstop\n17:55\nTPE T1\nUS$219\nTotal US$438\nSelect\nIncluded\n- 20% CO2e\nPeach\n07:15\nKIX T2\n3h 30m\nNonstop\n09:45\nTPE T1\nUS$239\nTotal US$478\nSelect\nIncluded\n- 23% CO2e\nEVA Air\n10:55\nKIX T1\n3h 15m\nNonstop\n13:10\nTPE T2\nUS$302\nTotal US$604\nSelect\nIncluded\n- 23% CO2e\nEVA Air\n18:10\nKIX T1\n3h 15m\nNonstop\n20:25\nTPE T2\nUS$327\nTotal US$654\nSelect\nIncluded\n- 10% CO2e\nSTARLUX Airlines\n14:00\nKIX T1\n3h 15m\nNonstop\n16:15\nTPE T1\nUS$346\nTotal US$691\nSelect\nIncluded\n- 6% CO2e\nChina Airlines\n19:00\nKIX T1\n3h 15m\nNonstop\n21:15\nTPE T2\nUS$470\nTotal US$939\nSelect\nIncluded\nAll Nippon Airways\noperated by EVA Air\n12:55\nKIX T1\n3h 10m\nNonstop\n15:05\nTPE T2\nUS$1,262\nTotal US$2,524\nSelect\nIncluded\nJapan Airlines\noperated by China Airlines\n19:00\nKIX T1\n3h 15m\nNonstop\n21:15\nTPE T2\nUS$1,406\nTotal US$2,812\nSelect\nIncluded\nAll Nippon Airways\noperated by EVA Air\n18:10\nKIX T1\n3h 15m\nNonstop\n20:25\nTPE T2\nUS$1,529\nTotal US$3,057\nSelect\nIncluded\nAll Nippon Airways\noperated by EVA Air\n10:55\nKIX T1\n3h 15m\nNonstop\n13:10\nTPE T2\nUS$1,573\nTotal US$3,146\nSelect\nIncluded\nAir Macau\noperated by EVA Air\n13:45\nKIX T1\n26h 10m\n20h 5m in Macau\n14:55\nTPE T2\n +1\nUS$134\nTotal US$268\nSelect\nIncluded\nAir Macau\n13:45\nKIX T1\n24h 55m\n18h 50m in Macau\n13:40\nTPE T1\n +1\nUS$148\nTotal US$296\nSelect\nCarry-on baggage included\nGreater Bay Airlines\n14:00\nKIX T1\n7h 15m\n1h in Hong Kong\n20:15\nTPE T1\nUS$170\nTotal US$339\nSelect\nCarry-on baggage included\nGreater Bay Airlines\n14:00\nKIX T1\n20h 50m\n14h 35m in Hong Kong\n09:50\nTPE T1\n +1\nUS$170\nTotal US$339\nSelect\nIncluded\nJin Air\n11:05\nKIX T1\n25h 25m\n20h 30m in Seoul\n11:30\nTPE T1\n +1\nUS$180\nTotal US$359\nSelect\nIncluded\nT'Way Air\n16:55\nKIX T1\n8h 35m\n4h 10m in Daegu\n00:30\nTPE T1\n +1\nUS$187\nTotal US$374\nSelect\nIncluded\nAir Macau\noperated by EVA Air\n13:45\nKIX T1\n9h 15m\n3h 5m in Macau\n22:00\nTPE T2\nUS$196\nTotal US$392\nSelect\nIncluded\nJeju Air\n10:40\nKIX T2\n14h 10m\n9h 50m in Busan\n23:50\nTPE T1\nUS$197\nTotal US$393\nSelect\nHong Kong: Free Layover Tour\nHK Express\n21:05\nKIX T1\n17h 50m\n11h 20m in Hong Kong\n13:55\nTPE T1\n +1\nUS$196\nTotal US$392\nSelect\nHong Kong: Free Layover Tour\nHK Express\n20:15\nKIX T1\n18h 40m\n12h 10m in Hong Kong\n13:55\nTPE T1\n +1\nUS$196\nTotal US$392\nSelect\nHong Kong: Free Layover Tour\nHK Express\n21:05\nKIX T1\n20h 40m\n14h 10m in Hong Kong\n16:45\nTPE T1\n +1\nUS$196\nTotal US$392\nSelect\nHong Kong: Free Layover Tour\nHK Express\n20:15\nKIX T1\n21h 30m\n15h in Hong Kong\n16:45\nTPE T1\n +1\nUS$196\nTotal US$392\nSelect\nHK Express\n17:10\nKIX T1\n21h 45m\n15h 15m in Hong Kong\n13:55\nTPE T1\n +1\nUS$196\nTotal US$392\nSelect\nIncluded\nHong Kong Airlines\n09:45\nKIX T1\n9h 35m\n3h 15m in Hong Kong\n18:20\nTPE T2\nUS$198\nTotal US$395\nSelect\nIncluded\nJapan Transocean Air\n14:00\nKIX T1\n19h 45m\n15h 35m in Okinawa\n08:45\nTPE T2\n +1\nUS$199\nTotal US$398\nSelect\nIncluded\nHong Kong Airlines\n09:45\nKIX T1\n11h 55m\n5h 30m in Hong Kong\n20:40\nTPE T2\nUS$200\nTotal US$399\nSelect\nIncluded\nHong Kong Airlines\n15:05\nKIX T1\n25h 25m\n19h in Hong Kong\n15:30\nTPE T2\n +1\nUS$204\nTotal US$407\nSelect\nIncluded\nHong Kong: Free Layover Tour\nHong Kong Airlines\n09:45\nKIX T1\n26h 5m\n19h 45m in Hong Kong\n10:50\nTPE T2\n +1\nUS$205\nTotal US$409\nSelect\nIncluded\nHong Kong Airlines\n15:05\nKIX T1\n28h 15m\n21h 55m in Hong Kong\n18:20\nTPE T2\n +1\nUS$205\nTotal US$409\nSelect\nHong Kong: Free Layover Tour\nHK Express\n21:05\nKIX T1\n17h 5m\n10h 30m in Hong Kong\n13:10\nTPE T1\n +1\nUS$209\nTotal US$417\nSelect\nHong Kong: Free Layover Tour\nHK Express\n20:15\nKIX T1\n17h 55m\n11h 20m in Hong Kong\n13:10\nTPE T1\n +1\nUS$209\nTotal US$417\nSelect\nHK Express\n17:10\nKIX T1\n21h\n14h 25m in Hong Kong\n13:10\nTPE T1\n +1\nUS$209\nTotal US$417\nSelect\nCarry-on baggage included\nSpring Airlines\n17:00\nKIX T2\n18h 30m\n13h 25m in Shanghai\n10:30\nTPE T1\n +1\nUS$211\nTotal US$422\nSelect\nIncluded\nHong Kong Airlines\n17:05\nKIX T1\n26h 15m\n19h 40m in Hong Kong\n18:20\nTPE T2\n +1\nUS$245\nTotal US$489\nSelect\nIncluded\nJuneyao Airlines\n22:10\nKIX T1\n14h 25m\n9h 50m in Shanghai\n11:35\nTPE T1\n +1\nUS$250\nTotal US$500\nSelect\nIncluded\nAir China\n13:50\nKIX T1\n22h 50m\n16h 10m in Beijing\n11:40\nTPE T2\n +1\nUS$265\nTotal US$529\nSelect\nIncluded\nJuneyao Airlines\n12:15\nKIX T1\n24h 20m\n19h 30m in Shanghai\n11:35\nTPE T1\n +1\nUS$311\nTotal US$621\nSelect\nIncluded\nShenzhen Airlines\n15:05\nKIX T1\n26h 10m\n19h 20m in Shenzhen\n16:15\nTPE T2\n +1\nUS$337\nTotal US$674\nUS$337\nSelect\nIncluded\nAsiana Airlines\n09:00\nKIX T1\n7h 45m\n2h 50m in Seoul\n15:45\nTPE T2\nUS$340\nTotal US$679\nSelect\nIncluded\nPhilippine Airlines\n10:15\nKIX T1\n11h 20m\n4h 20m in Manila\n20:35\nTPE T1\nUS$346\nTotal US$691\nSelect\nNo more results for economy\nOther classes\nBusiness\nIncluded\nChina Airlines\n(180°)\n12:45\nKIX T1\n3h 15m\nNonstop\n15:00\nTPE T2\nUS$592\nTotal US$1,183\nBusiness\nSelect\nFlights\n > \nTaipei Flights\n > \nto Taipei Flights\nBook flights from to Taipei on Trip.com\n\nFirst class | Business class | Economy class | Nonstop\n\nSearch for cheap flights from to Taipei on Trip.com. Trip.com provides the best real-time to Taipei airfares and flight deals available, featuring advanced flight planning tools like price alerts, deal finder fare calendars, and Flight + Hotel deals that make a Taipei vacation or Taipei tour more convenient and affordable.\n\nAward-winning\nSupport in approx. 30s\nRewards for booking"
    ]
  }
}