{
  "url": "https://www.trip.com/flights/taipei-to-osaka/tickets-tpe-kix?dcity=tpe&acity=kix&ddate=2026-02-28&flighttype=ow&class=y&quantity=2",
  "scraped_at": "2026-02-05T17:36:26.328168",
  "title": "Cheap Flights, Airline Tickets & Plane Tickets | Trip.com",
  "raw_text": "Go to main content\nTheme Detection\nHotels & Homes\nFlights\nTrains\nCar services\nApp\nUSD\nCustomer support\nFind bookings\nSign in / Register\nCheap Flights, Airline Tickets & Plane Tickets | Trip.com\nAllow notifications\nDon't miss out! Be the first to find out the latest travel info.\nAllow\nTaipei\nEdit\n2 adults\nEconomy\nFeb 28, 2026\nWed, Feb 25\nView\nThu, Feb 26\nView\nFri, Feb 27\nView\nSat, Feb 28\nUS$138\nSun, Mar 1\nView\nSat, Feb 21\nView\nSun, Feb 22\nView\nMon, Feb 23\nView\nTue, Feb 24\nView\nWed, Feb 25\nView\nThu, Feb 26\nView\nFri, Feb 27\nView\nSat, Feb 28\nUS$138\nSun, Mar 1\nView\nMon, Mar 2\nView\nTue, Mar 3\nView\nWed, Mar 4\nView\nThu, Mar 5\nView\nFri, Mar 6\nView\nSat, Mar 7\nView\nPrice graph\nRecommended\n Nonstop\n Checked baggage included\n Hide budget airlines\n Student tickets\n Carry-on baggage included\n Hide codeshare flights\nCO2e Lower emission flights\nShow More\nAlliance\nSkyTeam\nUS$262\nStar Alliance\nUS$282\nOneworld\nUS$319\nAirlines\nAll flights with the same airline\nAll airlines\nHong Kong Airlines (15)\nUS$138\nCathay Pacific (5)\nUS$319\nHK Express (5)\nUS$173\nPeach (4)\nUS$213\nPhilippine Airlines (3)\nUS$265\nShow More\nAlliance\nSkyTeam\nUS$262\nStar Alliance\nUS$282\nOneworld\nUS$319\nTimes\nDeparture time\n00:00–24:00\n00:00\n24:00\nArrival time\n00:00–24:00\n00:00\n24:00\nDuration\nAny\nStopover Duration\n1h–23h\n1h\n23h\nTotal Duration\n2h–27h 30m\n2h\n27h 30m\nStops\n1 stop or fewer\nUS$138\nStopover cities\nAny\nHong Kong\nUS$138\nManila\nUS$265\nMacau\nUS$185\nSeoul\nUS$282\nXiamen\nUS$273\nJeju\nUS$276\nAirports\nAny\nDeparture Airport\nTSA\nTaipei Songshan Airport\nUS$273\nTPE\nTaiwan Taoyuan International Airport\nUS$138\nArrival Airport\nKIX\nKansai International Airport\nUS$138\nAircrafts\nAny\nLarge aircraft\nUS$151\nMidsize aircraft\nUS$138\nCabin\nEconomy\nEconomy\nEconomy/premium economy\nPremium economy\nBusiness/first\nBusiness\nFirst class\nRecommended\nUS$151\nNonstop first\nUS$213\nCheapest\nUS$138\nSort by\nCreate price alert\nCheapest nonstop\nCarry-on baggage included\n- 16% CO2e\nAirAsia X Berhad\n15:40\nTPE T1\n2h 40m\nNonstop\n19:20\nKIX T1\nUS$151\nTotal US$301\nSelect\nCarry-on baggage included\nThai Vietjet Air\n07:30\nTPE T1\n2h 30m\nNonstop\n11:00\nKIX T1\nUS$174\nTotal US$348\nSelect\nCarry-on baggage included\n- 1% CO2e\nThai Lion Air\n09:00\nTPE T1\n2h 30m\nNonstop\n12:30\nKIX T1\nUS$180\nTotal US$360\nSelect\nCarry-on baggage included\nTigerair Taiwan\n14:40\nTPE T1\n2h 15m\nNonstop\n17:55\nKIX T1\nUS$201\nTotal US$401\nSelect\nPrice alerts\nWant a better deal? We'll notify you when the price drops below US$133.\nRecommended: US$133\nHigh chances of success\nOK\nCarry-on baggage included\nPeach\n01:45\nTPE T1\n2h 25m\nNonstop\n05:10\nKIX T2\nUS$213\nTotal US$425\nSelect\nCarry-on baggage included\n- 18% CO2e\nPeach\n18:50\nTPE T1\n2h 25m\nNonstop\n22:15\nKIX T2\nUS$213\nTotal US$425\nSelect\nCarry-on baggage included\nTigerair Taiwan\n07:00\nTPE T1\n2h 25m\nNonstop\n10:25\nKIX T1\nUS$217\nTotal US$434\nSelect\nCarry-on baggage included\nJetstar Japan\n02:30\nTPE T1\n2h 30m\nNonstop\n06:00\nKIX T1\nUS$222\nTotal US$443\nSelect\nCarry-on baggage included\nJetstar Japan\n18:10\nTPE T1\n2h 30m\nNonstop\n21:40\nKIX T1\nUS$222\nTotal US$444\nSelect\nIncluded\n- 18% CO2e\nPeach\n09:40\nTPE T1\n2h 30m\nNonstop\n13:10\nKIX T2\nUS$252\nTotal US$503\nSelect\nIncluded\nPeach\n13:40\nTPE T1\n2h 25m\nNonstop\n17:05\nKIX T2\nUS$252\nTotal US$503\nSelect\nIncluded\n- 3% CO2e\nChina Airlines\n14:20\nTPE T2\n2h 30m\nNonstop\n17:50\nKIX T1\nUS$262\nTotal US$524\nSelect\nIncluded\nChina Airlines\n09:45\nTPE T2\n2h 35m\nNonstop\n13:20\nKIX T1\nUS$271\nTotal US$542\nSelect\nIncluded\n- 21% CO2e\nEVA Air\n13:30\nTPE T2\n2h 25m\nNonstop\n16:55\nKIX T1\nUS$286\nTotal US$571\nSelect\nIncluded\n- 20% CO2e\nEVA Air\n08:20\nTPE T2\n2h 35m\nNonstop\n11:55\nKIX T1\nUS$296\nTotal US$592\nSelect\n<9 left\nIncluded\n- 21% CO2e\nEVA Air\n06:30\nTPE T2\n2h 25m\nNonstop\n09:55\nKIX T1\nUS$309\nTotal US$617\nSelect\nIncluded\n- 7% CO2e\nSTARLUX Airlines\n09:20\nTPE T1\n2h 30m\nNonstop\n12:50\nKIX T1\nUS$317\nTotal US$633\nSelect\nIncluded\n- 18% CO2e\nCathay Pacific\n11:15\nTPE T1\n2h 40m\nNonstop\n14:55\nKIX T1\nUS$319\nTotal US$637\nUS$292\nSelect\nIncluded\n- 2% CO2e\nSTARLUX Airlines\n07:40\nTPE T1\n2h 30m\nNonstop\n11:10\nKIX T1\nUS$341\nTotal US$681\nSelect\nIncluded\nJapan Airlines\noperated by China Airlines\n08:05\nTPE T2\n2h 30m\nNonstop\n11:35\nKIX T1\nUS$959\nTotal US$1,917\nSelect\nIncluded\nJapan Airlines\noperated by China Airlines\n09:45\nTPE T2\n2h 35m\nNonstop\n13:20\nKIX T1\nUS$959\nTotal US$1,917\nSelect\nIncluded\nJapan Airlines\noperated by China Airlines\n14:20\nTPE T2\n2h 30m\nNonstop\n17:50\nKIX T1\nUS$959\nTotal US$1,917\nSelect\nIncluded\nAll Nippon Airways\noperated by EVA Air\n06:30\nTPE T2\n2h 25m\nNonstop\n09:55\nKIX T1\nUS$964\nTotal US$1,928\nSelect\nIncluded\nAll Nippon Airways\noperated by EVA Air\n08:20\nTPE T2\n2h 35m\nNonstop\n11:55\nKIX T1\nUS$964\nTotal US$1,928\nSelect\nIncluded\nAll Nippon Airways\noperated by EVA Air\n13:30\nTPE T2\n2h 25m\nNonstop\n16:55\nKIX T1\nUS$964\nTotal US$1,928\nSelect\nCheapest\nIncluded\nHong Kong Airlines\n21:35\nTPE T2\n20h 30m\n14h 50m in Hong Kong\n19:05\nKIX T1\n +1\nUS$138\nTotal US$275\nSelect\nIncluded\nHong Kong Airlines\n19:20\nTPE T2\n22h 45m\n17h 10m in Hong Kong\n19:05\nKIX T1\n +1\nUS$139\nTotal US$278\nSelect\nHK Express\n21:15\nTPE T1\n21h 5m\n15h 30m in Hong Kong\n19:20\nKIX T1\n +1\nUS$173\nTotal US$346\nSelect\nHK Express\n21:15\nTPE T1\n18h\n12h 25m in Hong Kong\n16:15\nKIX T1\n +1\nUS$176\nTotal US$352\nSelect\nCarry-on baggage included\nGreater Bay Airlines\n02:10\nTPE T1\n9h 45m\n4h in Hong Kong\n12:55\nKIX T1\nUS$184\nTotal US$367\nSelect\nCarry-on baggage included\nGreater Bay Airlines\n21:45\nTPE T1\n14h 10m\n8h 40m in Hong Kong\n12:55\nKIX T1\n +1\nUS$184\nTotal US$367\nSelect\nIncluded\nAir Macau\n21:35\nTPE T1\n14h 10m\n8h 45m in Macau\n12:45\nKIX T1\n +1\nUS$185\nTotal US$369\nSelect\nIncluded\nAir Macau\n20:10\nTPE T1\n15h 35m\n10h 15m in Macau\n12:45\nKIX T1\n +1\nUS$185\nTotal US$369\nSelect\nHK Express\n17:40\nTPE T1\n21h 35m\n16h 10m in Hong Kong\n16:15\nKIX T1\n +1\nUS$188\nTotal US$375\nSelect\nIncluded\nHong Kong Airlines\n21:35\nTPE T2\n8h 40m\n3h in Hong Kong\n07:15\nKIX T1\n +1\nUS$191\nTotal US$382\nSelect\nIncluded\nHong Kong Airlines\n21:35\nTPE T2\n17h 30m\n11h 40m in Hong Kong\n16:05\nKIX T1\n +1\nUS$191\nTotal US$382\nSelect\nIncluded\nHong Kong: Free Layover Tour\nHong Kong Airlines\n11:50\nTPE T2\n18h 25m\n12h 45m in Hong Kong\n07:15\nKIX T1\n +1\nUS$191\nTotal US$382\nSelect\nIncluded\nHong Kong Airlines\n19:20\nTPE T2\n19h 45m\n14h in Hong Kong\n16:05\nKIX T1\n +1\nUS$191\nTotal US$382\nSelect\nIncluded\nHong Kong Airlines\n16:30\nTPE T2\n22h 35m\n16h 40m in Hong Kong\n16:05\nKIX T1\n +1\nUS$191\nTotal US$382\nSelect\nIncluded\nHong Kong Airlines\n16:30\nTPE T2\n25h 35m\n19h 50m in Hong Kong\n19:05\nKIX T1\n +1\nUS$191\nTotal US$382\nSelect\nIncluded\nHong Kong: Free Layover Tour\nHong Kong Airlines\n11:50\nTPE T2\n27h 15m\n21h 25m in Hong Kong\n16:05\nKIX T1\n +1\nUS$197\nTotal US$393\nSelect\nIncluded\nHong Kong Airlines\n21:35\nTPE T2\n15h 30m\n9h 50m in Hong Kong\n14:05\nKIX T1\n +1\nUS$218\nTotal US$436\nSelect\n<9 left\nIncluded\nHong Kong Airlines\n19:20\nTPE T2\n17h 45m\n12h 10m in Hong Kong\n14:05\nKIX T1\n +1\nUS$218\nTotal US$436\nSelect\n<9 left\nIncluded\nCathay Pacific\n21:15\nTPE T1\n8h 5m\n2h 25m in Hong Kong\n06:20\nKIX T1\n +1\nUS$425\nTotal US$850\nSelect\nIncluded\nHong Kong: Free Layover Tour\nCathay Pacific\n22:20\nTPE T1\n13h 25m\n7h 50m in Hong Kong\n12:45\nKIX T1\n +1\nUS$425\nTotal US$850\nSelect\nIncluded\nHong Kong: Free Layover Tour\nCathay Pacific\n22:20\nTPE T1\n15h 55m\n10h 15m in Hong Kong\n15:15\nKIX T1\n +1\nUS$425\nTotal US$850\nSelect\nFlights\n > \nFlights\n > \nTaipei to Flights\nBook flights from Taipei to on Trip.com\n\nFirst class | Business class | Economy class | Nonstop\n\nSearch for cheap flights from Taipei to on Trip.com. Trip.com provides the best real-time Taipei to airfares and flight deals available, featuring advanced flight planning tools like price alerts, deal finder fare calendars, and Taipei Flight + Hotel deals that make a vacation or tour more convenient and affordable.\n\nAward-winning\nSupport in approx. 30s\nRewards for booking\nContact us\nCustomer support\nService guarantee\nMore service info\nAbout\nAbout Trip.com\nNews\nCareers\nTerms & Conditions\nPrivacy Statement\nAccessibility statement\nAbout Trip.com Group\nOther services\nInvestor relations\nTrip.com Rewards\nAffiliate program\nList your property\nAll hotels\nBecome a Supplier\nSecurity\nPayment methods\nOur partners\nContact Center\nof the year 2025\nCopyright © 2025 Trip.com Travel Singapore Pte. Ltd. All rights reserved\nSite Operator: Trip.com Travel Singapore Pte. Ltd.",
  "extracted": {
    "flight": {},
    "hotel": {},
    "price": {},
    "dates": {},
    "inclusions": [],
    "date_pricing": {}
  },
  "extracted_elements": {
    "flight_element": [
      "AirAsia X Berhad\n15:40\nTPE T1\n2h 40m\nNonstop\n19:20\nKIX T1",
      "Thai Vietjet Air\n07:30\nTPE T1\n2h 30m\nNonstop\n11:00\nKIX T1",
      "Thai Lion Air\n09:00\nTPE T1\n2h 30m\nNonstop\n12:30\nKIX T1",
      "Tigerair Taiwan\n14:40\nTPE T1\n2h 15m\nNonstop\n17:55\nKIX T1",
      "Peach\n01:45\nTPE T1\n2h 25m\nNonstop\n05:10\nKIX T2"
    ],
    "price_class": [
      "Wed, Feb 25\nView\nThu, Feb 26\nView\nFri, Feb 27\nView\nSat, Feb 28\nUS$138\nSun, Mar 1\nView",
      "Wed, Feb 25\nView\nThu, Feb 26\nView\nFri, Feb 27\nView\nSat, Feb 28\nUS$138\nSun, Mar 1\nView",
      "Wed, Feb 25\nView\nThu, Feb 26\nView\nFri, Feb 27\nView\nSat, Feb 28\nUS$138\nSun, Mar 1\nView",
      "Wed, Feb 25\nView\nThu, Feb 26\nView\nFri, Feb 27\nView\nSat, Feb 28\nUS$138\nSun, Mar 1\nView",
      "Wed, Feb 25\nView\nThu, Feb 26\nView\nFri, Feb 27\nView\nSat, Feb 28\nUS$138\nSun, Mar 1\nView"
    ],
    "flight_class": [
      "Flights",
      "Taipei\nEdit\n2 adults\nEconomy\nFeb 28, 2026\nWed, Feb 25\nView\nThu, Feb 26\nView\nFri, Feb 27\nView\nSat, Feb 28\nUS$138\nSun, Mar 1\nView\nSat, Feb 21\nView\nSun, Feb 22\nView\nMon, Feb 23\nView\nTue, Feb 24\nView\nWed, Feb 25\nView\nThu, Feb 26\nView\nFri, Feb 27\nView\nSat, Feb 28\nUS$138\nSun, Mar 1\nView\nMon, Mar 2\nView\nTue, Mar 3\nView\nWed, Mar 4\nView\nThu, Mar 5\nView\nFri, Mar 6\nView\nSat, Mar 7\nView\nPrice graph\nRecommended\n Nonstop\n Checked baggage included\n Hide budget airlines\n Student tickets\n Carry-on baggage included\n Hide codeshare flights\nCO2e Lower emission flights\nShow More\nAlliance\nSkyTeam\nUS$262\nStar Alliance\nUS$282\nOneworld\nUS$319\nAirlines\nAll flights with the same airline\nAll airlines\nHong Kong Airlines (15)\nUS$138\nCathay Pacific (5)\nUS$319\nHK Express (5)\nUS$173\nPeach (4)\nUS$213\nPhilippine Airlines (3)\nUS$265\nShow More\nAlliance\nSkyTeam\nUS$262\nStar Alliance\nUS$282\nOneworld\nUS$319\nTimes\nDeparture time\n00:00–24:00\n00:00\n24:00\nArrival time\n00:00–24:00\n00:00\n24:00\nDuration\nAny\nStopover Duration\n1h–23h\n1h\n23h\nTotal Duration\n2h–27h 30m\n2h\n27h 30m\nStops\n1 stop or fewer\nUS$138\nStopover cities\nAny\nHong Kong\nUS$138\nManila\nUS$265\nMacau\nUS$185\nSeoul\nUS$282\nXiamen\nUS$273\nJeju\nUS$276\nAirports\nAny\nDeparture Airport\nTSA\nTaipei Songshan Airport\nUS$273\nTPE\nTaiwan Taoyuan International Airport\nUS$138\nArrival Airport\nKIX\nKansai International Airport\nUS$138\nAircrafts\nAny\nLarge aircraft\nUS$151\nMidsize aircraft\nUS$138\nCabin\nEconomy\nEconomy\nEconomy/premium economy\nPremium economy\nBusiness/first\nBusiness\nFirst class\nRecommended\nUS$151\nNonstop first\nUS$213\nCheapest\nUS$138\nSort by\nCreate price alert\nCheapest nonstop\nCarry-on baggage included\n- 16% CO2e\nAirAsia X Berhad\n15:40\nTPE T1\n2h 40m\nNonstop\n19:20\nKIX T1\nUS$151\nTotal US$301\nSelect\nCarry-on baggage included\nThai Vietjet Air\n07:30\nTPE T1\n2h 30m\nNonstop\n11:00\nKIX T1\nUS$174\nTotal US$348\nSelect\nCarry-on baggage included\n- 1% CO2e\nThai Lion Air\n09:00\nTPE T1\n2h 30m\nNonstop\n12:30\nKIX T1\nUS$180\nTotal US$360\nSelect\nCarry-on baggage included\nTigerair Taiwan\n14:40\nTPE T1\n2h 15m\nNonstop\n17:55\nKIX T1\nUS$201\nTotal US$401\nSelect\nPrice alerts\nWant a better deal? We'll notify you when the price drops below US$133.\nRecommended: US$133\nHigh chances of success\nOK\nCarry-on baggage included\nPeach\n01:45\nTPE T1\n2h 25m\nNonstop\n05:10\nKIX T2\nUS$213\nTotal US$425\nSelect\nCarry-on baggage included\n- 18% CO2e\nPeach\n18:50\nTPE T1\n2h 25m\nNonstop\n22:15\nKIX T2\nUS$213\nTotal US$425\nSelect\nCarry-on baggage included\nTigerair Taiwan\n07:00\nTPE T1\n2h 25m\nNonstop\n10:25\nKIX T1\nUS$217\nTotal US$434\nSelect\nCarry-on baggage included\nJetstar Japan\n02:30\nTPE T1\n2h 30m\nNonstop\n06:00\nKIX T1\nUS$222\nTotal US$443\nSelect\nCarry-on baggage included\nJetstar Japan\n18:10\nTPE T1\n2h 30m\nNonstop\n21:40\nKIX T1\nUS$222\nTotal US$444\nSelect\nIncluded\n- 18% CO2e\nPeach\n09:40\nTPE T1\n2h 30m\nNonstop\n13:10\nKIX T2\nUS$252\nTotal US$503\nSelect\nIncluded\nPeach\n13:40\nTPE T1\n2h 25m\nNonstop\n17:05\nKIX T2\nUS$252\nTotal US$503\nSelect\nIncluded\n- 3% CO2e\nChina Airlines\n14:20\nTPE T2\n2h 30m\nNonstop\n17:50\nKIX T1\nUS$262\nTotal US$524\nSelect\nIncluded\nChina Airlines\n09:45\nTPE T2\n2h 35m\nNonstop\n13:20\nKIX T1\nUS$271\nTotal US$542\nSelect\nIncluded\n- 21% CO2e\nEVA Air\n13:30\nTPE T2\n2h 25m\nNonstop\n16:55\nKIX T1\nUS$286\nTotal US$571\nSelect\nIncluded\n- 20% CO2e\nEVA Air\n08:20\nTPE T2\n2h 35m\nNonstop\n11:55\nKIX T1\nUS$296\nTotal US$592\nSelect\n<9 left\nIncluded\n- 21% CO2e\nEVA Air\n06:30\nTPE T2\n2h 25m\nNonstop\n09:55\nKIX T1\nUS$309\nTotal US$617\nSelect\nIncluded\n- 7% CO2e\nSTARLUX Airlines\n09:20\nTPE T1\n2h 30m\nNonstop\n12:50\nKIX T1\nUS$317\nTotal US$633\nSelect\nIncluded\n- 18% CO2e\nCathay Pacific\n11:15\nTPE T1\n2h 40m\nNonstop\n14:55\nKIX T1\nUS$319\nTotal US$637\nUS$292\nSelect\nIncluded\n- 2% CO2e\nSTARLUX Airlines\n07:40\nTPE T1\n2h 30m\nNonstop\n11:10\nKIX T1\nUS$341\nTotal US$681\nSelect\nIncluded\nJapan Airlines\noperated by China Airlines\n08:05\nTPE T2\n2h 30m\nNonstop\n11:35\nKIX T1\nUS$959\nTotal US$1,917\nSelect\nIncluded\nJapan Airlines\noperated by China Airlines\n09:45\nTPE T2\n2h 35m\nNonstop\n13:20\nKIX T1\nUS$959\nTotal US$1,917\nSelect\nIncluded\nJapan Airlines\noperated by China Airlines\n14:20\nTPE T2\n2h 30m\nNonstop\n17:50\nKIX T1\nUS$959\nTotal US$1,917\nSelect\nIncluded\nAll Nippon Airways\noperated by EVA Air\n06:30\nTPE T2\n2h 25m\nNonstop\n09:55\nKIX T1\nUS$964\nTotal US$1,928\nSelect\nIncluded\nAll Nippon Airways\noperated by EVA Air\n08:20\nTPE T2\n2h 35m\nNonstop\n11:55\nKIX T1\nUS$964\nTotal US$1,928\nSelect\nIncluded\nAll Nippon Airways\noperated by EVA Air\n13:30\nTPE T2\n2h 25m\nNonstop\n16:55\nKIX T1\nUS$964\nTotal US$1,928\nSelect\nCheapest\nIncluded\nHong Kong Airlines\n21:35\nTPE T2\n20h 30m\n14h 50m in Hong Kong\n19:05\nKIX T1\n +1\nUS$138\nTotal US$275\nSelect\nIncluded\nHong Kong Airlines\n19:20\nTPE T2\n22h 45m\n17h 10m in Hong Kong\n19:05\nKIX T1\n +1\nUS$139\nTotal US$278\nSelect\nHK Express\n21:15\nTPE T1\n21h 5m\n15h 30m in Hong Kong\n19:20\nKIX T1\n +1\nUS$173\nTotal US$346\nSelect\nHK Express\n21:15\nTPE T1\n18h\n12h 25m in Hong Kong\n16:15\nKIX T1\n +1\nUS$176\nTotal US$352\nSelect\nCarry-on baggage included\nGreater Bay Airlines\n02:10\nTPE T1\n9h 45m\n4h in Hong Kong\n12:55\nKIX T1\nUS$184\nTotal US$367\nSelect\nCarry-on baggage included\nGreater Bay Airlines\n21:45\nTPE T1\n14h 10m\n8h 40m in Hong Kong\n12:55\nKIX T1\n +1\nUS$184\nTotal US$367\nSelect\nIncluded\nAir Macau\n21:35\nTPE T1\n14h 10m\n8h 45m in Macau\n12:45\nKIX T1\n +1\nUS$185\nTotal US$369\nSelect\nIncluded\nAir Macau\n20:10\nTPE T1\n15h 35m\n10h 15m in Macau\n12:45\nKIX T1\n +1\nUS$185\nTotal US$369\nSelect\nHK Express\n17:40\nTPE T1\n21h 35m\n16h 10m in Hong Kong\n16:15\nKIX T1\n +1\nUS$188\nTotal US$375\nSelect\nIncluded\nHong Kong Airlines\n21:35\nTPE T2\n8h 40m\n3h in Hong Kong\n07:15\nKIX T1\n +1\nUS$191\nTotal US$382\nSelect\nIncluded\nHong Kong Airlines\n21:35\nTPE T2\n17h 30m\n11h 40m in Hong Kong\n16:05\nKIX T1\n +1\nUS$191\nTotal US$382\nSelect\nIncluded\nHong Kong: Free Layover Tour\nHong Kong Airlines\n11:50\nTPE T2\n18h 25m\n12h 45m in Hong Kong\n07:15\nKIX T1\n +1\nUS$191\nTotal US$382\nSelect\nIncluded\nHong Kong Airlines\n19:20\nTPE T2\n19h 45m\n14h in Hong Kong\n16:05\nKIX T1\n +1\nUS$191\nTotal US$382\nSelect\nIncluded\nHong Kong Airlines\n16:30\nTPE T2\n22h 35m\n16h 40m in Hong Kong\n16:05\nKIX T1\n +1\nUS$191\nTotal US$382\nSelect\nIncluded\nHong Kong Airlines\n16:30\nTPE T2\n25h 35m\n19h 50m in Hong Kong\n19:05\nKIX T1\n +1\nUS$191\nTotal US$382\nSelect\nIncluded\nHong Kong: Free Layover Tour\nHong Kong Airlines\n11:50\nTPE T2\n27h 15m\n21h 25m in Hong Kong\n16:05\nKIX T1\n +1\nUS$197\nTotal US$393\nSelect\nIncluded\nHong Kong Airlines\n21:35\nTPE T2\n15h 30m\n9h 50m in Hong Kong\n14:05\nKIX T1\n +1\nUS$218\nTotal US$436\nSelect\n<9 left\nIncluded\nHong Kong Airlines\n19:20\nTPE T2\n17h 45m\n12h 10m in Hong Kong\n14:05\nKIX T1\n +1\nUS$218\nTotal US$436\nSelect\n<9 left\nIncluded\nCathay Pacific\n21:15\nTPE T1\n8h 5m\n2h 25m in Hong Kong\n06:20\nKIX T1\n +1\nUS$425\nTotal US$850\nSelect\nIncluded\nHong Kong: Free Layover Tour\nCathay Pacific\n22:20\nTPE T1\n13h 25m\n7h 50m in Hong Kong\n12:45\nKIX T1\n +1\nUS$425\nTotal US$850\nSelect\nIncluded\nHong Kong: Free Layover Tour\nCathay Pacific\n22:20\nTPE T1\n15h 55m\n10h 15m in Hong Kong\n15:15\nKIX T1\n +1\nUS$425\nTotal US$850\nSelect\nFlights\n > \nFlights\n > \nTaipei to Flights\nBook flights from Taipei to on Trip.com\n\nFirst class | Business class | Economy class | Nonstop\n\nSearch for cheap flights from Taipei to on Trip.com. Trip.com provides the best real-time Taipei to airfares and flight deals available, featuring advanced flight planning tools like price alerts, deal finder fare calendars, and Taipei Flight + Hotel deals that make a vacation or tour more convenient and affordable.\n\nAward-winning\nSupport in approx. 30s\nRewards for booking",
      "Taipei\nEdit\n2 adults\nEconomy\nFeb 28, 2026\nWed, Feb 25\nView\nThu, Feb 26\nView\nFri, Feb 27\nView\nSat, Feb 28\nUS$138\nSun, Mar 1\nView",
      "DepartSat, Feb 28"
    ],
    "hotel_class": [
      "Hotels & Homes"
    ],
    "main": [
      "Cheap Flights, Airline Tickets & Plane Tickets | Trip.com\nAllow notifications\nDon't miss out! Be the first to find out the latest travel info.\nAllow\nTaipei\nEdit\n2 adults\nEconomy\nFeb 28, 2026\nWed, Feb 25\nView\nThu, Feb 26\nView\nFri, Feb 27\nView\nSat, Feb 28\nUS$138\nSun, Mar 1\nView\nSat, Feb 21\nView\nSun, Feb 22\nView\nMon, Feb 23\nView\nTue, Feb 24\nView\nWed, Feb 25\nView\nThu, Feb 26\nView\nFri, Feb 27\nView\nSat, Feb 28\nUS$138\nSun, Mar 1\nView\nMon, Mar 2\nView\nTue, Mar 3\nView\nWed, Mar 4\nView\nThu, Mar 5\nView\nFri, Mar 6\nView\nSat, Mar 7\nView\nPrice graph\nRecommended\n Nonstop\n Checked baggage included\n Hide budget airlines\n Student tickets\n Carry-on baggage included\n Hide codeshare flights\nCO2e Lower emission flights\nShow More\nAlliance\nSkyTeam\nUS$262\nStar Alliance\nUS$282\nOneworld\nUS$319\nAirlines\nAll flights with the same airline\nAll airlines\nHong Kong Airlines (15)\nUS$138\nCathay Pacific (5)\nUS$319\nHK Express (5)\nUS$173\nPeach (4)\nUS$213\nPhilippine Airlines (3)\nUS$265\nShow More\nAlliance\nSkyTeam\nUS$262\nStar Alliance\nUS$282\nOneworld\nUS$319\nTimes\nDeparture time\n00:00–24:00\n00:00\n24:00\nArrival time\n00:00–24:00\n00:00\n24:00\nDuration\nAny\nStopover Duration\n1h–23h\n1h\n23h\nTotal Duration\n2h–27h 30m\n2h\n27h 30m\nStops\n1 stop or fewer\nUS$138\nStopover cities\nAny\nHong Kong\nUS$138\nManila\nUS$265\nMacau\nUS$185\nSeoul\nUS$282\nXiamen\nUS$273\nJeju\nUS$276\nAirports\nAny\nDeparture Airport\nTSA\nTaipei Songshan Airport\nUS$273\nTPE\nTaiwan Taoyuan International Airport\nUS$138\nArrival Airport\nKIX\nKansai International Airport\nUS$138\nAircrafts\nAny\nLarge aircraft\nUS$151\nMidsize aircraft\nUS$138\nCabin\nEconomy\nEconomy\nEconomy/premium economy\nPremium economy\nBusiness/first\nBusiness\nFirst class\nRecommended\nUS$151\nNonstop first\nUS$213\nCheapest\nUS$138\nSort by\nCreate price alert\nCheapest nonstop\nCarry-on baggage included\n- 16% CO2e\nAirAsia X Berhad\n15:40\nTPE T1\n2h 40m\nNonstop\n19:20\nKIX T1\nUS$151\nTotal US$301\nSelect\nCarry-on baggage included\nThai Vietjet Air\n07:30\nTPE T1\n2h 30m\nNonstop\n11:00\nKIX T1\nUS$174\nTotal US$348\nSelect\nCarry-on baggage included\n- 1% CO2e\nThai Lion Air\n09:00\nTPE T1\n2h 30m\nNonstop\n12:30\nKIX T1\nUS$180\nTotal US$360\nSelect\nCarry-on baggage included\nTigerair Taiwan\n14:40\nTPE T1\n2h 15m\nNonstop\n17:55\nKIX T1\nUS$201\nTotal US$401\nSelect\nPrice alerts\nWant a better deal? We'll notify you when the price drops below US$133.\nRecommended: US$133\nHigh chances of success\nOK\nCarry-on baggage included\nPeach\n01:45\nTPE T1\n2h 25m\nNonstop\n05:10\nKIX T2\nUS$213\nTotal US$425\nSelect\nCarry-on baggage included\n- 18% CO2e\nPeach\n18:50\nTPE T1\n2h 25m\nNonstop\n22:15\nKIX T2\nUS$213\nTotal US$425\nSelect\nCarry-on baggage included\nTigerair Taiwan\n07:00\nTPE T1\n2h 25m\nNonstop\n10:25\nKIX T1\nUS$217\nTotal US$434\nSelect\nCarry-on baggage included\nJetstar Japan\n02:30\nTPE T1\n2h 30m\nNonstop\n06:00\nKIX T1\nUS$222\nTotal US$443\nSelect\nCarry-on baggage included\nJetstar Japan\n18:10\nTPE T1\n2h 30m\nNonstop\n21:40\nKIX T1\nUS$222\nTotal US$444\nSelect\nIncluded\n- 18% CO2e\nPeach\n09:40\nTPE T1\n2h 30m\nNonstop\n13:10\nKIX T2\nUS$252\nTotal US$503\nSelect\nIncluded\nPeach\n13:40\nTPE T1\n2h 25m\nNonstop\n17:05\nKIX T2\nUS$252\nTotal US$503\nSelect\nIncluded\n- 3% CO2e\nChina Airlines\n14:20\nTPE T2\n2h 30m\nNonstop\n17:50\nKIX T1\nUS$262\nTotal US$524\nSelect\nIncluded\nChina Airlines\n09:45\nTPE T2\n2h 35m\nNonstop\n13:20\nKIX T1\nUS$271\nTotal US$542\nSelect\nIncluded\n- 21% CO2e\nEVA Air\n13:30\nTPE T2\n2h 25m\nNonstop\n16:55\nKIX T1\nUS$286\nTotal US$571\nSelect\nIncluded\n- 20% CO2e\nEVA Air\n08:20\nTPE T2\n2h 35m\nNonstop\n11:55\nKIX T1\nUS$296\nTotal US$592\nSelect\n<9 left\nIncluded\n- 21% CO2e\nEVA Air\n06:30\nTPE T2\n2h 25m\nNonstop\n09:55\nKIX T1\nUS$309\nTotal US$617\nSelect\nIncluded\n- 7% CO2e\nSTARLUX Airlines\n09:20\nTPE T1\n2h 30m\nNonstop\n12:50\nKIX T1\nUS$317\nTotal US$633\nSelect\nIncluded\n- 18% CO2e\nCathay Pacific\n11:15\nTPE T1\n2h 40m\nNonstop\n14:55\nKIX T1\nUS$319\nTotal US$637\nUS$292\nSelect\nIncluded\n- 2% CO2e\nSTARLUX Airlines\n07:40\nTPE T1\n2h 30m\nNonstop\n11:10\nKIX T1\nUS$341\nTotal US$681\nSelect\nIncluded\nJapan Airlines\noperated by China Airlines\n08:05\nTPE T2\n2h 30m\nNonstop\n11:35\nKIX T1\nUS$959\nTotal US$1,917\nSelect\nIncluded\nJapan Airlines\noperated by China Airlines\n09:45\nTPE T2\n2h 35m\nNonstop\n13:20\nKIX T1\nUS$959\nTotal US$1,917\nSelect\nIncluded\nJapan Airlines\noperated by China Airlines\n14:20\nTPE T2\n2h 30m\nNonstop\n17:50\nKIX T1\nUS$959\nTotal US$1,917\nSelect\nIncluded\nAll Nippon Airways\noperated by EVA Air\n06:30\nTPE T2\n2h 25m\nNonstop\n09:55\nKIX T1\nUS$964\nTotal US$1,928\nSelect\nIncluded\nAll Nippon Airways\noperated by EVA Air\n08:20\nTPE T2\n2h 35m\nNonstop\n11:55\nKIX T1\nUS$964\nTotal US$1,928\nSelect\nIncluded\nAll Nippon Airways\noperated by EVA Air\n13:30\nTPE T2\n2h 25m\nNonstop\n16:55\nKIX T1\nUS$964\nTotal US$1,928\nSelect\nCheapest\nIncluded\nHong Kong Airlines\n21:35\nTPE T2\n20h 30m\n14h 50m in Hong Kong\n19:05\nKIX T1\n +1\nUS$138\nTotal US$275\nSelect\nIncluded\nHong Kong Airlines\n19:20\nTPE T2\n22h 45m\n17h 10m in Hong Kong\n19:05\nKIX T1\n +1\nUS$139\nTotal US$278\nSelect\nHK Express\n21:15\nTPE T1\n21h 5m\n15h 30m in Hong Kong\n19:20\nKIX T1\n +1\nUS$173\nTotal US$346\nSelect\nHK Express\n21:15\nTPE T1\n18h\n12h 25m in Hong Kong\n16:15\nKIX T1\n +1\nUS$176\nTotal US$352\nSelect\nCarry-on baggage included\nGreater Bay Airlines\n02:10\nTPE T1\n9h 45m\n4h in Hong Kong\n12:55\nKIX T1\nUS$184\nTotal US$367\nSelect\nCarry-on baggage included\nGreater Bay Airlines\n21:45\nTPE T1\n14h 10m\n8h 40m in Hong Kong\n12:55\nKIX T1\n +1\nUS$184\nTotal US$367\nSelect\nIncluded\nAir Macau\n21:35\nTPE T1\n14h 10m\n8h 45m in Macau\n12:45\nKIX T1\n +1\nUS$185\nTotal US$369\nSelect\nIncluded\nAir Macau\n20:10\nTPE T1\n15h 35m\n10h 15m in Macau\n12:45\nKIX T1\n +1\nUS$185\nTotal US$369\nSelect\nHK Express\n17:40\nTPE T1\n21h 35m\n16h 10m in Hong Kong\n16:15\nKIX T1\n +1\nUS$188\nTotal US$375\nSelect\nIncluded\nHong Kong Airlines\n21:35\nTPE T2\n8h 40m\n3h in Hong Kong\n07:15\nKIX T1\n +1\nUS$191\nTotal US$382\nSelect\nIncluded\nHong Kong Airlines\n21:35\nTPE T2\n17h 30m\n11h 40m in Hong Kong\n16:05\nKIX T1\n +1\nUS$191\nTotal US$382\nSelect\nIncluded\nHong Kong: Free Layover Tour\nHong Kong Airlines\n11:50\nTPE T2\n18h 25m\n12h 45m in Hong Kong\n07:15\nKIX T1\n +1\nUS$191\nTotal US$382\nSelect\nIncluded\nHong Kong Airlines\n19:20\nTPE T2\n19h 45m\n14h in Hong Kong\n16:05\nKIX T1\n +1\nUS$191\nTotal US$382\nSelect\nIncluded\nHong Kong Airlines\n16:30\nTPE T2\n22h 35m\n16h 40m in Hong Kong\n16:05\nKIX T1\n +1\nUS$191\nTotal US$382\nSelect\nIncluded\nHong Kong Airlines\n16:30\nTPE T2\n25h 35m\n19h 50m in Hong Kong\n19:05\nKIX T1\n +1\nUS$191\nTotal US$382\nSelect\nIncluded\nHong Kong: Free Layover Tour\nHong Kong Airlines\n11:50\nTPE T2\n27h 15m\n21h 25m in Hong Kong\n16:05\nKIX T1\n +1\nUS$197\nTotal US$393\nSelect\nIncluded\nHong Kong Airlines\n21:35\nTPE T2\n15h 30m\n9h 50m in Hong Kong\n14:05\nKIX T1\n +1\nUS$218\nTotal US$436\nSelect\n<9 left\nIncluded\nHong Kong Airlines\n19:20\nTPE T2\n17h 45m\n12h 10m in Hong Kong\n14:05\nKIX T1\n +1\nUS$218\nTotal US$436\nSelect\n<9 left\nIncluded\nCathay Pacific\n21:15\nTPE T1\n8h 5m\n2h 25m in Hong Kong\n06:20\nKIX T1\n +1\nUS$425\nTotal US$850\nSelect\nIncluded\nHong Kong: Free Layover Tour\nCathay Pacific\n22:20\nTPE T1\n13h 25m\n7h 50m in Hong Kong\n12:45\nKIX T1\n +1\nUS$425\nTotal US$850\nSelect\nIncluded\nHong Kong: Free Layover Tour\nCathay Pacific\n22:20\nTPE T1\n15h 55m\n10h 15m in Hong Kong\n15:15\nKIX T1\n +1\nUS$425\nTotal US$850\nSelect\nFlights\n > \nFlights\n > \nTaipei to Flights\nBook flights from Taipei to on Trip.com\n\nFirst class | Business class | Economy class | Nonstop\n\nSearch for cheap flights from Taipei to on Trip.com. Trip.com provides the best real-time Taipei to airfares and flight deals available, featuring advanced flight planning tools like price alerts, deal finder fare calendars, and Taipei Flight + Hotel deals that make a vacation or tour more convenient and affordable.\n\nAward-winning\nSupport in approx. 30s\nRewards for booking"
    ]
  }
}